Workbook

Sheet Workshop
A1: Demand forecasting workshop
A2: South Africa • 7 October 2026 • Proposed direction and provisional current-model examples
A4: Discussion | B4: Starting position | C4: Decision to record | D4: Lead / reviewer | E4: Agreed decision | F4: Next action / date
A5: Purpose | B5: Start with Baseline; follow formulas to sector blocks, Model run and Evidence. | C5: Source selection holds each historical comparator choice. FIASA is provisional; HML remains last. | D5: Nigel + Manish
A6: 1. Segment methods | B6: Methods sheet distinguishes the existing engine from the proposed method. | C6: Agree method, segment boundaries and missing components. | D6: Manish / Nigel
A7: 2. Geography | B7: Use national allocation where local evidence is weak; provincial calculations where defensible. | C7: Choose method by segment and define sales versus consumption location. | D7: Manish / Nigel
A8: 3. Worked examples | B8: Excel recalculates source choices, linked reporting totals, unit conversions and differences. | C8: Engine results are a frozen Python run. Input/scenario changes require a Python rerun and refreshed export. | D8: Manish / Nigel
A9: 4. Input ranges | B9: HML contains existing proposed demand ranges plus blank brackets for missing drivers. | C9: Agree low / medium / high inputs, reference case and annual paths. | D9: Nigel / Henry
A10: 5. Scenario combinations | B10: A higher input can raise or lower demand. Medium is not an approved baseline. | C10: Select compatible inputs; assess demand and supply independently. | D10: Nigel / Henry
A11: 6. Acceptance | B11: Review corrections before engine integration. | C11: Record evidence, decision, owner and next review trigger. | D11: Nigel
A12: Example scope | B12: Current high_demand scenario, vintage 2026. This is one existing case, not the proposed medium case. | C12: 2022–2023 model backcast; 2024–2035 model horizon. No row is observed merely because its year is historical. | D12: All readers
A13: Editable cells | B13: Yellow = missing/discussion inputs; blue = staged observations; green = current model or reporting calculations. | C13: Full-year observations stay in year columns. D may contain a clearly dated latest YTD/snapshot or older anchor. | D13: All readers
A14: Calculation boundary | B14: Demand figures are snapshots from the Python engine. Editing a discussion input does not rerun the engine. | C14: Only explicit reconciliation / allocation formulas recalculate in Excel. | D14: Manish
A15: Provincial example | B15: 2022 observed provincial petrol/diesel and Q1 2023 partial values are now shown below the allocation template. | C15: Sales location differs from consumption. No passenger allocation shares have been silently populated. | D15: Manish / Nigel
A16: Sources and run | B16: Recorded engine run: 2026-10-07T10:48:46.852505+00:00; commit 8c69f8333192483f19cd80911cb90fcd0943eb6b; high_demand; vintage 2026. | C16: Input and evidence SHA256 hashes are retained in workshop_data.json; no new model assumptions adopted. | D16: 2026 draft vintage
A17: Acceptance boundary | B17: 54 open exceptions at workbook preparation. Current inputs and outputs remain provisional. | C17: No source approval, peer-review completion or client acceptance is inferred. | D17: Nigel

Sheet Baseline
A1: Demand baseline and reconciliation
A2: Linked demand comparison. Full definitions: Notes. Historical sources: Source selection.
A4: Driver / output | B4: Unit | C4: Role | D4: Scalar / latest value | E4: Definition / period | F4: 2022 | G4: 2023 | H4: 2024 | I4: 2025 | J4: 2026 | K4: 2027 | L4: 2028 | M4: 2029 | N4: 2030 | O4: 2031 | P4: 2032 | Q4: 2033 | R4: 2034 | S4: 2035 | T4: Coverage / status | U4: Source | V4: Missing evidence / next action
A5: Petrol: national product comparison
A6: Selected historical petrol sales | B6: million L/year | C6: Linked observation | E6: Selected historical sales; see Source selection. [N001] | F6: =IF(ISNUMBER('Source selection'!F5),'Source selection'!F5,"") | G6: =IF(ISNUMBER('Source selection'!F6),'Source selection'!F6,"") | H6: =IF(ISNUMBER('Source selection'!F7),'Source selection'!F7,"") | I6: =IF(ISNUMBER('Source selection'!F8),'Source selection'!F8,"") | J6: =IF(ISNUMBER('Source selection'!F9),'Source selection'!F9,"") | T6: Working comparator; not approved | U6: Source selection → Evidence | V6: Manish reconciles scope/revisions; Nigel accepts source.
A7: Historical source / status | B7: text | C7: Selection status | E7: Selected source, or unresolved when unavailable. [N002] | F7: =IF(ISNUMBER('Source selection'!F5),'Source selection'!E5,"Unresolved") | G7: =IF(ISNUMBER('Source selection'!F6),'Source selection'!E6,"Unresolved") | H7: =IF(ISNUMBER('Source selection'!F7),'Source selection'!E7,"Unresolved") | I7: =IF(ISNUMBER('Source selection'!F8),'Source selection'!E8,"Unresolved") | J7: =IF(ISNUMBER('Source selection'!F9),'Source selection'!E9,"Unresolved") | T7: Not an additional demand series | U7: Source selection | V7: Review selected source before calibration.
A8: Current model road petrol | B8: million L/year | C8: Model output | E8: Passenger + LCV petrol. All-grade sales comparison. [N003] | F8: =IF(ISNUMBER('Petrol'!F23),'Petrol'!F23/1000000,"") | G8: =IF(ISNUMBER('Petrol'!G23),'Petrol'!G23/1000000,"") | H8: =IF(ISNUMBER('Petrol'!H23),'Petrol'!H23/1000000,"") | I8: =IF(ISNUMBER('Petrol'!I23),'Petrol'!I23/1000000,"") | J8: =IF(ISNUMBER('Petrol'!J23),'Petrol'!J23/1000000,"") | K8: =IF(ISNUMBER('Petrol'!K23),'Petrol'!K23/1000000,"") | L8: =IF(ISNUMBER('Petrol'!L23),'Petrol'!L23/1000000,"") | M8: =IF(ISNUMBER('Petrol'!M23),'Petrol'!M23/1000000,"") | ... S8: =IF(ISNUMBER('Petrol'!S23),'Petrol'!S23/1000000,"") | T8: 2026 vintage; current high_demand case; provisional. | U8: Petrol row 23 → Model run → Python engine | V8: Validate inputs and reconcile against observed data.
A9: Model less selected historical sales | B9: million L/year | C9: Reporting formula | E9: Model minus selected sales; scope requires reconciliation. [N004] | F9: =IF(COUNT(F6,F8)<2,"",F8-F6) | G9: =IF(COUNT(G6,G8)<2,"",G8-G6) | H9: =IF(COUNT(H6,H8)<2,"",H8-H6) | I9: =IF(COUNT(I6,I8)<2,"",I8-I6) | J9: =IF(COUNT(J6,J8)<2,"",J8-J6) | K9: =IF(COUNT(K6,K8)<2,"",K8-K6) | L9: =IF(COUNT(L6,L8)<2,"",L8-L6) | M9: =IF(COUNT(M6,M8)<2,"",M8-M6) | ... S9: =IF(COUNT(S6,S8)<2,"",S8-S6) | T9: Only where both values exist. | V9: G01: reconcile grade/segment scope.
A11: Diesel: segments and national product comparison
A12: Selected historical diesel sales | B12: million L/year | C12: Linked observation | E12: Selected historical sales; see Source selection. [N005] | F12: =IF(ISNUMBER('Source selection'!F10),'Source selection'!F10,"") | G12: =IF(ISNUMBER('Source selection'!F11),'Source selection'!F11,"") | H12: =IF(ISNUMBER('Source selection'!F12),'Source selection'!F12,"") | I12: =IF(ISNUMBER('Source selection'!F13),'Source selection'!F13,"") | J12: =IF(ISNUMBER('Source selection'!F14),'Source selection'!F14,"") | T12: Working comparator; not approved | U12: Source selection → Evidence | V12: Manish reconciles scope/revisions; Nigel accepts source.
A13: Historical source / status | B13: text | C13: Selection status | E13: Selected source, or unresolved when unavailable. [N006] | F13: =IF(ISNUMBER('Source selection'!F10),'Source selection'!E10,"Unresolved") | G13: =IF(ISNUMBER('Source selection'!F11),'Source selection'!E11,"Unresolved") | H13: =IF(ISNUMBER('Source selection'!F12),'Source selection'!E12,"Unresolved") | I13: =IF(ISNUMBER('Source selection'!F13),'Source selection'!E13,"Unresolved") | J13: =IF(ISNUMBER('Source selection'!F14),'Source selection'!E14,"Unresolved") | T13: Not an additional demand series | U13: Source selection | V13: Review selected source before calibration.
A14: All road diesel | B14: million L/year | C14: Model output | E14: Passenger + LCV + HCV diesel. [N007] | F14: =IF(ISNUMBER('Freight'!F57),'Freight'!F57/1,"") | G14: =IF(ISNUMBER('Freight'!G57),'Freight'!G57/1,"") | H14: =IF(ISNUMBER('Freight'!H57),'Freight'!H57/1,"") | I14: =IF(ISNUMBER('Freight'!I57),'Freight'!I57/1,"") | J14: =IF(ISNUMBER('Freight'!J57),'Freight'!J57/1,"") | K14: =IF(ISNUMBER('Freight'!K57),'Freight'!K57/1,"") | L14: =IF(ISNUMBER('Freight'!L57),'Freight'!L57/1,"") | M14: =IF(ISNUMBER('Freight'!M57),'Freight'!M57/1,"") | ... S14: =IF(ISNUMBER('Freight'!S57),'Freight'!S57/1,"") | T14: 2026 vintage; current high_demand case; provisional. | U14: Freight row 57 → Model run → Python engine | V14: Validate inputs and reconcile against observed data.
A15: Grid OCGT diesel | B15: million L/year | C15: Model output | E15: Grid OCGT model. Private backup not calibrated. [N008] | F15: =IF(ISNUMBER('Other demand'!F12),'Other demand'!F12/1,"") | G15: =IF(ISNUMBER('Other demand'!G12),'Other demand'!G12/1,"") | H15: =IF(ISNUMBER('Other demand'!H12),'Other demand'!H12/1,"") | I15: =IF(ISNUMBER('Other demand'!I12),'Other demand'!I12/1,"") | J15: =IF(ISNUMBER('Other demand'!J12),'Other demand'!J12/1,"") | K15: =IF(ISNUMBER('Other demand'!K12),'Other demand'!K12/1,"") | L15: =IF(ISNUMBER('Other demand'!L12),'Other demand'!L12/1,"") | M15: =IF(ISNUMBER('Other demand'!M12),'Other demand'!M12/1,"") | ... S15: =IF(ISNUMBER('Other demand'!S12),'Other demand'!S12/1,"") | T15: 2026 vintage; current high_demand case; provisional. | U15: Other demand row 12 → Model run → Python engine | V15: Validate inputs and reconcile against observed data.
A16: Agricultural diesel | B16: million L/year | C16: Model output | E16: GDP/capita method; provisional 2024 fuel baseline. [N009] | F16: =IF(ISNUMBER('Agriculture'!F13),'Agriculture'!F13/1,"") | G16: =IF(ISNUMBER('Agriculture'!G13),'Agriculture'!G13/1,"") | H16: =IF(ISNUMBER('Agriculture'!H13),'Agriculture'!H13/1,"") | I16: =IF(ISNUMBER('Agriculture'!I13),'Agriculture'!I13/1,"") | J16: =IF(ISNUMBER('Agriculture'!J13),'Agriculture'!J13/1,"") | K16: =IF(ISNUMBER('Agriculture'!K13),'Agriculture'!K13/1,"") | L16: =IF(ISNUMBER('Agriculture'!L13),'Agriculture'!L13/1,"") | M16: =IF(ISNUMBER('Agriculture'!M13),'Agriculture'!M13/1,"") | ... S16: =IF(ISNUMBER('Agriculture'!S13),'Agriculture'!S13/1,"") | T16: 2026 vintage; current high_demand case; provisional. | U16: Agriculture row 13 → Model run → Python engine | V16: Validate inputs and reconcile against observed data.
A17: Combined industrial diesel | B17: million L/year | C17: Model output | E17: Manufacturing + mining + construction combined. [N010] | F17: =IF(ISNUMBER('Manufacturing'!F24),'Manufacturing'!F24/1,"") | G17: =IF(ISNUMBER('Manufacturing'!G24),'Manufacturing'!G24/1,"") | H17: =IF(ISNUMBER('Manufacturing'!H24),'Manufacturing'!H24/1,"") | I17: =IF(ISNUMBER('Manufacturing'!I24),'Manufacturing'!I24/1,"") | J17: =IF(ISNUMBER('Manufacturing'!J24),'Manufacturing'!J24/1,"") | K17: =IF(ISNUMBER('Manufacturing'!K24),'Manufacturing'!K24/1,"") | L17: =IF(ISNUMBER('Manufacturing'!L24),'Manufacturing'!L24/1,"") | M17: =IF(ISNUMBER('Manufacturing'!M24),'Manufacturing'!M24/1,"") | ... S17: =IF(ISNUMBER('Manufacturing'!S24),'Manufacturing'!S24/1,"") | T17: 2026 vintage; current high_demand case; provisional. | U17: Manufacturing row 24 → Model run → Python engine | V17: Validate inputs and reconcile against observed data.
A18: Marine diesel | B18: million L/year | C18: Model output | E18: Marine diesel; 2022–23 model history unavailable. [N011] | F18: =IF(ISNUMBER('Other demand'!F34),'Other demand'!F34/1,"") | G18: =IF(ISNUMBER('Other demand'!G34),'Other demand'!G34/1,"") | H18: =IF(ISNUMBER('Other demand'!H34),'Other demand'!H34/1,"") | I18: =IF(ISNUMBER('Other demand'!I34),'Other demand'!I34/1,"") | J18: =IF(ISNUMBER('Other demand'!J34),'Other demand'!J34/1,"") | K18: =IF(ISNUMBER('Other demand'!K34),'Other demand'!K34/1,"") | L18: =IF(ISNUMBER('Other demand'!L34),'Other demand'!L34/1,"") | M18: =IF(ISNUMBER('Other demand'!M34),'Other demand'!M34/1,"") | ... S18: =IF(ISNUMBER('Other demand'!S34),'Other demand'!S34/1,"") | T18: 2026 vintage; current high_demand case; provisional. | U18: Other demand row 34 → Model run → Python engine | V18: Validate inputs and reconcile against observed data.
A19: Total model diesel | B19: million L/year | C19: Reporting formula | E19: Sum road, OCGT, agriculture, industry and marine. [N012] | F19: =IF(COUNT(F14:F18)<5,"",SUM(F14:F18)) | G19: =IF(COUNT(G14:G18)<5,"",SUM(G14:G18)) | H19: =IF(COUNT(H14:H18)<5,"",SUM(H14:H18)) | I19: =IF(COUNT(I14:I18)<5,"",SUM(I14:I18)) | J19: =IF(COUNT(J14:J18)<5,"",SUM(J14:J18)) | K19: =IF(COUNT(K14:K18)<5,"",SUM(K14:K18)) | L19: =IF(COUNT(L14:L18)<5,"",SUM(L14:L18)) | M19: =IF(COUNT(M14:M18)<5,"",SUM(M14:M18)) | ... S19: =IF(COUNT(S14:S18)<5,"",SUM(S14:S18)) | T19: Blank if any component is missing. | V19: G01/G12: reconcile domestic sales and bunkers.
A20: Model less selected historical sales | B20: million L/year | C20: Reporting formula | E20: Model minus selected sales; scope requires reconciliation. [N013] | F20: =IF(COUNT(F12,F19)<2,"",F19-F12) | G20: =IF(COUNT(G12,G19)<2,"",G19-G12) | H20: =IF(COUNT(H12,H19)<2,"",H19-H12) | I20: =IF(COUNT(I12,I19)<2,"",I19-I12) | J20: =IF(COUNT(J12,J19)<2,"",J19-J12) | K20: =IF(COUNT(K12,K19)<2,"",K19-K12) | L20: =IF(COUNT(L12,L19)<2,"",L19-L12) | M20: =IF(COUNT(M12,M19)<2,"",M19-M12) | ... S20: =IF(COUNT(S12,S19)<2,"",S19-S12) | T20: Only matched available years. | V20: G01: reconcile units, coverage and sales basis.
A21: Manufacturing-only baseline | B21: million L/year | C21: Missing input | E21: Included within industrial total; separate baseline missing. [N014] | T21: No matched observed 2022+ fuel series located. | U21: https://github.com/Africa-International-Advisors/liq… [N015] | V21: G06: reconcile manufacturing subsectors and scope.
A22: Mining-only baseline | B22: million L/year | C22: Missing input | D22: =IF(ISNUMBER('Mining'!D31),'Mining'!D31,"") | E22: 2021 anchor only; included within industrial total. [N016] | T22: 2021 anchor available; 2022+ fuel series missing. | U22: https://github.com/Africa-International-Advisors/liq… [N017] | V22: G07: verify site/end-use coverage and newer fuel data.
A23: Private backup / other diesel | B23: million L/year | C23: Missing input | E23: Baseline and sector overlap unresolved. [N018] | T23: Separate coverage and baseline unresolved. | V23: G09: source fuel/generation evidence; count once.
A25: Jet: national product comparison
A26: Selected historical jet sales | B26: million L/year | C26: Linked observation | E26: Selected historical sales; see Source selection. [N019] | F26: =IF(ISNUMBER('Source selection'!F15),'Source selection'!F15,"") | G26: =IF(ISNUMBER('Source selection'!F16),'Source selection'!F16,"") | H26: =IF(ISNUMBER('Source selection'!F17),'Source selection'!F17,"") | I26: =IF(ISNUMBER('Source selection'!F18),'Source selection'!F18,"") | J26: =IF(ISNUMBER('Source selection'!F19),'Source selection'!F19,"") | T26: Working comparator; not approved | U26: Source selection → Evidence | V26: Manish reconciles scope/revisions; Nigel accepts source.
A27: Historical source / status | B27: text | C27: Selection status | E27: Selected source, or unresolved when unavailable. [N020] | F27: =IF(ISNUMBER('Source selection'!F15),'Source selection'!E15,"Unresolved") | G27: =IF(ISNUMBER('Source selection'!F16),'Source selection'!E16,"Unresolved") | H27: =IF(ISNUMBER('Source selection'!F17),'Source selection'!E17,"Unresolved") | I27: =IF(ISNUMBER('Source selection'!F18),'Source selection'!E18,"Unresolved") | J27: =IF(ISNUMBER('Source selection'!F19),'Source selection'!E19,"Unresolved") | T27: Not an additional demand series | U27: Source selection | V27: Review selected source before calibration.
A28: Current model jet | B28: million L/year | C28: Model output | E28: GDP/capita and passenger regression. [N021] | F28: =IF(ISNUMBER('Other demand'!F20),'Other demand'!F20/1,"") | G28: =IF(ISNUMBER('Other demand'!G20),'Other demand'!G20/1,"") | H28: =IF(ISNUMBER('Other demand'!H20),'Other demand'!H20/1,"") | I28: =IF(ISNUMBER('Other demand'!I20),'Other demand'!I20/1,"") | J28: =IF(ISNUMBER('Other demand'!J20),'Other demand'!J20/1,"") | K28: =IF(ISNUMBER('Other demand'!K20),'Other demand'!K20/1,"") | L28: =IF(ISNUMBER('Other demand'!L20),'Other demand'!L20/1,"") | M28: =IF(ISNUMBER('Other demand'!M20),'Other demand'!M20/1,"") | ... S28: =IF(ISNUMBER('Other demand'!S20),'Other demand'!S20/1,"") | T28: 2026 vintage; current high_demand case; provisional. | U28: Other demand row 20 → Model run → Python engine | V28: Validate inputs and reconcile against observed data.
A29: Model less selected historical sales | B29: million L/year | C29: Reporting formula | E29: Model minus selected sales; reconcile coverage. [N022] | F29: =IF(COUNT(F26,F28)<2,"",F28-F26) | G29: =IF(COUNT(G26,G28)<2,"",G28-G26) | H29: =IF(COUNT(H26,H28)<2,"",H28-H26) | I29: =IF(COUNT(I26,I28)<2,"",I28-I26) | J29: =IF(COUNT(J26,J28)<2,"",J28-J26) | K29: =IF(COUNT(K26,K28)<2,"",K28-K26) | L29: =IF(COUNT(L26,L28)<2,"",L28-L26) | M29: =IF(COUNT(M26,M28)<2,"",M28-M26) | ... S29: =IF(COUNT(S26,S28)<2,"",S28-S26) | T29: Only where both values exist. | V29: G10: calibrate aircraft/airport coverage.
A31: Marine fuel oil: scope is narrower than total national fuel oil
A32: Selected historical fuel oil sales | B32: million L/year | C32: Linked observation | E32: National fuel-oil sales; includes more than marine. [N023] | F32: =IF(ISNUMBER('Source selection'!F20),'Source selection'!F20,"") | G32: =IF(ISNUMBER('Source selection'!F21),'Source selection'!F21,"") | H32: =IF(ISNUMBER('Source selection'!F22),'Source selection'!F22,"") | I32: =IF(ISNUMBER('Source selection'!F23),'Source selection'!F23,"") | J32: =IF(ISNUMBER('Source selection'!F24),'Source selection'!F24,"") | T32: Working comparator; not approved | U32: Source selection → Evidence | V32: Manish reconciles scope/revisions; Nigel accepts source.
A33: Current model marine fuel oil | B33: million L/year | C33: Model output | E33: Marine fuel oil only; narrower than national sales. [N024] | F33: =IF(ISNUMBER('Other demand'!F35),'Other demand'!F35/1,"") | G33: =IF(ISNUMBER('Other demand'!G35),'Other demand'!G35/1,"") | H33: =IF(ISNUMBER('Other demand'!H35),'Other demand'!H35/1,"") | I33: =IF(ISNUMBER('Other demand'!I35),'Other demand'!I35/1,"") | J33: =IF(ISNUMBER('Other demand'!J35),'Other demand'!J35/1,"") | K33: =IF(ISNUMBER('Other demand'!K35),'Other demand'!K35/1,"") | L33: =IF(ISNUMBER('Other demand'!L35),'Other demand'!L35/1,"") | M33: =IF(ISNUMBER('Other demand'!M35),'Other demand'!M35/1,"") | ... S33: =IF(ISNUMBER('Other demand'!S35),'Other demand'!S35/1,"") | T33: 2026 vintage; current high_demand case; provisional. | U33: Other demand row 35 → Model run → Python engine | V33: Validate inputs and reconcile against observed data.
A35: Baseline selection | B35: decision | C35: Missing input | E35: Historical comparator selection is explicit on Source selection.… [N025] | T35: Review before calibration. | V35: Nigel selects baseline after Manish reconciliation.
A36: Latest partial periods | B36: reading note | C36: Evidence note | E36: Full annual observations occupy year columns. A separate D value… [N026] | T36: FY OCGT explicitly uses year ending March. | V36: Do not annualise partial 2026 observations silently.
A37: Run provenance | B37: record | C37: Evidence note | E37: Commit 8c69f8333192483f19cd80911cb90fcd0943eb6b; vintage 2026;… [N027] | T37: 54 open governance exceptions at preparation. | U37: https://github.com/Africa-International-Advisors/liq… [N028] | V37: Outputs remain provisional.

Sheet Source selection
A1: Source selection
A2: Working comparator choice per fuel/year • FIASA retains the previous comparison; no business approval inferred.
A4: Product | B4: Year | C4: FIASA candidate | D4: Department candidate | E4: Working selection | F4: Selected million L | G4: Availability / review | H4: Owner | I4: Decision basis | J4: Review trigger
A5: petrol | B5: 2022 | C5: =IF(ISNUMBER('Evidence'!F5),'Evidence'!F5,"") | D5: =IF(ISNUMBER('Evidence'!F6),'Evidence'!F6,"") | E5: Department | F5: =IF(E5="FIASA",IF(ISNUMBER(C5),C5,""),IF(E5="Department",IF(ISNUMBER(D5),D5,""),"")) | G5: =IF(E5="Unresolved","No source selected",IF(ISNUMBER(F5),"Working choice - awaiting review","Selected source missing")) | H5: Nigel / Manish | I5: Working comparator only; retain prior FIASA comparison pending reconciliation. | J5: Before baseline acceptance
A6: petrol | B6: 2023 | C6: =IF(ISNUMBER('Evidence'!G5),'Evidence'!G5,"") | D6: =IF(ISNUMBER('Evidence'!G6),'Evidence'!G6,"") | E6: Department | F6: =IF(E6="FIASA",IF(ISNUMBER(C6),C6,""),IF(E6="Department",IF(ISNUMBER(D6),D6,""),"")) | G6: =IF(E6="Unresolved","No source selected",IF(ISNUMBER(F6),"Working choice - awaiting review","Selected source missing")) | H6: Nigel / Manish | I6: Working comparator only; retain prior FIASA comparison pending reconciliation. | J6: Before baseline acceptance
A7: petrol | B7: 2024 | C7: =IF(ISNUMBER('Evidence'!H5),'Evidence'!H5,"") | D7: =IF(ISNUMBER('Evidence'!H6),'Evidence'!H6,"") | E7: FIASA | F7: =IF(E7="FIASA",IF(ISNUMBER(C7),C7,""),IF(E7="Department",IF(ISNUMBER(D7),D7,""),"")) | G7: =IF(E7="Unresolved","No source selected",IF(ISNUMBER(F7),"Working choice - awaiting review","Selected source missing")) | H7: Nigel / Manish | I7: Working comparator only; retain prior FIASA comparison pending reconciliation. | J7: Before baseline acceptance
A8: petrol | B8: 2025 | C8: =IF(ISNUMBER('Evidence'!I5),'Evidence'!I5,"") | D8: =IF(ISNUMBER('Evidence'!I6),'Evidence'!I6,"") | E8: Unresolved | F8: =IF(E8="FIASA",IF(ISNUMBER(C8),C8,""),IF(E8="Department",IF(ISNUMBER(D8),D8,""),"")) | G8: =IF(E8="Unresolved","No source selected",IF(ISNUMBER(F8),"Working choice - awaiting review","Selected source missing")) | H8: Nigel / Manish | I8: Working comparator only; retain prior FIASA comparison pending reconciliation. | J8: Before baseline acceptance
A9: petrol | B9: 2026 | C9: =IF(ISNUMBER('Evidence'!J5),'Evidence'!J5,"") | D9: =IF(ISNUMBER('Evidence'!J6),'Evidence'!J6,"") | E9: Unresolved | F9: =IF(E9="FIASA",IF(ISNUMBER(C9),C9,""),IF(E9="Department",IF(ISNUMBER(D9),D9,""),"")) | G9: =IF(E9="Unresolved","No source selected",IF(ISNUMBER(F9),"Working choice - awaiting review","Selected source missing")) | H9: Nigel / Manish | I9: Working comparator only; retain prior FIASA comparison pending reconciliation. | J9: Before baseline acceptance
A10: diesel | B10: 2022 | C10: =IF(ISNUMBER('Evidence'!F7),'Evidence'!F7,"") | D10: =IF(ISNUMBER('Evidence'!F8),'Evidence'!F8,"") | E10: Department | F10: =IF(E10="FIASA",IF(ISNUMBER(C10),C10,""),IF(E10="Department",IF(ISNUMBER(D10),D10,""),"")) | G10: =IF(E10="Unresolved","No source selected",IF(ISNUMBER(F10),"Working choice - awaiting review","Selected source missing")) | H10: Nigel / Manish | I10: Working comparator only; retain prior FIASA comparison pending reconciliation. | J10: Before baseline acceptance
A11: diesel | B11: 2023 | C11: =IF(ISNUMBER('Evidence'!G7),'Evidence'!G7,"") | D11: =IF(ISNUMBER('Evidence'!G8),'Evidence'!G8,"") | E11: Department | F11: =IF(E11="FIASA",IF(ISNUMBER(C11),C11,""),IF(E11="Department",IF(ISNUMBER(D11),D11,""),"")) | G11: =IF(E11="Unresolved","No source selected",IF(ISNUMBER(F11),"Working choice - awaiting review","Selected source missing")) | H11: Nigel / Manish | I11: Working comparator only; retain prior FIASA comparison pending reconciliation. | J11: Before baseline acceptance
A12: diesel | B12: 2024 | C12: =IF(ISNUMBER('Evidence'!H7),'Evidence'!H7,"") | D12: =IF(ISNUMBER('Evidence'!H8),'Evidence'!H8,"") | E12: FIASA | F12: =IF(E12="FIASA",IF(ISNUMBER(C12),C12,""),IF(E12="Department",IF(ISNUMBER(D12),D12,""),"")) | G12: =IF(E12="Unresolved","No source selected",IF(ISNUMBER(F12),"Working choice - awaiting review","Selected source missing")) | H12: Nigel / Manish | I12: Working comparator only; retain prior FIASA comparison pending reconciliation. | J12: Before baseline acceptance
A13: diesel | B13: 2025 | C13: =IF(ISNUMBER('Evidence'!I7),'Evidence'!I7,"") | D13: =IF(ISNUMBER('Evidence'!I8),'Evidence'!I8,"") | E13: Unresolved | F13: =IF(E13="FIASA",IF(ISNUMBER(C13),C13,""),IF(E13="Department",IF(ISNUMBER(D13),D13,""),"")) | G13: =IF(E13="Unresolved","No source selected",IF(ISNUMBER(F13),"Working choice - awaiting review","Selected source missing")) | H13: Nigel / Manish | I13: Working comparator only; retain prior FIASA comparison pending reconciliation. | J13: Before baseline acceptance
A14: diesel | B14: 2026 | C14: =IF(ISNUMBER('Evidence'!J7),'Evidence'!J7,"") | D14: =IF(ISNUMBER('Evidence'!J8),'Evidence'!J8,"") | E14: Unresolved | F14: =IF(E14="FIASA",IF(ISNUMBER(C14),C14,""),IF(E14="Department",IF(ISNUMBER(D14),D14,""),"")) | G14: =IF(E14="Unresolved","No source selected",IF(ISNUMBER(F14),"Working choice - awaiting review","Selected source missing")) | H14: Nigel / Manish | I14: Working comparator only; retain prior FIASA comparison pending reconciliation. | J14: Before baseline acceptance
A15: jet | B15: 2022 | C15: =IF(ISNUMBER('Evidence'!F9),'Evidence'!F9,"") | D15: =IF(ISNUMBER('Evidence'!F10),'Evidence'!F10,"") | E15: Department | F15: =IF(E15="FIASA",IF(ISNUMBER(C15),C15,""),IF(E15="Department",IF(ISNUMBER(D15),D15,""),"")) | G15: =IF(E15="Unresolved","No source selected",IF(ISNUMBER(F15),"Working choice - awaiting review","Selected source missing")) | H15: Nigel / Manish | I15: Working comparator only; retain prior FIASA comparison pending reconciliation. | J15: Before baseline acceptance
A16: jet | B16: 2023 | C16: =IF(ISNUMBER('Evidence'!G9),'Evidence'!G9,"") | D16: =IF(ISNUMBER('Evidence'!G10),'Evidence'!G10,"") | E16: Department | F16: =IF(E16="FIASA",IF(ISNUMBER(C16),C16,""),IF(E16="Department",IF(ISNUMBER(D16),D16,""),"")) | G16: =IF(E16="Unresolved","No source selected",IF(ISNUMBER(F16),"Working choice - awaiting review","Selected source missing")) | H16: Nigel / Manish | I16: Working comparator only; retain prior FIASA comparison pending reconciliation. | J16: Before baseline acceptance
A17: jet | B17: 2024 | C17: =IF(ISNUMBER('Evidence'!H9),'Evidence'!H9,"") | D17: =IF(ISNUMBER('Evidence'!H10),'Evidence'!H10,"") | E17: FIASA | F17: =IF(E17="FIASA",IF(ISNUMBER(C17),C17,""),IF(E17="Department",IF(ISNUMBER(D17),D17,""),"")) | G17: =IF(E17="Unresolved","No source selected",IF(ISNUMBER(F17),"Working choice - awaiting review","Selected source missing")) | H17: Nigel / Manish | I17: Working comparator only; retain prior FIASA comparison pending reconciliation. | J17: Before baseline acceptance
A18: jet | B18: 2025 | C18: =IF(ISNUMBER('Evidence'!I9),'Evidence'!I9,"") | D18: =IF(ISNUMBER('Evidence'!I10),'Evidence'!I10,"") | E18: Unresolved | F18: =IF(E18="FIASA",IF(ISNUMBER(C18),C18,""),IF(E18="Department",IF(ISNUMBER(D18),D18,""),"")) | G18: =IF(E18="Unresolved","No source selected",IF(ISNUMBER(F18),"Working choice - awaiting review","Selected source missing")) | H18: Nigel / Manish | I18: Working comparator only; retain prior FIASA comparison pending reconciliation. | J18: Before baseline acceptance
A19: jet | B19: 2026 | C19: =IF(ISNUMBER('Evidence'!J9),'Evidence'!J9,"") | D19: =IF(ISNUMBER('Evidence'!J10),'Evidence'!J10,"") | E19: Unresolved | F19: =IF(E19="FIASA",IF(ISNUMBER(C19),C19,""),IF(E19="Department",IF(ISNUMBER(D19),D19,""),"")) | G19: =IF(E19="Unresolved","No source selected",IF(ISNUMBER(F19),"Working choice - awaiting review","Selected source missing")) | H19: Nigel / Manish | I19: Working comparator only; retain prior FIASA comparison pending reconciliation. | J19: Before baseline acceptance
A20: fuel_oil | B20: 2022 | C20: =IF(ISNUMBER('Evidence'!F11),'Evidence'!F11,"") | D20: =IF(ISNUMBER('Evidence'!F12),'Evidence'!F12,"") | E20: Department | F20: =IF(E20="FIASA",IF(ISNUMBER(C20),C20,""),IF(E20="Department",IF(ISNUMBER(D20),D20,""),"")) | G20: =IF(E20="Unresolved","No source selected",IF(ISNUMBER(F20),"Working choice - awaiting review","Selected source missing")) | H20: Nigel / Manish | I20: Working comparator only; retain prior FIASA comparison pending reconciliation. | J20: Before baseline acceptance
A21: fuel_oil | B21: 2023 | C21: =IF(ISNUMBER('Evidence'!G11),'Evidence'!G11,"") | D21: =IF(ISNUMBER('Evidence'!G12),'Evidence'!G12,"") | E21: Department | F21: =IF(E21="FIASA",IF(ISNUMBER(C21),C21,""),IF(E21="Department",IF(ISNUMBER(D21),D21,""),"")) | G21: =IF(E21="Unresolved","No source selected",IF(ISNUMBER(F21),"Working choice - awaiting review","Selected source missing")) | H21: Nigel / Manish | I21: Working comparator only; retain prior FIASA comparison pending reconciliation. | J21: Before baseline acceptance
A22: fuel_oil | B22: 2024 | C22: =IF(ISNUMBER('Evidence'!H11),'Evidence'!H11,"") | D22: =IF(ISNUMBER('Evidence'!H12),'Evidence'!H12,"") | E22: FIASA | F22: =IF(E22="FIASA",IF(ISNUMBER(C22),C22,""),IF(E22="Department",IF(ISNUMBER(D22),D22,""),"")) | G22: =IF(E22="Unresolved","No source selected",IF(ISNUMBER(F22),"Working choice - awaiting review","Selected source missing")) | H22: Nigel / Manish | I22: Working comparator only; retain prior FIASA comparison pending reconciliation. | J22: Before baseline acceptance
A23: fuel_oil | B23: 2025 | C23: =IF(ISNUMBER('Evidence'!I11),'Evidence'!I11,"") | D23: =IF(ISNUMBER('Evidence'!I12),'Evidence'!I12,"") | E23: Unresolved | F23: =IF(E23="FIASA",IF(ISNUMBER(C23),C23,""),IF(E23="Department",IF(ISNUMBER(D23),D23,""),"")) | G23: =IF(E23="Unresolved","No source selected",IF(ISNUMBER(F23),"Working choice - awaiting review","Selected source missing")) | H23: Nigel / Manish | I23: Working comparator only; retain prior FIASA comparison pending reconciliation. | J23: Before baseline acceptance
A24: fuel_oil | B24: 2026 | C24: =IF(ISNUMBER('Evidence'!J11),'Evidence'!J11,"") | D24: =IF(ISNUMBER('Evidence'!J12),'Evidence'!J12,"") | E24: Unresolved | F24: =IF(E24="FIASA",IF(ISNUMBER(C24),C24,""),IF(E24="Department",IF(ISNUMBER(D24),D24,""),"")) | G24: =IF(E24="Unresolved","No source selected",IF(ISNUMBER(F24),"Working choice - awaiting review","Selected source missing")) | H24: Nigel / Manish | I24: Working comparator only; retain prior FIASA comparison pending reconciliation. | J24: Before baseline acceptance

Sheet Methods
A1: Demand methods by segment
A2: Agree the method and geographic definition before choosing numerical ranges.
A4: Product / segment | B4: Current model | C4: Proposed direction | D4: National / provincial treatment | E4: Boundary and overlap check | F4: Evidence / workshop decision
A5: Petrol passenger | B5: National passenger/LCV/HCV cohort model; GDP/capita predicts sales. EV uptake, scrappage, km and fixed cohort efficiency determine litres. | C5: Retain cohort logic; calibrate opening stock and sales. Separate BEV, PHEV and conventional hybrid. | D5: Allocate national totals initially; local stock/activity calculations when evidence supports them. | E5: New-sales shares are not fleet shares. Apply efficiency improvements to new cohorts only. | F5: Confirm opening stock, drivetrain basis, survival and mileage. Sources: vehicles.yaml; vehicles.py.
A6: Diesel road freight | B6: Heavy-commercial diesel cohort calculation; LCV activity also includes freight and other uses. | C6: Choose fleet or tonne-km method. Separate diesel, BEV and hybrid trucks by duty cycle; sales feed cohorts, and work shares reflect mileage/payload. | D6: Define province of fuel purchase versus consumption/corridor. Registrations alone do not locate fuel use. | E6: Do not add the two methods. Deduct rail diversion once. Separate mining off-road from road trucks. | F6: Agree freight/LCV scope, truck BEV/hybrid paths, payload, empty running and charging feasibility. See Freight rows 30–45.
A7: Other road demand | B7: Passenger and LCV diesel, and LCV petrol, sit in the vehicle model. | C7: Retain class-specific calculations and identify buses/taxis explicitly where evidence allows. | D7: National control totals; documented local allocation or fleet method. | E7: Do not omit non-freight diesel when reporting national diesel demand. | F7: Clarify which vehicle classes include taxis/buses and commercial passenger services.
A8: Diesel agriculture | B8: Held baseline × (GDP/capita ratio)^elasticity. 2024 baseline 700 million L; elasticity 0.2. Both provisional. | C8: Reconciled baseline × agricultural activity ratio × relative fuel intensity. Select crops/hectares/output or subsegments. | D8: Provincial agricultural activity allocates baseline and drives changes; national total sums local results. | E8: Separate machinery, irrigation, road vehicles and backup generation. | F8: Choose source/baseline year and activity proxy; agree whether intensity already includes mechanisation.
A9: Diesel manufacturing | B9: Current combined industrial bucket includes manufacturing, mining and construction; no separate manufacturing output. | C9: Separate manufacturing baseline × production/activity × relative intensity × remaining diesel fraction. | D9: Local manufacturing/site activity where evidenced; retain unknown coverage. | E9: Separate process/equipment diesel from road freight and backup generation. Electrification is counted once. | F9: See Manufacturing. Split/revise the combined baseline explicitly and retain construction/other.
A10: Diesel generation | B10: National OCGT capacity/load factor/efficiency pathway. | C10: Plant generation × fuel per kWh; grid plants and private backup separately. | D10: Grid plants assigned by location; private backup needs an evidenced allocation. | E10: No second load-shedding increment if already in generation. Fiscal/calendar and plant coverage must match. | F10: Fit generation-to-litres; agree dispatch and private-backup evidence.
A11: Jet aviation | B11: Legacy passenger regression; movement-driver proposal awaits refit. | C11: Aircraft activity × calibrated fuel relationship including aircraft/route mix. | D11: Airport-level evidence preferred; sum airports and retain unallocated coverage. | E11: Distinguish fuel uplift from overflight/use. Cargo, non-ACSA and international scope explicit. | F11: Match movements with jet deliveries. SAF changes fossil share, not total jet litres by itself.
A12: Marine / other | B12: Held marine baseline, GDP response and product split; other uses need a coverage review. | C12: Port/vessel activity × fuel intensity or reconciled indexed baseline. | D12: Port evidence where available; unknown location remains unallocated. | E12: Define domestic versus international bunkers; diesel grade and fuel oil stay explicit. | F12: Agree coverage and identify residual demand without treating the residual as a new measured segment.
A13: Cross-cutting rule | B13: One fuel total must reconcile across all included segments. | C13: National total = provinces + explicitly unallocated demand. | D13: Use one approach per segment: allocated or locally calculated. | E13: Do not reallocate a component already calculated provincially. GDP must not multiply several overlapping effects. | F13: Source: https://github.com/Africa-International-Advisors/liquid_fuels_model/blob/8c69f8333192483f19cd80911cb90fcd0943eb6b/workstreams/WS0_governance/workplan/fuel_lever_review_2026-10-07.md
A14: Diesel mining | B14: Current combined industrial bucket; no separate mining output. | C14: Mining baseline × activity × operating intensity × remaining diesel fraction; fit sites/subsectors where possible. | D14: Mine-site geography and activity; explicit unallocated remainder. | E14: Separate mine-site/off-road work from public-road freight; backup fuel belongs to one segment. | F14: See Mining. Review commodity output versus material moved and mine-equipment electrification.

Sheet Petrol
A1: Petrol passenger demand
A2: Current national high_demand case • Values are provisional model inputs/outputs, not observed demand.
A4: Driver / output | B4: Unit | C4: Role | D4: Scalar / latest value | E4: Definition / period | F4: 2022 | G4: 2023 | H4: 2024 | I4: 2025 | J4: 2026 | K4: 2027 | L4: 2028 | M4: 2029 | N4: 2030 | O4: 2031 | P4: 2032 | Q4: 2033 | R4: 2034 | S4: 2035 | T4: Coverage / status | U4: Source | V4: Missing evidence / next action
A5: Current engine inputs
A6: GDP per capita | B6: 2015 ZAR/person | C6: Input series | E6: Shared macro driver. Model forecasts beyond the source observation window. | F6: =IF(ISNUMBER('Model run'!F5),'Model run'!F5,"") | G6: =IF(ISNUMBER('Model run'!G5),'Model run'!G5,"") | H6: =IF(ISNUMBER('Model run'!H5),'Model run'!H5,"") | I6: =IF(ISNUMBER('Model run'!I5),'Model run'!I5,"") | J6: =IF(ISNUMBER('Model run'!J5),'Model run'!J5,"") | K6: =IF(ISNUMBER('Model run'!K5),'Model run'!K5,"") | L6: =IF(ISNUMBER('Model run'!L5),'Model run'!L5,"") | M6: =IF(ISNUMBER('Model run'!M5),'Model run'!M5,"") | ... S6: =IF(ISNUMBER('Model run'!S5),'Model run'!S5,"")
A7: New-sales regression slope | B7: vehicles / ZAR pc | C7: Scalar | D7: =IF(ISNUMBER('Model run'!D6),'Model run'!D6,"") | E7: Sales = max(0, slope × GDP/capita + intercept). Applies to all new vehicles.
A8: New-sales regression intercept | B8: vehicles/year | C8: Scalar | D8: =IF(ISNUMBER('Model run'!D7),'Model run'!D7,"") | E8: Legacy fitted parameter; historical validity needs review.
A9: Passenger share of new sales | B9: share | C9: Scalar | D9: =IF(ISNUMBER('Model run'!D8),'Model run'!D8,"") | E9: Current provisional split of total modelled new sales.
A10: Petrol share of passenger ICE sales | B10: share | C10: Scalar | D10: =IF(ISNUMBER('Model run'!D9),'Model run'!D9,"") | E10: Applies after current EV adjustment. Hybrids are not separately modelled.
A11: Passenger annual mileage | B11: km/vehicle/year | C11: Scalar | D11: =IF(ISNUMBER('Model run'!D10),'Model run'!D10,"") | E11: Current placeholder. Proposed HML brackets appear on HML sheet.
A12: Passenger retirement rate | B12: share/year | C12: Scalar | D12: =IF(ISNUMBER('Model run'!D11),'Model run'!D11,"") | E12: Current engine scraps all cohorts, including additions, within the year.
A13: Base new petrol vehicle consumption | B13: L/100 km | C13: Scalar | D13: =IF(ISNUMBER('Model run'!D12),'Model run'!D12,"") | E13: Entry-cohort baseline before cumulative efficiency gains.
A14: New-cohort efficiency gain | B14: fraction/year | C14: Input series | E14: Applied cumulatively to new cohorts; older cohorts retain their… [N029] | F14: =IF(ISNUMBER('Model run'!F13),'Model run'!F13,"") | G14: =IF(ISNUMBER('Model run'!G13),'Model run'!G13,"") | H14: =IF(ISNUMBER('Model run'!H13),'Model run'!H13,"") | I14: =IF(ISNUMBER('Model run'!I13),'Model run'!I13,"") | J14: =IF(ISNUMBER('Model run'!J13),'Model run'!J13,"") | K14: =IF(ISNUMBER('Model run'!K13),'Model run'!K13,"") | L14: =IF(ISNUMBER('Model run'!L13),'Model run'!L13,"") | M14: =IF(ISNUMBER('Model run'!M13),'Model run'!M13,"") | ... S14: =IF(ISNUMBER('Model run'!S13),'Model run'!S13,"")
A15: EV curve ceiling | B15: share | C15: Parameter | D15: =IF(ISNUMBER('Model run'!D14),'Model run'!D14,"") | E15: Current logistic curve parameter. Proposed BEV sales ranges are separate.
A16: EV curve midpoint / slope | B16: year / years | C16: Parameters | E16: 2040 / 3. Confirm sales basis and replace with reviewed drivetrain paths.
A17: Current engine outputs and reporting calculations
A18: Passenger petrol fleet | B18: vehicles | C18: Engine output | E18: Cohort stock from engine diagnostics. Opening stock is… [N030] | F18: =IF(ISNUMBER('Model run'!F15),'Model run'!F15,"") | G18: =IF(ISNUMBER('Model run'!G15),'Model run'!G15,"") | H18: =IF(ISNUMBER('Model run'!H15),'Model run'!H15,"") | I18: =IF(ISNUMBER('Model run'!I15),'Model run'!I15,"") | J18: =IF(ISNUMBER('Model run'!J15),'Model run'!J15,"") | K18: =IF(ISNUMBER('Model run'!K15),'Model run'!K15,"") | L18: =IF(ISNUMBER('Model run'!L15),'Model run'!L15,"") | M18: =IF(ISNUMBER('Model run'!M15),'Model run'!M15,"") | ... S18: =IF(ISNUMBER('Model run'!S15),'Model run'!S15,"")
A19: Passenger petrol vehicle-km | B19: km/year | C19: Engine output | E19: Engine diagnostic activity for petrol passenger cohorts. | F19: =IF(ISNUMBER('Model run'!F16),'Model run'!F16,"") | G19: =IF(ISNUMBER('Model run'!G16),'Model run'!G16,"") | H19: =IF(ISNUMBER('Model run'!H16),'Model run'!H16,"") | I19: =IF(ISNUMBER('Model run'!I16),'Model run'!I16,"") | J19: =IF(ISNUMBER('Model run'!J16),'Model run'!J16,"") | K19: =IF(ISNUMBER('Model run'!K16),'Model run'!K16,"") | L19: =IF(ISNUMBER('Model run'!L16),'Model run'!L16,"") | M19: =IF(ISNUMBER('Model run'!M16),'Model run'!M16,"") | ... S19: =IF(ISNUMBER('Model run'!S16),'Model run'!S16,"")
A20: Passenger petrol demand | B20: L/year | C20: Engine output | E20: Calculated by the Python cohort engine. | F20: =IF(ISNUMBER('Model run'!F17),'Model run'!F17,"") | G20: =IF(ISNUMBER('Model run'!G17),'Model run'!G17,"") | H20: =IF(ISNUMBER('Model run'!H17),'Model run'!H17,"") | I20: =IF(ISNUMBER('Model run'!I17),'Model run'!I17,"") | J20: =IF(ISNUMBER('Model run'!J17),'Model run'!J17,"") | K20: =IF(ISNUMBER('Model run'!K17),'Model run'!K17,"") | L20: =IF(ISNUMBER('Model run'!L17),'Model run'!L17,"") | M20: =IF(ISNUMBER('Model run'!M17),'Model run'!M17,"") | ... S20: =IF(ISNUMBER('Model run'!S17),'Model run'!S17,"")
A21: Passenger petrol demand | B21: million L/year | C21: Reporting formula | E21: Unit conversion of the engine output. | F21: =F20/1000000 | G21: =G20/1000000 | H21: =H20/1000000 | I21: =I20/1000000 | J21: =J20/1000000 | K21: =K20/1000000 | L21: =L20/1000000 | M21: =M20/1000000 | ... S21: =S20/1000000
A22: Implied fleet-average consumption | B22: L/100 km | C22: Reporting formula | E22: Fuel / vehicle-km × 100. Reporting diagnostic, not new-cohort consumption. | F22: =IF(F19=0,"",F20/F19*100) | G22: =IF(G19=0,"",G20/G19*100) | H22: =IF(H19=0,"",H20/H19*100) | I22: =IF(I19=0,"",I20/I19*100) | J22: =IF(J19=0,"",J20/J19*100) | K22: =IF(K19=0,"",K20/K19*100) | L22: =IF(L19=0,"",L20/L19*100) | M22: =IF(M19=0,"",M20/M19*100) | ... S22: =IF(S19=0,"",S20/S19*100)
A23: All road petrol demand | B23: L/year | C23: Engine output | E23: Includes passenger and LCV petrol. Does not claim all-product/sector coverage. | F23: =IF(COUNT(F20,F46)<2,"",F20+F46) | G23: =IF(COUNT(G20,G46)<2,"",G20+G46) | H23: =IF(COUNT(H20,H46)<2,"",H20+H46) | I23: =IF(COUNT(I20,I46)<2,"",I20+I46) | J23: =IF(COUNT(J20,J46)<2,"",J20+J46) | K23: =IF(COUNT(K20,K46)<2,"",K20+K46) | L23: =IF(COUNT(L20,L46)<2,"",L20+L46) | M23: =IF(COUNT(M20,M46)<2,"",M20+M46) | ... S23: =IF(COUNT(S20,S46)<2,"",S20+S46)
A25: Proposed input/output rows to agree and populate
A26: New passenger sales / BEV share | B26: vehicles / share | C26: Workshop input | E26: New sales evidence is now in rows 35–41. Class-specific adoption… [N031]
A27: Verified opening fleet | B27: vehicles at date | C27: Workshop input | E27: All-drivetrain stock is in row 36. Petrol-only opening fleet and… [N032]
A28: Reported total petrol sales | B28: million L/year | C28: Staged observation | D28: =IF(ISNUMBER('Evidence'!D5),'Evidence'!D5,"") | E28: FIASA staged reported sales; latest edition selected by existing… [N033] | F28: =IF(ISNUMBER('Evidence'!F5),'Evidence'!F5,"") | G28: =IF(ISNUMBER('Evidence'!G5),'Evidence'!G5,"") | H28: =IF(ISNUMBER('Evidence'!H5),'Evidence'!H5,"") | I28: =IF(ISNUMBER('Evidence'!I5),'Evidence'!I5,"") | J28: =IF(ISNUMBER('Evidence'!J5),'Evidence'!J5,"") | K28: =IF(ISNUMBER('Evidence'!K5),'Evidence'!K5,"") | L28: =IF(ISNUMBER('Evidence'!L5),'Evidence'!L5,"") | M28: =IF(ISNUMBER('Evidence'!M5),'Evidence'!M5,"") | ... S28: =IF(ISNUMBER('Evidence'!S5),'Evidence'!S5,"") | T28: Unreviewed source extract; annual cells contain… [N034] | U28: Evidence row 5; assumptions/2026/timeseries/fuel_sales_fiasa.csv | V28: All-product comparator; compare with road total,… [N035]
A30: Source | B30: URL | C30: Source | E30: https://github.com/Africa-International-Advisors/liquid_fuels_mode… [N036]
A31: Calculation source | B31: URL | C31: Source | E31: https://github.com/Africa-International-Advisors/liquid_fuels_mode… [N037]
A32: Macro / efficiency sources | B32: URL | C32: Source | E32: https://github.com/Africa-International-Advisors/liquid_fuels_mode… [N038]
A34: Available historical evidence: separate from current engine inputs
A35: New passenger-car sales | B35: vehicles/year | C35: Staged observation | D35: =IF(ISNUMBER('Evidence'!D13),'Evidence'!D13,"") | E35: NAAMSA actual new sales. Published 2026/27 projections excluded… [N039] | F35: =IF(ISNUMBER('Evidence'!F13),'Evidence'!F13,"") | G35: =IF(ISNUMBER('Evidence'!G13),'Evidence'!G13,"") | H35: =IF(ISNUMBER('Evidence'!H13),'Evidence'!H13,"") | I35: =IF(ISNUMBER('Evidence'!I13),'Evidence'!I13,"") | J35: =IF(ISNUMBER('Evidence'!J13),'Evidence'!J13,"") | K35: =IF(ISNUMBER('Evidence'!K13),'Evidence'!K13,"") | L35: =IF(ISNUMBER('Evidence'!L13),'Evidence'!L13,"") | M35: =IF(ISNUMBER('Evidence'!M13),'Evidence'!M13,"") | ... S35: =IF(ISNUMBER('Evidence'!S13),'Evidence'!S13,"") | T35: Unreviewed source extract; annual cells contain… [N040] | U35: Evidence row 13;… [N041] | V35: G02: fit class-specific sales and compare with… [N042]
A36: Registered cars, all drivetrains | B36: vehicles | C36: Staged observation | D36: =IF(ISNUMBER('Evidence'!D20),'Evidence'!D20,"") | E36: eNaTIS December snapshots; latest June 2026 kept separately. No… [N043] | F36: =IF(ISNUMBER('Evidence'!F20),'Evidence'!F20,"") | G36: =IF(ISNUMBER('Evidence'!G20),'Evidence'!G20,"") | H36: =IF(ISNUMBER('Evidence'!H20),'Evidence'!H20,"") | I36: =IF(ISNUMBER('Evidence'!I20),'Evidence'!I20,"") | J36: =IF(ISNUMBER('Evidence'!J20),'Evidence'!J20,"") | K36: =IF(ISNUMBER('Evidence'!K20),'Evidence'!K20,"") | L36: =IF(ISNUMBER('Evidence'!L20),'Evidence'!L20,"") | M36: =IF(ISNUMBER('Evidence'!M20),'Evidence'!M20,"") | ... S36: =IF(ISNUMBER('Evidence'!S20),'Evidence'!S20,"") | T36: Unreviewed source extract; annual cells contain… [N044] | U36: Evidence row 20;… [N045] | V36: G02: obtain petrol/diesel/BEV/hybrid and age split.
A37: BEV new sales — all market | B37: vehicles/year | C37: Staged observation | D37: =IF(ISNUMBER('Evidence'!D17),'Evidence'!D17,"") | E37: All-market drivetrain sales; passenger/truck split is not… [N046] | F37: =IF(ISNUMBER('Evidence'!F17),'Evidence'!F17,"") | G37: =IF(ISNUMBER('Evidence'!G17),'Evidence'!G17,"") | H37: =IF(ISNUMBER('Evidence'!H17),'Evidence'!H17,"") | I37: =IF(ISNUMBER('Evidence'!I17),'Evidence'!I17,"") | J37: =IF(ISNUMBER('Evidence'!J17),'Evidence'!J17,"") | K37: =IF(ISNUMBER('Evidence'!K17),'Evidence'!K17,"") | L37: =IF(ISNUMBER('Evidence'!L17),'Evidence'!L17,"") | M37: =IF(ISNUMBER('Evidence'!M17),'Evidence'!M17,"") | ... S37: =IF(ISNUMBER('Evidence'!S17),'Evidence'!S17,"") | T37: Unreviewed source extract; annual cells contain… [N047] | U37: Evidence row 17;… [N048] | V37: G03: class split missing; do not treat as… [N049]
A38: PHEV new sales — all market | B38: vehicles/year | C38: Staged observation | D38: =IF(ISNUMBER('Evidence'!D18),'Evidence'!D18,"") | E38: All-market drivetrain sales; passenger/truck split is not… [N050] | F38: =IF(ISNUMBER('Evidence'!F18),'Evidence'!F18,"") | G38: =IF(ISNUMBER('Evidence'!G18),'Evidence'!G18,"") | H38: =IF(ISNUMBER('Evidence'!H18),'Evidence'!H18,"") | I38: =IF(ISNUMBER('Evidence'!I18),'Evidence'!I18,"") | J38: =IF(ISNUMBER('Evidence'!J18),'Evidence'!J18,"") | K38: =IF(ISNUMBER('Evidence'!K18),'Evidence'!K18,"") | L38: =IF(ISNUMBER('Evidence'!L18),'Evidence'!L18,"") | M38: =IF(ISNUMBER('Evidence'!M18),'Evidence'!M18,"") | ... S38: =IF(ISNUMBER('Evidence'!S18),'Evidence'!S18,"") | T38: Unreviewed source extract; annual cells contain… [N051] | U38: Evidence row 18;… [N052] | V38: G03: class split and electric-km fraction missing.
A39: Conventional hybrid new sales | B39: vehicles/year | C39: Staged observation | D39: =IF(ISNUMBER('Evidence'!D19),'Evidence'!D19,"") | E39: All-market drivetrain sales; passenger/truck split is not… [N053] | F39: =IF(ISNUMBER('Evidence'!F19),'Evidence'!F19,"") | G39: =IF(ISNUMBER('Evidence'!G19),'Evidence'!G19,"") | H39: =IF(ISNUMBER('Evidence'!H19),'Evidence'!H19,"") | I39: =IF(ISNUMBER('Evidence'!I19),'Evidence'!I19,"") | J39: =IF(ISNUMBER('Evidence'!J19),'Evidence'!J19,"") | K39: =IF(ISNUMBER('Evidence'!K19),'Evidence'!K19,"") | L39: =IF(ISNUMBER('Evidence'!L19),'Evidence'!L19,"") | M39: =IF(ISNUMBER('Evidence'!M19),'Evidence'!M19,"") | ... S39: =IF(ISNUMBER('Evidence'!S19),'Evidence'!S19,"") | T39: Unreviewed source extract; annual cells contain… [N054] | U39: Evidence row 19;… [N055] | V39: G03: source class-specific efficiency and mix.
A40: Total new-vehicle sales | B40: vehicles/year | C40: Staged observation | D40: =IF(ISNUMBER('Evidence'!D16),'Evidence'!D16,"") | E40: NAAMSA actual new sales. Published 2026/27 projections excluded… [N056] | F40: =IF(ISNUMBER('Evidence'!F16),'Evidence'!F16,"") | G40: =IF(ISNUMBER('Evidence'!G16),'Evidence'!G16,"") | H40: =IF(ISNUMBER('Evidence'!H16),'Evidence'!H16,"") | I40: =IF(ISNUMBER('Evidence'!I16),'Evidence'!I16,"") | J40: =IF(ISNUMBER('Evidence'!J16),'Evidence'!J16,"") | K40: =IF(ISNUMBER('Evidence'!K16),'Evidence'!K16,"") | L40: =IF(ISNUMBER('Evidence'!L16),'Evidence'!L16,"") | M40: =IF(ISNUMBER('Evidence'!M16),'Evidence'!M16,"") | ... S40: =IF(ISNUMBER('Evidence'!S16),'Evidence'!S16,"") | T40: Unreviewed source extract; annual cells contain… [N057] | U40: Evidence row 16;… [N058] | V40: G02/G03: same-market denominator only; reconcile… [N059]
A41: BEV share of total market sales | B41: share | C41: Reporting formula | E41: All-market share = BEV sales / total market sales. Not passenger-specific. | F41: =IF(COUNT(F37,F40)<2,"",IF(F40=0,"",F37/F40)) | G41: =IF(COUNT(G37,G40)<2,"",IF(G40=0,"",G37/G40)) | H41: =IF(COUNT(H37,H40)<2,"",IF(H40=0,"",H37/H40)) | I41: =IF(COUNT(I37,I40)<2,"",IF(I40=0,"",I37/I40)) | J41: =IF(COUNT(J37,J40)<2,"",IF(J40=0,"",J37/J40)) | K41: =IF(COUNT(K37,K40)<2,"",IF(K40=0,"",K37/K40)) | L41: =IF(COUNT(L37,L40)<2,"",IF(L40=0,"",L37/L40)) | M41: =IF(COUNT(M37,M40)<2,"",IF(M40=0,"",M37/M40)) | ... S41: =IF(COUNT(S37,S40)<2,"",IF(S40=0,"",S37/S40)) | T41: Years with both observations only. | U41: https://github.com/Africa-International-Advisors/liq… [N060] | V41: G03: obtain class-level denominator before adoption.
A42: Updated observed GDP per capita | B42: 2015 ZAR/person | C42: Staged observation | D42: =IF(ISNUMBER('Evidence'!D25),'Evidence'!D25,"") | E42: Stats SA annual actual in staged reporting copy. Sector value… [N061] | F42: =IF(ISNUMBER('Evidence'!F25),'Evidence'!F25,"") | G42: =IF(ISNUMBER('Evidence'!G25),'Evidence'!G25,"") | H42: =IF(ISNUMBER('Evidence'!H25),'Evidence'!H25,"") | I42: =IF(ISNUMBER('Evidence'!I25),'Evidence'!I25,"") | J42: =IF(ISNUMBER('Evidence'!J25),'Evidence'!J25,"") | K42: =IF(ISNUMBER('Evidence'!K25),'Evidence'!K25,"") | L42: =IF(ISNUMBER('Evidence'!L25),'Evidence'!L25,"") | M42: =IF(ISNUMBER('Evidence'!M25),'Evidence'!M25,"") | ... S42: =IF(ISNUMBER('Evidence'!S25),'Evidence'!S25,"") | T42: Unreviewed source extract; annual cells contain… [N062] | U42: Evidence row 25;… [N063] | V42: G02: reconcile updated series against engine macro assumptions.
A44: LCV petrol stock | B44: vehicles | C44: Linked model output | E44: Model run row 54; Python vehicle cohort result. | F44: =IF(ISNUMBER('Model run'!F54),'Model run'!F54,"") | G44: =IF(ISNUMBER('Model run'!G54),'Model run'!G54,"") | H44: =IF(ISNUMBER('Model run'!H54),'Model run'!H54,"") | I44: =IF(ISNUMBER('Model run'!I54),'Model run'!I54,"") | J44: =IF(ISNUMBER('Model run'!J54),'Model run'!J54,"") | K44: =IF(ISNUMBER('Model run'!K54),'Model run'!K54,"") | L44: =IF(ISNUMBER('Model run'!L54),'Model run'!L54,"") | M44: =IF(ISNUMBER('Model run'!M54),'Model run'!M54,"") | ... S44: =IF(ISNUMBER('Model run'!S54),'Model run'!S54,"")
A45: LCV petrol vehicle kilometres | B45: vehicle km/year | C45: Linked model output | E45: Model run row 55; Python vehicle cohort result. | F45: =IF(ISNUMBER('Model run'!F55),'Model run'!F55,"") | G45: =IF(ISNUMBER('Model run'!G55),'Model run'!G55,"") | H45: =IF(ISNUMBER('Model run'!H55),'Model run'!H55,"") | I45: =IF(ISNUMBER('Model run'!I55),'Model run'!I55,"") | J45: =IF(ISNUMBER('Model run'!J55),'Model run'!J55,"") | K45: =IF(ISNUMBER('Model run'!K55),'Model run'!K55,"") | L45: =IF(ISNUMBER('Model run'!L55),'Model run'!L55,"") | M45: =IF(ISNUMBER('Model run'!M55),'Model run'!M55,"") | ... S45: =IF(ISNUMBER('Model run'!S55),'Model run'!S55,"")
A46: LCV petrol demand | B46: L/year | C46: Linked model output | E46: Model run row 56; Python vehicle cohort result. | F46: =IF(ISNUMBER('Model run'!F56),'Model run'!F56,"") | G46: =IF(ISNUMBER('Model run'!G56),'Model run'!G56,"") | H46: =IF(ISNUMBER('Model run'!H56),'Model run'!H56,"") | I46: =IF(ISNUMBER('Model run'!I56),'Model run'!I56,"") | J46: =IF(ISNUMBER('Model run'!J56),'Model run'!J56,"") | K46: =IF(ISNUMBER('Model run'!K56),'Model run'!K56,"") | L46: =IF(ISNUMBER('Model run'!L56),'Model run'!L56,"") | M46: =IF(ISNUMBER('Model run'!M56),'Model run'!M56,"") | ... S46: =IF(ISNUMBER('Model run'!S56),'Model run'!S56,"")

Sheet Freight
A1: Diesel road freight demand
A2: Current national heavy-commercial example • Heavy trucks are only part of road-freight demand.
A4: Driver / output | B4: Unit | C4: Role | D4: Scalar / latest value | E4: Definition / period | F4: 2022 | G4: 2023 | H4: 2024 | I4: 2025 | J4: 2026 | K4: 2027 | L4: 2028 | M4: 2029 | N4: 2030 | O4: 2031 | P4: 2032 | Q4: 2033 | R4: 2034 | S4: 2035 | T4: Coverage / status | U4: Source | V4: Missing evidence / next action
A5: Current fleet-method inputs
A6: GDP per capita | B6: 2015 ZAR/person | C6: Input series | E6: Same national vehicle-sales regression as Petrol sheet. | F6: =IF(ISNUMBER('Model run'!F19),'Model run'!F19,"") | G6: =IF(ISNUMBER('Model run'!G19),'Model run'!G19,"") | H6: =IF(ISNUMBER('Model run'!H19),'Model run'!H19,"") | I6: =IF(ISNUMBER('Model run'!I19),'Model run'!I19,"") | J6: =IF(ISNUMBER('Model run'!J19),'Model run'!J19,"") | K6: =IF(ISNUMBER('Model run'!K19),'Model run'!K19,"") | L6: =IF(ISNUMBER('Model run'!L19),'Model run'!L19,"") | M6: =IF(ISNUMBER('Model run'!M19),'Model run'!M19,"") | ... S6: =IF(ISNUMBER('Model run'!S19),'Model run'!S19,"")
A7: HCV share of new vehicle sales | B7: share | C7: Scalar | D7: =IF(ISNUMBER('Model run'!D20),'Model run'!D20,"") | E7: Current provisional class split.
A8: Diesel share of HCV ICE sales | B8: share | C8: Scalar | D8: =IF(ISNUMBER('Model run'!D21),'Model run'!D21,"") | E8: Current model applies its common EV adjustment before the diesel split.
A9: Heavy-truck annual mileage | B9: km/vehicle/year | C9: Scalar | D9: =IF(ISNUMBER('Model run'!D22),'Model run'!D22,"") | E9: Current provisional assumption.
A10: Heavy-truck retirement rate | B10: share/year | C10: Scalar | D10: =IF(ISNUMBER('Model run'!D23),'Model run'!D23,"") | E10: Flat retirement assumption across cohorts.
A11: Base new-truck consumption | B11: L/100 km | C11: Scalar | D11: =IF(ISNUMBER('Model run'!D24),'Model run'!D24,"") | E11: Entry-cohort baseline before efficiency improvement.
A12: New-cohort efficiency gain | B12: fraction/year | C12: Input series | E12: Applies to new cohorts only. | F12: =IF(ISNUMBER('Model run'!F25),'Model run'!F25,"") | G12: =IF(ISNUMBER('Model run'!G25),'Model run'!G25,"") | H12: =IF(ISNUMBER('Model run'!H25),'Model run'!H25,"") | I12: =IF(ISNUMBER('Model run'!I25),'Model run'!I25,"") | J12: =IF(ISNUMBER('Model run'!J25),'Model run'!J25,"") | K12: =IF(ISNUMBER('Model run'!K25),'Model run'!K25,"") | L12: =IF(ISNUMBER('Model run'!L25),'Model run'!L25,"") | M12: =IF(ISNUMBER('Model run'!M25),'Model run'!M25,"") | ... S12: =IF(ISNUMBER('Model run'!S25),'Model run'!S25,"")
A14: Current engine outputs and reporting calculations
A15: Heavy-truck diesel fleet | B15: vehicles | C15: Engine output | E15: National HCV diesel cohort stock. | F15: =IF(ISNUMBER('Model run'!F26),'Model run'!F26,"") | G15: =IF(ISNUMBER('Model run'!G26),'Model run'!G26,"") | H15: =IF(ISNUMBER('Model run'!H26),'Model run'!H26,"") | I15: =IF(ISNUMBER('Model run'!I26),'Model run'!I26,"") | J15: =IF(ISNUMBER('Model run'!J26),'Model run'!J26,"") | K15: =IF(ISNUMBER('Model run'!K26),'Model run'!K26,"") | L15: =IF(ISNUMBER('Model run'!L26),'Model run'!L26,"") | M15: =IF(ISNUMBER('Model run'!M26),'Model run'!M26,"") | ... S15: =IF(ISNUMBER('Model run'!S26),'Model run'!S26,"")
A16: Heavy-truck vehicle-km | B16: km/year | C16: Engine output | E16: National HCV diesel activity. | F16: =IF(ISNUMBER('Model run'!F27),'Model run'!F27,"") | G16: =IF(ISNUMBER('Model run'!G27),'Model run'!G27,"") | H16: =IF(ISNUMBER('Model run'!H27),'Model run'!H27,"") | I16: =IF(ISNUMBER('Model run'!I27),'Model run'!I27,"") | J16: =IF(ISNUMBER('Model run'!J27),'Model run'!J27,"") | K16: =IF(ISNUMBER('Model run'!K27),'Model run'!K27,"") | L16: =IF(ISNUMBER('Model run'!L27),'Model run'!L27,"") | M16: =IF(ISNUMBER('Model run'!M27),'Model run'!M27,"") | ... S16: =IF(ISNUMBER('Model run'!S27),'Model run'!S27,"")
A17: Heavy-truck diesel demand | B17: L/year | C17: Engine output | E17: Current Python engine output. Does not include LCV freight. | F17: =IF(ISNUMBER('Model run'!F28),'Model run'!F28,"") | G17: =IF(ISNUMBER('Model run'!G28),'Model run'!G28,"") | H17: =IF(ISNUMBER('Model run'!H28),'Model run'!H28,"") | I17: =IF(ISNUMBER('Model run'!I28),'Model run'!I28,"") | J17: =IF(ISNUMBER('Model run'!J28),'Model run'!J28,"") | K17: =IF(ISNUMBER('Model run'!K28),'Model run'!K28,"") | L17: =IF(ISNUMBER('Model run'!L28),'Model run'!L28,"") | M17: =IF(ISNUMBER('Model run'!M28),'Model run'!M28,"") | ... S17: =IF(ISNUMBER('Model run'!S28),'Model run'!S28,"")
A18: Heavy-truck diesel demand | B18: million L/year | C18: Reporting formula | E18: Unit conversion of engine output. | F18: =F17/1000000 | G18: =G17/1000000 | H18: =H17/1000000 | I18: =I17/1000000 | J18: =J17/1000000 | K18: =K17/1000000 | L18: =L17/1000000 | M18: =M17/1000000 | ... S18: =S17/1000000
A19: Implied fleet-average consumption | B19: L/100 km | C19: Reporting formula | E19: Fuel / vehicle-km × 100. | F19: =IF(F16=0,"",F17/F16*100) | G19: =IF(G16=0,"",G17/G16*100) | H19: =IF(H16=0,"",H17/H16*100) | I19: =IF(I16=0,"",I17/I16*100) | J19: =IF(J16=0,"",J17/J16*100) | K19: =IF(K16=0,"",K17/K16*100) | L19: =IF(L16=0,"",L17/L16*100) | M19: =IF(M16=0,"",M17/M16*100) | ... S19: =IF(S16=0,"",S17/S16*100)
A21: Alternative tonne-km method: agree before implementation
A22: Reference road freight activity | B22: tonne-km/year | C22: Workshop input | E22: Choose eligible road work before rail diversion; tonnes alone omit distance.
A23: Road work diverted to rail | B23: share of reference | C23: Workshop input | E23: Deduct once. If already reflected in the road activity path, do… [N064]
A24: Freight fuel intensity | B24: L/tonne-km | C24: Workshop input | E24: Calibrate to payload, empty running and vehicle mix.
A25: Alternative freight demand | B25: million L/year | C25: Proposed output | E25: Reference tonne-km × (1 − eligible diversion share) × L/tonne-km… [N065]
A26: Geographic definition | B26: decision | C26: Workshop input | E26: Agree fuel sales location versus consumption/corridor. Do not… [N066]
A28: Source | B28: URL | C28: Source | E28: https://github.com/Africa-International-Advisors/liquid_fuels_mode… [N067]
A30: Freight electrification: current setting and proposed replacement
A31: Current common EV share of new sales | B31: share | C31: Engine output | E31: Existing engine curve applied to HCV as well as other classes.… [N068] | F31: =IF(ISNUMBER('Model run'!F29),'Model run'!F29,"") | G31: =IF(ISNUMBER('Model run'!G29),'Model run'!G29,"") | H31: =IF(ISNUMBER('Model run'!H29),'Model run'!H29,"") | I31: =IF(ISNUMBER('Model run'!I29),'Model run'!I29,"") | J31: =IF(ISNUMBER('Model run'!J29),'Model run'!J29,"") | K31: =IF(ISNUMBER('Model run'!K29),'Model run'!K29,"") | L31: =IF(ISNUMBER('Model run'!L29),'Model run'!L29,"") | M31: =IF(ISNUMBER('Model run'!M29),'Model run'!M29,"") | ... S31: =IF(ISNUMBER('Model run'!S29),'Model run'!S29,"")
A32: Truck BEV share of new sales | B32: share | C32: Workshop input | E32: Separate light delivery, regional and long-haul cohorts. Use… [N069]
A33: Truck hybrid / PHEV new-sales share | B33: share | C33: Workshop input | E33: Separate from BEVs. Record residual diesel use; PHEV… [N070]
A34: Opening fleet and survival by drivetrain | B34: vehicles / survival | C34: Workshop input | E34: New-sales shares become stock through cohort additions and… [N071]
A35: Mileage by drivetrain / duty cycle | B35: km/vehicle/year | C35: Workshop input | E35: Electric and diesel trucks can perform different annual work. Use… [N072]
A36: Truck electricity intensity | B36: kWh/km | C36: Workshop input | E36: Optional electricity requirement and charging-feasibility check.… [N073]
A37: Charging and operating constraints | B37: eligibility / timing | C37: Workshop input | E37: Depot/corridor access, charging power, dwell time, grid… [N074]
A38: Electric freight share of road work | B38: share of tonne-km | C38: Proposed output | E38: For tonne-km method: derive consistent work share from drivetrain… [N075]
A39: Truck diesel demand after transition | B39: million L/year | C39: Proposed output | E39: Fleet method: sum diesel/hybrid cohort vehicles × km × L/100 km /… [N076]
A40: Rail and electrification interaction | B40: decision | C40: Workshop input | E40: Rail diversion first defines remaining road work. Drivetrain… [N077]
A41: Province / corridor treatment | B41: decision | C41: Workshop input | E41: Electrify feasible routes/depot fleets first; reconcile… [N078]
A43: H/M/L brackets | B43: decision | C43: Workshop input | E43: Set truck BEV shares, hybrid treatment and rollout dates by duty… [N079]
A45: Current curve source | B45: URL | C45: Source | E45: https://github.com/Africa-International-Advisors/liquid_fuels_mode… [N080]
A47: Available freight evidence: activity is not yet calibrated to litres
A48: Medium/heavy commercial new sales | B48: vehicles/year | C48: Staged observation | D48: =IF(ISNUMBER('Evidence'!D15),'Evidence'!D15,"") | E48: NAAMSA actual new sales. Published 2026/27 projections excluded… [N081] | F48: =IF(ISNUMBER('Evidence'!F15),'Evidence'!F15,"") | G48: =IF(ISNUMBER('Evidence'!G15),'Evidence'!G15,"") | H48: =IF(ISNUMBER('Evidence'!H15),'Evidence'!H15,"") | I48: =IF(ISNUMBER('Evidence'!I15),'Evidence'!I15,"") | J48: =IF(ISNUMBER('Evidence'!J15),'Evidence'!J15,"") | K48: =IF(ISNUMBER('Evidence'!K15),'Evidence'!K15,"") | L48: =IF(ISNUMBER('Evidence'!L15),'Evidence'!L15,"") | M48: =IF(ISNUMBER('Evidence'!M15),'Evidence'!M15,"") | ... S48: =IF(ISNUMBER('Evidence'!S15),'Evidence'!S15,"") | T48: Unreviewed source extract; annual cells contain… [N082] | U48: Evidence row 15;… [N083] | V48: G04: align medium/heavy sales with HCV engine and… [N084]
A49: Registered trucks, all drivetrains | B49: vehicles | C49: Staged observation | D49: =IF(ISNUMBER('Evidence'!D22),'Evidence'!D22,"") | E49: eNaTIS December snapshots; latest June 2026 kept separately. No… [N085] | F49: =IF(ISNUMBER('Evidence'!F22),'Evidence'!F22,"") | G49: =IF(ISNUMBER('Evidence'!G22),'Evidence'!G22,"") | H49: =IF(ISNUMBER('Evidence'!H22),'Evidence'!H22,"") | I49: =IF(ISNUMBER('Evidence'!I22),'Evidence'!I22,"") | J49: =IF(ISNUMBER('Evidence'!J22),'Evidence'!J22,"") | K49: =IF(ISNUMBER('Evidence'!K22),'Evidence'!K22,"") | L49: =IF(ISNUMBER('Evidence'!L22),'Evidence'!L22,"") | M49: =IF(ISNUMBER('Evidence'!M22),'Evidence'!M22,"") | ... S49: =IF(ISNUMBER('Evidence'!S22),'Evidence'!S22,"") | T49: Unreviewed source extract; annual cells contain… [N086] | U49: Evidence row 22;… [N087] | V49: G04: reconcile vehicle definition, drivetrain and… [N088]
A50: Road freight payload | B50: thousand tonnes | C50: Staged observation | D50: =IF(ISNUMBER('Evidence'!D32),'Evidence'!D32,"") | E50: Complete calendar years only; 2026 Jan–Jul shown separately.… [N089] | F50: =IF(ISNUMBER('Evidence'!F32),'Evidence'!F32,"") | G50: =IF(ISNUMBER('Evidence'!G32),'Evidence'!G32,"") | H50: =IF(ISNUMBER('Evidence'!H32),'Evidence'!H32,"") | I50: =IF(ISNUMBER('Evidence'!I32),'Evidence'!I32,"") | J50: =IF(ISNUMBER('Evidence'!J32),'Evidence'!J32,"") | K50: =IF(ISNUMBER('Evidence'!K32),'Evidence'!K32,"") | L50: =IF(ISNUMBER('Evidence'!L32),'Evidence'!L32,"") | M50: =IF(ISNUMBER('Evidence'!M32),'Evidence'!M32,"") | ... S50: =IF(ISNUMBER('Evidence'!S32),'Evidence'!S32,"") | T50: Unreviewed source extract; annual cells contain… [N090] | U50: Evidence row 32;… [N091] | V50: G04: tonnes need distance/payload/empty-running… [N092]
A51: Rail freight payload | B51: thousand tonnes | C51: Staged observation | D51: =IF(ISNUMBER('Evidence'!D33),'Evidence'!D33,"") | E51: Complete calendar years only; 2026 Jan–Jul shown separately.… [N093] | F51: =IF(ISNUMBER('Evidence'!F33),'Evidence'!F33,"") | G51: =IF(ISNUMBER('Evidence'!G33),'Evidence'!G33,"") | H51: =IF(ISNUMBER('Evidence'!H33),'Evidence'!H33,"") | I51: =IF(ISNUMBER('Evidence'!I33),'Evidence'!I33,"") | J51: =IF(ISNUMBER('Evidence'!J33),'Evidence'!J33,"") | K51: =IF(ISNUMBER('Evidence'!K33),'Evidence'!K33,"") | L51: =IF(ISNUMBER('Evidence'!L33),'Evidence'!L33,"") | M51: =IF(ISNUMBER('Evidence'!M33),'Evidence'!M33,"") | ... S51: =IF(ISNUMBER('Evidence'!S33),'Evidence'!S33,"") | T51: Unreviewed source extract; annual cells contain… [N094] | U51: Evidence row 33;… [N095] | V51: G04: source feasible diversion by… [N096]
A52: LCV new sales | B52: vehicles/year | C52: Staged observation | D52: =IF(ISNUMBER('Evidence'!D14),'Evidence'!D14,"") | E52: NAAMSA actual new sales. Published 2026/27 projections excluded… [N097] | F52: =IF(ISNUMBER('Evidence'!F14),'Evidence'!F14,"") | G52: =IF(ISNUMBER('Evidence'!G14),'Evidence'!G14,"") | H52: =IF(ISNUMBER('Evidence'!H14),'Evidence'!H14,"") | I52: =IF(ISNUMBER('Evidence'!I14),'Evidence'!I14,"") | J52: =IF(ISNUMBER('Evidence'!J14),'Evidence'!J14,"") | K52: =IF(ISNUMBER('Evidence'!K14),'Evidence'!K14,"") | L52: =IF(ISNUMBER('Evidence'!L14),'Evidence'!L14,"") | M52: =IF(ISNUMBER('Evidence'!M14),'Evidence'!M14,"") | ... S52: =IF(ISNUMBER('Evidence'!S14),'Evidence'!S14,"") | T52: Unreviewed source extract; annual cells contain… [N098] | U52: Evidence row 14;… [N099] | V52: G04: determine freight versus passenger/other LCV work.
A53: Truck-specific BEV sales / fleet | B53: vehicles or share | C53: Missing input | E53: All-market NEV data exists on Petrol sheet; no truck-specific… [N100] | T53: Current generic EV curve is shown in row 31. | V53: G05: source truck registrations/sales, fleet… [N101]
A55: Passenger diesel demand | B55: L/year | C55: Linked model output | E55: Model run row 57; Python vehicle cohort result. | F55: =IF(ISNUMBER('Model run'!F57),'Model run'!F57,"") | G55: =IF(ISNUMBER('Model run'!G57),'Model run'!G57,"") | H55: =IF(ISNUMBER('Model run'!H57),'Model run'!H57,"") | I55: =IF(ISNUMBER('Model run'!I57),'Model run'!I57,"") | J55: =IF(ISNUMBER('Model run'!J57),'Model run'!J57,"") | K55: =IF(ISNUMBER('Model run'!K57),'Model run'!K57,"") | L55: =IF(ISNUMBER('Model run'!L57),'Model run'!L57,"") | M55: =IF(ISNUMBER('Model run'!M57),'Model run'!M57,"") | ... S55: =IF(ISNUMBER('Model run'!S57),'Model run'!S57,"")
A56: LCV diesel demand | B56: L/year | C56: Linked model output | E56: Model run row 58; Python vehicle cohort result. | F56: =IF(ISNUMBER('Model run'!F58),'Model run'!F58,"") | G56: =IF(ISNUMBER('Model run'!G58),'Model run'!G58,"") | H56: =IF(ISNUMBER('Model run'!H58),'Model run'!H58,"") | I56: =IF(ISNUMBER('Model run'!I58),'Model run'!I58,"") | J56: =IF(ISNUMBER('Model run'!J58),'Model run'!J58,"") | K56: =IF(ISNUMBER('Model run'!K58),'Model run'!K58,"") | L56: =IF(ISNUMBER('Model run'!L58),'Model run'!L58,"") | M56: =IF(ISNUMBER('Model run'!M58),'Model run'!M58,"") | ... S56: =IF(ISNUMBER('Model run'!S58),'Model run'!S58,"")
A57: All road diesel | B57: million L/year | C57: Reporting formula | E57: HCV + passenger + LCV; freight share within LCV remains unresolved. | F57: =IF(COUNT(F17,F55,F56)<3,"",SUM(F17,F55,F56)/1000000) | G57: =IF(COUNT(G17,G55,G56)<3,"",SUM(G17,G55,G56)/1000000) | H57: =IF(COUNT(H17,H55,H56)<3,"",SUM(H17,H55,H56)/1000000) | I57: =IF(COUNT(I17,I55,I56)<3,"",SUM(I17,I55,I56)/1000000) | J57: =IF(COUNT(J17,J55,J56)<3,"",SUM(J17,J55,J56)/1000000) | K57: =IF(COUNT(K17,K55,K56)<3,"",SUM(K17,K55,K56)/1000000) | L57: =IF(COUNT(L17,L55,L56)<3,"",SUM(L17,L55,L56)/1000000) | M57: =IF(COUNT(M17,M55,M56)<3,"",SUM(M17,M55,M56)/1000000) | ... S57: =IF(COUNT(S17,S55,S56)<3,"",SUM(S17,S55,S56)/1000000)

Sheet Agriculture
A1: Agricultural diesel demand
A2: Current national held method alongside proposed sector-activity method • No new inputs adopted.
A4: Driver / output | B4: Unit | C4: Role | D4: Scalar / latest value | E4: Definition / period | F4: 2022 | G4: 2023 | H4: 2024 | I4: 2025 | J4: 2026 | K4: 2027 | L4: 2028 | M4: 2029 | N4: 2030 | O4: 2031 | P4: 2032 | Q4: 2033 | R4: 2034 | S4: 2035 | T4: Coverage / status | U4: Source | V4: Missing evidence / next action
A5: Current held-method inputs
A6: Base-year demand | B6: L/year | C6: Scalar | D6: 0.7e9 | E6: Current registered placeholder, not a verified agricultural fuel baseline.
A7: Base year | B7: year | C7: Scalar | D7: =IF(ISNUMBER('Model run'!D30),'Model run'!D30,"") | E7: A dated baseline, not a recurring annual observation.
A8: GDP/capita elasticity | B8: dimensionless | C8: Scalar | D8: =IF(ISNUMBER('Model run'!D31),'Model run'!D31,"") | E8: Provisional GDP proxy, pending an agricultural driver.
A9: GDP per capita | B9: 2015 ZAR/person | C9: Input series | E9: Current driver used by the held engine. | F9: =IF(ISNUMBER('Model run'!F32),'Model run'!F32,"") | G9: =IF(ISNUMBER('Model run'!G32),'Model run'!G32,"") | H9: =IF(ISNUMBER('Model run'!H32),'Model run'!H32,"") | I9: =IF(ISNUMBER('Model run'!I32),'Model run'!I32,"") | J9: =IF(ISNUMBER('Model run'!J32),'Model run'!J32,"") | K9: =IF(ISNUMBER('Model run'!K32),'Model run'!K32,"") | L9: =IF(ISNUMBER('Model run'!L32),'Model run'!L32,"") | M9: =IF(ISNUMBER('Model run'!M32),'Model run'!M32,"") | ... S9: =IF(ISNUMBER('Model run'!S32),'Model run'!S32,"")
A11: Current engine outputs
A12: Agricultural diesel demand | B12: L/year | C12: Engine output | E12: Engine: baseline × (GDP/capita / base-year GDP/capita)^elasticity. | F12: =IF(ISNUMBER('Model run'!F33),'Model run'!F33,"") | G12: =IF(ISNUMBER('Model run'!G33),'Model run'!G33,"") | H12: =IF(ISNUMBER('Model run'!H33),'Model run'!H33,"") | I12: =IF(ISNUMBER('Model run'!I33),'Model run'!I33,"") | J12: =IF(ISNUMBER('Model run'!J33),'Model run'!J33,"") | K12: =IF(ISNUMBER('Model run'!K33),'Model run'!K33,"") | L12: =IF(ISNUMBER('Model run'!L33),'Model run'!L33,"") | M12: =IF(ISNUMBER('Model run'!M33),'Model run'!M33,"") | ... S12: =IF(ISNUMBER('Model run'!S33),'Model run'!S33,"")
A13: Agricultural diesel demand | B13: million L/year | C13: Reporting formula | E13: Unit conversion. Current provisional series, not the proposed activity method. | F13: =F12/1000000 | G13: =G12/1000000 | H13: =H12/1000000 | I13: =I12/1000000 | J13: =J12/1000000 | K13: =K12/1000000 | L13: =L12/1000000 | M13: =M12/1000000 | ... S13: =S12/1000000
A15: Proposed sector-activity method
A16: Reviewed baseline demand | B16: million L at base year | C16: Workshop input | E16: A 2021 source anchor is available in row 30, but has not been… [N102]
A17: Agricultural activity index | B17: base year = 100 | C17: Workshop input | E17: Real agricultural GVA is available in row 29. Select/rebase an… [N103]
A18: Relative fuel intensity | B18: base year = 1 | C18: Workshop input | E18: Lower values mean less fuel per activity unit; mechanisation can… [N104]
A19: Proposed agricultural demand | B19: million L/year | C19: Proposed output | E19: Reviewed base demand × activity index / 100 × relative intensity.… [N105]
A20: Provincial activity / baseline shares | B20: share or local index | C20: Workshop input | E20: Use local agricultural evidence; confirm that national… [N106]
A21: Sector boundaries | B21: decision | C21: Workshop input | E21: Resolve irrigation, off-road machinery, road vehicles and backup… [N107]
A23: Industry / mining extension | B23: method | C23: Proposal | E23: Apply the same structure separately to mining, manufacturing and… [N108]
A25: Source | B25: URL | C25: Source | E25: https://github.com/Africa-International-Advisors/liquid_fuels_mode… [N109]
A26: Calculation source | B26: URL | C26: Source | E26: https://github.com/Africa-International-Advisors/liquid_fuels_mode… [N110]
A28: Available agricultural evidence
A29: Agriculture/forestry/fishing real GVA | B29: bn 2015 ZAR | C29: Staged observation | D29: =IF(ISNUMBER('Evidence'!D26),'Evidence'!D26,"") | E29: Stats SA annual actual in staged reporting copy. Sector value… [N111] | F29: =IF(ISNUMBER('Evidence'!F26),'Evidence'!F26,"") | G29: =IF(ISNUMBER('Evidence'!G26),'Evidence'!G26,"") | H29: =IF(ISNUMBER('Evidence'!H26),'Evidence'!H26,"") | I29: =IF(ISNUMBER('Evidence'!I26),'Evidence'!I26,"") | J29: =IF(ISNUMBER('Evidence'!J26),'Evidence'!J26,"") | K29: =IF(ISNUMBER('Evidence'!K26),'Evidence'!K26,"") | L29: =IF(ISNUMBER('Evidence'!L26),'Evidence'!L26,"") | M29: =IF(ISNUMBER('Evidence'!M26),'Evidence'!M26,"") | ... S29: =IF(ISNUMBER('Evidence'!S26),'Evidence'!S26,"") | T29: Unreviewed source extract; annual cells contain… [N112] | U29: Evidence row 26;… [N113] | V29: G08: choose crop/area/output proxy and rebase to… [N114]
A30: 2021 agriculture/forestry diesel | B30: million L/year | C30: Staged observation | D30: =IF(ISNUMBER('Evidence'!D39),'Evidence'!D39,"") | E30: D is reported 2021 fuel use. No 2022–26 fuel observations inferred. | T30: Older anchor; source extraction and scope need review. | U30: https://github.com/Africa-International-Advisors/liq… [N115] | V30: G08: reconcile forestry/fishing and… [N116]

Sheet Manufacturing
A1: Manufacturing diesel demand
A2: Proposed separate sector block • Current engine still combines manufacturing, mining and construction.
A4: Driver / output | B4: Unit | C4: Role | D4: Scalar / latest value | E4: Definition / period | F4: 2022 | G4: 2023 | H4: 2024 | I4: 2025 | J4: 2026 | K4: 2027 | L4: 2028 | M4: 2029 | N4: 2030 | O4: 2031 | P4: 2032 | Q4: 2033 | R4: 2034 | S4: 2035 | T4: Coverage / status | U4: Source | V4: Missing evidence / next action
A5: Separate manufacturing assumptions to agree
A6: Reviewed manufacturing baseline | B6: million L/year | C6: Workshop input | E6: 2021 industry parent exists (row 34), but is not… [N117]
A7: Baseline year | B7: year | C7: Workshop input | E7: Dated observation; agree before indexing the activity series.
A8: Manufacturing production index | B8: base year = 100 | C8: Workshop input | E8: Observed production indices now appear in row 32. Rebase to the… [N118]
A9: Relative fuel intensity | B9: base year = 1 | C9: Workshop input | E9: Efficiency and process mix for continuing diesel uses. Exclude… [N119]
A10: Electrification: remaining diesel fraction | B10: base year = 1 | C10: Workshop input | E10: After baseline, fraction of counterfactual diesel retained as… [N120]
A11: Private backup generation | B11: scope decision | C11: Workshop input | E11: Include here OR in generation. Record whether the baseline… [N121]
A12: Provincial baseline / activity | B12: share or local index | C12: Workshop input | E12: Use manufacturing establishments/production, not population by… [N122]
A14: Proposed calculated demand
A15: Manufacturing diesel demand | B15: million L/year | C15: Proposed output | E15: Baseline × activity/100 × relative intensity × remaining diesel… [N123]
A16: Observed manufacturing diesel | B16: million L/year | C16: Workshop input | E16: Matched-period comparator; total national diesel sales cannot… [N124]
A17: Calculated less observed demand | B17: million L/year | C17: Proposed output | E17: Reconcile only against matched manufacturing scope. No… [N125]
A19: Combined industrial reference: not manufacturing demand
A20: Current combined industrial baseline | B20: L/year | C20: Scalar | D20: 2.5e9 | E20: ONE provisional total for manufacturing + mining + construction.… [N126]
A21: Combined baseline year | B21: year | C21: Scalar | D21: =IF(ISNUMBER('Model run'!D34),'Model run'!D34,"") | E21: Current main vintage; branch replacement proposals are not adopted here.
A22: Combined GDP/capita elasticity | B22: dimensionless | C22: Scalar | D22: =IF(ISNUMBER('Model run'!D35),'Model run'!D35,"") | E22: Current combined held-method parameter. Not a manufacturing-specific estimate.
A23: Combined industrial diesel | B23: L/year | C23: Engine output | E23: Existing engine output shown ONCE as a reference for the future… [N127] | F23: =IF(ISNUMBER('Model run'!F36),'Model run'!F36,"") | G23: =IF(ISNUMBER('Model run'!G36),'Model run'!G36,"") | H23: =IF(ISNUMBER('Model run'!H36),'Model run'!H36,"") | I23: =IF(ISNUMBER('Model run'!I36),'Model run'!I36,"") | J23: =IF(ISNUMBER('Model run'!J36),'Model run'!J36,"") | K23: =IF(ISNUMBER('Model run'!K36),'Model run'!K36,"") | L23: =IF(ISNUMBER('Model run'!L36),'Model run'!L36,"") | M23: =IF(ISNUMBER('Model run'!M36),'Model run'!M36,"") | ... S23: =IF(ISNUMBER('Model run'!S36),'Model run'!S36,"")
A24: Combined industrial diesel | B24: million L/year | C24: Reporting formula | E24: Unit conversion only. This is not a separate additive segment. | F24: =F23/1000000 | G24: =G23/1000000 | H24: =H23/1000000 | I24: =I23/1000000 | J24: =J23/1000000 | K24: =K23/1000000 | L24: =L23/1000000 | M24: =M23/1000000 | ... S24: =S23/1000000
A26: Split and reconcile the combined total | B26: decision | C26: Workshop input | E26: Manufacturing + mining + construction/other + unallocated must… [N128]
A28: Input source | B28: URL | C28: Source | E28: https://github.com/Africa-International-Advisors/liquid_fuels_mode… [N129]
A29: Calculation source | B29: URL | C29: Source | E29: https://github.com/Africa-International-Advisors/liquid_fuels_mode… [N130]
A31: Available manufacturing evidence
A32: Manufacturing production volume | B32: index 2019=100 | C32: Staged observation | D32: =IF(ISNUMBER('Evidence'!D30),'Evidence'!D30,"") | E32: Arithmetic mean of all 12 monthly production indices; 2026… [N131] | F32: =IF(ISNUMBER('Evidence'!F30),'Evidence'!F30,"") | G32: =IF(ISNUMBER('Evidence'!G30),'Evidence'!G30,"") | H32: =IF(ISNUMBER('Evidence'!H30),'Evidence'!H30,"") | I32: =IF(ISNUMBER('Evidence'!I30),'Evidence'!I30,"") | J32: =IF(ISNUMBER('Evidence'!J30),'Evidence'!J30,"") | K32: =IF(ISNUMBER('Evidence'!K30),'Evidence'!K30,"") | L32: =IF(ISNUMBER('Evidence'!L30),'Evidence'!L30,"") | M32: =IF(ISNUMBER('Evidence'!M30),'Evidence'!M30,"") | ... S32: =IF(ISNUMBER('Evidence'!S30),'Evidence'!S30,"") | T32: Unreviewed source extract; annual cells contain… [N132] | U32: Evidence row 30;… [N133] | V32: G06: match subsectors to fuel scope; rebase to… [N134]
A33: Manufacturing real GVA | B33: bn 2015 ZAR | C33: Staged observation | D33: =IF(ISNUMBER('Evidence'!D27),'Evidence'!D27,"") | E33: Stats SA annual actual in staged reporting copy. Sector value… [N135] | F33: =IF(ISNUMBER('Evidence'!F27),'Evidence'!F27,"") | G33: =IF(ISNUMBER('Evidence'!G27),'Evidence'!G27,"") | H33: =IF(ISNUMBER('Evidence'!H27),'Evidence'!H27,"") | I33: =IF(ISNUMBER('Evidence'!I27),'Evidence'!I27,"") | J33: =IF(ISNUMBER('Evidence'!J27),'Evidence'!J27,"") | K33: =IF(ISNUMBER('Evidence'!K27),'Evidence'!K27,"") | L33: =IF(ISNUMBER('Evidence'!L27),'Evidence'!L27,"") | M33: =IF(ISNUMBER('Evidence'!M27),'Evidence'!M27,"") | ... S33: =IF(ISNUMBER('Evidence'!S27),'Evidence'!S27,"") | T33: Unreviewed source extract; annual cells contain… [N136] | U33: Evidence row 27;… [N137] | V33: G06: alternative activity proxy, not additive to… [N138]
A34: 2021 energy-balance industry total | B34: million L/year | C34: Staged observation | D34: =IF(ISNUMBER('Evidence'!D40),'Evidence'!D40,"") | E34: Parent industry total includes mining and construction. It is not… [N139] | T34: Dated 2021 reference; no numerical split adopted. | U34: https://github.com/Africa-International-Advisors/liq… [N140] | V34: G06: reconcile manufacturing subsector rows and… [N141]
A35: 2021 construction diesel | B35: million L/year | C35: Staged observation | D35: =IF(ISNUMBER('Evidence'!D41),'Evidence'!D41,"") | E35: Construction child of source industry total, shown separately to… [N142] | T35: Older source anchor only. | U35: https://github.com/Africa-International-Advisors/liq… [N143] | V35: G06/G07: retain construction/other when splitting… [N144]

Sheet Mining
A1: Mining diesel demand
A2: Proposed separate sector block • Separate off-road mine equipment from public-road freight and private generation.
A4: Driver / output | B4: Unit | C4: Role | D4: Scalar / latest value | E4: Definition / period | F4: 2022 | G4: 2023 | H4: 2024 | I4: 2025 | J4: 2026 | K4: 2027 | L4: 2028 | M4: 2029 | N4: 2030 | O4: 2031 | P4: 2032 | Q4: 2033 | R4: 2034 | S4: 2035 | T4: Coverage / status | U4: Source | V4: Missing evidence / next action
A5: Separate mining assumptions to agree
A6: Reviewed mining baseline | B6: million L/year | C6: Workshop input | E6: 2021 mining fuel is shown in row 31. Source newer years and… [N145]
A7: Baseline year | B7: year | C7: Workshop input | E7: Match the activity and fuel observation periods.
A8: Mining activity index | B8: base year = 100 | C8: Workshop input | E8: Production index and GVA now appear in rows 29–30. Select one… [N146]
A9: Relative operating intensity | B9: base year = 1 | C9: Workshop input | E9: Reflect depth, haul work, equipment mix and efficiency. Avoid… [N147]
A10: Electrification: remaining diesel fraction | B10: base year = 1 | C10: Workshop input | E10: Eligible off-road diesel work retained after switching equipment… [N148]
A11: Mine backup generation | B11: scope decision | C11: Workshop input | E11: Separate from machinery; count in mining OR private generation once.
A12: Provincial site / activity allocation | B12: share or local index | C12: Workshop input | E12: Locate mine demand by site/activity; use explicit unallocated… [N149]
A14: Proposed calculated demand
A15: Mining diesel demand | B15: million L/year | C15: Proposed output | E15: Baseline × activity/100 × relative intensity × remaining diesel… [N150]
A16: Observed mining diesel | B16: million L/year | C16: Workshop input | E16: Matched mining scope; separate public-road haul and process/backup uses.
A17: Calculated less observed demand | B17: million L/year | C17: Proposed output | E17: No numerical forecast or observed comparison until the sector… [N151]
A19: Reconciliation and workshop decisions
A20: Current combined model reference | B20: cross-reference | C20: Source | E20: Manufacturing rows 20–24 hold the combined industrial… [N152]
A21: Public-road freight boundary | B21: decision | C21: Workshop input | E21: Mine-to-port road trucks belong to freight if already in that… [N153]
A22: Construction and other remainder | B22: decision | C22: Workshop input | E22: Reconcile the combined baseline with manufacturing, mining and… [N154]
A24: H/M/L brackets and reference case | B24: decision | C24: Workshop input | E24: Agree mining activity, intensity and electrification separately.… [N155]
A26: Input source | B26: URL | C26: Source | E26: https://github.com/Africa-International-Advisors/liquid_fuels_mode… [N156]
A28: Available mining evidence
A29: Mining production volume | B29: index 2019=100 | C29: Staged observation | D29: =IF(ISNUMBER('Evidence'!D31),'Evidence'!D31,"") | E29: Arithmetic mean of all 12 monthly production indices; 2026… [N157] | F29: =IF(ISNUMBER('Evidence'!F31),'Evidence'!F31,"") | G29: =IF(ISNUMBER('Evidence'!G31),'Evidence'!G31,"") | H29: =IF(ISNUMBER('Evidence'!H31),'Evidence'!H31,"") | I29: =IF(ISNUMBER('Evidence'!I31),'Evidence'!I31,"") | J29: =IF(ISNUMBER('Evidence'!J31),'Evidence'!J31,"") | K29: =IF(ISNUMBER('Evidence'!K31),'Evidence'!K31,"") | L29: =IF(ISNUMBER('Evidence'!L31),'Evidence'!L31,"") | M29: =IF(ISNUMBER('Evidence'!M31),'Evidence'!M31,"") | ... S29: =IF(ISNUMBER('Evidence'!S31),'Evidence'!S31,"") | T29: Unreviewed source extract; annual cells contain… [N158] | U29: Evidence row 31;… [N159] | V29: G07: test commodity output versus material… [N160]
A30: Mining/quarrying real GVA | B30: bn 2015 ZAR | C30: Staged observation | D30: =IF(ISNUMBER('Evidence'!D28),'Evidence'!D28,"") | E30: Stats SA annual actual in staged reporting copy. Sector value… [N161] | F30: =IF(ISNUMBER('Evidence'!F28),'Evidence'!F28,"") | G30: =IF(ISNUMBER('Evidence'!G28),'Evidence'!G28,"") | H30: =IF(ISNUMBER('Evidence'!H28),'Evidence'!H28,"") | I30: =IF(ISNUMBER('Evidence'!I28),'Evidence'!I28,"") | J30: =IF(ISNUMBER('Evidence'!J28),'Evidence'!J28,"") | K30: =IF(ISNUMBER('Evidence'!K28),'Evidence'!K28,"") | L30: =IF(ISNUMBER('Evidence'!L28),'Evidence'!L28,"") | M30: =IF(ISNUMBER('Evidence'!M28),'Evidence'!M28,"") | ... S30: =IF(ISNUMBER('Evidence'!S28),'Evidence'!S28,"") | T30: Unreviewed source extract; annual cells contain… [N162] | U30: Evidence row 28;… [N163] | V30: G07: alternative activity proxy; do not multiply… [N164]
A31: 2021 mining/quarrying diesel | B31: million L/year | C31: Staged observation | D31: =IF(ISNUMBER('Evidence'!D42),'Evidence'!D42,"") | E31: D is a 2021 anchor. Not a 2022 observation or approved starting assumption. | T31: Source fuel use available only through 2021. | U31: https://github.com/Africa-International-Advisors/liq… [N165] | V31: G07: verify machinery/haulage/backup boundaries and… [N166]

Sheet Other demand
A1: Power, aviation and marine demand
A2: Current engine inputs and available observations • Partial periods and fiscal years remain explicit.
A4: Driver / output | B4: Unit | C4: Role | D4: Scalar / latest value | E4: Definition / period | F4: 2022 | G4: 2023 | H4: 2024 | I4: 2025 | J4: 2026 | K4: 2027 | L4: 2028 | M4: 2029 | N4: 2030 | O4: 2031 | P4: 2032 | Q4: 2033 | R4: 2034 | S4: 2035 | T4: Coverage / status | U4: Source | V4: Missing evidence / next action
A5: Power-generation diesel
A6: Eskom OCGT generation | B6: GWh / financial year | C6: Staged observation | D6: =IF(ISNUMBER('Evidence'!D34),'Evidence'!D34,"") | E6: Full financial year ending 31 March in the column year. Not… [N167] | F6: =IF(ISNUMBER('Evidence'!F34),'Evidence'!F34,"") | G6: =IF(ISNUMBER('Evidence'!G34),'Evidence'!G34,"") | H6: =IF(ISNUMBER('Evidence'!H34),'Evidence'!H34,"") | I6: =IF(ISNUMBER('Evidence'!I34),'Evidence'!I34,"") | J6: =IF(ISNUMBER('Evidence'!J34),'Evidence'!J34,"") | K6: =IF(ISNUMBER('Evidence'!K34),'Evidence'!K34,"") | L6: =IF(ISNUMBER('Evidence'!L34),'Evidence'!L34,"") | M6: =IF(ISNUMBER('Evidence'!M34),'Evidence'!M34,"") | ... S6: =IF(ISNUMBER('Evidence'!S34),'Evidence'!S34,"") | T6: Unreviewed source extract; annual cells contain… [N168] | U6: Evidence row 34;… [N169] | V6: G09: source matched litres and convert FY evidence… [N170]
A7: IPP OCGT generation | B7: GWh / financial year | C7: Staged observation | D7: =IF(ISNUMBER('Evidence'!D35),'Evidence'!D35,"") | E7: Full financial year ending 31 March in the column year. Not… [N171] | F7: =IF(ISNUMBER('Evidence'!F35),'Evidence'!F35,"") | G7: =IF(ISNUMBER('Evidence'!G35),'Evidence'!G35,"") | H7: =IF(ISNUMBER('Evidence'!H35),'Evidence'!H35,"") | I7: =IF(ISNUMBER('Evidence'!I35),'Evidence'!I35,"") | J7: =IF(ISNUMBER('Evidence'!J35),'Evidence'!J35,"") | K7: =IF(ISNUMBER('Evidence'!K35),'Evidence'!K35,"") | L7: =IF(ISNUMBER('Evidence'!L35),'Evidence'!L35,"") | M7: =IF(ISNUMBER('Evidence'!M35),'Evidence'!M35,"") | ... S7: =IF(ISNUMBER('Evidence'!S35),'Evidence'!S35,"") | T7: Unreviewed source extract; annual cells contain… [N172] | U7: Evidence row 35;… [N173] | V7: G09: match plant set and fuel-burn evidence.
A8: Combined OCGT generation | B8: GWh / financial year | C8: Staged observation | D8: =IF(ISNUMBER('Evidence'!D36),'Evidence'!D36,"") | E8: Full financial year ending 31 March in the column year. Not… [N174] | F8: =IF(ISNUMBER('Evidence'!F36),'Evidence'!F36,"") | G8: =IF(ISNUMBER('Evidence'!G36),'Evidence'!G36,"") | H8: =IF(ISNUMBER('Evidence'!H36),'Evidence'!H36,"") | I8: =IF(ISNUMBER('Evidence'!I36),'Evidence'!I36,"") | J8: =IF(ISNUMBER('Evidence'!J36),'Evidence'!J36,"") | K8: =IF(ISNUMBER('Evidence'!K36),'Evidence'!K36,"") | L8: =IF(ISNUMBER('Evidence'!L36),'Evidence'!L36,"") | M8: =IF(ISNUMBER('Evidence'!M36),'Evidence'!M36,"") | ... S8: =IF(ISNUMBER('Evidence'!S36),'Evidence'!S36,"") | T8: Unreviewed source extract; annual cells contain… [N175] | U8: Evidence row 36;… [N176] | V8: Comparison total only; do not add to Eskom + IPP again.
A9: Current engine load factor | B9: share | C9: Current input | E9: Legacy scenario path. Not measured dispatch. | F9: =IF(ISNUMBER('Model run'!F37),'Model run'!F37,"") | G9: =IF(ISNUMBER('Model run'!G37),'Model run'!G37,"") | H9: =IF(ISNUMBER('Model run'!H37),'Model run'!H37,"") | I9: =IF(ISNUMBER('Model run'!I37),'Model run'!I37,"") | J9: =IF(ISNUMBER('Model run'!J37),'Model run'!J37,"") | K9: =IF(ISNUMBER('Model run'!K37),'Model run'!K37,"") | L9: =IF(ISNUMBER('Model run'!L37),'Model run'!L37,"") | M9: =IF(ISNUMBER('Model run'!M37),'Model run'!M37,"") | ... S9: =IF(ISNUMBER('Model run'!S37),'Model run'!S37,"") | T9: Current high_demand input. | U9: https://github.com/Africa-International-Advisors/liq… [N177] | V9: G09: calibrate against operating generation and plant scope.
A10: Current thermal efficiency | B10: share | C10: Current scalar | D10: =IF(ISNUMBER('Model run'!D38),'Model run'!D38,"") | E10: Fraction of fuel energy converted to electricity. | T10: Legacy input. | U10: https://github.com/Africa-International-Advisors/liq… [N178] | V10: Review conversion with matched plant data.
A11: Diesel energy content | B11: MJ/L | C11: Current scalar | D11: =IF(ISNUMBER('Model run'!D39),'Model run'!D39,"") | E11: Current engine conversion input. | T11: Legacy input. | U11: https://github.com/Africa-International-Advisors/liq… [N179] | V11: Verify product and unit basis.
A12: Current OCGT diesel demand | B12: million L/year | C12: Model output | E12: Calendar-year model output; do not directly tie to FY generation… [N180] | F12: =IF(ISNUMBER('Model run'!F40),'Model run'!F40,"") | G12: =IF(ISNUMBER('Model run'!G40),'Model run'!G40,"") | H12: =IF(ISNUMBER('Model run'!H40),'Model run'!H40,"") | I12: =IF(ISNUMBER('Model run'!I40),'Model run'!I40,"") | J12: =IF(ISNUMBER('Model run'!J40),'Model run'!J40,"") | K12: =IF(ISNUMBER('Model run'!K40),'Model run'!K40,"") | L12: =IF(ISNUMBER('Model run'!L40),'Model run'!L40,"") | M12: =IF(ISNUMBER('Model run'!M40),'Model run'!M40,"") | ... S12: =IF(ISNUMBER('Model run'!S40),'Model run'!S40,"") | T12: 2026 vintage; current high_demand case; provisional. | U12: https://github.com/Africa-International-Advisors/liq… [N181] | V12: Validate inputs and reconcile against observed data.
A13: Private backup diesel baseline | B13: million L/year | C13: Missing input | E13: No separate observed litres established. Some may already be in… [N182] | T13: Missing coverage and calibration. | V13: G09: source dispatch/fuel observations and sector overlap.
A16: Jet aviation
A17: ACSA aircraft departures | B17: departures | C17: Staged observation | D17: =IF(ISNUMBER('Evidence'!D38),'Evidence'!D38,"") | E17: ACSA departures only; sums monthly total-flight rows without… [N183] | F17: =IF(ISNUMBER('Evidence'!F38),'Evidence'!F38,"") | G17: =IF(ISNUMBER('Evidence'!G38),'Evidence'!G38,"") | H17: =IF(ISNUMBER('Evidence'!H38),'Evidence'!H38,"") | I17: =IF(ISNUMBER('Evidence'!I38),'Evidence'!I38,"") | J17: =IF(ISNUMBER('Evidence'!J38),'Evidence'!J38,"") | K17: =IF(ISNUMBER('Evidence'!K38),'Evidence'!K38,"") | L17: =IF(ISNUMBER('Evidence'!L38),'Evidence'!L38,"") | M17: =IF(ISNUMBER('Evidence'!M38),'Evidence'!M38,"") | ... S17: =IF(ISNUMBER('Evidence'!S38),'Evidence'!S38,"") | T17: Unreviewed source extract; annual cells contain… [N184] | U17: Evidence row 38;… [N185] | V17: G10: fit movements to jet uplift, aircraft/route… [N186]
A18: ACSA passenger departures | B18: departures | C18: Staged observation | D18: =IF(ISNUMBER('Evidence'!D37),'Evidence'!D37,"") | E18: ACSA departures only; sums monthly total-flight rows without… [N187] | F18: =IF(ISNUMBER('Evidence'!F37),'Evidence'!F37,"") | G18: =IF(ISNUMBER('Evidence'!G37),'Evidence'!G37,"") | H18: =IF(ISNUMBER('Evidence'!H37),'Evidence'!H37,"") | I18: =IF(ISNUMBER('Evidence'!I37),'Evidence'!I37,"") | J18: =IF(ISNUMBER('Evidence'!J37),'Evidence'!J37,"") | K18: =IF(ISNUMBER('Evidence'!K37),'Evidence'!K37,"") | L18: =IF(ISNUMBER('Evidence'!L37),'Evidence'!L37,"") | M18: =IF(ISNUMBER('Evidence'!M37),'Evidence'!M37,"") | ... S18: =IF(ISNUMBER('Evidence'!S37),'Evidence'!S37,"") | T18: Unreviewed source extract; annual cells contain… [N188] | U18: Evidence row 37;… [N189] | V18: G10: match legacy passenger input coverage and periods.
A19: Current engine passenger departures | B19: passengers/year | C19: Current input | E19: Legacy regression driver; separate from new ACSA observations. | F19: =IF(ISNUMBER('Model run'!F41),'Model run'!F41,"") | G19: =IF(ISNUMBER('Model run'!G41),'Model run'!G41,"") | H19: =IF(ISNUMBER('Model run'!H41),'Model run'!H41,"") | I19: =IF(ISNUMBER('Model run'!I41),'Model run'!I41,"") | J19: =IF(ISNUMBER('Model run'!J41),'Model run'!J41,"") | K19: =IF(ISNUMBER('Model run'!K41),'Model run'!K41,"") | L19: =IF(ISNUMBER('Model run'!L41),'Model run'!L41,"") | M19: =IF(ISNUMBER('Model run'!M41),'Model run'!M41,"") | ... S19: =IF(ISNUMBER('Model run'!S41),'Model run'!S41,"") | T19: Historical/forecast legacy path. | U19: https://github.com/Africa-International-Advisors/liq… [N190] | V19: Fit proposed movement-based model before replacing… [N191]
A20: Current jet demand | B20: million L/year | C20: Model output | E20: Legacy two-driver regression. | F20: =IF(ISNUMBER('Model run'!F42),'Model run'!F42,"") | G20: =IF(ISNUMBER('Model run'!G42),'Model run'!G42,"") | H20: =IF(ISNUMBER('Model run'!H42),'Model run'!H42,"") | I20: =IF(ISNUMBER('Model run'!I42),'Model run'!I42,"") | J20: =IF(ISNUMBER('Model run'!J42),'Model run'!J42,"") | K20: =IF(ISNUMBER('Model run'!K42),'Model run'!K42,"") | L20: =IF(ISNUMBER('Model run'!L42),'Model run'!L42,"") | M20: =IF(ISNUMBER('Model run'!M42),'Model run'!M42,"") | ... S20: =IF(ISNUMBER('Model run'!S42),'Model run'!S42,"") | T20: 2026 vintage; current high_demand case; provisional. | U20: https://github.com/Africa-International-Advisors/liq… [N192] | V20: Validate inputs and reconcile against observed data.
A21: Reported jet sales — FIASA | B21: million L/year | C21: Staged observation | D21: =IF(ISNUMBER('Evidence'!D9),'Evidence'!D9,"") | E21: FIASA staged reported sales; latest edition selected by existing… [N193] | F21: =IF(ISNUMBER('Evidence'!F9),'Evidence'!F9,"") | G21: =IF(ISNUMBER('Evidence'!G9),'Evidence'!G9,"") | H21: =IF(ISNUMBER('Evidence'!H9),'Evidence'!H9,"") | I21: =IF(ISNUMBER('Evidence'!I9),'Evidence'!I9,"") | J21: =IF(ISNUMBER('Evidence'!J9),'Evidence'!J9,"") | K21: =IF(ISNUMBER('Evidence'!K9),'Evidence'!K9,"") | L21: =IF(ISNUMBER('Evidence'!L9),'Evidence'!L9,"") | M21: =IF(ISNUMBER('Evidence'!M9),'Evidence'!M9,"") | ... S21: =IF(ISNUMBER('Evidence'!S9),'Evidence'!S9,"") | T21: Unreviewed source extract; annual cells contain… [N194] | U21: Evidence row 9; assumptions/2026/timeseries/fuel_sales_fiasa.csv | V21: G10: match fuel product, airport/airline and… [N195]
A22: Legacy jet regression intercept | B22: L/year | C22: Current scalar | D22: =IF(ISNUMBER('Model run'!D43),'Model run'!D43,"") | E22: Jet = intercept + GDP/capita coefficient × GDP/capita + passenger… [N196] | T22: Legacy fit; not refitted. | U22: https://github.com/Africa-International-Advisors/liq… [N197] | V22: Review model and unit basis.
A23: GDP/capita coefficient | B23: L per ZAR/person | C23: Current scalar | D23: =IF(ISNUMBER('Model run'!D44),'Model run'!D44,"") | E23: Used with current macro path. | T23: Legacy fit. | U23: https://github.com/Africa-International-Advisors/liq… [N198] | V23: Validate driver overlap and fit.
A24: Passenger coefficient | B24: L per departure | C24: Current scalar | D24: =IF(ISNUMBER('Model run'!D45),'Model run'!D45,"") | E24: Passenger departure basis. | T24: Legacy fit. | U24: https://github.com/Africa-International-Advisors/liq… [N199] | V24: Refit using matched aircraft and fuel data.
A27: Marine demand
A28: durban provisional port baseline | B28: million L/year | C28: Current scalar | D28: =IF(ISNUMBER('Model run'!D46),'Model run'!D46,"") | E28: Current 2024 placeholder; not measured port bunkering. | T28: Provisional held baseline. | U28: https://github.com/Africa-International-Advisors/liq… [N200] | V28: G12: source annual port/product bunker deliveries.
A29: cape_town provisional port baseline | B29: million L/year | C29: Current scalar | D29: =IF(ISNUMBER('Model run'!D47),'Model run'!D47,"") | E29: Current 2024 placeholder; not measured port bunkering. | T29: Provisional held baseline. | U29: https://github.com/Africa-International-Advisors/liq… [N201] | V29: G12: source annual port/product bunker deliveries.
A30: saldanha provisional port baseline | B30: million L/year | C30: Current scalar | D30: =IF(ISNUMBER('Model run'!D48),'Model run'!D48,"") | E30: Current 2024 placeholder; not measured port bunkering. | T30: Provisional held baseline. | U30: https://github.com/Africa-International-Advisors/liq… [N202] | V30: G12: source annual port/product bunker deliveries.
A31: Marine GDP/capita elasticity | B31: dimensionless | C31: Current scalar | D31: =IF(ISNUMBER('Model run'!D49),'Model run'!D49,"") | E31: Current proxy response. | T31: Provisional. | U31: https://github.com/Africa-International-Advisors/liq… [N203] | V31: Replace/test against vessel/port activity.
A32: Marine fuel-oil share | B32: share | C32: Current scalar | D32: =IF(ISNUMBER('Model run'!D50),'Model run'!D50,"") | E32: One provisional split across ports. | T32: Not port-specific. | U32: https://github.com/Africa-International-Advisors/liq… [N204] | V32: G12: source product shares.
A33: Marine diesel share | B33: share | C33: Current scalar | D33: =IF(ISNUMBER('Model run'!D51),'Model run'!D51,"") | E33: Diesel_500ppm; part of total diesel comparison. | T33: Not port-specific. | U33: https://github.com/Africa-International-Advisors/liq… [N205] | V33: G12: reconcile domestic and international bunkers.
A34: Marine diesel demand | B34: million L/year | C34: Model output | E34: No 2022–23 output from current marine engine. | H34: =IF(ISNUMBER('Model run'!H52),'Model run'!H52,"") | I34: =IF(ISNUMBER('Model run'!I52),'Model run'!I52,"") | J34: =IF(ISNUMBER('Model run'!J52),'Model run'!J52,"") | K34: =IF(ISNUMBER('Model run'!K52),'Model run'!K52,"") | L34: =IF(ISNUMBER('Model run'!L52),'Model run'!L52,"") | M34: =IF(ISNUMBER('Model run'!M52),'Model run'!M52,"") | N34: =IF(ISNUMBER('Model run'!N52),'Model run'!N52,"") | O34: =IF(ISNUMBER('Model run'!O52),'Model run'!O52,"") | ... S34: =IF(ISNUMBER('Model run'!S52),'Model run'!S52,"") | T34: 2026 vintage; current high_demand case; provisional. | U34: https://github.com/Africa-International-Advisors/liq… [N206] | V34: Validate inputs and reconcile against observed data.
A35: Marine fuel-oil demand | B35: million L/year | C35: Model output | E35: Marine only; does not represent all national fuel-oil consumption. | H35: =IF(ISNUMBER('Model run'!H53),'Model run'!H53,"") | I35: =IF(ISNUMBER('Model run'!I53),'Model run'!I53,"") | J35: =IF(ISNUMBER('Model run'!J53),'Model run'!J53,"") | K35: =IF(ISNUMBER('Model run'!K53),'Model run'!K53,"") | L35: =IF(ISNUMBER('Model run'!L53),'Model run'!L53,"") | M35: =IF(ISNUMBER('Model run'!M53),'Model run'!M53,"") | N35: =IF(ISNUMBER('Model run'!N53),'Model run'!N53,"") | O35: =IF(ISNUMBER('Model run'!O53),'Model run'!O53,"") | ... S35: =IF(ISNUMBER('Model run'!S53),'Model run'!S53,"") | T35: 2026 vintage; current high_demand case; provisional. | U35: https://github.com/Africa-International-Advisors/liq… [N207] | V35: Validate inputs and reconcile against observed data.

Sheet Provincial
A1: Provincial allocation example
A2: Petrol passenger demand • Shares are blank pending evidence. This is allocation, not a local-driver forecast.
A4: Province / control | B4: Row type | C4: Evidence / method | D4: 2022 | E4: 2023 | F4: 2024 | G4: 2025 | H4: 2026 | I4: 2027 | J4: 2028 | K4: 2029 | L4: 2030 | M4: 2031 | N4: 2032 | O4: 2033 | P4: 2034 | Q4: 2035 | R4: Latest partial value | S4: Latest period | T4: Coverage / status | U4: Source | V4: Missing evidence / next action
A5: National passenger petrol | B5: million L/year | C5: Linked to Petrol current-engine output | D5: ='Petrol'!F21 | E5: ='Petrol'!G21 | F5: ='Petrol'!H21 | G5: ='Petrol'!I21 | H5: ='Petrol'!J21 | I5: ='Petrol'!K21 | J5: ='Petrol'!L21 | K5: ='Petrol'!M21 | ... Q5: ='Petrol'!S21
A7: Eastern Cape | B7: Allocation share | C7: Enter annual share and source; 0 only if confirmed
A8: Free State | B8: Allocation share | C8: Enter annual share and source; 0 only if confirmed
A9: Gauteng | B9: Allocation share | C9: Enter annual share and source; 0 only if confirmed
A10: KwaZulu-Natal | B10: Allocation share | C10: Enter annual share and source; 0 only if confirmed
A11: Limpopo | B11: Allocation share | C11: Enter annual share and source; 0 only if confirmed
A12: Mpumalanga | B12: Allocation share | C12: Enter annual share and source; 0 only if confirmed
A13: Northern Cape | B13: Allocation share | C13: Enter annual share and source; 0 only if confirmed
A14: North West | B14: Allocation share | C14: Enter annual share and source; 0 only if confirmed
A15: Western Cape | B15: Allocation share | C15: Enter annual share and source; 0 only if confirmed
A16: Share total | B16: share | C16: Reporting calculation | D16: =IF(COUNT(D7:D15)=0,"",SUM(D7:D15)) | E16: =IF(COUNT(E7:E15)=0,"",SUM(E7:E15)) | F16: =IF(COUNT(F7:F15)=0,"",SUM(F7:F15)) | G16: =IF(COUNT(G7:G15)=0,"",SUM(G7:G15)) | H16: =IF(COUNT(H7:H15)=0,"",SUM(H7:H15)) | I16: =IF(COUNT(I7:I15)=0,"",SUM(I7:I15)) | J16: =IF(COUNT(J7:J15)=0,"",SUM(J7:J15)) | K16: =IF(COUNT(K7:K15)=0,"",SUM(K7:K15)) | ... Q16: =IF(COUNT(Q7:Q15)=0,"",SUM(Q7:Q15))
A18: Eastern Cape | B18: million L/year | C18: National demand × entered share | D18: =IF(ISNUMBER(D7),D$5*D7,"") | E18: =IF(ISNUMBER(E7),E$5*E7,"") | F18: =IF(ISNUMBER(F7),F$5*F7,"") | G18: =IF(ISNUMBER(G7),G$5*G7,"") | H18: =IF(ISNUMBER(H7),H$5*H7,"") | I18: =IF(ISNUMBER(I7),I$5*I7,"") | J18: =IF(ISNUMBER(J7),J$5*J7,"") | K18: =IF(ISNUMBER(K7),K$5*K7,"") | ... Q18: =IF(ISNUMBER(Q7),Q$5*Q7,"")
A19: Free State | B19: million L/year | C19: National demand × entered share | D19: =IF(ISNUMBER(D8),D$5*D8,"") | E19: =IF(ISNUMBER(E8),E$5*E8,"") | F19: =IF(ISNUMBER(F8),F$5*F8,"") | G19: =IF(ISNUMBER(G8),G$5*G8,"") | H19: =IF(ISNUMBER(H8),H$5*H8,"") | I19: =IF(ISNUMBER(I8),I$5*I8,"") | J19: =IF(ISNUMBER(J8),J$5*J8,"") | K19: =IF(ISNUMBER(K8),K$5*K8,"") | ... Q19: =IF(ISNUMBER(Q8),Q$5*Q8,"")
A20: Gauteng | B20: million L/year | C20: National demand × entered share | D20: =IF(ISNUMBER(D9),D$5*D9,"") | E20: =IF(ISNUMBER(E9),E$5*E9,"") | F20: =IF(ISNUMBER(F9),F$5*F9,"") | G20: =IF(ISNUMBER(G9),G$5*G9,"") | H20: =IF(ISNUMBER(H9),H$5*H9,"") | I20: =IF(ISNUMBER(I9),I$5*I9,"") | J20: =IF(ISNUMBER(J9),J$5*J9,"") | K20: =IF(ISNUMBER(K9),K$5*K9,"") | ... Q20: =IF(ISNUMBER(Q9),Q$5*Q9,"")
A21: KwaZulu-Natal | B21: million L/year | C21: National demand × entered share | D21: =IF(ISNUMBER(D10),D$5*D10,"") | E21: =IF(ISNUMBER(E10),E$5*E10,"") | F21: =IF(ISNUMBER(F10),F$5*F10,"") | G21: =IF(ISNUMBER(G10),G$5*G10,"") | H21: =IF(ISNUMBER(H10),H$5*H10,"") | I21: =IF(ISNUMBER(I10),I$5*I10,"") | J21: =IF(ISNUMBER(J10),J$5*J10,"") | K21: =IF(ISNUMBER(K10),K$5*K10,"") | ... Q21: =IF(ISNUMBER(Q10),Q$5*Q10,"")
A22: Limpopo | B22: million L/year | C22: National demand × entered share | D22: =IF(ISNUMBER(D11),D$5*D11,"") | E22: =IF(ISNUMBER(E11),E$5*E11,"") | F22: =IF(ISNUMBER(F11),F$5*F11,"") | G22: =IF(ISNUMBER(G11),G$5*G11,"") | H22: =IF(ISNUMBER(H11),H$5*H11,"") | I22: =IF(ISNUMBER(I11),I$5*I11,"") | J22: =IF(ISNUMBER(J11),J$5*J11,"") | K22: =IF(ISNUMBER(K11),K$5*K11,"") | ... Q22: =IF(ISNUMBER(Q11),Q$5*Q11,"")
A23: Mpumalanga | B23: million L/year | C23: National demand × entered share | D23: =IF(ISNUMBER(D12),D$5*D12,"") | E23: =IF(ISNUMBER(E12),E$5*E12,"") | F23: =IF(ISNUMBER(F12),F$5*F12,"") | G23: =IF(ISNUMBER(G12),G$5*G12,"") | H23: =IF(ISNUMBER(H12),H$5*H12,"") | I23: =IF(ISNUMBER(I12),I$5*I12,"") | J23: =IF(ISNUMBER(J12),J$5*J12,"") | K23: =IF(ISNUMBER(K12),K$5*K12,"") | ... Q23: =IF(ISNUMBER(Q12),Q$5*Q12,"")
A24: Northern Cape | B24: million L/year | C24: National demand × entered share | D24: =IF(ISNUMBER(D13),D$5*D13,"") | E24: =IF(ISNUMBER(E13),E$5*E13,"") | F24: =IF(ISNUMBER(F13),F$5*F13,"") | G24: =IF(ISNUMBER(G13),G$5*G13,"") | H24: =IF(ISNUMBER(H13),H$5*H13,"") | I24: =IF(ISNUMBER(I13),I$5*I13,"") | J24: =IF(ISNUMBER(J13),J$5*J13,"") | K24: =IF(ISNUMBER(K13),K$5*K13,"") | ... Q24: =IF(ISNUMBER(Q13),Q$5*Q13,"")
A25: North West | B25: million L/year | C25: National demand × entered share | D25: =IF(ISNUMBER(D14),D$5*D14,"") | E25: =IF(ISNUMBER(E14),E$5*E14,"") | F25: =IF(ISNUMBER(F14),F$5*F14,"") | G25: =IF(ISNUMBER(G14),G$5*G14,"") | H25: =IF(ISNUMBER(H14),H$5*H14,"") | I25: =IF(ISNUMBER(I14),I$5*I14,"") | J25: =IF(ISNUMBER(J14),J$5*J14,"") | K25: =IF(ISNUMBER(K14),K$5*K14,"") | ... Q25: =IF(ISNUMBER(Q14),Q$5*Q14,"")
A26: Western Cape | B26: million L/year | C26: National demand × entered share | D26: =IF(ISNUMBER(D15),D$5*D15,"") | E26: =IF(ISNUMBER(E15),E$5*E15,"") | F26: =IF(ISNUMBER(F15),F$5*F15,"") | G26: =IF(ISNUMBER(G15),G$5*G15,"") | H26: =IF(ISNUMBER(H15),H$5*H15,"") | I26: =IF(ISNUMBER(I15),I$5*I15,"") | J26: =IF(ISNUMBER(J15),J$5*J15,"") | K26: =IF(ISNUMBER(K15),K$5*K15,"") | ... Q26: =IF(ISNUMBER(Q15),Q$5*Q15,"")
A27: Allocated demand | B27: million L/year | C27: Reporting calculation | D27: =IF(COUNT(D18:D26)=0,"",SUM(D18:D26)) | E27: =IF(COUNT(E18:E26)=0,"",SUM(E18:E26)) | F27: =IF(COUNT(F18:F26)=0,"",SUM(F18:F26)) | G27: =IF(COUNT(G18:G26)=0,"",SUM(G18:G26)) | H27: =IF(COUNT(H18:H26)=0,"",SUM(H18:H26)) | I27: =IF(COUNT(I18:I26)=0,"",SUM(I18:I26)) | J27: =IF(COUNT(J18:J26)=0,"",SUM(J18:J26)) | K27: =IF(COUNT(K18:K26)=0,"",SUM(K18:K26)) | ... Q27: =IF(COUNT(Q18:Q26)=0,"",SUM(Q18:Q26))
A28: Unallocated demand | B28: million L/year | C28: Residual includes all missing allocations | D28: =D5-SUM(D18:D26) | E28: =E5-SUM(E18:E26) | F28: =F5-SUM(F18:F26) | G28: =G5-SUM(G18:G26) | H28: =H5-SUM(H18:H26) | I28: =I5-SUM(I18:I26) | J28: =J5-SUM(J18:J26) | K28: =K5-SUM(K18:K26) | ... Q28: =Q5-SUM(Q18:Q26)
A29: Allocation check | B29: check | C29: Complete when nine numeric shares sum to 100% | D29: =IF(COUNT(D7:D15)<9,"Missing shares",IF(ABS(SUM(D7:D15)-1)<0.000001,"Reconciled","Shares do not sum to 100%")) | E29: =IF(COUNT(E7:E15)<9,"Missing shares",IF(ABS(SUM(E7:E15)-1)<0.000001,"Reconciled","Shares do not sum to 100%")) | F29: =IF(COUNT(F7:F15)<9,"Missing shares",IF(ABS(SUM(F7:F15)-1)<0.000001,"Reconciled","Shares do not sum to 100%")) | G29: =IF(COUNT(G7:G15)<9,"Missing shares",IF(ABS(SUM(G7:G15)-1)<0.000001,"Reconciled","Shares do not sum to 100%")) | H29: =IF(COUNT(H7:H15)<9,"Missing shares",IF(ABS(SUM(H7:H15)-1)<0.000001,"Reconciled","Shares do not sum to 100%")) | I29: =IF(COUNT(I7:I15)<9,"Missing shares",IF(ABS(SUM(I7:I15)-1)<0.000001,"Reconciled","Shares do not sum to 100%")) | J29: =IF(COUNT(J7:J15)<9,"Missing shares",IF(ABS(SUM(J7:J15)-1)<0.000001,"Reconciled","Shares do not sum to 100%")) | K29: =IF(COUNT(K7:K15)<9,"Missing shares",IF(ABS(SUM(K7:K15)-1)<0.000001,"Reconciled","Shares do not sum to 100%")) | ... Q29: =IF(COUNT(Q7:Q15)<9,"Missing shares",IF(ABS(SUM(Q7:Q15)-1)<0.000001,"Reconciled","Shares do not sum to 100%"))
A31: Other segments | B31: Workshop decision | C31: Repeat by segment with its own allocation evidence. For local calculations, replace allocated rows with engine outputs; retain national reconciliation.
A33: Observed provincial fuel sales
A34: EC petrol | B34: million L/year | C34: Observed product sales, not passenger/freight-only demand. | D34: =IF(ISNUMBER('Evidence'!F43),'Evidence'!F43,"") | R34: =IF(ISNUMBER('Evidence'!D43),'Evidence'!D43,"") | S34: 2023 Q1 only | T34: 2022 full year; latest Q1 2023 in R, not annualised. | U34: https://github.com/Africa-International-Advisors/liquid_fuels_model/blob/8c69f8333192483f19cd80911cb90fcd0943eb6b/assumptions/2026/timeseries/fuel_sales_department_by_province_quarterly.csv | V34: G11: obtain later complete years and sector allocation. Do not use total petrol shares automatically for passenger demand.
A35: FS petrol | B35: million L/year | C35: Observed product sales, not passenger/freight-only demand. | D35: =IF(ISNUMBER('Evidence'!F44),'Evidence'!F44,"") | R35: =IF(ISNUMBER('Evidence'!D44),'Evidence'!D44,"") | S35: 2023 Q1 only | T35: 2022 full year; latest Q1 2023 in R, not annualised. | U35: https://github.com/Africa-International-Advisors/liquid_fuels_model/blob/8c69f8333192483f19cd80911cb90fcd0943eb6b/assumptions/2026/timeseries/fuel_sales_department_by_province_quarterly.csv | V35: G11: obtain later complete years and sector allocation. Do not use total petrol shares automatically for passenger demand.
A36: GP petrol | B36: million L/year | C36: Observed product sales, not passenger/freight-only demand. | D36: =IF(ISNUMBER('Evidence'!F45),'Evidence'!F45,"") | R36: =IF(ISNUMBER('Evidence'!D45),'Evidence'!D45,"") | S36: 2023 Q1 only | T36: 2022 full year; latest Q1 2023 in R, not annualised. | U36: https://github.com/Africa-International-Advisors/liquid_fuels_model/blob/8c69f8333192483f19cd80911cb90fcd0943eb6b/assumptions/2026/timeseries/fuel_sales_department_by_province_quarterly.csv | V36: G11: obtain later complete years and sector allocation. Do not use total petrol shares automatically for passenger demand.
A37: KZN petrol | B37: million L/year | C37: Observed product sales, not passenger/freight-only demand. | D37: =IF(ISNUMBER('Evidence'!F46),'Evidence'!F46,"") | R37: =IF(ISNUMBER('Evidence'!D46),'Evidence'!D46,"") | S37: 2023 Q1 only | T37: 2022 full year; latest Q1 2023 in R, not annualised. | U37: https://github.com/Africa-International-Advisors/liquid_fuels_model/blob/8c69f8333192483f19cd80911cb90fcd0943eb6b/assumptions/2026/timeseries/fuel_sales_department_by_province_quarterly.csv | V37: G11: obtain later complete years and sector allocation. Do not use total petrol shares automatically for passenger demand.
A38: LP petrol | B38: million L/year | C38: Observed product sales, not passenger/freight-only demand. | D38: =IF(ISNUMBER('Evidence'!F47),'Evidence'!F47,"") | R38: =IF(ISNUMBER('Evidence'!D47),'Evidence'!D47,"") | S38: 2023 Q1 only | T38: 2022 full year; latest Q1 2023 in R, not annualised. | U38: https://github.com/Africa-International-Advisors/liquid_fuels_model/blob/8c69f8333192483f19cd80911cb90fcd0943eb6b/assumptions/2026/timeseries/fuel_sales_department_by_province_quarterly.csv | V38: G11: obtain later complete years and sector allocation. Do not use total petrol shares automatically for passenger demand.
A39: MP petrol | B39: million L/year | C39: Observed product sales, not passenger/freight-only demand. | D39: =IF(ISNUMBER('Evidence'!F48),'Evidence'!F48,"") | R39: =IF(ISNUMBER('Evidence'!D48),'Evidence'!D48,"") | S39: 2023 Q1 only | T39: 2022 full year; latest Q1 2023 in R, not annualised. | U39: https://github.com/Africa-International-Advisors/liquid_fuels_model/blob/8c69f8333192483f19cd80911cb90fcd0943eb6b/assumptions/2026/timeseries/fuel_sales_department_by_province_quarterly.csv | V39: G11: obtain later complete years and sector allocation. Do not use total petrol shares automatically for passenger demand.
A40: NC petrol | B40: million L/year | C40: Observed product sales, not passenger/freight-only demand. | D40: =IF(ISNUMBER('Evidence'!F49),'Evidence'!F49,"") | R40: =IF(ISNUMBER('Evidence'!D49),'Evidence'!D49,"") | S40: 2023 Q1 only | T40: 2022 full year; latest Q1 2023 in R, not annualised. | U40: https://github.com/Africa-International-Advisors/liquid_fuels_model/blob/8c69f8333192483f19cd80911cb90fcd0943eb6b/assumptions/2026/timeseries/fuel_sales_department_by_province_quarterly.csv | V40: G11: obtain later complete years and sector allocation. Do not use total petrol shares automatically for passenger demand.
A41: NW petrol | B41: million L/year | C41: Observed product sales, not passenger/freight-only demand. | D41: =IF(ISNUMBER('Evidence'!F50),'Evidence'!F50,"") | R41: =IF(ISNUMBER('Evidence'!D50),'Evidence'!D50,"") | S41: 2023 Q1 only | T41: 2022 full year; latest Q1 2023 in R, not annualised. | U41: https://github.com/Africa-International-Advisors/liquid_fuels_model/blob/8c69f8333192483f19cd80911cb90fcd0943eb6b/assumptions/2026/timeseries/fuel_sales_department_by_province_quarterly.csv | V41: G11: obtain later complete years and sector allocation. Do not use total petrol shares automatically for passenger demand.
A42: WC petrol | B42: million L/year | C42: Observed product sales, not passenger/freight-only demand. | D42: =IF(ISNUMBER('Evidence'!F51),'Evidence'!F51,"") | R42: =IF(ISNUMBER('Evidence'!D51),'Evidence'!D51,"") | S42: 2023 Q1 only | T42: 2022 full year; latest Q1 2023 in R, not annualised. | U42: https://github.com/Africa-International-Advisors/liquid_fuels_model/blob/8c69f8333192483f19cd80911cb90fcd0943eb6b/assumptions/2026/timeseries/fuel_sales_department_by_province_quarterly.csv | V42: G11: obtain later complete years and sector allocation. Do not use total petrol shares automatically for passenger demand.
A43: EC diesel | B43: million L/year | C43: Observed product sales, not passenger/freight-only demand. | D43: =IF(ISNUMBER('Evidence'!F52),'Evidence'!F52,"") | R43: =IF(ISNUMBER('Evidence'!D52),'Evidence'!D52,"") | S43: 2023 Q1 only | T43: 2022 full year; latest Q1 2023 in R, not annualised. | U43: https://github.com/Africa-International-Advisors/liquid_fuels_model/blob/8c69f8333192483f19cd80911cb90fcd0943eb6b/assumptions/2026/timeseries/fuel_sales_department_by_province_quarterly.csv | V43: G11: obtain later complete years and sector allocation. Do not use total petrol shares automatically for passenger demand.
A44: FS diesel | B44: million L/year | C44: Observed product sales, not passenger/freight-only demand. | D44: =IF(ISNUMBER('Evidence'!F53),'Evidence'!F53,"") | R44: =IF(ISNUMBER('Evidence'!D53),'Evidence'!D53,"") | S44: 2023 Q1 only | T44: 2022 full year; latest Q1 2023 in R, not annualised. | U44: https://github.com/Africa-International-Advisors/liquid_fuels_model/blob/8c69f8333192483f19cd80911cb90fcd0943eb6b/assumptions/2026/timeseries/fuel_sales_department_by_province_quarterly.csv | V44: G11: obtain later complete years and sector allocation. Do not use total petrol shares automatically for passenger demand.
A45: GP diesel | B45: million L/year | C45: Observed product sales, not passenger/freight-only demand. | D45: =IF(ISNUMBER('Evidence'!F54),'Evidence'!F54,"") | R45: =IF(ISNUMBER('Evidence'!D54),'Evidence'!D54,"") | S45: 2023 Q1 only | T45: 2022 full year; latest Q1 2023 in R, not annualised. | U45: https://github.com/Africa-International-Advisors/liquid_fuels_model/blob/8c69f8333192483f19cd80911cb90fcd0943eb6b/assumptions/2026/timeseries/fuel_sales_department_by_province_quarterly.csv | V45: G11: obtain later complete years and sector allocation. Do not use total petrol shares automatically for passenger demand.
... A51: WC diesel | B51: million L/year | C51: Observed product sales, not passenger/freight-only demand. | D51: =IF(ISNUMBER('Evidence'!F60),'Evidence'!F60,"") | R51: =IF(ISNUMBER('Evidence'!D60),'Evidence'!D60,"") | S51: 2023 Q1 only | T51: 2022 full year; latest Q1 2023 in R, not annualised. | U51: https://github.com/Africa-International-Advisors/liquid_fuels_model/blob/8c69f8333192483f19cd80911cb90fcd0943eb6b/assumptions/2026/timeseries/fuel_sales_department_by_province_quarterly.csv | V51: G11: obtain later complete years and sector allocation. Do not use total petrol shares automatically for passenger demand.
A53: Nine provinces: petrol | B53: million L/year | C53: Sum only when all nine annual observations exist. | D53: =IF(COUNT(D34:D42)<9,"",SUM(D34:D42)) | E53: =IF(COUNT(E34:E42)<9,"",SUM(E34:E42)) | F53: =IF(COUNT(F34:F42)<9,"",SUM(F34:F42)) | G53: =IF(COUNT(G34:G42)<9,"",SUM(G34:G42)) | H53: =IF(COUNT(H34:H42)<9,"",SUM(H34:H42)) | I53: =IF(COUNT(I34:I42)<9,"",SUM(I34:I42)) | J53: =IF(COUNT(J34:J42)<9,"",SUM(J34:J42)) | K53: =IF(COUNT(K34:K42)<9,"",SUM(K34:K42)) | ... Q53: =IF(COUNT(Q34:Q42)<9,"",SUM(Q34:Q42))
A54: Department national petrol | B54: million L/year | C54: Same publisher comparator; coverage still requires reconciliation. | D54: =IF(ISNUMBER('Evidence'!F6),'Evidence'!F6,"") | E54: =IF(ISNUMBER('Evidence'!G6),'Evidence'!G6,"") | F54: =IF(ISNUMBER('Evidence'!H6),'Evidence'!H6,"") | G54: =IF(ISNUMBER('Evidence'!I6),'Evidence'!I6,"") | H54: =IF(ISNUMBER('Evidence'!J6),'Evidence'!J6,"") | I54: =IF(ISNUMBER('Evidence'!K6),'Evidence'!K6,"") | J54: =IF(ISNUMBER('Evidence'!L6),'Evidence'!L6,"") | K54: =IF(ISNUMBER('Evidence'!M6),'Evidence'!M6,"") | ... Q54: =IF(ISNUMBER('Evidence'!S6),'Evidence'!S6,"")
A55: Provincial minus national | B55: million L/year | C55: Difference retained explicitly; do not force a tie. | D55: =IF(COUNT(D53,D54)<2,"",D53-D54) | E55: =IF(COUNT(E53,E54)<2,"",E53-E54) | F55: =IF(COUNT(F53,F54)<2,"",F53-F54) | G55: =IF(COUNT(G53,G54)<2,"",G53-G54) | H55: =IF(COUNT(H53,H54)<2,"",H53-H54) | I55: =IF(COUNT(I53,I54)<2,"",I53-I54) | J55: =IF(COUNT(J53,J54)<2,"",J53-J54) | K55: =IF(COUNT(K53,K54)<2,"",K53-K54) | ... Q55: =IF(COUNT(Q53,Q54)<2,"",Q53-Q54)
A57: Nine provinces: diesel | B57: million L/year | C57: Sum only when all nine annual observations exist. | D57: =IF(COUNT(D43:D51)<9,"",SUM(D43:D51)) | E57: =IF(COUNT(E43:E51)<9,"",SUM(E43:E51)) | F57: =IF(COUNT(F43:F51)<9,"",SUM(F43:F51)) | G57: =IF(COUNT(G43:G51)<9,"",SUM(G43:G51)) | H57: =IF(COUNT(H43:H51)<9,"",SUM(H43:H51)) | I57: =IF(COUNT(I43:I51)<9,"",SUM(I43:I51)) | J57: =IF(COUNT(J43:J51)<9,"",SUM(J43:J51)) | K57: =IF(COUNT(K43:K51)<9,"",SUM(K43:K51)) | ... Q57: =IF(COUNT(Q43:Q51)<9,"",SUM(Q43:Q51))
A58: Department national diesel | B58: million L/year | C58: Same publisher comparator; coverage still requires reconciliation. | D58: =IF(ISNUMBER('Evidence'!F8),'Evidence'!F8,"") | E58: =IF(ISNUMBER('Evidence'!G8),'Evidence'!G8,"") | F58: =IF(ISNUMBER('Evidence'!H8),'Evidence'!H8,"") | G58: =IF(ISNUMBER('Evidence'!I8),'Evidence'!I8,"") | H58: =IF(ISNUMBER('Evidence'!J8),'Evidence'!J8,"") | I58: =IF(ISNUMBER('Evidence'!K8),'Evidence'!K8,"") | J58: =IF(ISNUMBER('Evidence'!L8),'Evidence'!L8,"") | K58: =IF(ISNUMBER('Evidence'!M8),'Evidence'!M8,"") | ... Q58: =IF(ISNUMBER('Evidence'!S8),'Evidence'!S8,"")
A59: Provincial minus national | B59: million L/year | C59: Difference retained explicitly; do not force a tie. | D59: =IF(COUNT(D57,D58)<2,"",D57-D58) | E59: =IF(COUNT(E57,E58)<2,"",E57-E58) | F59: =IF(COUNT(F57,F58)<2,"",F57-F58) | G59: =IF(COUNT(G57,G58)<2,"",G57-G58) | H59: =IF(COUNT(H57,H58)<2,"",H57-H58) | I59: =IF(COUNT(I57,I58)<2,"",I57-I58) | J59: =IF(COUNT(J57,J58)<2,"",J57-J58) | K59: =IF(COUNT(K57,K58)<2,"",K57-K58) | ... Q59: =IF(COUNT(Q57,Q58)<2,"",Q57-Q58)

Sheet Evidence
A1: Evidence
A2: Raw source extracts • complete annual periods only; partial periods and older anchors stay in D.
A4: Series / driver | B4: Unit | C4: Role | D4: Scalar / latest | E4: Definition / period | F4: 2022 | G4: 2023 | H4: 2024 | I4: 2025 | J4: 2026 | K4: 2027 | L4: 2028 | M4: 2029 | N4: 2030 | O4: 2031 | P4: 2032 | Q4: 2033 | R4: 2034 | S4: 2035 | T4: Status | U4: Source / dependency | V4: Review action
A5: sales_petrol | B5: million L/year | C5: Source observation | E5: FIASA staged reported sales; latest edition selected by existing… [N208] | F5: 9185 | G5: 9037 | H5: 9029 | T5: Unreviewed source extract | U5: assumptions/2026/timeseries/fuel_sales_fiasa.csv | V5: Manish: reconcile scope and revisions before adoption.
A6: dept_petrol | B6: million L/year | C6: Source observation | E6: Department sales with four reported quarters. Preserve… [N209] | F6: 9184.8699 | G6: 9036.9501 | T6: Unreviewed source extract | U6: assumptions/2026/timeseries/fuel_sales_department.csv | V6: Manish: reconcile scope and revisions before adoption.
A7: sales_diesel | B7: million L/year | C7: Source observation | E7: FIASA staged reported sales; latest edition selected by existing… [N210] | F7: 12717 | G7: 12907 | H7: 11734 | T7: Unreviewed source extract | U7: assumptions/2026/timeseries/fuel_sales_fiasa.csv | V7: Manish: reconcile scope and revisions before adoption.
A8: dept_diesel | B8: million L/year | C8: Source observation | E8: Department sales with four reported quarters. Preserve… [N211] | F8: 12717.326 | G8: 12907.5 | T8: Unreviewed source extract | U8: assumptions/2026/timeseries/fuel_sales_department.csv | V8: Manish: reconcile scope and revisions before adoption.
A9: sales_jet | B9: million L/year | C9: Source observation | E9: FIASA staged reported sales; latest edition selected by existing… [N212] | F9: 1478 | G9: 1844 | H9: 1955 | T9: Unreviewed source extract | U9: assumptions/2026/timeseries/fuel_sales_fiasa.csv | V9: Manish: reconcile scope and revisions before adoption.
A10: dept_jet | B10: million L/year | C10: Source observation | E10: Department sales with four reported quarters. Preserve… [N213] | F10: 1478.1499 | G10: 1843.9718 | T10: Unreviewed source extract | U10: assumptions/2026/timeseries/fuel_sales_department.csv | V10: Manish: reconcile scope and revisions before adoption.
A11: sales_fuel_oil | B11: million L/year | C11: Source observation | E11: FIASA staged reported sales; latest edition selected by existing… [N214] | F11: 594 | G11: 658 | H11: 441 | T11: Unreviewed source extract | U11: assumptions/2026/timeseries/fuel_sales_fiasa.csv | V11: Manish: reconcile scope and revisions before adoption.
A12: dept_fuel_oil | B12: million L/year | C12: Source observation | E12: Department sales with four reported quarters. Preserve… [N215] | F12: 594.04016 | G12: 658.09304 | T12: Unreviewed source extract | U12: assumptions/2026/timeseries/fuel_sales_department.csv | V12: Manish: reconcile scope and revisions before adoption.
A13: sales_vehicles_cars | B13: vehicles/year | C13: Source observation | E13: NAAMSA actual new sales. Published 2026/27 projections excluded… [N216] | F13: 363681 | G13: 347377 | H13: 351553 | I13: 422463 | T13: Unreviewed source extract | U13: assumptions/2026/timeseries/new_vehicle_market_naamsa.csv | V13: Manish: reconcile scope and revisions before adoption.
A14: sales_vehicles_light_commercial | B14: vehicles/year | C14: Source observation | E14: NAAMSA actual new sales. Published 2026/27 projections excluded… [N217] | F14: 135711 | G14: 151490 | H14: 133375 | I14: 143964 | T14: Unreviewed source extract | U14: assumptions/2026/timeseries/new_vehicle_market_naamsa.csv | V14: Manish: reconcile scope and revisions before adoption.
A15: sales_vehicles_medium_heavy_commercial | B15: vehicles/year | C15: Source observation | E15: NAAMSA actual new sales. Published 2026/27 projections excluded… [N218] | F15: 29942 | G15: 32690 | H15: 31175 | I15: 30911 | T15: Unreviewed source extract | U15: assumptions/2026/timeseries/new_vehicle_market_naamsa.csv | V15: Manish: reconcile scope and revisions before adoption.
A16: sales_vehicles_total | B16: vehicles/year | C16: Source observation | E16: NAAMSA actual new sales. Published 2026/27 projections excluded… [N219] | F16: 529335 | G16: 531557 | H16: 516103 | I16: 597338 | T16: Unreviewed source extract | U16: assumptions/2026/timeseries/new_vehicle_market_naamsa.csv | V16: Manish: reconcile scope and revisions before adoption.
A17: nev_battery_electric | B17: vehicles/year | C17: Source observation | E17: All-market drivetrain sales; passenger/truck split is not… [N220] | F17: 502 | G17: 929 | H17: 1257 | I17: 1088 | T17: Unreviewed source extract | U17: assumptions/2026/timeseries/nev_sales_naamsa.csv | V17: Manish: reconcile scope and revisions before adoption.
A18: nev_plug_in_hybrid | B18: vehicles/year | C18: Source observation | E18: All-market drivetrain sales; passenger/truck split is not… [N221] | F18: 122 | G18: 368 | H18: 738 | I18: 2810 | T18: Unreviewed source extract | U18: assumptions/2026/timeseries/nev_sales_naamsa.csv | V18: Manish: reconcile scope and revisions before adoption.
A19: nev_traditional_hybrid | B19: vehicles/year | C19: Source observation | E19: All-market drivetrain sales; passenger/truck split is not… [N222] | F19: 4070 | G19: 6485 | H19: 13616 | I19: 12818 | T19: Unreviewed source extract | U19: assumptions/2026/timeseries/nev_sales_naamsa.csv | V19: Manish: reconcile scope and revisions before adoption.
A20: stock_cars | B20: vehicles | C20: Source observation | D20: 8340592 | E20: eNaTIS December snapshots; latest June 2026 kept separately. No… [N223] | F20: 7685153 | G20: 7794164 | H20: 7949275 | I20: 8184111 | T20: Unreviewed source extract | U20: assumptions/2026/timeseries/vehicle_population_natis.csv | V20: Manish: reconcile scope and revisions before adoption.
A21: stock_light_commercial | B21: vehicles | C21: Source observation | D21: 2816547 | E21: eNaTIS December snapshots; latest June 2026 kept separately. No… [N224] | F21: 2658416 | G21: 2689310 | H21: 2725606 | I21: 2776258 | T21: Unreviewed source extract | U21: assumptions/2026/timeseries/vehicle_population_natis.csv | V21: Manish: reconcile scope and revisions before adoption.
A22: stock_trucks | B22: vehicles | C22: Source observation | D22: 409049 | E22: eNaTIS December snapshots; latest June 2026 kept separately. No… [N225] | F22: 385845 | G22: 392349 | H22: 398542 | I22: 404752 | T22: Unreviewed source extract | U22: assumptions/2026/timeseries/vehicle_population_natis.csv | V22: Manish: reconcile scope and revisions before adoption.
A23: stock_buses | B23: vehicles | C23: Source observation | D23: 66872 | E23: eNaTIS December snapshots; latest June 2026 kept separately. No… [N226] | F23: 64170 | G23: 64982 | H23: 65792 | I23: 66249 | T23: Unreviewed source extract | U23: assumptions/2026/timeseries/vehicle_population_natis.csv | V23: Manish: reconcile scope and revisions before adoption.
A24: stock_minibuses | B24: vehicles | C24: Source observation | D24: 356997 | E24: eNaTIS December snapshots; latest June 2026 kept separately. No… [N227] | F24: 349335 | G24: 355235 | H24: 355139 | I24: 355145 | T24: Unreviewed source extract | U24: assumptions/2026/timeseries/vehicle_population_natis.csv | V24: Manish: reconcile scope and revisions before adoption.
A25: macro_gdp_per_capita | B25: 2015 ZAR/person | C25: Source observation | E25: Stats SA annual actual in staged reporting copy. Sector value… [N228] | F25: 76055.067 | G25: 75781.521 | H25: 75255.629 | I25: 75149.986 | T25: Unreviewed source extract | U25: pptx/story/evidence_2026_10_06/macro_statssa.csv | V25: Manish: reconcile scope and revisions before adoption.
A26: macro_agriculture_forestry_and_fishing | B26: bn 2015 ZAR | C26: Source observation | E26: Stats SA annual actual in staged reporting copy. Sector value… [N229] | F26: 131.77064 | G26: 125.74664 | H26: 114.79164 | I26: 134.79675 | T26: Unreviewed source extract | U26: pptx/story/evidence_2026_10_06/macro_statssa.csv | V26: Manish: reconcile scope and revisions before adoption.
A27: macro_manufacturing | B27: bn 2015 ZAR | C27: Source observation | E27: Stats SA annual actual in staged reporting copy. Sector value… [N230] | F27: 523.09075 | G27: 524.99375 | H27: 523.15075 | I27: 516.98565 | T27: Unreviewed source extract | U27: pptx/story/evidence_2026_10_06/macro_statssa.csv | V27: Manish: reconcile scope and revisions before adoption.
A28: macro_mining_and_quarrying | B28: bn 2015 ZAR | C28: Source observation | E28: Stats SA annual actual in staged reporting copy. Sector value… [N231] | F28: 204.45292 | G28: 204.2287 | H28: 205.12583 | I28: 205.46489 | T28: Unreviewed source extract | U28: pptx/story/evidence_2026_10_06/macro_statssa.csv | V28: Manish: reconcile scope and revisions before adoption.
A29: macro_construction | B29: bn 2015 ZAR | C29: Source observation | E29: Stats SA annual actual in staged reporting copy. Sector value… [N232] | F29: 110.06509 | G29: 109.56509 | H29: 103.62509 | I29: 99.098521 | T29: Unreviewed source extract | U29: pptx/story/evidence_2026_10_06/macro_statssa.csv | V29: Manish: reconcile scope and revisions before adoption.
A30: manufacturing_volume_total | B30: index 2019=100 | C30: Source observation | D30: 87.714286 | E30: Arithmetic mean of all 12 monthly production indices; 2026… [N233] | F30: 93.141667 | G30: 93.716667 | H30: 93.333333 | I30: 92.141667 | T30: Unreviewed source extract | U30: pptx/story/evidence_2026_10_06/activity_statssa_monthly.csv | V30: Manish: reconcile scope and revisions before adoption.
A31: mining_volume_total | B31: index 2019=100 | C31: Source observation | D31: 90.685714 | E31: Arithmetic mean of all 12 monthly production indices; 2026… [N234] | F31: 93.008333 | G31: 93.016667 | H31: 93.533333 | I31: 93.708333 | T31: Unreviewed source extract | U31: pptx/story/evidence_2026_10_06/activity_statssa_monthly.csv | V31: Manish: reconcile scope and revisions before adoption.
A32: freight_payload_road | B32: thousand tonnes | C32: Source observation | D32: 568029 | E32: Complete calendar years only; 2026 Jan–Jul shown separately.… [N235] | F32: 1048547 | G32: 1060419 | H32: 979798 | I32: 975176 | T32: Unreviewed source extract | U32: pptx/story/evidence_2026_10_06/activity_statssa_monthly.csv | V32: Manish: reconcile scope and revisions before adoption.
A33: freight_payload_rail | B33: thousand tonnes | C33: Source observation | D33: 101145 | E33: Complete calendar years only; 2026 Jan–Jul shown separately.… [N236] | F33: 155913 | G33: 160100 | H33: 160745 | I33: 168259 | T33: Unreviewed source extract | U33: pptx/story/evidence_2026_10_06/activity_statssa_monthly.csv | V33: Manish: reconcile scope and revisions before adoption.
A34: eskom_ocgt | B34: GWh / financial year | C34: Source observation | E34: Full financial year ending 31 March in the column year. Not… [N237] | F34: 1826 | G34: 3018 | H34: 3634 | I34: 2176 | J34: 811 | T34: Unreviewed source extract | U34: assumptions/2026/timeseries/ocgt_generation_eskom.csv | V34: Manish: reconcile scope and revisions before adoption.
A35: ipp_ocgt | B35: GWh / financial year | C35: Source observation | E35: Full financial year ending 31 March in the column year. Not… [N238] | G35: 1098 | H35: 1509 | I35: 662 | J35: 268 | T35: Unreviewed source extract | U35: assumptions/2026/timeseries/ocgt_generation_eskom.csv | V35: Manish: reconcile scope and revisions before adoption.
A36: eskom_and_ipp_ocgt | B36: GWh / financial year | C36: Source observation | E36: Full financial year ending 31 March in the column year. Not… [N239] | G36: 4116 | H36: 5143 | I36: 2838 | J36: 1079 | T36: Unreviewed source extract | U36: assumptions/2026/timeseries/ocgt_generation_eskom.csv | V36: Manish: reconcile scope and revisions before adoption.
A37: acsa_passengers | B37: departures | C37: Source observation | D37: 13249170 | E37: ACSA departures only; sums monthly total-flight rows without… [N240] | F37: 14986458 | G37: 17846377 | H37: 18785364 | I37: 20197976 | T37: Unreviewed source extract | U37: assumptions/2026/timeseries/air_traffic_acsa.csv | V37: Manish: reconcile scope and revisions before adoption.
A38: acsa_aircraft_movements | B38: departures | C38: Source observation | D38: 155688 | E38: ACSA departures only; sums monthly total-flight rows without… [N241] | F38: 207504 | G38: 225422 | H38: 227773 | I38: 230996 | T38: Unreviewed source extract | U38: assumptions/2026/timeseries/air_traffic_acsa.csv | V38: Manish: reconcile scope and revisions before adoption.
A39: Agriculture: 2021 agriculture/forestry diesel | B39: million L/year | C39: Staged observation | D39: 1058.399 | E39: D is reported 2021 fuel use. No 2022–26 fuel observations inferred. | T39: Older anchor; not adopted | U39: https://github.com/Africa-International-Advisors/liq… [N242] | V39: Check date and scope before adopting.
A40: Manufacturing: 2021 energy-balance industry total | B40: million L/year | C40: Staged observation | D40: 1499.1393 | E40: Parent industry total includes mining and construction. It is not… [N243] | T40: Older anchor; not adopted | U40: https://github.com/Africa-International-Advisors/liq… [N244] | V40: Check date and scope before adopting.
A41: Manufacturing: 2021 construction diesel | B41: million L/year | C41: Staged observation | D41: 48.69243 | E41: Construction child of source industry total, shown separately to… [N245] | T41: Older anchor; not adopted | U41: https://github.com/Africa-International-Advisors/liq… [N246] | V41: Check date and scope before adopting.
A42: Mining: 2021 mining/quarrying diesel | B42: million L/year | C42: Staged observation | D42: 1293.8134 | E42: D is a 2021 anchor. Not a 2022 observation or approved starting assumption. | T42: Older anchor; not adopted | U42: https://github.com/Africa-International-Advisors/liq… [N247] | V42: Check date and scope before adopting.
A43: Provincial: EC petrol / million L/year | B43: million L | C43: Source observation | D43: 169.98342 | E43: 2022 full year. Latest separate value: 2023 Q1 only | F43: 703.13244 | T43: 2022 full year; latest Q1 2023 in R, not annualised. | U43: https://github.com/Africa-International-Advisors/liq… [N248] | V43: Sales geography; not automatically consumption geography.
A44: Provincial: FS petrol / million L/year | B44: million L | C44: Source observation | D44: 134.24809 | E44: 2022 full year. Latest separate value: 2023 Q1 only | F44: 587.45801 | T44: 2022 full year; latest Q1 2023 in R, not annualised. | U44: https://github.com/Africa-International-Advisors/liq… [N249] | V44: Sales geography; not automatically consumption geography.
A45: Provincial: GP petrol / million L/year | B45: million L | C45: Source observation | D45: 866.54293 | E45: 2022 full year. Latest separate value: 2023 Q1 only | F45: 3530.4403 | T45: 2022 full year; latest Q1 2023 in R, not annualised. | U45: https://github.com/Africa-International-Advisors/liq… [N250] | V45: Sales geography; not automatically consumption geography.
A46: Provincial: KZN petrol / million L/year | B46: million L | C46: Source observation | D46: 365.04971 | E46: 2022 full year. Latest separate value: 2023 Q1 only | F46: 1498.9379 | T46: 2022 full year; latest Q1 2023 in R, not annualised. | U46: https://github.com/Africa-International-Advisors/liq… [N251] | V46: Sales geography; not automatically consumption geography.
A47: Provincial: LP petrol / million L/year | B47: million L | C47: Source observation | D47: 68.092021 | E47: 2022 full year. Latest separate value: 2023 Q1 only | F47: 273.64405 | T47: 2022 full year; latest Q1 2023 in R, not annualised. | U47: https://github.com/Africa-International-Advisors/liq… [N252] | V47: Sales geography; not automatically consumption geography.
A48: Provincial: MP petrol / million L/year | B48: million L | C48: Source observation | D48: 159.66703 | E48: 2022 full year. Latest separate value: 2023 Q1 only | F48: 612.26565 | T48: 2022 full year; latest Q1 2023 in R, not annualised. | U48: https://github.com/Africa-International-Advisors/liq… [N253] | V48: Sales geography; not automatically consumption geography.
A49: Provincial: NC petrol / million L/year | B49: million L | C49: Source observation | D49: 24.616719 | E49: 2022 full year. Latest separate value: 2023 Q1 only | F49: 99.829929 | T49: 2022 full year; latest Q1 2023 in R, not annualised. | U49: https://github.com/Africa-International-Advisors/liq… [N254] | V49: Sales geography; not automatically consumption geography.
A50: Provincial: NW petrol / million L/year | B50: million L | C50: Source observation | D50: 107.87281 | E50: 2022 full year. Latest separate value: 2023 Q1 only | F50: 448.15623 | T50: 2022 full year; latest Q1 2023 in R, not annualised. | U50: https://github.com/Africa-International-Advisors/liq… [N255] | V50: Sales geography; not automatically consumption geography.
A51: Provincial: WC petrol / million L/year | B51: million L | C51: Source observation | D51: 366.9834 | E51: 2022 full year. Latest separate value: 2023 Q1 only | F51: 1431.0055 | T51: 2022 full year; latest Q1 2023 in R, not annualised. | U51: https://github.com/Africa-International-Advisors/liq… [N256] | V51: Sales geography; not automatically consumption geography.
A52: Provincial: EC diesel / million L/year | B52: million L | C52: Source observation | D52: 249.20989 | E52: 2022 full year. Latest separate value: 2023 Q1 only | F52: 1032.3522 | T52: 2022 full year; latest Q1 2023 in R, not annualised. | U52: https://github.com/Africa-International-Advisors/liq… [N257] | V52: Sales geography; not automatically consumption geography.
A53: Provincial: FS diesel / million L/year | B53: million L | C53: Source observation | D53: 171.38098 | E53: 2022 full year. Latest separate value: 2023 Q1 only | F53: 781.86116 | T53: 2022 full year; latest Q1 2023 in R, not annualised. | U53: https://github.com/Africa-International-Advisors/liq… [N258] | V53: Sales geography; not automatically consumption geography.
A54: Provincial: GP diesel / million L/year | B54: million L | C54: Source observation | D54: 819.75479 | E54: 2022 full year. Latest separate value: 2023 Q1 only | F54: 3278.9905 | T54: 2022 full year; latest Q1 2023 in R, not annualised. | U54: https://github.com/Africa-International-Advisors/liq… [N259] | V54: Sales geography; not automatically consumption geography.
... A60: Provincial: WC diesel / million L/year | B60: million L | C60: Source observation | D60: 741.74414 | E60: 2022 full year. Latest separate value: 2023 Q1 only | F60: 2499.7695 | T60: 2022 full year; latest Q1 2023 in R, not annualised. | U60: https://github.com/Africa-International-Advisors/liq… [N265] | V60: Sales geography; not automatically consumption geography.

Sheet Model run
A1: Model run
A2: Frozen Python run inputs/results • changing an input here does NOT rerun the engine; rerun Python and refresh this workbook.
A4: Series / driver | B4: Unit | C4: Role | D4: Scalar / latest | E4: Definition / period | F4: 2022 | G4: 2023 | H4: 2024 | I4: 2025 | J4: 2026 | K4: 2027 | L4: 2028 | M4: 2029 | N4: 2030 | O4: 2031 | P4: 2032 | Q4: 2033 | R4: 2034 | S4: 2035 | T4: Status | U4: Source / dependency | V4: Review action
A5: Petrol: GDP per capita | B5: 2015 ZAR/person | C5: Input series | E5: Shared macro driver. Model forecasts beyond the source observation window. | F5: 76790.165 | G5: 76777.926 | H5: 76356.557 | I5: 75873.54 | J5: 76305.621 | K5: 76770.113 | L5: 77267.03 | M5: 77793.85 | N5: 78347.237 | O5: 78904.56 | P5: 79465.847 | Q5: 80031.127 | R5: 80600.429 | S5: 81173.78 | T5: Frozen current high_demand; provisional | U5: Petrol 6: current engine input/result | V5: Engine dependency is in Python; Excel links expose… [N266]
A6: Petrol: New-sales regression slope | B6: vehicles / ZAR pc | C6: Scalar | D6: 37.3149 | E6: Sales = max(0, slope × GDP/capita + intercept). Applies to all new vehicles. | T6: Frozen current high_demand; provisional | U6: Petrol 7: current engine input/result | V6: Engine dependency is in Python; Excel links expose… [N267]
A7: Petrol: New-sales regression intercept | B7: vehicles/year | C7: Scalar | D7: -2387744 | E7: Legacy fitted parameter; historical validity needs review. | T7: Frozen current high_demand; provisional | U7: Petrol 8: current engine input/result | V7: Engine dependency is in Python; Excel links expose… [N268]
A8: Petrol: Passenger share of new sales | B8: share | C8: Scalar | D8: 0.78 | E8: Current provisional split of total modelled new sales. | T8: Frozen current high_demand; provisional | U8: Petrol 9: current engine input/result | V8: Engine dependency is in Python; Excel links expose… [N269]
A9: Petrol: Petrol share of passenger ICE sales | B9: share | C9: Scalar | D9: 0.83 | E9: Applies after current EV adjustment. Hybrids are not separately modelled. | T9: Frozen current high_demand; provisional | U9: Petrol 10: current engine input/result | V9: Engine dependency is in Python; Excel links expose… [N270]
A10: Petrol: Passenger annual mileage | B10: km/vehicle/year | C10: Scalar | D10: 17000 | E10: Current placeholder. Proposed HML brackets appear on HML sheet. | T10: Frozen current high_demand; provisional | U10: Petrol 11: current engine input/result | V10: Engine dependency is in Python; Excel links expose… [N271]
A11: Petrol: Passenger retirement rate | B11: share/year | C11: Scalar | D11: 0.04 | E11: Current engine scraps all cohorts, including additions, within the year. | T11: Frozen current high_demand; provisional | U11: Petrol 12: current engine input/result | V11: Engine dependency is in Python; Excel links expose… [N272]
A12: Petrol: Base new petrol vehicle consumption | B12: L/100 km | C12: Scalar | D12: 9.5 | E12: Entry-cohort baseline before cumulative efficiency gains. | T12: Frozen current high_demand; provisional | U12: Petrol 13: current engine input/result | V12: Engine dependency is in Python; Excel links expose… [N273]
A13: Petrol: New-cohort efficiency gain | B13: fraction/year | C13: Input series | E13: Applied cumulatively to new cohorts; older cohorts retain their… [N274] | F13: 0.01 | G13: 0.01 | H13: 0.01 | I13: 0.01 | J13: 0.01 | K13: 0.01 | L13: 0.01 | M13: 0.01 | N13: 0.01 | O13: 0.01 | P13: 0.01 | Q13: 0.01 | R13: 0.01 | S13: 0.01 | T13: Frozen current high_demand; provisional | U13: Petrol 14: current engine input/result | V13: Engine dependency is in Python; Excel links expose… [N275]
A14: Petrol: EV curve ceiling | B14: share | C14: Parameter | D14: 0.3 | E14: Current logistic curve parameter. Proposed BEV sales ranges are separate. | T14: Frozen current high_demand; provisional | U14: Petrol 15: current engine input/result | V14: Engine dependency is in Python; Excel links expose… [N276]
A15: Petrol: Passenger petrol fleet | B15: vehicles | C15: Engine output | E15: Cohort stock from engine diagnostics. Opening stock is… [N277] | F15: 4105442.8 | G15: 4237510.4 | H15: 4354416.5 | I15: 4455304.5 | J15: 4561932.7 | K15: 4674714.4 | L15: 4793999.2 | M15: 4919998.1 | N15: 5052743.7 | O15: 5191624 | P15: 5335891.8 | Q15: 5484628 | R15: 5636707.4 | S15: 5790782.3 | T15: Frozen current high_demand; provisional | U15: Petrol 18: current engine input/result | V15: Engine dependency is in Python; Excel links expose… [N278]
A16: Petrol: Passenger petrol vehicle-km | B16: km/year | C16: Engine output | E16: Engine diagnostic activity for petrol passenger cohorts. | F16: 6.9792528e+10 | G16: 7.2037677e+10 | H16: 7.402508e+10 | I16: 7.5740177e+10 | J16: 7.7552856e+10 | K16: 7.9470144e+10 | L16: 8.1497987e+10 | M16: 8.3639968e+10 | N16: 8.5896643e+10 | O16: 8.8257608e+10 | P16: 9.0710161e+10 | Q16: 9.3238675e+10 | R16: 9.5824025e+10 | S16: 9.84433e+10 | T16: Frozen current high_demand; provisional | U16: Petrol 19: current engine input/result | V16: Engine dependency is in Python; Excel links expose… [N279]
A17: Petrol: Passenger petrol demand | B17: L/year | C17: Engine output | E17: Calculated by the Python cohort engine. | F17: 6.6044466e+09 | G17: 6.7999147e+09 | H17: 6.9677952e+09 | I17: 7.1073167e+09 | J17: 7.25179e+09 | K17: 7.401723e+09 | L17: 7.5575086e+09 | M17: 7.7193195e+09 | N17: 7.8870601e+09 | O17: 8.0597089e+09 | P17: 8.2360784e+09 | Q17: 8.4147712e+09 | R17: 8.5941424e+09 | S17: 8.7722883e+09 | T17: Frozen current high_demand; provisional | U17: Petrol 20: current engine input/result | V17: Engine dependency is in Python; Excel links expose… [N280]
A18: Petrol: All road petrol demand | B18: L/year | C18: Engine output | E18: Includes passenger and LCV petrol. Does not claim all-product/sector coverage. | F18: 7.5243133e+09 | G18: 7.7428552e+09 | H18: 7.9296854e+09 | I18: 8.0839568e+09 | J18: 8.2440252e+09 | K18: 8.4104622e+09 | L18: 8.5837073e+09 | M18: 8.7639464e+09 | N18: 8.9510574e+09 | O18: 9.1438537e+09 | P18: 9.3409602e+09 | Q18: 9.5407623e+09 | R18: 9.7413633e+09 | S18: 9.9405714e+09 | T18: Frozen current high_demand; provisional | U18: Petrol 23: current engine input/result | V18: Engine dependency is in Python; Excel links expose… [N281]
A19: Freight: GDP per capita | B19: 2015 ZAR/person | C19: Input series | E19: Same national vehicle-sales regression as Petrol sheet. | F19: 76790.165 | G19: 76777.926 | H19: 76356.557 | I19: 75873.54 | J19: 76305.621 | K19: 76770.113 | L19: 77267.03 | M19: 77793.85 | N19: 78347.237 | O19: 78904.56 | P19: 79465.847 | Q19: 80031.127 | R19: 80600.429 | S19: 81173.78 | T19: Frozen current high_demand; provisional | U19: Freight 6: current engine input/result | V19: Engine dependency is in Python; Excel links expose… [N282]
A20: Freight: HCV share of new vehicle sales | B20: share | C20: Scalar | D20: 0.04 | E20: Current provisional class split. | T20: Frozen current high_demand; provisional | U20: Freight 7: current engine input/result | V20: Engine dependency is in Python; Excel links expose… [N283]
A21: Freight: Diesel share of HCV ICE sales | B21: share | C21: Scalar | D21: 1 | E21: Current model applies its common EV adjustment before the diesel split. | T21: Frozen current high_demand; provisional | U21: Freight 8: current engine input/result | V21: Engine dependency is in Python; Excel links expose… [N284]
A22: Freight: Heavy-truck annual mileage | B22: km/vehicle/year | C22: Scalar | D22: 70000 | E22: Current provisional assumption. | T22: Frozen current high_demand; provisional | U22: Freight 9: current engine input/result | V22: Engine dependency is in Python; Excel links expose… [N285]
A23: Freight: Heavy-truck retirement rate | B23: share/year | C23: Scalar | D23: 0.06 | E23: Flat retirement assumption across cohorts. | T23: Frozen current high_demand; provisional | U23: Freight 10: current engine input/result | V23: Engine dependency is in Python; Excel links expose… [N286]
A24: Freight: Base new-truck consumption | B24: L/100 km | C24: Scalar | D24: 35 | E24: Entry-cohort baseline before efficiency improvement. | T24: Frozen current high_demand; provisional | U24: Freight 11: current engine input/result | V24: Engine dependency is in Python; Excel links expose… [N287]
A25: Freight: New-cohort efficiency gain | B25: fraction/year | C25: Input series | E25: Applies to new cohorts only. | F25: 0.005 | G25: 0.005 | H25: 0.005 | I25: 0.005 | J25: 0.005 | K25: 0.005 | L25: 0.005 | M25: 0.005 | N25: 0.005 | O25: 0.005 | P25: 0.005 | Q25: 0.005 | R25: 0.005 | S25: 0.005 | T25: Frozen current high_demand; provisional | U25: Freight 12: current engine input/result | V25: Engine dependency is in Python; Excel links expose… [N288]
A26: Freight: Heavy-truck diesel fleet | B26: vehicles | C26: Engine output | E26: National HCV diesel cohort stock. | F26: 213882.42 | G26: 218974.26 | H26: 223162.94 | I26: 226414.14 | J26: 230061.68 | K26: 234120.68 | L26: 238602.49 | M26: 243510.24 | N26: 248836.61 | O26: 254535.76 | P26: 260554.99 | Q26: 266832.51 | R26: 273295.57 | S26: 279859.59 | T26: Frozen current high_demand; provisional | U26: Freight 15: current engine input/result | V26: Engine dependency is in Python; Excel links expose… [N289]
A27: Freight: Heavy-truck vehicle-km | B27: km/year | C27: Engine output | E27: National HCV diesel activity. | F27: 1.4971769e+10 | G27: 1.5328198e+10 | H27: 1.5621406e+10 | I27: 1.584899e+10 | J27: 1.6104318e+10 | K27: 1.6388447e+10 | L27: 1.6702174e+10 | M27: 1.7045717e+10 | N27: 1.7418563e+10 | O27: 1.7817503e+10 | P27: 1.8238849e+10 | Q27: 1.8678275e+10 | R27: 1.913069e+10 | S27: 1.9590172e+10 | T27: Frozen current high_demand; provisional | U27: Freight 16: current engine input/result | V27: Engine dependency is in Python; Excel links expose… [N290]
A28: Freight: Heavy-truck diesel demand | B28: L/year | C28: Engine output | E28: Current Python engine output. Does not include LCV freight. | F28: 5.2283569e+09 | G28: 5.3450953e+09 | H28: 5.4383972e+09 | I28: 5.507718e+09 | J28: 5.5848914e+09 | K28: 5.6702318e+09 | L28: 5.7639553e+09 | M28: 5.8660772e+09 | N28: 5.9763651e+09 | O28: 6.0936974e+09 | P28: 6.2168065e+09 | Q28: 6.3442332e+09 | R28: 6.4742882e+09 | S28: 6.605038e+09 | T28: Frozen current high_demand; provisional | U28: Freight 17: current engine input/result | V28: Engine dependency is in Python; Excel links expose… [N291]
A29: Freight: Current common EV share of new sales | B29: share | C29: Engine output | E29: Existing engine curve applied to HCV as well as other classes.… [N292] | F29: 0.00074178695 | G29: 0.0010342354 | H29: 0.0014414259 | I29: 0.0020078553 | J29: 0.0027947878 | K29: 0.0038861183 | L29: 0.005395863 | M29: 0.007477328 | N29: 0.010333559 | O29: 0.014227762 | P29: 0.019490751 | Q29: 0.026519903 | R29: 0.035760877 | S29: 0.047660731 | T29: Frozen current high_demand; provisional | U29: Freight 31: current engine input/result | V29: Engine dependency is in Python; Excel links expose… [N293]
A30: Agriculture: Base year | B30: year | C30: Scalar | D30: 2024 | E30: A dated baseline, not a recurring annual observation. | T30: Frozen current high_demand; provisional | U30: Agriculture 7: current engine input/result | V30: Engine dependency is in Python; Excel links expose… [N294]
A31: Agriculture: GDP/capita elasticity | B31: dimensionless | C31: Scalar | D31: 0.2 | E31: Provisional GDP proxy, pending an agricultural driver. | T31: Frozen current high_demand; provisional | U31: Agriculture 8: current engine input/result | V31: Engine dependency is in Python; Excel links expose… [N295]
A32: Agriculture: GDP per capita | B32: 2015 ZAR/person | C32: Input series | E32: Current driver used by the held engine. | F32: 76790.165 | G32: 76777.926 | H32: 76356.557 | I32: 75873.54 | J32: 76305.621 | K32: 76770.113 | L32: 77267.03 | M32: 77793.85 | N32: 78347.237 | O32: 78904.56 | P32: 79465.847 | Q32: 80031.127 | R32: 80600.429 | S32: 81173.78 | T32: Frozen current high_demand; provisional | U32: Agriculture 9: current engine input/result | V32: Engine dependency is in Python; Excel links expose… [N296]
A33: Agriculture: Agricultural diesel demand | B33: L/year | C33: Engine output | E33: Engine: baseline × (GDP/capita / base-year GDP/capita)^elasticity. | F33: 7.0079322e+08 | G33: 7.0077088e+08 | H33: 700000000 | I33: 6.9911214e+08 | J33: 6.9990658e+08 | K33: 7.0075662e+08 | L33: 7.0166145e+08 | M33: 7.0261566e+08 | N33: 7.0361244e+08 | O33: 7.0461063e+08 | P33: 7.0561024e+08 | Q33: 7.0661127e+08 | R33: 7.0761372e+08 | S33: 7.0861759e+08 | T33: Frozen current high_demand; provisional | U33: Agriculture 12: current engine input/result | V33: Engine dependency is in Python; Excel links expose… [N297]
A34: Manufacturing: Combined baseline year | B34: year | C34: Scalar | D34: 2024 | E34: Current main vintage; branch replacement proposals are not adopted here. | T34: Frozen current high_demand; provisional | U34: Manufacturing 21: current engine input/result | V34: Engine dependency is in Python; Excel links expose… [N298]
A35: Manufacturing: Combined GDP/capita elasticity | B35: dimensionless | C35: Scalar | D35: 1 | E35: Current combined held-method parameter. Not a manufacturing-specific estimate. | T35: Frozen current high_demand; provisional | U35: Manufacturing 22: current engine input/result | V35: Engine dependency is in Python; Excel links expose… [N299]
A36: Manufacturing: Combined industrial diesel | B36: L/year | C36: Engine output | E36: Existing engine output shown ONCE as a reference for the future… [N300] | F36: 2.5141968e+09 | G36: 2.5137961e+09 | H36: 2500000000 | I36: 2.4841855e+09 | J36: 2.4983323e+09 | K36: 2.5135403e+09 | L36: 2.5298099e+09 | M36: 2.5470586e+09 | N36: 2.5651771e+09 | O36: 2.5834245e+09 | P36: 2.6018017e+09 | Q36: 2.6203096e+09 | R36: 2.6389491e+09 | S36: 2.6577213e+09 | T36: Frozen current high_demand; provisional | U36: Manufacturing 23: current engine input/result | V36: Engine dependency is in Python; Excel links expose… [N301]
A37: Other demand: Current engine load factor | B37: share | C37: Current input | E37: Legacy scenario path. Not measured dispatch. | F37: 0.45 | G37: 0.5603 | H37: 0.5456 | I37: 0.626 | J37: 0.7 | K37: 0.71 | L37: 0.7 | M37: 0.7 | N37: 0.7 | O37: 0.7 | P37: 0.7 | Q37: 0.7 | R37: 0.7 | S37: 0.7 | T37: Frozen current high_demand; provisional | U37: https://github.com/Africa-International-Advisors/liq… [N302] | V37: Engine dependency is in Python; Excel links expose… [N303]
A38: Other demand: Current thermal efficiency | B38: share | C38: Current scalar | D38: 0.4 | E38: Fraction of fuel energy converted to electricity. | T38: Frozen current high_demand; provisional | U38: https://github.com/Africa-International-Advisors/liq… [N304] | V38: Engine dependency is in Python; Excel links expose… [N305]
A39: Other demand: Diesel energy content | B39: MJ/L | C39: Current scalar | D39: 36.9 | E39: Current engine conversion input. | T39: Frozen current high_demand; provisional | U39: https://github.com/Africa-International-Advisors/liq… [N306] | V39: Engine dependency is in Python; Excel links expose… [N307]
A40: Other demand: Current OCGT diesel demand | B40: million L/year | C40: Model output | E40: Calendar-year model output; do not directly tie to FY generation… [N308] | F40: 2953.6156 | G40: 3677.5796 | H40: 3581.0948 | I40: 4108.8075 | J40: 4594.5132 | K40: 4660.1491 | L40: 4594.5132 | M40: 4594.5132 | N40: 4594.5132 | O40: 4594.5132 | P40: 4594.5132 | Q40: 4594.5132 | R40: 4594.5132 | S40: 4594.5132 | T40: Frozen current high_demand; provisional | U40: https://github.com/Africa-International-Advisors/liq… [N309] | V40: Engine dependency is in Python; Excel links expose… [N310]
A41: Other demand: Current engine passenger departures | B41: passengers/year | C41: Current input | E41: Legacy regression driver; separate from new ACSA observations. | F41: 15813215 | G41: 17730490 | H41: 17000000 | I41: 19000000 | J41: 21000000 | K41: 22366223 | L41: 23832227 | M41: 25394321 | N41: 27058803 | O41: 28832385 | P41: 30722217 | Q41: 32735918 | R41: 34881609 | S41: 37167940 | T41: Frozen current high_demand; provisional | U41: https://github.com/Africa-International-Advisors/liq… [N311] | V41: Engine dependency is in Python; Excel links expose… [N312]
A42: Other demand: Current jet demand | B42: million L/year | C42: Model output | E42: Legacy two-driver regression. | F42: 1591.8858 | G42: 1742.4582 | H42: 1601.4445 | I42: 1666.1872 | J42: 1910.5954 | K42: 2110.7994 | L42: 2325.331 | M42: 2553.4003 | N42: 2794.8549 | O42: 3045.7871 | P42: 3306.7731 | Q42: 3578.4263 | R42: 3861.4002 | S42: 4156.3905 | T42: Frozen current high_demand; provisional | U42: https://github.com/Africa-International-Advisors/liq… [N313] | V42: Engine dependency is in Python; Excel links expose… [N314]
A43: Other demand: Legacy jet regression intercept | B43: L/year | C43: Current scalar | D43: -1.4746409e+10 | E43: Jet = intercept + GDP/capita coefficient × GDP/capita + passenger… [N315] | T43: Frozen current high_demand; provisional | U43: https://github.com/Africa-International-Advisors/liq… [N316] | V43: Engine dependency is in Python; Excel links expose… [N317]
A44: Other demand: GDP/capita coefficient | B44: L per ZAR/person | C44: Current scalar | D44: 196334.93 | E44: Used with current macro path. | T44: Frozen current high_demand; provisional | U44: https://github.com/Africa-International-Advisors/liq… [N318] | V44: Engine dependency is in Python; Excel links expose… [N319]
A45: Other demand: Passenger coefficient | B45: L per departure | C45: Current scalar | D45: 79.787865 | E45: Passenger departure basis. | T45: Frozen current high_demand; provisional | U45: https://github.com/Africa-International-Advisors/liq… [N320] | V45: Engine dependency is in Python; Excel links expose… [N321]
A46: Other demand: durban provisional port baseline | B46: million L/year | C46: Current scalar | D46: 1500 | E46: Current 2024 placeholder; not measured port bunkering. | T46: Frozen current high_demand; provisional | U46: https://github.com/Africa-International-Advisors/liq… [N322] | V46: Engine dependency is in Python; Excel links expose… [N323]
A47: Other demand: cape_town provisional port baseline | B47: million L/year | C47: Current scalar | D47: 500 | E47: Current 2024 placeholder; not measured port bunkering. | T47: Frozen current high_demand; provisional | U47: https://github.com/Africa-International-Advisors/liq… [N324] | V47: Engine dependency is in Python; Excel links expose… [N325]
A48: Other demand: saldanha provisional port baseline | B48: million L/year | C48: Current scalar | D48: 200 | E48: Current 2024 placeholder; not measured port bunkering. | T48: Frozen current high_demand; provisional | U48: https://github.com/Africa-International-Advisors/liq… [N326] | V48: Engine dependency is in Python; Excel links expose… [N327]
A49: Other demand: Marine GDP/capita elasticity | B49: dimensionless | C49: Current scalar | D49: 0.4 | E49: Current proxy response. | T49: Frozen current high_demand; provisional | U49: https://github.com/Africa-International-Advisors/liq… [N328] | V49: Engine dependency is in Python; Excel links expose… [N329]
A50: Other demand: Marine fuel-oil share | B50: share | C50: Current scalar | D50: 0.65 | E50: One provisional split across ports. | T50: Frozen current high_demand; provisional | U50: https://github.com/Africa-International-Advisors/liq… [N330] | V50: Engine dependency is in Python; Excel links expose… [N331]
A51: Other demand: Marine diesel share | B51: share | C51: Current scalar | D51: 0.35 | E51: Diesel_500ppm; part of total diesel comparison. | T51: Frozen current high_demand; provisional | U51: https://github.com/Africa-International-Advisors/liq… [N332] | V51: Engine dependency is in Python; Excel links expose… [N333]
A52: Other demand: Marine diesel demand | B52: million L/year | C52: Model output | E52: No 2022–23 output from current marine engine. | H52: 770 | I52: 768.04794 | J52: 769.7945 | K52: 771.66546 | L52: 773.65953 | M52: 775.7652 | N52: 777.96787 | O52: 780.1768 | P52: 782.39199 | Q52: 784.61348 | R52: 786.84127 | S52: 789.07539 | T52: Frozen current high_demand; provisional | U52: https://github.com/Africa-International-Advisors/liq… [N334] | V52: Engine dependency is in Python; Excel links expose… [N335]
A53: Other demand: Marine fuel-oil demand | B53: million L/year | C53: Model output | E53: Marine only; does not represent all national fuel-oil consumption. | H53: 1430 | I53: 1426.3747 | J53: 1429.6183 | K53: 1433.093 | L53: 1436.7963 | M53: 1440.7068 | N53: 1444.7975 | O53: 1448.8998 | P53: 1453.0137 | Q53: 1457.1393 | R53: 1461.2766 | S53: 1465.4257 | T53: Frozen current high_demand; provisional | U53: https://github.com/Africa-International-Advisors/liq… [N336] | V53: Engine dependency is in Python; Excel links expose… [N337]
A54: LCV petrol stock | B54: vehicles | C54: Python result | E54: lcv / petrol_95 / stock | F54: 314192.9 | G54: 322939.14 | H54: 330432.67 | I54: 336615.35 | J54: 343295.79 | K54: 350502.17 | L54: 358257.4 | M54: 366572.88 | N54: 375445.49 | O54: 384819.12 | P54: 394627.29 | Q54: 404790.21 | R54: 415212.01 | S54: 425779.56 | T54: Frozen high_demand | U54: src/lfm/model/demand/vehicles.py | V54: Uses vehicle inputs shown on sector tabs; refresh via Python.
A55: LCV petrol vehicle kilometres | B55: vehicle km/year | C55: Python result | E55: lcv / petrol_95 / vehicle_km | F55: 8.7974011e+09 | G55: 9.0422961e+09 | H55: 9.2521147e+09 | I55: 9.4252297e+09 | J55: 9.612282e+09 | K55: 9.8140609e+09 | L55: 1.0031207e+10 | M55: 1.0264041e+10 | N55: 1.0512474e+10 | O55: 1.0774935e+10 | P55: 1.1049564e+10 | Q55: 1.1334126e+10 | R55: 1.1625936e+10 | S55: 1.1921828e+10 | T55: Frozen high_demand | U55: src/lfm/model/demand/vehicles.py | V55: Uses vehicle inputs shown on sector tabs; refresh via Python.
A56: LCV petrol demand | B56: L/year | C56: Python result | E56: lcv / petrol_95 / litres | F56: 9.1986669e+08 | G56: 9.4294053e+08 | H56: 9.6189018e+08 | I56: 9.766401e+08 | J56: 9.922352e+08 | K56: 1.0087393e+09 | L56: 1.0261987e+09 | M56: 1.0446269e+09 | N56: 1.0639973e+09 | O56: 1.0841448e+09 | P56: 1.1048818e+09 | Q56: 1.1259911e+09 | R56: 1.1472208e+09 | S56: 1.1682831e+09 | T56: Frozen high_demand | U56: src/lfm/model/demand/vehicles.py | V56: Uses vehicle inputs shown on sector tabs; refresh via Python.
A57: Passenger diesel demand | B57: L/year | C57: Python result | E57: passenger / diesel_50ppm / litres | F57: 1.0700172e+09 | G57: 1.1030539e+09 | H57: 1.131874e+09 | I57: 1.1563025e+09 | J57: 1.1818702e+09 | K57: 1.2086699e+09 | L57: 1.2367767e+09 | M57: 1.2662297e+09 | N57: 1.2970229e+09 | O57: 1.3289913e+09 | P57: 1.3619391e+09 | Q57: 1.3956311e+09 | R57: 1.4297856e+09 | S57: 1.4640711e+09 | T57: Frozen high_demand | U57: src/lfm/model/demand/vehicles.py | V57: Uses vehicle inputs shown on sector tabs; refresh via Python.
A58: LCV diesel demand | B58: L/year | C58: Python result | E58: lcv / diesel_50ppm / litres | F58: 1.8435799e+09 | G58: 1.892347e+09 | H58: 1.9332951e+09 | I58: 1.9661764e+09 | J58: 2.0013468e+09 | K58: 2.0389492e+09 | L58: 2.0790932e+09 | M58: 2.1218213e+09 | N58: 2.1670934e+09 | O58: 2.2145753e+09 | P58: 2.2638799e+09 | Q58: 2.3145518e+09 | R58: 2.3660543e+09 | S58: 2.4177642e+09 | T58: Frozen high_demand | U58: src/lfm/model/demand/vehicles.py | V58: Uses vehicle inputs shown on sector tabs; refresh via Python.
A61: Run provenance | B61: record | C61: Frozen export | E61: 2026-10-07T10:48:46.852505+00:00;… [N338]
A64: Input snapshot manifest | B64: SHA256 | C64: Audit record | E64: Paths and hashes identify the captured input files;… [N339]
A65: assumptions/2026/_meta.yaml | B65: SHA256 | C65: Frozen file | E65: 0e3bc69dba8106755b3e1e6403460b0fad8e2bbe007745c940233ba8a044b6a2
A66: assumptions/2026/agriculture.yaml | B66: SHA256 | C66: Frozen file | E66: 9af1efe4bf94b6efccfb04e67222961da53ec5192ecd7d8c708221b7ddbff407
A67: assumptions/2026/aviation.yaml | B67: SHA256 | C67: Frozen file | E67: 8eb68563f2d8466df52f7460028b9d4df1e480a463baf63645fbe34e92baee12
A68: assumptions/2026/fuel_lever_design.yaml | B68: SHA256 | C68: Frozen file | E68: 26bd2b42eb5f21e5167ce831acd2963e9c0f7f33870f6f356becb7d7622dc458
A69: assumptions/2026/generation.yaml | B69: SHA256 | C69: Frozen file | E69: 60afb39b8dade734943b98cec9295258d400b6d62a4031dd3110228a94557518
A70: assumptions/2026/industrial.yaml | B70: SHA256 | C70: Frozen file | E70: 371d67d323cbf21b5c018b4bca4a6c372480f860f29b659afcb132bc279262ab
A71: assumptions/2026/infrastructure/storag… [N340] | B71: SHA256 | C71: Frozen file | E71: 3fe3d166768ecfe702fbe7a487dd04083f42f75a70454f8dd48097e779d4ac73
A72: assumptions/2026/infrastructure/storag… [N341] | B72: SHA256 | C72: Frozen file | E72: cc3bf1ce107458f5dbab71090bdfbcd379cdeb491a725368fea6c8b00d831e5a
A73: assumptions/2026/macro.yaml | B73: SHA256 | C73: Frozen file | E73: d800f8024eaa02a9528cfbc1032c035c4e826dbd897da3bc3a6ead4d4ca68b29
A74: assumptions/2026/marine.yaml | B74: SHA256 | C74: Frozen file | E74: cc38dd8c98d286e0f6fd4c748779e2d1aaf075e7630e76235a21d072da773a91
... A127: assumptions/2026/vehicles.yaml | B127: SHA256 | C127: Frozen file | E127: e77eb3eceb54949da864a8d522d71db9950d738a69b97af6a58692e6666a028a

Sheet Data gaps
A1: Data needed to close the baseline
A2: Available does not mean approved • Owners follow the existing workplan; review triggers are explicit.
A4: ID | B4: Demand component | C4: Available evidence | D4: Missing input / decision | E4: Retrieval starting point | F4: Owner / reviewer | G4: Next action | H4: Closure trigger
A5: G01 | B5: National fuel balance | C5: 2022–24 reported sales; department comparison through 2023. Current engine output available. | D5: 2024 source choice; 2025–26 sales; grades, bunkers and segment scope. | E5: FIASA editions and department originals; matched production/trade/stocks. | F5: Manish / Nigel | G5: Reconcile source/product/period; record adopted national baseline. | H5: Before calibration or forecast acceptance.
A6: G02 | B6: Fleet and new sales | C6: 2022–25 sales and December fleet snapshots; June 2026 stock separately. | D6: Opening stock by age/fuel/drivetrain; class mapping; survival and mileage. | E6: eNaTIS, NAAMSA and registration/odometer evidence. | F6: Manish / Nigel | G6: Reconcile observed stock with engine backfill; fit sales and survival. | H6: Before vehicle baseline adoption.
A7: G03 | B7: Passenger electrification | C7: 2022–25 BEV/PHEV/HEV sales for total market. | D7: Passenger-specific denominators, fleet stock and hybrid fuel savings. | E7: NAAMSA class/drivetrain data and vehicle-use evidence. | F7: Manish / Nigel | G7: Separate sales shares from fleet shares; calibrate electric distance and fuel use. | H7: Before passenger H/M/L integration.
A8: G04 | B8: Road freight activity | C8: Annual road/rail payload through 2025; Jan–Jul 2026 separately; truck sales/stock. | D8: Tonne-km, distance, payload, empty running; LCV freight scope. | E8: Stats SA transport evidence, operators, corridor studies and fleet records. | F8: Manish / Nigel | G8: Choose fleet or tonne-km method; retain other as cross-check. | H8: Before freight fuel calibration.
A9: G05 | B9: Freight electrification | C9: Current generic EV curve is visible. No truck-specific observations established. | D9: Truck BEV/hybrid sales/stock by duty cycle; utilisation and charging rollout. | E9: Commercial-vehicle registrations/sales; depot and fleet operating evidence. | F9: Manish / Nigel | G9: Define delivery/regional/long-haul paths and coherent work shares. | H9: Before freight H/M/L integration.
A10: G06 | B10: Manufacturing | C10: 2022–25 production/GVA; Jan–Jul 2026 production. 2021 industry parent available. | D10: Manufacturing-only fuel baseline, subsector intensity and electrification. | E10: 2021 energy-balance subsectors; newer department/industry fuel records. | F10: Manish / Nigel | G10: Reconcile manufacturing children and unspecified industry; do not assign industry parent to manufacturing. | H10: Before splitting industrial engine bucket.
A11: G07 | B11: Mining and construction | C11: 2021 mining/construction diesel anchors; 2022–25 mining activity, Jan–Jul 2026 index. | D11: 2022+ fuel use; site/commodity split; off-road/public-road boundary; electrification. | E11: Mine/site fuel and production records; energy balance; industry disclosures. | F11: Manish / Nigel | G11: Match baseline/activity; preserve construction and unresolved remainder. | H11: Before separate mining forecast.
A12: G08 | B12: Agriculture | C12: 2021 agriculture/forestry fuel anchor; 2022–25 real GVA. | D12: Newer fuel baseline; crop/area/irrigation activity; intensity and scope. | E12: Department energy balance, agricultural statistics and sector fuel-use records. | F12: Manish / Nigel | G12: Choose activity proxy and base year; reconcile forestry/fishing/backup coverage. | H12: Before replacing held GDP proxy.
A13: G09 | B13: Generation | C13: Eskom/IPP FY generation through March 2026; current engine inputs/output. | D13: Matched fuel burn, calendar-year bridge; private-backup coverage. | E13: Eskom/IPP operating and fuel records; private generator evidence. | F13: Manish / Henry | G13: Reconcile GWh-to-litres and sector overlaps; count private backup once. | H13: Before generation calibration.
A14: G10 | B14: Aviation | C14: 2022–25 ACSA departures; Jan–Aug 2026 separately; jet sales through 2024. | D14: Aircraft/route mix, cargo/non-ACSA coverage and matched jet uplift. | E14: ACSA and airport/airline fuel delivery records. | F14: Manish / Nigel | G14: Fit proposed movement model and back-test; preserve source coverage. | H14: Before jet driver replacement.
A15: G11 | B15: Provincial demand | C15: 2022 full-year sales; Q1 2023 separately. National difference retained. | D15: 2023+ complete provincial fuel sales and sector-specific distribution. | E15: Department district/provincial workbooks and provincial/site activity sources. | F15: Manish / Nigel | G15: Resolve completeness; choose allocation or local calculation by segment. | H15: Before provincial forecast acceptance.
... A17: G13 | B17: Ranges and annual forecast paths | C17: Existing proposed H/M/L endpoints retained on last tab. | D17: Agreed medium/reference, annual paths and compatible provincial/sector settings. | E17: Review existing lever design against the above baseline evidence. | F17: Nigel / Henry | G17: Select input ranges and scenario combinations; record acceptance and implementation. | H17: Before forecast integration.

Sheet Notes
A1: Detailed notes
A2: Full descriptions retained from the working tables. Match the N-reference or sheet/cell below.
A4: Reference | B4: Sheet | C4: Cell | D4: Driver / output | E4: Full text
A5: N001 | B5: Baseline | C5: E6 | D5: Selected historical petrol sales | E5: Choice is explicit by year on Source selection. Alternative series remain on Evidence.
A6: N002 | B6: Baseline | C6: E7 | D6: Historical source / status | E6: Source name shown when available; no automatic fallback if selected evidence is missing.
A7: N003 | B7: Baseline | C7: E8 | D7: Current model road petrol | E7: Passenger + LCV petrol_95. Reported sales cover petrol grades; scope bridge remains open.
A8: N004 | B8: Baseline | C8: E9 | D8: Model less selected historical sales | E8: Working discrepancy, not a calibrated residual or extra segment.
A9: N005 | B9: Baseline | C9: E12 | D9: Selected historical diesel sales | E9: Choice is explicit by year on Source selection. Alternative series remain on Evidence.
A10: N006 | B10: Baseline | C10: E13 | D10: Historical source / status | E10: Source name shown when available; no automatic fallback if selected evidence is missing.
A11: N007 | B11: Baseline | C11: E14 | D11: All road diesel | E11: Passenger + LCV + HCV diesel; HCV alone is not national freight demand.
A12: N008 | B12: Baseline | C12: E15 | D12: Grid OCGT diesel | E12: Operational plant set and current load-factor path. Private backup is not separately calibrated.
A13: N009 | B13: Baseline | C13: E16 | D13: Agricultural diesel | E13: Held GDP/capita method with provisional 2024 baseline.
A14: N010 | B14: Baseline | C14: E17 | D14: Combined industrial diesel | E14: Manufacturing + mining + construction remain ONE aggregate engine bucket.
A15: N011 | B15: Baseline | C15: E18 | D15: Marine diesel | E15: Marine diesel_500ppm. No 2022-23 backcast provided by current marine engine.
... A376: N372 | B376: Model run | C376: A126 | D376: assumptions/2026/timeseries/vehicle_population_natis.csv | E376: assumptions/2026/timeseries/vehicle_population_natis.csv

Sheet HML
A1: Demand input ranges
A2: L/M/H orders each input; it does not order fuel demand. Existing values are proposals. Blanks require workshop decisions.
A4: Fuel / segment | B4: Driver | C4: Unit | D4: Year | E4: Low | F4: Medium | G4: High | H4: Higher input means | I4: Basis / rationale | J4: Annual path and dependencies | K4: Accepted reference | L4: Decision / owner | M4: Source
A5: diesel | B5: Freight activity 2024 = 100 | C5: index_2024_100 | D5: 2030 | E5: 95 | F5: 115 | G5: 135 | H5: More diesel | I5: 2024 = 100 Observed proxy. Observed freight proxy, not fuel demand | J5: Authored flat / recovery / expansion tests. Apply before rail diversion; calibrate litres per activity unit. Annual path not agreed. | L5: Proposed; Manish evidence, Nigel decision | M5: https://github.com/Africa-International-Advisors/liquid_fuels_model/blob/8c69f8333192483f19cd80911cb90fcd0943eb6b/assumptions/2026/timeseries/fuel_lever_design_2026_10_07.csv
A6: diesel | B6: Freight activity 2024 = 100 | C6: index_2024_100 | D6: 2035 | E6: 95 | F6: 135 | G6: 175 | H6: More diesel | I6: 2024 = 100 Observed proxy. Observed freight proxy, not fuel demand | J6: Authored flat / recovery / expansion tests. Apply before rail diversion; calibrate litres per activity unit. Annual path not agreed. | L6: Proposed; Manish evidence, Nigel decision | M6: https://github.com/Africa-International-Advisors/liquid_fuels_model/blob/8c69f8333192483f19cd80911cb90fcd0943eb6b/assumptions/2026/timeseries/fuel_lever_design_2026_10_07.csv
A7: diesel | B7: Road freight moved to rail % of reference road work | C7: % | D7: 2030 | E7: 0 | F7: 0.1 | G7: 0.2 | H7: Less road diesel | I7: No agreed diversion M is proposed. Authored modal-shift sensitivity; rail capacity unverified | J7: Higher diversion lowers road diesel. Avoid subtracting rail again if already embedded in the activity path. Annual path not agreed. | L7: Proposed; Manish evidence, Nigel decision | M7: https://github.com/Africa-International-Advisors/liquid_fuels_model/blob/8c69f8333192483f19cd80911cb90fcd0943eb6b/assumptions/2026/timeseries/fuel_lever_design_2026_10_07.csv
A8: diesel | B8: Road freight moved to rail % of reference road work | C8: % | D8: 2035 | E8: 0 | F8: 0.2 | G8: 0.35 | H8: Less road diesel | I8: No agreed diversion M is proposed. Authored modal-shift sensitivity; rail capacity unverified | J8: Higher diversion lowers road diesel. Avoid subtracting rail again if already embedded in the activity path. Annual path not agreed. | L8: Proposed; Manish evidence, Nigel decision | M8: https://github.com/Africa-International-Advisors/liquid_fuels_model/blob/8c69f8333192483f19cd80911cb90fcd0943eb6b/assumptions/2026/timeseries/fuel_lever_design_2026_10_07.csv
A9: diesel | B9: Diesel OCGT generation FY2024 = 100 | C9: index_FY2024_100 | D9: 2030 | E9: 10 | F9: 25 | G9: 60 | H9: More diesel | I9: FY2024 = 100 Latest trend is lower. Observed OCGT trend; all target-year indices authored | J9: Test grid recovery versus stress. Use one generation path; do not add a second load-shedding allowance. Annual path not agreed. | L9: Proposed; Manish evidence, Nigel decision | M9: https://github.com/Africa-International-Advisors/liquid_fuels_model/blob/8c69f8333192483f19cd80911cb90fcd0943eb6b/assumptions/2026/timeseries/fuel_lever_design_2026_10_07.csv
A10: diesel | B10: Diesel OCGT generation FY2024 = 100 | C10: index_FY2024_100 | D10: 2035 | E10: 5 | F10: 15 | G10: 50 | H10: More diesel | I10: FY2024 = 100 Latest trend is lower. Observed OCGT trend; all target-year indices authored | J10: Test grid recovery versus stress. Use one generation path; do not add a second load-shedding allowance. Annual path not agreed. | L10: Proposed; Manish evidence, Nigel decision | M10: https://github.com/Africa-International-Advisors/liquid_fuels_model/blob/8c69f8333192483f19cd80911cb90fcd0943eb6b/assumptions/2026/timeseries/fuel_lever_design_2026_10_07.csv
A11: diesel | B11: New-vehicle efficiency gain % per year | C11: % per year | D11: 2030 | E11: 0.005 | F11: 0.0075 | G11: 0.01 | H11: Less fuel | I11: Legacy: 0.5–1.0% New cohorts only. Registered diesel efficiency CSV; unreviewed | J11: Existing low/high input endpoints; M is a proposed midpoint. Higher gain lowers new-cohort fuel use. Annual path not agreed. | L11: Proposed; Manish evidence, Nigel decision | M11: https://github.com/Africa-International-Advisors/liquid_fuels_model/blob/8c69f8333192483f19cd80911cb90fcd0943eb6b/assumptions/2026/timeseries/fuel_lever_design_2026_10_07.csv
A12: diesel | B12: New-vehicle efficiency gain % per year | C12: % per year | D12: 2035 | E12: 0.005 | F12: 0.0075 | G12: 0.01 | H12: Less fuel | I12: Legacy: 0.5–1.0% New cohorts only. Registered diesel efficiency CSV; unreviewed | J12: Existing low/high input endpoints; M is a proposed midpoint. Higher gain lowers new-cohort fuel use. Annual path not agreed. | L12: Proposed; Manish evidence, Nigel decision | M12: https://github.com/Africa-International-Advisors/liquid_fuels_model/blob/8c69f8333192483f19cd80911cb90fcd0943eb6b/assumptions/2026/timeseries/fuel_lever_design_2026_10_07.csv
A13: jet | B13: Aircraft movements 2024 = 100 | C13: index_2024_100 | D13: 2030 | E13: 100 | F13: 120 | G13: 140 | H13: More jet | I13: 2024 = 100 ACSA coverage only. Registered ACSA movement source; target indices authored | J13: Authored flat / recovery / expansion tests. Follow Manish's movement driver; re-fit against matched jet deliveries. Annual path not agreed. | L13: Proposed; Manish evidence, Nigel decision | M13: https://github.com/Africa-International-Advisors/liquid_fuels_model/blob/8c69f8333192483f19cd80911cb90fcd0943eb6b/assumptions/2026/timeseries/fuel_lever_design_2026_10_07.csv
A14: jet | B14: Aircraft movements 2024 = 100 | C14: index_2024_100 | D14: 2035 | E14: 100 | F14: 145 | G14: 190 | H14: More jet | I14: 2024 = 100 ACSA coverage only. Registered ACSA movement source; target indices authored | J14: Authored flat / recovery / expansion tests. Follow Manish's movement driver; re-fit against matched jet deliveries. Annual path not agreed. | L14: Proposed; Manish evidence, Nigel decision | M14: https://github.com/Africa-International-Advisors/liquid_fuels_model/blob/8c69f8333192483f19cd80911cb90fcd0943eb6b/assumptions/2026/timeseries/fuel_lever_design_2026_10_07.csv
A15: jet | B15: Fuel burn per movement 2024 = 100 | C15: index_2024_100 | D15: 2030 | E15: 80 | F15: 90 | G15: 100 | H15: Confirm fuel effect | I15: 2024 = 100 assumed Not yet measured. Authored intensity tests; ICAO supports mechanism, not these SA values | J15: Lower burn lowers litres. Separate aircraft efficiency from route length, aircraft size and international mix. Annual path not agreed. | L15: Proposed; Manish evidence, Nigel decision | M15: https://github.com/Africa-International-Advisors/liquid_fuels_model/blob/8c69f8333192483f19cd80911cb90fcd0943eb6b/assumptions/2026/timeseries/fuel_lever_design_2026_10_07.csv
A16: jet | B16: Fuel burn per movement 2024 = 100 | C16: index_2024_100 | D16: 2035 | E16: 65 | F16: 80 | G16: 100 | H16: Confirm fuel effect | I16: 2024 = 100 assumed Not yet measured. Authored intensity tests; ICAO supports mechanism, not these SA values | J16: Lower burn lowers litres. Separate aircraft efficiency from route length, aircraft size and international mix. Annual path not agreed. | L16: Proposed; Manish evidence, Nigel decision | M16: https://github.com/Africa-International-Advisors/liquid_fuels_model/blob/8c69f8333192483f19cd80911cb90fcd0943eb6b/assumptions/2026/timeseries/fuel_lever_design_2026_10_07.csv
... A26: petrol | B26: New-vehicle efficiency gain % per year | C26: % per year | D26: 2035 | E26: 0.01 | F26: 0.0125 | G26: 0.015 | H26: Less fuel | I26: Legacy: 1.0–1.5% New cohorts only. Registered gasoline efficiency CSV; unreviewed | J26: Existing low/high input endpoints; M is a proposed midpoint. Preserve each cohort's entry-year consumption. Annual path not agreed. | L26: Proposed; Manish evidence, Nigel decision | M26: https://github.com/Africa-International-Advisors/liquid_fuels_model/blob/8c69f8333192483f19cd80911cb90fcd0943eb6b/assumptions/2026/timeseries/fuel_lever_design_2026_10_07.csv
A27: Petrol | B27: Hybrid / PHEV new-sales shares | C27: % | D27: 2030 | H27: Less fuel per km; not zero | I27: No numerical range proposed in this workbook. | J27: Separate drivetrains; shares reconcile; PHEV electric-distance fraction needed. Specify annual path. | L27: Open; Manish evidence, Nigel decision | M27: https://github.com/Africa-International-Advisors/liquid_fuels_model/blob/8c69f8333192483f19cd80911cb90fcd0943eb6b/workstreams/WS0_governance/workplan/fuel_lever_review_2026-10-07.md
A28: Petrol | B28: Hybrid / PHEV new-sales shares | C28: % | D28: 2035 | H28: Less fuel per km; not zero | I28: No numerical range proposed in this workbook. | J28: Separate drivetrains; shares reconcile; PHEV electric-distance fraction needed. Specify annual path. | L28: Open; Manish evidence, Nigel decision | M28: https://github.com/Africa-International-Advisors/liquid_fuels_model/blob/8c69f8333192483f19cd80911cb90fcd0943eb6b/workstreams/WS0_governance/workplan/fuel_lever_review_2026-10-07.md
A29: Road vehicles | B29: Retirement / survival | C29: % per year | D29: 2030 | H29: Depends on replacement and fleet mix | I29: No numerical range proposed in this workbook. | J29: Fit opening fleet and cohort survival; current flat rates are provisional. Specify annual path. | L29: Open; Manish evidence, Nigel decision | M29: https://github.com/Africa-International-Advisors/liquid_fuels_model/blob/8c69f8333192483f19cd80911cb90fcd0943eb6b/workstreams/WS0_governance/workplan/fuel_lever_review_2026-10-07.md
A30: Road vehicles | B30: Retirement / survival | C30: % per year | D30: 2035 | H30: Depends on replacement and fleet mix | I30: No numerical range proposed in this workbook. | J30: Fit opening fleet and cohort survival; current flat rates are provisional. Specify annual path. | L30: Open; Manish evidence, Nigel decision | M30: https://github.com/Africa-International-Advisors/liquid_fuels_model/blob/8c69f8333192483f19cd80911cb90fcd0943eb6b/workstreams/WS0_governance/workplan/fuel_lever_review_2026-10-07.md
A31: Diesel freight | B31: Payload / empty running | C31: definition due | D31: 2030 | H31: Depends on metric | I31: No numerical range proposed in this workbook. | J31: Choose tonne-km or fleet method; separate load factor from empty-running share. Specify annual path. | L31: Open; Manish evidence, Nigel decision | M31: https://github.com/Africa-International-Advisors/liquid_fuels_model/blob/8c69f8333192483f19cd80911cb90fcd0943eb6b/workstreams/WS0_governance/workplan/fuel_lever_review_2026-10-07.md
A32: Diesel freight | B32: Payload / empty running | C32: definition due | D32: 2035 | H32: Depends on metric | I32: No numerical range proposed in this workbook. | J32: Choose tonne-km or fleet method; separate load factor from empty-running share. Specify annual path. | L32: Open; Manish evidence, Nigel decision | M32: https://github.com/Africa-International-Advisors/liquid_fuels_model/blob/8c69f8333192483f19cd80911cb90fcd0943eb6b/workstreams/WS0_governance/workplan/fuel_lever_review_2026-10-07.md
A33: Diesel agriculture | B33: Agricultural activity | C33: index, base = 100 | D33: 2030 | H33: More diesel | I33: No numerical range proposed in this workbook. | J33: Choose activity and baseline year; reconcile provincial/sector scope. Specify annual path. | L33: Open; Manish evidence, Nigel decision | M33: https://github.com/Africa-International-Advisors/liquid_fuels_model/blob/8c69f8333192483f19cd80911cb90fcd0943eb6b/workstreams/WS0_governance/workplan/fuel_lever_review_2026-10-07.md
A34: Diesel agriculture | B34: Agricultural activity | C34: index, base = 100 | D34: 2035 | H34: More diesel | I34: No numerical range proposed in this workbook. | J34: Choose activity and baseline year; reconcile provincial/sector scope. Specify annual path. | L34: Open; Manish evidence, Nigel decision | M34: https://github.com/Africa-International-Advisors/liquid_fuels_model/blob/8c69f8333192483f19cd80911cb90fcd0943eb6b/workstreams/WS0_governance/workplan/fuel_lever_review_2026-10-07.md
A35: Diesel agriculture | B35: Relative fuel intensity | C35: base = 1 | D35: 2030 | H35: More diesel | I35: No numerical range proposed in this workbook. | J35: Separate intensity changes from activity; avoid overlapping efficiency effects. Specify annual path. | L35: Open; Manish evidence, Nigel decision | M35: https://github.com/Africa-International-Advisors/liquid_fuels_model/blob/8c69f8333192483f19cd80911cb90fcd0943eb6b/workstreams/WS0_governance/workplan/fuel_lever_review_2026-10-07.md
A36: Diesel agriculture | B36: Relative fuel intensity | C36: base = 1 | D36: 2035 | H36: More diesel | I36: No numerical range proposed in this workbook. | J36: Separate intensity changes from activity; avoid overlapping efficiency effects. Specify annual path. | L36: Open; Manish evidence, Nigel decision | M36: https://github.com/Africa-International-Advisors/liquid_fuels_model/blob/8c69f8333192483f19cd80911cb90fcd0943eb6b/workstreams/WS0_governance/workplan/fuel_lever_review_2026-10-07.md
A37: Diesel manufacturing | B37: Sector activity | C37: index, base = 100 | D37: 2030 | H37: More diesel | I37: No numerical range proposed in this workbook. | J37: Manufacturing-specific activity and intensity; electrification separate unless already embedded. Reconcile baseline split. Specify annual path. | L37: Open; Manish evidence, Nigel decision | M37: https://github.com/Africa-International-Advisors/liquid_fuels_model/blob/8c69f8333192483f19cd80911cb90fcd0943eb6b/workstreams/WS0_governance/workplan/fuel_lever_review_2026-10-07.md
A38: Diesel manufacturing | B38: Sector activity | C38: index, base = 100 | D38: 2035 | H38: More diesel | I38: No numerical range proposed in this workbook. | J38: Manufacturing-specific activity and intensity; electrification separate unless already embedded. Reconcile baseline split. Specify annual path. | L38: Open; Manish evidence, Nigel decision | M38: https://github.com/Africa-International-Advisors/liquid_fuels_model/blob/8c69f8333192483f19cd80911cb90fcd0943eb6b/workstreams/WS0_governance/workplan/fuel_lever_review_2026-10-07.md
... A61: Diesel mining | B61: Remaining diesel fraction after electrification | C61: base year = 1 | D61: 2035 | H61: More diesel | I61: No numerical brackets agreed. | J61: Mine-equipment-specific transition; do not borrow road-truck uptake. Annual path to agree. | L61: Open; Manish evidence, Nigel decision | M61: Workshop proposal, 7 October 2026; no numerical assumption adopted.
A63: Workshop rules
A64: Scenario construction | B64: Select low / medium / high independently for each input. Do not select all highs and call it high demand. | I64: Medium is a proposed reference, not an approved baseline. | J64: Keep supply utilisation, yields and restarts on an independent supply axis. | L64: Nigel / Henry
A65: Annual paths | B65: Endpoints do not define the intervening years. | I65: Agree opening observation, timing, ramp, constraints and post-2035 treatment. | J65: Reconcile provincial weighted adoption with a national target when one is imposed. | L65: Manish / Nigel

Sheet History
A1: Historical baseline, 2012-2025
A2: Layout follows the table drawn at the 7 October check-in. Observations are values from the registered inputs; totals and balances are formulas. Million litres a year, calendar years unless a row says otherwise.
A4: Driver / output | B4: Unit | C4: Role | D4: Scalar / latest value | E4: Definition / period | F4: 2012 | G4: 2013 | H4: 2014 | I4: 2015 | J4: 2016 | K4: 2017 | L4: 2018 | M4: 2019 | N4: 2020 | O4: 2021 | P4: 2022 | Q4: 2023 | R4: 2024 | S4: 2025 | T4: Coverage / status | U4: Source | V4: Missing evidence / next action
A5: 1. Department sales by province: petrol
A6: Gauteng petrol | B6: million L/year | C6: Observation to 2022; estimate after | E6: District-level sales summed to province, 2013-2022. Shows where fuel was sold, not where it was used. 2023 (yellow, italic) holds ESTIMATES from section 6, not department data; 2024 and 2025 are blank. | G6: 4171.9835 | H6: 3979.9971 | I6: 4119.3667 | J6: 4176.9778 | K6: 4088.4051 | L6: 3997.042 | M6: 4076.2446 | N6: 3135.0668 | O6: 3440.8174 | P6: 3530.4403 | Q6: =IF(ISNUMBER(Q86),Q86,"") | R6: =IF(ISNUMBER(R86),R86,"") | S6: =IF(ISNUMBER(S86),S86,"") | T6: 2013-2022 observed; 2023-2025 estimated | U6: Department of Mineral and Petroleum Resources, sales volumes, district workbooks; estimates: see section 6 | V6: Replace the estimates when the department publishes district data after 2023 quarter 1
A7: KwaZulu-Natal petrol | B7: million L/year | C7: Observation to 2022; estimate after | E7: District-level sales summed to province, 2013-2022. Shows where fuel was sold, not where it was used. 2023 (yellow, italic) holds ESTIMATES from section 6, not department data; 2024 and 2025 are blank. | G7: 1812.812 | H7: 1720.8025 | I7: 1787.553 | J7: 1765.6762 | K7: 1725.656 | L7: 1631.9803 | M7: 1678.4933 | N7: 1448.37 | O7: 1549.9221 | P7: 1498.9379 | Q7: =IF(ISNUMBER(Q87),Q87,"") | R7: =IF(ISNUMBER(R87),R87,"") | S7: =IF(ISNUMBER(S87),S87,"") | T7: 2013-2022 observed; 2023-2025 estimated | U7: Department of Mineral and Petroleum Resources, sales volumes, district workbooks; estimates: see section 6 | V7: Replace the estimates when the department publishes district data after 2023 quarter 1
A8: Western Cape petrol | B8: million L/year | C8: Observation to 2022; estimate after | E8: District-level sales summed to province, 2013-2022. Shows where fuel was sold, not where it was used. 2023 (yellow, italic) holds ESTIMATES from section 6, not department data; 2024 and 2025 are blank. | G8: 1723.8819 | H8: 1721.1272 | I8: 1745.4482 | J8: 1825.1998 | K8: 1773.0428 | L8: 1693.799 | M8: 1657.9981 | N8: 1307.4771 | O8: 1401.7429 | P8: 1431.0055 | Q8: =IF(ISNUMBER(Q88),Q88,"") | R8: =IF(ISNUMBER(R88),R88,"") | S8: =IF(ISNUMBER(S88),S88,"") | T8: 2013-2022 observed; 2023-2025 estimated | U8: Department of Mineral and Petroleum Resources, sales volumes, district workbooks; estimates: see section 6 | V8: Replace the estimates when the department publishes district data after 2023 quarter 1
A9: Eastern Cape petrol | B9: million L/year | C9: Observation to 2022; estimate after | E9: District-level sales summed to province, 2013-2022. Shows where fuel was sold, not where it was used. 2023 (yellow, italic) holds ESTIMATES from section 6, not department data; 2024 and 2025 are blank. | G9: 803.77468 | H9: 819.49159 | I9: 869.8725 | J9: 857.74124 | K9: 831.68812 | L9: 809.7137 | M9: 793.1128 | N9: 678.80191 | O9: 734.78996 | P9: 703.13244 | Q9: =IF(ISNUMBER(Q89),Q89,"") | R9: =IF(ISNUMBER(R89),R89,"") | S9: =IF(ISNUMBER(S89),S89,"") | T9: 2013-2022 observed; 2023-2025 estimated | U9: Department of Mineral and Petroleum Resources, sales volumes, district workbooks; estimates: see section 6 | V9: Replace the estimates when the department publishes district data after 2023 quarter 1
A10: Mpumalanga petrol | B10: million L/year | C10: Observation to 2022; estimate after | E10: District-level sales summed to province, 2013-2022. Shows where fuel was sold, not where it was used. 2023 (yellow, italic) holds ESTIMATES from section 6, not department data; 2024 and 2025 are blank. | G10: 831.70021 | H10: 827.86684 | I10: 955.039 | J10: 1029.3943 | K10: 962.78017 | L10: 879.95514 | M10: 801.57411 | N10: 690.51116 | O10: 661.62121 | P10: 612.26565 | Q10: =IF(ISNUMBER(Q90),Q90,"") | R10: =IF(ISNUMBER(R90),R90,"") | S10: =IF(ISNUMBER(S90),S90,"") | T10: 2013-2022 observed; 2023-2025 estimated | U10: Department of Mineral and Petroleum Resources, sales volumes, district workbooks; estimates: see section 6 | V10: Replace the estimates when the department publishes district data after 2023 quarter 1
A11: Free State petrol | B11: million L/year | C11: Observation to 2022; estimate after | E11: District-level sales summed to province, 2013-2022. Shows where fuel was sold, not where it was used. 2023 (yellow, italic) holds ESTIMATES from section 6, not department data; 2024 and 2025 are blank. | G11: 966.96948 | H11: 936.72123 | I11: 921.28759 | J11: 814.79378 | K11: 813.97095 | L11: 970.62487 | M11: 824.69139 | N11: 724.09523 | O11: 694.69561 | P11: 587.45801 | Q11: =IF(ISNUMBER(Q91),Q91,"") | R11: =IF(ISNUMBER(R91),R91,"") | S11: =IF(ISNUMBER(S91),S91,"") | T11: 2013-2022 observed; 2023-2025 estimated | U11: Department of Mineral and Petroleum Resources, sales volumes, district workbooks; estimates: see section 6 | V11: Replace the estimates when the department publishes district data after 2023 quarter 1
A12: North West petrol | B12: million L/year | C12: Observation to 2022; estimate after | E12: District-level sales summed to province, 2013-2022. Shows where fuel was sold, not where it was used. 2023 (yellow, italic) holds ESTIMATES from section 6, not department data; 2024 and 2025 are blank. | G12: 603.84079 | H12: 521.00824 | I12: 529.80649 | J12: 514.43739 | K12: 514.14322 | L12: 477.70129 | M12: 488.90772 | N12: 411.78136 | O12: 445.21786 | P12: 448.15623 | Q12: =IF(ISNUMBER(Q92),Q92,"") | R12: =IF(ISNUMBER(R92),R92,"") | S12: =IF(ISNUMBER(S92),S92,"") | T12: 2013-2022 observed; 2023-2025 estimated | U12: Department of Mineral and Petroleum Resources, sales volumes, district workbooks; estimates: see section 6 | V12: Replace the estimates when the department publishes district data after 2023 quarter 1
A13: Limpopo petrol | B13: million L/year | C13: Observation to 2022; estimate after | E13: District-level sales summed to province, 2013-2022. Shows where fuel was sold, not where it was used. 2023 (yellow, italic) holds ESTIMATES from section 6, not department data; 2024 and 2025 are blank. | G13: 403.18783 | H13: 382.40065 | I13: 410.4566 | J13: 357.19249 | K13: 355.79367 | L13: 366.57194 | M13: 350.05766 | N13: 276.51209 | O13: 276.41706 | P13: 273.64405 | Q13: =IF(ISNUMBER(Q93),Q93,"") | R13: =IF(ISNUMBER(R93),R93,"") | S13: =IF(ISNUMBER(S93),S93,"") | T13: 2013-2022 observed; 2023-2025 estimated | U13: Department of Mineral and Petroleum Resources, sales volumes, district workbooks; estimates: see section 6 | V13: Replace the estimates when the department publishes district data after 2023 quarter 1
A14: Northern Cape petrol | B14: million L/year | C14: Observation to 2022; estimate after | E14: District-level sales summed to province, 2013-2022. Shows where fuel was sold, not where it was used. 2023 (yellow, italic) holds ESTIMATES from section 6, not department data; 2024 and 2025 are blank. | G14: 121.96366 | H14: 121.24953 | I14: 130.82437 | J14: 120.83944 | K14: 108.33104 | L14: 101.61097 | M14: 102.12831 | N14: 88.855296 | O14: 96.360077 | P14: 99.829929 | Q14: =IF(ISNUMBER(Q94),Q94,"") | R14: =IF(ISNUMBER(R94),R94,"") | S14: =IF(ISNUMBER(S94),S94,"") | T14: 2013-2022 observed; 2023-2025 estimated | U14: Department of Mineral and Petroleum Resources, sales volumes, district workbooks; estimates: see section 6 | V14: Replace the estimates when the department publishes district data after 2023 quarter 1
A15: Sum of nine provinces, petrol | B15: million L/year | C15: Reporting formula | E15: Sum of the nine rows above. From 2023 it sums estimates, which add to the national figure by construction. | F15: =IF(COUNT(F6:F14)<9,"",SUM(F6:F14)) | G15: =IF(COUNT(G6:G14)<9,"",SUM(G6:G14)) | H15: =IF(COUNT(H6:H14)<9,"",SUM(H6:H14)) | I15: =IF(COUNT(I6:I14)<9,"",SUM(I6:I14)) | J15: =IF(COUNT(J6:J14)<9,"",SUM(J6:J14)) | K15: =IF(COUNT(K6:K14)<9,"",SUM(K6:K14)) | L15: =IF(COUNT(L6:L14)<9,"",SUM(L6:L14)) | M15: =IF(COUNT(M6:M14)<9,"",SUM(M6:M14)) | ... S15: =IF(COUNT(S6:S14)<9,"",SUM(S6:S14)) | U15: Calculated in this workbook from the rows named in the definition
A16: Department national file, petrol | B16: million L/year | C16: Source observation | E16: National annual workbook, years with four quarters reported. | F16: 12060.33 | G16: 11439.925 | H16: 10890.208 | I16: 11475.709 | J16: 11462.252 | K16: 11174.083 | L16: 11141.631 | M16: 10773.208 | N16: 8761.471 | O16: 9301.5842 | P16: 9184.8699 | Q16: 9036.9501 | T16: 2012-2023; nothing published for 2024 or 2025 | U16: Department of Mineral and Petroleum Resources, sales volumes, national workbooks | V16: Add 2024 and 2025 when the department publishes them
A17: Provinces less national, petrol | B17: million L/year | C17: Reporting formula | E17: Difference between the department's two files. The provincial figures are used as published. 2014: the district file's third quarter is higher than the national file. 2018: the first-quarter district sheet lists six fewer districts, so the provincial sum is about 2% low. Zero from 2023 only because the estimates are shares of the national figure. | F17: =IF(COUNT(F15,F16)<2,"",F15-F16) | G17: =IF(COUNT(G15,G16)<2,"",G15-G16) | H17: =IF(COUNT(H15,H16)<2,"",H15-H16) | I17: =IF(COUNT(I15,I16)<2,"",I15-I16) | J17: =IF(COUNT(J15,J16)<2,"",J15-J16) | K17: =IF(COUNT(K15,K16)<2,"",K15-K16) | L17: =IF(COUNT(L15,L16)<2,"",L15-L16) | M17: =IF(COUNT(M15,M16)<2,"",M15-M16) | ... S17: =IF(COUNT(S15,S16)<2,"",S15-S16) | U17: Calculated in this workbook from the rows named in the definition | V17: See integrity_flag_log_2026-10-06.md
A18: Why 2024 and 2025 are blank, petrol | C18: Note | E18: The department has published no petrol sales after 2023, by province or nationally, so there is no total to split. FIASA and JODI each have a national 2024 figure (9,029 and 10,138 million litres) but neither is reliable, so FIASA is not used and JODI is not used. FIASA: its 2024 and 2025 annual reports give different figures for 2024 (8,763 in the 2024 edition), its 2025 row is a copy of its 2024 row, and it attributes its sales to the department, which has published none. JODI: its demand was 2,648 and 3,035 million litres above department sales in 2022 and 2023, so it is not on the same basis, and every entry carries JODI's lowest reliability code. Neither has provincial data, and neither has a 2025 figure. | T18: 2024 and 2025 blank | U18: FIASA annual reports 2024 (p.32) and 2025 (p.47); JODI oil database; department sales volumes page | V18: Fill in when the department publishes
A20: 1. Department sales by province: diesel
A21: Gauteng diesel | B21: million L/year | C21: Observation to 2022; estimate after | E21: District-level sales summed to province, 2013-2022. Shows where fuel was sold, not where it was used. 2023 (yellow, italic) holds ESTIMATES from section 6, not department data; 2024 and 2025 are blank. | G21: 2785.4298 | H21: 3118.078 | I21: 3160.4269 | J21: 2953.3257 | K21: 3125.5234 | L21: 3320.0433 | M21: 3565.209 | N21: 2950.6708 | O21: 3205.1913 | P21: 3278.9905 | Q21: =IF(ISNUMBER(Q106),Q106,"") | R21: =IF(ISNUMBER(R106),R106,"") | S21: =IF(ISNUMBER(S106),S106,"") | T21: 2013-2022 observed; 2023-2025 estimated | U21: Department of Mineral and Petroleum Resources, sales volumes, district workbooks; estimates: see section 6 | V21: Replace the estimates when the department publishes district data after 2023 quarter 1
A22: KwaZulu-Natal diesel | B22: million L/year | C22: Observation to 2022; estimate after | E22: District-level sales summed to province, 2013-2022. Shows where fuel was sold, not where it was used. 2023 (yellow, italic) holds ESTIMATES from section 6, not department data; 2024 and 2025 are blank. | G22: 2252.1565 | H22: 2131.2562 | I22: 2125.0067 | J22: 2176.8973 | K22: 2459.7014 | L22: 2374.694 | M22: 2576.0354 | N22: 2610.3203 | O22: 2724.4225 | P22: 2785.5548 | Q22: =IF(ISNUMBER(Q107),Q107,"") | R22: =IF(ISNUMBER(R107),R107,"") | S22: =IF(ISNUMBER(S107),S107,"") | T22: 2013-2022 observed; 2023-2025 estimated | U22: Department of Mineral and Petroleum Resources, sales volumes, district workbooks; estimates: see section 6 | V22: Replace the estimates when the department publishes district data after 2023 quarter 1
A23: Western Cape diesel | B23: million L/year | C23: Observation to 2022; estimate after | E23: District-level sales summed to province, 2013-2022. Shows where fuel was sold, not where it was used. 2023 (yellow, italic) holds ESTIMATES from section 6, not department data; 2024 and 2025 are blank. | G23: 1987.5328 | H23: 2371.6273 | I23: 2951.0171 | J23: 1896.0105 | K23: 1854.2224 | L23: 1849.5607 | M23: 2061.8367 | N23: 1849.4091 | O23: 2608.3712 | P23: 2499.7695 | Q23: =IF(ISNUMBER(Q108),Q108,"") | R23: =IF(ISNUMBER(R108),R108,"") | S23: =IF(ISNUMBER(S108),S108,"") | T23: 2013-2022 observed; 2023-2025 estimated | U23: Department of Mineral and Petroleum Resources, sales volumes, district workbooks; estimates: see section 6 | V23: Replace the estimates when the department publishes district data after 2023 quarter 1
