Workbook

Sheet Contents
A1: Master data book: sourced data for the South Africa story
A2: The one place to look for a sourced figure, set out by data request (DR01, DR04, DR07, DR08). Petrol and diesel only. Every figure names its source. Built by python -m lfm.scripts.build_data_requests_workbook --vintage 2026; do not edit by hand.
A4: Sheet | B4: What it holds | C4: From source | D4: Calculated | E4: Not available
A5: DR01 national balance | B5: Sales, production, imports and exports by year, with the difference between supply and sales | C5: 8 | D5: 2 | E5: 2
A6: DR01 sales by province | B6: Petrol and diesel sold in each of the nine provinces by year; 2023 estimated
A7: DR01 demand by sector | B7: Diesel and petrol used by industry, mining, agriculture, transport and other sectors, 2014 to 2021
A8: DR01 sector activity | B8: Mining, manufacturing and agriculture: activity to 2025, diesel per unit of activity, and estimated diesel after 2021
A9: DR04 routes and access | B9: Pipeline limit and cost, regulated and published transport costs, port use, access at Durban and Lesedi, competing routes | C9: 66 | D9: 6 | E9: 7
A10: DR04 entry points | B10: Petrol and diesel imports cleared at each customs office, by year
A11: DR04 transport cost | B11: The Durban to Gauteng route by cost element, and the regulated transport differential for all 54 pricing zones
A12: DR07 demand evidence | B12: Eskom and independent diesel burn, plant dates, vehicle fleet, new vehicles, efficiency, freight and rail | C12: 75 | D12: 21 | E12: 5
A13: DR07 fleet by province | B13: Registered vehicles by class and province, and petrol and diesel vehicles by province
A14: DR08 refinery supply | B14: Capacity, status and closure dates, output by plant and nationally, yields, utilisation and outlook | C14: 43 | D14: 19 | E14: 2
A15: Market sizing | B15: What Vopak Durban and Vopak Lesedi can reach: site markets, the inland-bound flow, the trunk line and what the tanks allow
A16: Not available | B16: The 17 items that could not be found, with the reason for each
A18: Colours
A19: Blue: read from a published source
A20: White: calculated here from figures on the sheet
A21: Yellow: not available

Sheet DR01 national balance
A1: DR01 National balance: petrol and diesel
A2: Billion litres, calendar years. Blank means not published. Sales are the department's figures: provinces added up for 2014 to 2022, the national total for 2023. FIASA and JODI are not used.
A5: Petrol
A6: Line | B6: 2014 | C6: 2015 | D6: 2016 | E6: 2017 | F6: 2018 | G6: 2019 | H6: 2020 | I6: 2021 | J6: 2022 | K6: 2023 | L6: 2024 | M6: 2025 | N6: Source | O6: Note
A7: Sales | B7: 11.030665 | C7: 11.469654 | D7: 11.462252 | E7: 11.173811 | F7: 10.928999 | G7: 10.773208 | H7: 8.761471 | I7: 9.3015842 | J7: 9.1848699 | K7: 9.0369501 | N7: Department of Mineral and Petroleum Resources, fuel sales volumes | O7: Nothing published after 2023.
A8: Production | B8: 10.82816 | C8: 10.457813 | D8: 10.393066 | E8: 9.43444 | F8: 9.97456 | G8: 10.424467 | H8: 7.895 | I8: 6.3513067 | N8: Department of Mineral and Petroleum Resources, energy balances, one file a year | O8: The last balance published is 2021.
A9: Imports | B9: 1.1501948 | C9: 1.8696452 | D9: 1.3956385 | E9: 2.1141565 | F9: 1.8297713 | G9: 1.4773858 | H9: 1.7196731 | I9: 4.0086128 | J9: 5.4552618 | K9: 4.4827748 | L9: 4.0008544 | M9: 4.4534712 | N9: SARS customs, trade statistics portal, petrol and diesel tariff lines | O9: Complete calendar years, in litres.
A10: Exports | B10: 0.98951589 | C10: 1.0856704 | D10: 1.1573288 | E10: 1.0758862 | F10: 1.1350503 | G10: 1.1747018 | H10: 1.1547791 | I10: 1.0524951 | J10: 0.85461371 | K10: 0.99401956 | L10: 0.91974502 | M10: 0.80176247 | N10: SARS customs, trade statistics portal, petrol and diesel tariff lines
A11: Stock change | N11: None | O11: Not published by any source used.
A12: Supply less sales | B12: =IF(COUNT(B7,B8,B9,B10)<4,"",B8+B9-B10-B7) | C12: =IF(COUNT(C7,C8,C9,C10)<4,"",C8+C9-C10-C7) | D12: =IF(COUNT(D7,D8,D9,D10)<4,"",D8+D9-D10-D7) | E12: =IF(COUNT(E7,E8,E9,E10)<4,"",E8+E9-E10-E7) | F12: =IF(COUNT(F7,F8,F9,F10)<4,"",F8+F9-F10-F7) | G12: =IF(COUNT(G7,G8,G9,G10)<4,"",G8+G9-G10-G7) | H12: =IF(COUNT(H7,H8,H9,H10)<4,"",H8+H9-H10-H7) | I12: =IF(COUNT(I7,I8,I9,I10)<4,"",I8+I9-I10-I7) | ... M12: =IF(COUNT(M7,M8,M9,M10)<4,"",M8+M9-M10-M7) | N12: Calculated: production + imports - exports - sales | O12: Stock change and statistical difference together. Shown only where all four lines exist.
A14: Diesel
A15: Line | B15: 2014 | C15: 2015 | D15: 2016 | E15: 2017 | F15: 2018 | G15: 2019 | H15: 2020 | I15: 2021 | J15: 2022 | K15: 2023 | L15: 2024 | M15: 2025 | N15: Source | O15: Note
A16: Sales | B16: 12.74339 | C16: 13.492151 | D16: 12.082374 | E16: 12.14515 | F16: 12.31862 | G16: 12.908631 | H16: 11.689958 | I16: 12.945018 | J16: 12.717326 | K16: 12.9075 | N16: Department of Mineral and Petroleum Resources, fuel sales volumes | O16: Nothing published after 2023.
A17: Production | B17: 9.58774 | C17: 9.368482 | D17: 9.01419 | E17: 7.921726 | F17: 8.425262 | G17: 9.080357 | H17: 6.4478095 | I17: 5.3149643 | N17: Department of Mineral and Petroleum Resources, energy balances, one file a year | O17: The last balance published is 2021.
A18: Imports | B18: 4.9917123 | C18: 6.450779 | D18: 4.424295 | E18: 6.0374599 | F18: 5.1229595 | G18: 5.5902721 | H18: 6.8149854 | I18: 9.7613953 | J18: 11.954257 | K18: 12.870032 | L18: 10.792547 | M18: 12.24872 | N18: SARS customs, trade statistics portal, petrol and diesel tariff lines | O18: Complete calendar years, in litres.
A19: Exports | B19: 1.4937626 | C19: 1.612855 | D19: 1.8856054 | E19: 1.7826741 | F19: 1.5820701 | G19: 1.7413773 | H19: 0.91381452 | I19: 0.89348811 | J19: 0.88919907 | K19: 0.88944591 | L19: 0.79583468 | M19: 0.74670021 | N19: SARS customs, trade statistics portal, petrol and diesel tariff lines
A20: Stock change | N20: None | O20: Not published by any source used.
A21: Supply less sales | B21: =IF(COUNT(B16,B17,B18,B19)<4,"",B17+B18-B19-B16) | C21: =IF(COUNT(C16,C17,C18,C19)<4,"",C17+C18-C19-C16) | D21: =IF(COUNT(D16,D17,D18,D19)<4,"",D17+D18-D19-D16) | E21: =IF(COUNT(E16,E17,E18,E19)<4,"",E17+E18-E19-E16) | F21: =IF(COUNT(F16,F17,F18,F19)<4,"",F17+F18-F19-F16) | G21: =IF(COUNT(G16,G17,G18,G19)<4,"",G17+G18-G19-G16) | H21: =IF(COUNT(H16,H17,H18,H19)<4,"",H17+H18-H19-H16) | I21: =IF(COUNT(I16,I17,I18,I19)<4,"",I17+I18-I19-I16) | ... M21: =IF(COUNT(M16,M17,M18,M19)<4,"",M17+M18-M19-M16) | N21: Calculated: production + imports - exports - sales | O21: Stock change and statistical difference together. Shown only where all four lines exist.

Sheet DR01 sales by province
A1: DR01 Sales by province: petrol and diesel
A2: Billion litres, calendar years. 2013 to 2022 are the department's district data added up by province (blue). 2023 is an estimate (yellow): the national total split by each province's share of sales in the first quarter of 2023. 2024 and 2025 are blank.
A5: Petrol
A6: Province | B6: 2013 | C6: 2014 | D6: 2015 | E6: 2016 | F6: 2017 | G6: 2018 | H6: 2019 | I6: 2020 | J6: 2021 | K6: 2022 | L6: 2023 | M6: 2024 | N6: 2025 | O6: Source | P6: Note
A7: Gauteng | B7: 4.1719835 | C7: 3.9799971 | D7: 4.1193667 | E7: 4.1769778 | F7: 4.0884051 | G7: 3.997042 | H7: 4.0762446 | I7: 3.1350668 | J7: 3.4408174 | K7: 3.5304403 | L7: 3.460323 | O7: Department of Mineral and Petroleum Resources, fuel sales volumes by magisterial district | P7: 2023 is an estimate. Nothing published by province after the first quarter of 2023.
A8: KwaZulu-Natal | B8: 1.812812 | C8: 1.7208025 | D8: 1.787553 | E8: 1.7656762 | F8: 1.725656 | G8: 1.6319803 | H8: 1.6784933 | I8: 1.44837 | J8: 1.5499221 | K8: 1.4989379 | L8: 1.457735 | O8: Department of Mineral and Petroleum Resources, fuel sales volumes by magisterial district | P8: 2023 is an estimate. Nothing published by province after the first quarter of 2023.
A9: Western Cape | B9: 1.7238819 | C9: 1.7211272 | D9: 1.7454482 | E9: 1.8251998 | F9: 1.7730428 | G9: 1.693799 | H9: 1.6579981 | I9: 1.3074771 | J9: 1.4017429 | K9: 1.4310055 | L9: 1.4654567 | O9: Department of Mineral and Petroleum Resources, fuel sales volumes by magisterial district | P9: 2023 is an estimate. Nothing published by province after the first quarter of 2023.
A10: Eastern Cape | B10: 0.80377468 | C10: 0.81949159 | D10: 0.8698725 | E10: 0.85774124 | F10: 0.83168812 | G10: 0.8097137 | H10: 0.7931128 | I10: 0.67880191 | J10: 0.73478996 | K10: 0.70313244 | L10: 0.67878638 | O10: Department of Mineral and Petroleum Resources, fuel sales volumes by magisterial district | P10: 2023 is an estimate. Nothing published by province after the first quarter of 2023.
A11: Mpumalanga | B11: 0.83170021 | C11: 0.82786684 | D11: 0.955039 | E11: 1.0293943 | F11: 0.96278017 | G11: 0.87995514 | H11: 0.80157411 | I11: 0.69051116 | J11: 0.66162121 | K11: 0.61226565 | L11: 0.63759045 | O11: Department of Mineral and Petroleum Resources, fuel sales volumes by magisterial district | P11: 2023 is an estimate. Nothing published by province after the first quarter of 2023.
A12: Free State | B12: 0.96696948 | C12: 0.93672123 | D12: 0.92128759 | E12: 0.81479378 | F12: 0.81397095 | G12: 0.97062487 | H12: 0.82469139 | I12: 0.72409523 | J12: 0.69469561 | K12: 0.58745801 | L12: 0.53608626 | O12: Department of Mineral and Petroleum Resources, fuel sales volumes by magisterial district | P12: 2023 is an estimate. Nothing published by province after the first quarter of 2023.
A13: North West | B13: 0.60384079 | C13: 0.52100824 | D13: 0.52980649 | E13: 0.51443739 | F13: 0.51414322 | G13: 0.47770129 | H13: 0.48890772 | I13: 0.41178136 | J13: 0.44521786 | K13: 0.44815623 | L13: 0.43076315 | O13: Department of Mineral and Petroleum Resources, fuel sales volumes by magisterial district | P13: 2023 is an estimate. Nothing published by province after the first quarter of 2023.
A14: Limpopo | B14: 0.40318783 | C14: 0.38240065 | D14: 0.4104566 | E14: 0.35719249 | F14: 0.35579367 | G14: 0.36657194 | H14: 0.35005766 | I14: 0.27651209 | J14: 0.27641706 | K14: 0.27364405 | L14: 0.2719085 | O14: Department of Mineral and Petroleum Resources, fuel sales volumes by magisterial district | P14: 2023 is an estimate. Nothing published by province after the first quarter of 2023.
A15: Northern Cape | B15: 0.12196366 | C15: 0.12124953 | D15: 0.13082437 | E15: 0.12083944 | F15: 0.10833104 | G15: 0.10161097 | H15: 0.10212831 | I15: 0.088855296 | J15: 0.096360077 | K15: 0.099829929 | L15: 0.098300729 | O15: Department of Mineral and Petroleum Resources, fuel sales volumes by magisterial district | P15: 2023 is an estimate. Nothing published by province after the first quarter of 2023.
A16: Nine provinces | B16: =IF(COUNT(B7:B15)=0,"",SUM(B7:B15)) | C16: =IF(COUNT(C7:C15)=0,"",SUM(C7:C15)) | D16: =IF(COUNT(D7:D15)=0,"",SUM(D7:D15)) | E16: =IF(COUNT(E7:E15)=0,"",SUM(E7:E15)) | F16: =IF(COUNT(F7:F15)=0,"",SUM(F7:F15)) | G16: =IF(COUNT(G7:G15)=0,"",SUM(G7:G15)) | H16: =IF(COUNT(H7:H15)=0,"",SUM(H7:H15)) | I16: =IF(COUNT(I7:I15)=0,"",SUM(I7:I15)) | ... N16: =IF(COUNT(N7:N15)=0,"",SUM(N7:N15)) | O16: Calculated: sum of the rows above | P16: The sales line on the national balance sheet.
A17: National file, for comparison | B17: 11.439925 | C17: 10.890208 | D17: 11.475709 | E17: 11.462252 | F17: 11.174083 | G17: 11.141631 | H17: 10.773208 | I17: 8.761471 | J17: 9.3015842 | K17: 9.1848699 | L17: 9.0369501 | O17: Department of Mineral and Petroleum Resources, national fuel sales volumes | P17: The 2023 estimates add up to this by construction. The two files differ in 2014 and 2018.
A19: Diesel
A20: Province | B20: 2013 | C20: 2014 | D20: 2015 | E20: 2016 | F20: 2017 | G20: 2018 | H20: 2019 | I20: 2020 | J20: 2021 | K20: 2022 | L20: 2023 | M20: 2024 | N20: 2025 | O20: Source | P20: Note
A21: Gauteng | B21: 2.7854298 | C21: 3.118078 | D21: 3.1604269 | E21: 2.9533257 | F21: 3.1255234 | G21: 3.3200433 | H21: 3.565209 | I21: 2.9506708 | J21: 3.2051913 | K21: 3.2789905 | L21: 3.3502336 | O21: Department of Mineral and Petroleum Resources, fuel sales volumes by magisterial district | P21: 2023 is an estimate. Nothing published by province after the first quarter of 2023.
A22: KwaZulu-Natal | B22: 2.2521565 | C22: 2.1312562 | D22: 2.1250067 | E22: 2.1768973 | F22: 2.4597014 | G22: 2.374694 | H22: 2.5760354 | I22: 2.6103203 | J22: 2.7244225 | K22: 2.7855548 | L22: 2.4505852 | O22: Department of Mineral and Petroleum Resources, fuel sales volumes by magisterial district | P22: 2023 is an estimate. Nothing published by province after the first quarter of 2023.
A23: Western Cape | B23: 1.9875328 | C23: 2.3716273 | D23: 2.9510171 | E23: 1.8960105 | F23: 1.8542224 | G23: 1.8495607 | H23: 2.0618367 | I23: 1.8494091 | J23: 2.6083712 | K23: 2.4997695 | L23: 3.031414 | O23: Department of Mineral and Petroleum Resources, fuel sales volumes by magisterial district | P23: 2023 is an estimate. Nothing published by province after the first quarter of 2023.
A24: Eastern Cape | B24: 0.78214884 | C24: 0.80722424 | D24: 0.92926903 | E24: 0.92814183 | F24: 0.93732341 | G24: 0.96060541 | H24: 0.99903178 | I24: 0.93681699 | J24: 1.0364548 | K24: 1.0323522 | L24: 1.0184892 | O24: Department of Mineral and Petroleum Resources, fuel sales volumes by magisterial district | P24: 2023 is an estimate. Nothing published by province after the first quarter of 2023.
A25: Mpumalanga | B25: 1.4888311 | C25: 1.5133165 | D25: 1.4993294 | E25: 1.6312066 | F25: 1.5460486 | G25: 1.5766914 | H25: 1.4351283 | I25: 1.3074244 | J25: 1.2756094 | K25: 1.1449241 | L25: 1.1815546 | O25: Department of Mineral and Petroleum Resources, fuel sales volumes by magisterial district | P25: 2023 is an estimate. Nothing published by province after the first quarter of 2023.
A26: Free State | B26: 1.2925251 | C26: 1.2491798 | D26: 1.2590152 | E26: 1.1249072 | F26: 0.93016393 | G26: 1.0072792 | H26: 1.0590539 | I26: 1.0305888 | J26: 1.0256523 | K26: 0.78186116 | L26: 0.70041229 | O26: Department of Mineral and Petroleum Resources, fuel sales volumes by magisterial district | P26: 2023 is an estimate. Nothing published by province after the first quarter of 2023.
A27: North West | B27: 0.66259176 | C27: 0.63727812 | D27: 0.65900795 | E27: 0.65041846 | F27: 0.58716232 | G27: 0.51402503 | H27: 0.51835939 | I27: 0.4361658 | J27: 0.50040565 | K27: 0.61990649 | L27: 0.56858027 | O27: Department of Mineral and Petroleum Resources, fuel sales volumes by magisterial district | P27: 2023 is an estimate. Nothing published by province after the first quarter of 2023.
A28: Limpopo | B28: 0.42448303 | C28: 0.40841603 | D28: 0.3712796 | E28: 0.30922616 | F28: 0.27471398 | G28: 0.2956001 | H28: 0.26969798 | I28: 0.216124 | J28: 0.21025773 | K28: 0.22198744 | L28: 0.24381457 | O28: Department of Mineral and Petroleum Resources, fuel sales volumes by magisterial district | P28: 2023 is an estimate. Nothing published by province after the first quarter of 2023.
A29: Northern Cape | B29: 0.46534822 | C29: 0.50701367 | D29: 0.53779946 | E29: 0.4122403 | F29: 0.43029076 | G29: 0.42012136 | H29: 0.4242787 | I29: 0.35243756 | J29: 0.35865318 | K29: 0.35198012 | L29: 0.36241629 | O29: Department of Mineral and Petroleum Resources, fuel sales volumes by magisterial district | P29: 2023 is an estimate. Nothing published by province after the first quarter of 2023.
A30: Nine provinces | B30: =IF(COUNT(B21:B29)=0,"",SUM(B21:B29)) | C30: =IF(COUNT(C21:C29)=0,"",SUM(C21:C29)) | D30: =IF(COUNT(D21:D29)=0,"",SUM(D21:D29)) | E30: =IF(COUNT(E21:E29)=0,"",SUM(E21:E29)) | F30: =IF(COUNT(F21:F29)=0,"",SUM(F21:F29)) | G30: =IF(COUNT(G21:G29)=0,"",SUM(G21:G29)) | H30: =IF(COUNT(H21:H29)=0,"",SUM(H21:H29)) | I30: =IF(COUNT(I21:I29)=0,"",SUM(I21:I29)) | ... N30: =IF(COUNT(N21:N29)=0,"",SUM(N21:N29)) | O30: Calculated: sum of the rows above | P30: The sales line on the national balance sheet.
A31: National file, for comparison | B31: 12.141282 | C31: 12.615023 | D31: 13.520139 | E31: 12.082374 | F31: 12.147245 | G31: 12.538744 | H31: 12.908631 | I31: 11.689958 | J31: 12.945783 | K31: 12.717326 | L31: 12.9075 | O31: Department of Mineral and Petroleum Resources, national fuel sales volumes | P31: The 2023 estimates add up to this by construction. The two files differ in 2014 and 2018.
A33: 2024 and 2025 are blank: the department has published no sales after 2023. FIASA and JODI carry figures for those years, but they are not used.

Sheet DR01 demand by sector
A1: DR01 Demand by sector: diesel and petrol
A2: Billion litres, calendar years, as reported in the department's energy balances. The last balance is 2021, so nothing later is published by sector. Blank means the balance gives no figure.
A5: Diesel
A6: Sector | B6: 2014 | C6: 2015 | D6: 2016 | E6: 2017 | F6: 2018 | G6: 2019 | H6: 2020 | I6: 2021 | J6: Source | K6: Note
A7: All sectors | B7: 12.597876 | C7: 13.49109 | D7: 12.794349 | E7: 13.258459 | F7: 13.204751 | G7: 13.535823 | H7: 12.179677 | I7: 13.407266 | J7: Department of Mineral and Petroleum Resources, energy balances, one file a year | K7: The department's total for all sectors. It is not the sales figure on the national balance sheet.
A8: Road transport | B8: 8.903131 | C8: 9.428381 | D8: 4.3963865 | E8: 9.359175 | F8: 6.3919425 | G8: 6.725982 | H8: 5.8481915 | I8: 6.3279573 | J8: Department of Mineral and Petroleum Resources, energy balances, one file a year
A9: Rail | B9: 0.09044075 | C9: 0.12395326 | D9: 0.18690598 | E9: 0.13610452 | F9: 0.16974334 | G9: 0.12818266 | H9: 0.099427187 | I9: 0.01312792 | J9: Department of Mineral and Petroleum Resources, energy balances, one file a year
A10: Industry, all | B10: 1.6397506 | C10: 1.9331292 | D10: 1.3197982 | E10: 1.5438398 | F10: 1.8844217 | G10: 1.8979908 | H10: 1.4462207 | I10: 1.4991393 | J10: Department of Mineral and Petroleum Resources, energy balances, one file a year | K10: Mining, construction, manufacturing and industry not specified, together. Manufacturing and other industry is this line less the two below.
A11: Mining (part of industry) | B11: 1.5050322 | C11: 1.8183965 | D11: 1.0442531 | E11: 1.300426 | F11: 1.650123 | G11: 1.6672493 | H11: 1.2634057 | I11: 1.2938134 | J11: Department of Mineral and Petroleum Resources, energy balances, one file a year
A12: Construction (part of industry) | B12: 0.13471839 | C12: 0.11473268 | D12: 0.13869362 | E12: 0.12446979 | F12: 0.074592859 | H12: 0.042847406 | I12: 0.04869243 | J12: Department of Mineral and Petroleum Resources, energy balances, one file a year
A13: Agriculture | B13: 1.0924988 | C13: 1.0734942 | D13: 1.8872789 | E13: 1.876914 | F13: 0.89988344 | G13: 0.92184869 | H13: 1.0489635 | I13: 1.0583989 | J13: Department of Mineral and Petroleum Resources, energy balances, one file a year
A14: Commercial and public services | B14: 0.023462721 | C14: 0.014730648 | D14: 4.9728395 | F14: 3.8237085 | G14: 3.8215455 | H14: 3.6391218 | I14: 4.2999757 | J14: Department of Mineral and Petroleum Resources, energy balances, one file a year | K14: Jumps from almost nothing to several billion litres from 2016: the department moved volumes between sectors, so read with care.
A15: Households | B15: 0.0076144878 | C15: 0.0055073389 | E15: 0.00030523999 | F15: 0.001321481 | G15: 0.00071392102 | H15: 0.0060975581 | I15: 0.00201032 | J15: Department of Mineral and Petroleum Resources, energy balances, one file a year
A16: Power stations | B16: 1.1785999 | C16: 1.2478 | D16: 1.2478001 | E16: 0.01 | F16: 0.01 | G16: 0.028724191 | J16: Department of Mineral and Petroleum Resources, energy balances, one file a year | K16: The balances record little or none after 2016; Eskom's own reported fuel is on the DR07 sheet.
A18: Petrol
A19: Sector | B19: 2014 | C19: 2015 | D19: 2016 | E19: 2017 | F19: 2018 | G19: 2019 | H19: 2020 | I19: 2021 | J19: Source | K19: Note
A20: All sectors | B20: 10.855633 | C20: 11.467667 | D20: 12.105125 | E20: 11.812068 | F20: 11.715421 | G20: 11.382889 | H20: 9.274792 | I20: 9.836176 | J20: Department of Mineral and Petroleum Resources, energy balances, one file a year | K20: The department's total for all sectors. It is not the sales figure on the national balance sheet.
A21: Road transport | B21: 10.599969 | C21: 11.20332 | D21: 7.8504055 | E21: 7.799955 | F21: 9.421383 | G21: 10.179225 | H21: 8.15771 | I21: 8.734665 | J21: Department of Mineral and Petroleum Resources, energy balances, one file a year
A22: Rail | B22: 0.018827936 | C22: 0.047792777 | D22: 0.04603073 | E22: 0.05994 | F22: 0.035428523 | G22: 0.00079180579 | H22: 0.000738724 | I22: 0.00011681 | J22: Department of Mineral and Petroleum Resources, energy balances, one file a year
A23: Industry, all | B23: 0.023601798 | C23: 0.0060527821 | D23: 0.031182868 | E23: 0.10085648 | F23: 0.18482997 | G23: 0.18297078 | H23: 0.086091569 | I23: 0.06503531 | J23: Department of Mineral and Petroleum Resources, energy balances, one file a year | K23: Mining, construction, manufacturing and industry not specified, together. Manufacturing and other industry is this line less the two below.
A24: Mining (part of industry) | B24: 0.016619383 | C24: 0.0056376621 | D24: 0.0048052275 | E24: 0.072304039 | F24: 0.15942438 | G24: 0.15853869 | H24: 0.07227907 | I24: 0.05449402 | J24: Department of Mineral and Petroleum Resources, energy balances, one file a year
A25: Construction (part of industry) | B25: 0.006982415 | C25: 0.00041512 | D25: 0.0033661768 | E25: 0.0066261699 | F25: 0.0013684966 | G25: 0.00056973407 | H25: 0.00061182007 | I25: 0.00105943 | J25: Department of Mineral and Petroleum Resources, energy balances, one file a year
A26: Agriculture | B26: 0.15722427 | C26: 0.1724905 | D26: 1.9288791 | E26: 1.95126 | F26: 0.12049402 | G26: 0.10681195 | H26: 0.11402438 | I26: 0.12018356 | J26: Department of Mineral and Petroleum Resources, energy balances, one file a year
A27: Commercial and public services | B27: 0.0037713159 | C27: 0.003779845 | D27: 2.2438662 | E27: 1.8833842 | F27: 1.9471366 | G27: 0.90765475 | H27: 0.90489988 | I27: 0.90667726 | J27: Department of Mineral and Petroleum Resources, energy balances, one file a year | K27: Jumps from almost nothing to several billion litres from 2016: the department moved volumes between sectors, so read with care.
A28: Households | B28: 0.003343123 | C28: 0.002184249 | F28: 0.000179702 | G28: 0.000167353 | H28: 1.5799e-05 | I28: 1.481e-05 | J28: Department of Mineral and Petroleum Resources, energy balances, one file a year

Sheet DR01 sector activity
A1: DR01 Sector activity: mining, manufacturing and agriculture
A2: Activity is published to 2025; diesel by sector stops at 2021. The estimate for later years is the average diesel per unit of activity in 2018 to 2021 times the activity of that year. Diesel is read from the demand by sector sheet, not repeated here.
A5: Mining
A6: Line | B6: Unit | C6: 2014 | D6: 2015 | E6: 2016 | F6: 2017 | G6: 2018 | H6: 2019 | I6: 2020 | J6: 2021 | K6: 2022 | L6: 2023 | M6: 2024 | N6: 2025 | O6: Source | P6: Note
A7: Mining production volume | B7: index, 2019 = 100 | C7: 99.033333 | D7: 102.24167 | E7: 98.916667 | F7: 102.53333 | G7: 100.925 | H7: 99.983333 | I7: 89.1 | J7: 100.875 | K7: 93.008333 | L7: 93.016667 | M7: 93.533333 | N7: 93.708333 | O7: Statistics South Africa, Mining production and sales (P2041) | P7: Published to 2025.
A8: Diesel per unit of activity | B8: million litres per index point | C8: ='DR01 demand by sector'!B11*1000/C7 | D8: ='DR01 demand by sector'!C11*1000/D7 | E8: ='DR01 demand by sector'!D11*1000/E7 | F8: ='DR01 demand by sector'!E11*1000/F7 | G8: ='DR01 demand by sector'!F11*1000/G7 | H8: ='DR01 demand by sector'!G11*1000/H7 | I8: ='DR01 demand by sector'!H11*1000/I7 | J8: ='DR01 demand by sector'!I11*1000/J7 | O8: Calculated: diesel on the demand by sector sheet over the activity above | P8: The energy balance's mining line includes mines' haul trucks and road vehicles.
A9: Estimated diesel after 2021 | B9: billion litres | K9: =AVERAGE(G8:J8)*K7/1000 | L9: =AVERAGE(G8:J8)*L7/1000 | M9: =AVERAGE(G8:J8)*M7/1000 | N9: =AVERAGE(G8:J8)*N7/1000 | O9: Calculated: average diesel per unit of activity, 2018 to 2021, times that year's activity | P9: An estimate, not an observation and not an accepted model input. Holds diesel per unit of activity constant. For Nigel to agree.
A11: Manufacturing and other industry
A12: Line | B12: Unit | C12: 2014 | D12: 2015 | E12: 2016 | F12: 2017 | G12: 2018 | H12: 2019 | I12: 2020 | J12: 2021 | K12: 2022 | L12: 2023 | M12: 2024 | N12: 2025 | O12: Source | P12: Note
A13: Manufacturing production volume | B13: index, 2019 = 100 | C13: 100.11667 | D13: 100.1 | E13: 100.80833 | F13: 100.13333 | G13: 101.1 | H13: 99.983333 | I13: 87.666667 | J13: 93.116667 | K13: 93.141667 | L13: 93.716667 | M13: 93.333333 | N13: 92.141667 | O13: Statistics South Africa, Manufacturing production and sales (P3041.2) | P13: Published to 2025.
A14: Diesel per unit of activity | B14: million litres per index point | C14: =('DR01 demand by sector'!B10-'DR01 demand by sector'!B11-N('DR01 demand by sector'!B12))*1000/C13 | D14: =('DR01 demand by sector'!C10-'DR01 demand by sector'!C11-N('DR01 demand by sector'!C12))*1000/D13 | E14: =('DR01 demand by sector'!D10-'DR01 demand by sector'!D11-N('DR01 demand by sector'!D12))*1000/E13 | F14: =('DR01 demand by sector'!E10-'DR01 demand by sector'!E11-N('DR01 demand by sector'!E12))*1000/F13 | G14: =('DR01 demand by sector'!F10-'DR01 demand by sector'!F11-N('DR01 demand by sector'!F12))*1000/G13 | H14: =('DR01 demand by sector'!G10-'DR01 demand by sector'!G11-N('DR01 demand by sector'!G12))*1000/H13 | I14: =('DR01 demand by sector'!H10-'DR01 demand by sector'!H11-N('DR01 demand by sector'!H12))*1000/I13 | J14: =('DR01 demand by sector'!I10-'DR01 demand by sector'!I11-N('DR01 demand by sector'!I12))*1000/J13 | O14: Calculated: diesel on the demand by sector sheet over the activity above | P14: Diesel is industry less mining less construction. It is small (0.1 to 0.3 billion litres), so it moves with reclassification more than with output.
A15: Estimated diesel after 2021 | B15: billion litres | K15: =AVERAGE(G14:J14)*K13/1000 | L15: =AVERAGE(G14:J14)*L13/1000 | M15: =AVERAGE(G14:J14)*M13/1000 | N15: =AVERAGE(G14:J14)*N13/1000 | O15: Calculated: average diesel per unit of activity, 2018 to 2021, times that year's activity | P15: An estimate, not an observation and not an accepted model input. Holds diesel per unit of activity constant. For Nigel to agree.
A17: Agriculture
A18: Line | B18: Unit | C18: 2014 | D18: 2015 | E18: 2016 | F18: 2017 | G18: 2018 | H18: 2019 | I18: 2020 | J18: 2021 | K18: 2022 | L18: 2023 | M18: 2024 | N18: 2025 | O18: Source | P18: Note
A19: Agriculture, forestry and fishing real value added | B19: billion rand, 2015 prices | C19: 102.48769 | D19: 98.759569 | E19: 93.672105 | F19: 111.54508 | G19: 112.09493 | H19: 104.78476 | I19: 122.8701 | J19: 128.98309 | K19: 131.77064 | L19: 125.74664 | M19: 114.79164 | N19: 134.79675 | O19: Statistics South Africa, Gross domestic product (P0441) | P19: Published to 2025.
A20: Diesel per unit of activity | B20: million litres per billion rand | C20: ='DR01 demand by sector'!B13*1000/C19 | D20: ='DR01 demand by sector'!C13*1000/D19 | E20: ='DR01 demand by sector'!D13*1000/E19 | F20: ='DR01 demand by sector'!E13*1000/F19 | G20: ='DR01 demand by sector'!F13*1000/G19 | H20: ='DR01 demand by sector'!G13*1000/H19 | I20: ='DR01 demand by sector'!H13*1000/I19 | J20: ='DR01 demand by sector'!I13*1000/J19 | O20: Calculated: diesel on the demand by sector sheet over the activity above | P20: The balance's 2016 and 2017 figures are about double the other years and look like reclassification.
A21: Estimated diesel after 2021 | B21: billion litres | K21: =AVERAGE(G20:J20)*K19/1000 | L21: =AVERAGE(G20:J20)*L19/1000 | M21: =AVERAGE(G20:J20)*M19/1000 | N21: =AVERAGE(G20:J20)*N19/1000 | O21: Calculated: average diesel per unit of activity, 2018 to 2021, times that year's activity | P21: An estimate, not an observation and not an accepted model input. Holds diesel per unit of activity constant. For Nigel to agree.

Sheet DR04 routes and access
A1: DR04 Routes and access
A2: 66 facts from sources (blue), 6 calculated (white), 7 not available (yellow). Petrol and diesel only. Figures reported for several years are set out one column a year; every row names its source.
A5: Pipeline limit
A6: Item | B6: Asset or route | C6: Unit | D6: Basis | E6: 2021 | F6: 2022 | G6: 2023 | H6: 2024 | S6: Status | T6: Source | U6: Page | V6: Note
A7: Trunk line use | B7: Multi-product pipeline, Durban to Jameson Park | C7: million litres a week | D7: years to March | E7: 81 | F7: 91 | G7: 87 | H7: 97 | S7: From source | T7: Transnet Pipelines Report 2024, key performance indicators | U7: PDF p.5 | V7: About two thirds full in the year to March 2024: 97 a week is 5.0 billion litres a year. Not split by product. The target for the year to March 2025 was 104.
A8: Refined products moved, whole network | B8: All Transnet refined-product pipelines | C8: billion litres | D8: years to March | E8: 9 | F8: 9.79 | G8: 9.68 | H8: 9.51 | S8: From source | T8: Transnet Pipelines Report 2024, key performance indicators | U8: PDF p.5 | V8: Petrol and diesel grades on every Transnet line, including those fed by Natref and Secunda; jet fuel and crude are reported separately. Not the trunk line alone.
A9: Item | B9: Asset or route | C9: Unit | D9: Period | E9: Value | S9: Status | T9: Source | U9: Page | V9: Note
A10: Trunk line capacity | B10: Durban to Jameson Park, 24-inch multi-product line | C10: million litres a week | D10: as stated in 2020 | E10: 148 | S10: From source | T10: Transnet Pipelines 2020 report | U10: PDF p.3 | V10: Not confirmed as today's capacity; later phases and pump stations may have changed it.
A11: Trunk line capacity, annualised | B11: Durban to Jameson Park, 24-inch multi-product line | C11: billion litres a year | D11: as stated in 2020 | E11: 7.7 | S11: Calculated | T11: 148 million litres a week x 52 | U11: PDF p.3 | V11: Assumes every week at full rate; real annual capacity is lower.
A12: Trunk line capacity, latest statement | B12: Multi-product pipeline, Durban to Jameson Park | C12: million litres a week | D12: years to March 2021 to 2024, and the 2025 target | E12: 148 | S12: From source | T12: Transnet Pipelines Report 2024, key performance indicators | U12: PDF p.5 | V12: Unchanged from the 2020 figure: Transnet reports use against a capacity of 148 in every year. The latest report found is for the year to March 2024.
A13: Trunk line use, annualised | B13: Multi-product pipeline, Durban to Jameson Park | C13: billion litres a year | D13: year to March 2024 | E13: 5.04 | S13: Calculated | T13: 97 million litres a week x 52 | U13: PDF p.5 | V13: All refined products the line carried. Petrol and diesel are not reported separately.
A14: Inland accumulation facility | B14: Jameson Park, Gauteng (Transnet's TM2) | C14: million litres | D14: operational since December 2017 | E14: 180 | S14: From source | T14: Transnet Pipelines 2020 report | U14: PDF p.3 | V14: Working capacity by product not stated.
A15: Jameson Park and Transnet's storage sites out for proposal | B15: Jameson Park, Gauteng (Transnet's TM2) | D15: request for proposals, closes 4 December 2026 | E15: Not one of the five sites | S15: From source | T15: Transnet Pipelines, leasing opportunities: Kroonstad, Standerton, Magdala, Ladysmith and Bethlehem | V15: Transnet's own storage at Jameson Park is existing capacity beside Vopak Lesedi, which is connected to the same pipeline. Raised by Nigel on 9 October.
A16: Products carried on the trunk line | B16: Durban to Jameson Park | D16: as stated in 2020 | E16: Two diesel grades, two petrol grades, jet fuel | S16: From source | T16: Transnet Pipelines 2020 report | U16: PDF p.3
A17: Old Durban to Johannesburg pipeline | B17: Durban to Johannesburg (DJP) | D17: as stated in 2020 | E17: Being decommissioned; completion expected 2021 | S17: From source | T17: Transnet Pipelines 2020 report | U17: PDF p.3 | V17: Whether decommissioning is complete is not confirmed from a later source.
A18: Pipeline use as a share of capacity | B18: Transnet pipelines from Durban | C18: % | D18: as told to Parliament, 2026 | E18: About 70 | S18: From source | T18: Report of five Portfolio Committees on the Island View directive, 11 March 2026 (Parliament) | U18: section 3.1 | V18: The Minister of Transport's estimate, all products. New Island View leases are to require more use of the pipeline.
A20: Pipeline cost
A21: Item | B21: Asset or route | C21: Unit | D21: Basis | E21: 2023/24 | F21: 2024/25 | G21: 2025/26 | H21: 2026/27 | S21: Status | T21: Source | U21: Page | V21: Note
A22: Pipeline tariff, Durban to Alrode | B22: Durban to Alrode (Johannesburg) | C22: cents a litre | D22: financial years | E22: 61.74 | F22: 67.99 | S22: From source | T22: NERSA statement of 15 March 2024, as quoted by Engineering News | V22: Read from a news report quoting the regulator word for word; NERSA's own statement was not located. A 10.13% increase.
A23: Pipeline tariff, Durban to Alrode | B23: Durban to Alrode (Johannesburg) | C23: cents a litre | D23: financial years | G23: 73.22 | H23: 77.02 | S23: Calculated | T23: 67.99 plus the increases of 5.23 and 3.80 in NERSA's statement of 15 April 2025 | U23: p.1 | V23: Assumes the stated effect on the fuel price is the change in this tariff, as it was in 2024/25. To confirm in the reasons for decision.
A24: Item | B24: Asset or route | C24: Unit | D24: Period | E24: Value | S24: Status | T24: Source | U24: Page | V24: Note
A25: Effect of the tariff decision on the fuel price | B25: Durban to Johannesburg proxy | C25: cents a litre | D25: 2025/26; 2026/27 | E25: +5.23; +3.80 | S25: From source | T25: NERSA media statement, 15 April 2025 | U25: p.1 | V25: This is the change, not the tariff. The tariff by route is in the reasons for decision, not yet obtained.
A26: What the tariff covers | B26: Transnet's petroleum pipelines system | D26: decision of 27 February 2025 | E26: One set of tariffs for the whole licensed system; the department uses Durban to Alrode as its proxy for moving fuel from Durban to Johannesburg | S26: From source | T26: NERSA media statement, 15 April 2025 | U26: p.1 | V26: The statement does not say which products or which line each route tariff applies to; that is in the reasons for decision, not found online. Nigel to validate (call of 9 October).
A27: Tariff on routes other than Durban to Alrode | B27: Other inland routes | C27: cents a litre | D27: 2026/27 | E27: Not available | S27: Not available | T27: NERSA reasons for decision (not obtained) | V27: Needed to compare destinations other than Gauteng. NERSA's decisions pages were searched again on 9 October; the route table was not found online. Owner: Manish.
A29: Delivered cost
A30: Item | B30: Asset or route | C30: Unit | D30: Basis | E30: 2012 | F30: 2013 | G30: 2014 | H30: 2015 | I30: 2016 | J30: 2017 | K30: 2018 | L30: 2019 | M30: 2020 | N30: 2021 | O30: 2022 | P30: 2023 | Q30: 2024 | R30: 2025 | S30: Status | T30: Source | U30: Page | V30: Note
A31: Regulated transport cost to Gauteng in the diesel price | B31: Coast to Gauteng | C31: cents a litre | D31: year end | E31: 26.8 | F31: 28.9 | G31: 33.1 | H31: 35.3 | I31: 41 | J31: 41.5 | K31: 51.7 | L31: 57.4 | M31: 63.7 | N31: 64.9 | O31: 64.9 | P31: 75.7 | Q31: 75.7 | S31: From source | T31: Department of Mineral and Petroleum Resources, yearly price tables (levies, taxes and margins) | U31: Transport cost column | V31: The figure in the last month the department published for each year (April for 2024). It is reset each April. A regulated allowance, not a commercial rate. The April 2024 table shows 75.7 while the zone list of the same month shows 82.8.
A32: Regulated transport cost to Gauteng in the petrol price | B32: Coast to Gauteng | C32: cents a litre | D32: year end | E32: 26.8 | F32: 28.9 | G32: 28.9 | H32: 35.3 | I32: 41 | J32: 41.5 | K32: 51.7 | L32: 57.4 | M32: 63.7 | N32: 64.9 | O32: 67.9 | P32: 75.7 | Q32: 75.7 | S32: From source | T32: Department of Mineral and Petroleum Resources, yearly price tables (levies, taxes and margins) | U32: Transport cost column | V32: The figure in the last month the department published for each year (April for 2024). It is reset each April. A regulated allowance, not a commercial rate. The April 2024 table shows 75.7 while the zone list of the same month shows 82.8. The department's petrol table shows 28.9 throughout 2014, where its diesel table and zone list show 33.1 from April.
A33: Road freight income per tonne carried, all goods | B33: Road, South Africa | C33: rand a tonne | D33: calendar years | L33: 182 | Q33: 204 | R33: 205 | S33: Calculated | T33: Statistics South Africa, Land transport survey (P7162), July 2026 release | U33: series roadincf over roadpayl | V33: Income divided by payload. All goods and all distances together, so not a fuel rate or a route rate.
A34: Rail freight income per tonne carried, all goods | B34: Rail, South Africa | C34: rand a tonne | D34: calendar years | L34: 205 | Q34: 269 | R34: 272 | S34: Calculated | T34: Statistics South Africa, Land transport survey (P7162), July 2026 release | U34: series railincf over railpayl | V34: Income divided by payload. Mostly bulk minerals over long distances, so not a fuel rate.
A35: Item | B35: Asset or route | C35: Unit | D35: Basis | E35: 2024/25 | F35: 2025/26 | G35: 2026/27 | S35: Status | T35: Source | U35: Page | V35: Note
A36: Regulated transport differential less the pipeline tariff, Gauteng | B36: Coast to Gauteng | C36: cents a litre | D36: financial years | E36: 14.8 | F36: 13.9 | G36: 14.1 | S36: Calculated | T36: Gauteng differential (82.8, 87.1, 91.1) less the Durban to Alrode tariff (67.99, 73.22, 77.02) | V36: About 14 cents a litre in each year. What it pays for is not itemised in any document found: the department's working rules for the zone differentials were looked for on its site and in the price releases. The 2025 release shows the differentials are rebuilt from the pipeline tariff to each zone's supply point.
A37: Item | B37: Asset or route | C37: Unit | D37: Period | E37: Value | S37: Status | T37: Source | U37: Page | V37: Note
A38: Regulated price difference, inland less coast, diesel wholesale | B38: Gauteng less coast | C38: cents a litre | D38: July 2024 | E38: 79 | S38: From source | T38: Department of Mineral and Petroleum Resources, regulated fuel prices | V38: The regulated allowance for moving fuel inland, not an operator's actual cost. Coast series held ends November 2025.
A39: Regulated price difference, inland less coast, diesel wholesale | B39: Gauteng less coast | C39: cents a litre | D39: July 2025 | E39: 83.3 | S39: From source | T39: Department of Mineral and Petroleum Resources, regulated fuel prices | V39: The regulated allowance for moving fuel inland, not an operator's actual cost. Coast series held ends November 2025.
A40: Regulated price difference, inland less coast, diesel wholesale | B40: Gauteng less coast | C40: cents a litre | D40: November 2025 | E40: 83.3 | S40: From source | T40: Department of Mineral and Petroleum Resources, regulated fuel prices | V40: The regulated allowance for moving fuel inland, not an operator's actual cost. Coast series held ends November 2025.
A41: Regulated transport differential, Gauteng (zone 9C) | B41: Coast to Gauteng | C41: cents a litre | D41: April 2014 | E41: 33.1 | S41: From source | T41: Department zone lists (2014, 2024); Central Energy Fund price composition (2025, 2026) | U41: CEF p.3 | V41: The regulated allowance for getting petrol and diesel to Gauteng, which the regulator ties to the pipeline tariff. Not a commercial rate.
A42: Regulated transport differential, Gauteng (zone 9C) | B42: Coast to Gauteng | C42: cents a litre | D42: April 2024 | E42: 82.8 | S42: From source | T42: Department zone lists (2014, 2024); Central Energy Fund price composition (2025, 2026) | U42: CEF p.3 | V42: The regulated allowance for getting petrol and diesel to Gauteng, which the regulator ties to the pipeline tariff. Not a commercial rate.
A43: Regulated transport differential, Gauteng (zone 9C) | B43: Coast to Gauteng | C43: cents a litre | D43: June 2025 | E43: 87.1 | S43: From source | T43: Department zone lists (2014, 2024); Central Energy Fund price composition (2025, 2026) | U43: CEF p.3 | V43: The regulated allowance for getting petrol and diesel to Gauteng, which the regulator ties to the pipeline tariff. Not a commercial rate.
A44: Regulated transport differential, Gauteng (zone 9C) | B44: Coast to Gauteng | C44: cents a litre | D44: April 2026 | E44: 91.1 | S44: From source | T44: Department zone lists (2014, 2024); Central Energy Fund price composition (2025, 2026) | U44: CEF p.3 | V44: The regulated allowance for getting petrol and diesel to Gauteng, which the regulator ties to the pipeline tariff. Not a commercial rate.
A45: Regulated transport differential, all zones | B45: Coast to each of 54 pricing zones | C45: cents a litre | D45: April 2024 | E45: 3.8 to 179.6 | S45: From source | T45: Department diesel wholesale price list, effective 3 April 2024 | U45: pp.1-2 | V45: Lowest at the coast (zone 1A), highest in zone 17A. By zone on the DR04 transport cost sheet. The files do not say which mode serves each zone.
A46: Regulated secondary distribution (depot to service station by road) | B46: All zones | C46: cents a litre | D46: April 2024 | E46: 17.2 | S46: From source | T46: Department diesel margins (2024); Central Energy Fund price composition (2026) | U46: CEF p.3 | V46: The only regulated road delivery element. One national figure; it does not vary by distance.
A47: Regulated secondary distribution (depot to service station by road) | B47: All zones | C47: cents a litre | D47: April 2026 | E47: 19.1 | S47: From source | T47: Department diesel margins (2024); Central Energy Fund price composition (2026) | U47: CEF p.3 | V47: The only regulated road delivery element. One national figure; it does not vary by distance.
A48: Regulated secondary storage | B48: All zones | C48: cents a litre | D48: April 2024 | E48: 36.6 | S48: From source | T48: Department diesel margins (2024); Central Energy Fund price composition (2026) | U48: CEF p.3 | V48: The regulated allowance for depot storage, which is the service a terminal such as Lesedi sells. One national figure.
A49: Regulated secondary storage | B49: All zones | C49: cents a litre | D49: April 2026 | E49: 39 | S49: From source | T49: Department diesel margins (2024); Central Energy Fund price composition (2026) | U49: CEF p.3 | V49: The regulated allowance for depot storage, which is the service a terminal such as Lesedi sells. One national figure.
A50: Road against pipeline, as stated by a haulier | B50: Durban to Gauteng | D50: May 2025 | E50: Pipeline plus the last stretch by truck costs about a third more than trucking all the way | S50: From source | T50: Bloomberg, 12 May 2025, quoting the managing director of a fuel haulier | V50: One operator's statement, with no rate given. It implies road is competitive with the pipeline; it is not a measured cost.
A51: Road freight rate, as Transnet compares it | B51: Road, containers, average haul 507 km | C51: rand per net tonne-kilometre | D51: 2025 | E51: 1.23 | S51: From source | T51: Transnet Rail Infrastructure Manager, Tariff Proposal 2025/26 | U51: PDF p.18, Table 8 | V51: Containers, not fuel tankers. From a 2022 freight study Transnet commissioned, raised by inflation.
A52: Rail freight rate, as Transnet compares it | B52: Rail, containers, average haul 507 km | C52: rand per net tonne-kilometre | D52: 2025 | E52: 0.43 | S52: From source | T52: Transnet Rail Infrastructure Manager, Tariff Proposal 2025/26 | U52: PDF p.18, Table 8 | V52: Containers, not fuel. Road is 2.9 times rail on this comparison.
A53: Rail track access charge, grain and tankers | B53: Rail, any route | D53: 2024/25, approved | E53: 30 rand per train-kilometre plus 6.96 cents per gross tonne-kilometre | S53: From source | T53: Transnet Rail Infrastructure Manager, Tariff Proposal 2025/26 | U53: PDF p.12, Table 1 | V53: What a train operator pays Transnet for the track. Not the rate a shipper pays.
A54: Commercial road tanker rate, Durban to Gauteng | B54: Road | C54: cents a litre | E54: Not available | S54: Not available | T54: None public | V54: No fuel tanker rate is published. The rows above are the nearest published figures: a container rate and an all-goods average. Needs Vopak or a haulier quote.
A55: Rail rate, Durban to Gauteng | B55: Rail | C55: cents a litre | E55: Not available | S55: Not available | T55: None public | V55: Transnet does not publish a fuel rate. The rows above give its container rate and its track access charge for tankers. Needs Transnet or Vopak.
A56: Matched delivered cost, Durban to Gauteng, by mode | B56: Pipeline against road and rail | C56: cents a litre | E56: Not available | S56: Not available | T56: None published for road or rail | V56: Pipeline: 77.02 (tariff) or 91.1 (regulated allowance) in 2026/27. No fuel tanker or rail rate is published, so the modes cannot be set side by side. Looked in: Transnet's tariff proposal, Stats SA, NERSA, Parliament. Needs Vopak or a haulier.
A58: Port use
A59: Item | B59: Asset or route | C59: Unit | D59: Basis | E59: 2024 | F59: 2025 | S59: Status | T59: Source | U59: Page | V59: Note
A60: Petrol and diesel imports cleared | B60: Durban customs office | C60: billion litres | D60: calendar years | E60: 11.84 | F60: 13.16 | S60: From source | T60: SARS customs, by office | V60: Customs office of clearance: the nearest public record of entry port, not a berth or terminal record.
A61: Durban share of petrol and diesel imports | B61: Durban customs office | C61: % | D61: calendar years | E61: 80 | F61: 78.8 | S61: From source | T61: SARS customs, by office
A62: Petrol and diesel imports cleared | B62: Richards Bay customs office | C62: billion litres | D62: calendar years | E62: 0.39 | F62: 0.66 | S62: From source | T62: SARS customs, by office
A63: Petrol and diesel imports cleared | B63: Cape Town customs office | C63: billion litres | D63: calendar years | E63: 1.09 | F63: 1.52 | S63: From source | T63: SARS customs, by office
A64: Petrol and diesel imports by road from Mozambique | B64: Komatipoort customs office | C64: billion litres | D64: calendar years | E64: 0.19 | F64: 0.09 | S64: From source | T64: SARS customs, by office | V64: The only recorded entry from the Maputo and Matola side.
A66: Port limit
A67: Item | B67: Asset or route | C67: Unit | D67: Period | E67: Value | S67: Status | T67: Source | U67: Page | V67: Note
A68: Berths | B68: Durban | D68: as on the page, read 8 October 2026 | E68: 58 berths, 41 in operation, of which 8 liquid bulk | S68: From source | T68: Transnet National Ports Authority, Our Ports page | U68: Port of Durban, Fast Fact | V68: No capacity in kilolitres is given on the page.
A69: Berths | B69: Richards Bay | D69: as on the page, read 8 October 2026 | E69: 22 berths, of which 2 liquid bulk | S69: From source | T69: Transnet National Ports Authority, Our Ports page | U69: Port of Richards Bay, Fast Fact | V69: No capacity in kilolitres is given on the page.
A70: Planned berth change at Island View | B70: Durban, Island View, Berth 1 | D70: 2026, port framework plan 2022-2032 | E70: To be rebuilt | S70: From source | T70: Port authority tariff application slides, 2 September 2025 | U70: PDF p.14 | V70: Whether either is delivered is shown only by colour on the slide, which the text does not carry.
A71: Planned berth change at Island View | B71: Durban, Island View, Berth 3 | D71: 2026, port framework plan 2022-2032 | E71: To convert from dry bulk to liquid bulk | S71: From source | T71: Port authority tariff application slides, 2 September 2025 | U71: PDF p.14 | V71: Whether either is delivered is shown only by colour on the slide, which the text does not carry.
A72: Planned liquid bulk berth at Richards Bay | B72: Richards Bay, berth 210 | D72: 2025, port framework plan 2022-2032 | E72: New liquid bulk berth | S72: From source | T72: Port authority tariff application slides, 2 September 2025 | U72: PDF pp.11-12 | V72: Delivery status not readable from the text.
A73: Planned liquid bulk berth at Richards Bay | B73: Richards Bay, South Dunes | D73: 2024, port framework plan 2022-2032 | E73: Liquid bulk development | S73: From source | T73: Port authority tariff application slides, 2 September 2025 | U73: PDF pp.11-12 | V73: Delivery status not readable from the text.
A74: Berths at Island View | B74: Durban, Island View | D74: 2026 | E74: 10 berths, working 24 hours | S74: From source | T74: Report of five Portfolio Committees on the Island View directive, 11 March 2026 (Parliament) | U74: section 2.1 | V74: One berth also handles dry bulk. Product leaves the tanks by pipeline, road and rail.
A75: Terminal operator at Island View | B75: Bidvest Tank Terminal | D75: 2026 | E75: Lease holder; lease to be renewed for 25 years | S75: From source | T75: Report of five Portfolio Committees on the Island View directive, 11 March 2026 (Parliament) | U75: section 2.2 | V75: Not all store petrol and diesel.
A76: Terminal operator at Island View | B76: H&R | D76: 2026 | E76: Lease holder; lease to be renewed for 25 years | S76: From source | T76: Report of five Portfolio Committees on the Island View directive, 11 March 2026 (Parliament) | U76: section 2.2 | V76: Not all store petrol and diesel.
A77: Terminal operator at Island View | B77: Chemoleo | D77: 2026 | E77: Lease holder; lease to be renewed for 25 years | S77: From source | T77: Report of five Portfolio Committees on the Island View directive, 11 March 2026 (Parliament) | U77: section 2.2 | V77: Not all store petrol and diesel.
A78: Terminal operator at Island View | B78: Unico Tec | D78: 2026 | E78: Lease holder; lease to be renewed for 25 years | S78: From source | T78: Report of five Portfolio Committees on the Island View directive, 11 March 2026 (Parliament) | U78: section 2.2 | V78: Not all store petrol and diesel.
A79: Terminal operator at Island View | B79: Astron Energy | D79: 2026 | E79: Lease holder; lease to be renewed for 25 years | S79: From source | T79: Report of five Portfolio Committees on the Island View directive, 11 March 2026 (Parliament) | U79: section 2.2 | V79: Not all store petrol and diesel.
... A85: TotalEnergies' storage constraint | B85: Durban, Island View | D85: 2024 | E85: Could import only 78% of its fuel needs | S85: From source | T85: Report of five Portfolio Committees on the Island View directive, 11 March 2026 (Parliament) | U85: section 5 | V85: The operator's statement to Parliament: its Island View storage is too small and full cargoes cannot be offloaded into its site.
A86: Liquid bulk capacity and tankage | B86: Durban, Island View | C86: kilolitres a year; berths; m3 | E86: Not available | S86: Not available | T86: None found for petrol and diesel | V86: Parliament's report gives berths and tenants but no capacity. Earlier search summaries quoting 19.5 million kilolitres a year were not traced to a document. Needs the port authority or Vopak.
A88: Access
A89: Item | B89: Asset or route | C89: Unit | D89: Period | E89: Value | S89: Status | T89: Source | U89: Page | V89: Note
A90: Lesedi connection to the pipeline | B90: Vopak Lesedi, Jameson Park | D90: licence of 26 August 2020 | E90: Four pipelines to the Transnet system at Jameson Park; intake from the Transnet pipeline | S90: From source | T90: NERSA reasons for decision, Vopak licence amendment | U90: PDF p.6
A91: Lesedi dispatch | B91: Vopak Lesedi, Jameson Park | C91: road loading bays | D91: 2025 | E91: 8 | S91: From source | T91: NERSA reasons for decision, Vopak licence amendment | U91: PDF p.7 | V91: Dispatch is by road only; no rail or outbound pipeline is mentioned.
A92: Lesedi licensed capacity | B92: Vopak Lesedi, Jameson Park | C92: m3 | D92: 2020 | E92: 100000 | S92: From source | T92: NERSA reasons for decision, Vopak licence amendment | U92: PDF p.6 | V92: Design capacity. Six tanks (three diesel, three petrol) plus two diesel tanks.
A93: Lesedi licensed capacity | B93: Vopak Lesedi, Jameson Park | C93: m3 | D93: after the 2025 expansion | E93: 140000 | S93: From source | T93: NERSA reasons for decision, Vopak licence amendment | U93: PDF p.6 | V93: Design capacity. Six tanks (three diesel, three petrol) plus two diesel tanks.
A94: Who ships to Lesedi | B94: Durban to Jameson Park | D94: 2024/25 | E94: Lesedi's contracted customers are shippers on the Transnet pipeline from Durban, with one exception | S94: From source | T94: NERSA reasons for decision, Vopak licence amendment | U94: PDF p.9 | V94: Customer names are redacted.
A95: Durban terminal receipt | B95: Vopak Terminal Durban, Island View | D95: undated allocation mechanism | E95: By ship (own lines at jetties 1, 2 and 4; industry lines at berths 6, 7 and 8) and by pipeline transfer from neighbouring companies | S95: From source | T95: Vopak Terminal Durban allocation mechanism filed with NERSA | U95: p.5 | V95: The document is old: it gives 18,091 m3 of petroleum storage, far below today's. Berth access needs confirming with Vopak.
A96: Durban terminal dispatch | B96: Vopak Terminal Durban, Island View | D96: undated allocation mechanism | E96: Mainly road; also ship or barge loading and pipeline transfer | S96: From source | T96: Vopak Terminal Durban allocation mechanism filed with NERSA | U96: pp.4, 6 | V96: Whether Vopak Durban injects directly into the Transnet trunk line is not stated in this document.
A97: Notice period at Durban | B97: Vopak Terminal Durban, a vessel | D97: undated allocation mechanism | E97: Two weeks | S97: From source | T97: Vopak Terminal Durban allocation mechanism filed with NERSA | U97: p.3 | V97: Old document; confirm with Vopak.
A98: Notice period at Durban | B98: Vopak Terminal Durban, a pipeline transfer | D98: undated allocation mechanism | E98: One week | S98: From source | T98: Vopak Terminal Durban allocation mechanism filed with NERSA | U98: p.3 | V98: Old document; confirm with Vopak.
A99: Notice period at Durban | B99: Vopak Terminal Durban, road loading | D99: undated allocation mechanism | E99: Two days | S99: From source | T99: Vopak Terminal Durban allocation mechanism filed with NERSA | U99: p.3 | V99: Old document; confirm with Vopak.
A100: Direct injection into the pipeline from a Durban terminal | B100: Former Sapref site, Bayhead A, diesel | D100: licence amended 30 June 2025 | E100: Two 14-inch lines, 1,200 m, to Transnet's pipeline terminal | S100: From source | T100: NERSA decision on the Sapref Island View licence amendment, approved 30 June 2025 | U100: PDF pp.10, 19 | V100: A competing Durban terminal injects directly. Five lines were added to the licence for this.
A101: Direct injection into the pipeline from a Durban terminal | B101: Former Sapref site, Bayhead A, petrol | D101: licence amended 30 June 2025 | E101: Two 14-inch lines, 1,200 m, to Transnet's pipeline terminal | S101: From source | T101: NERSA decision on the Sapref Island View licence amendment, approved 30 June 2025 | U101: PDF pp.10, 19 | V101: A competing Durban terminal injects directly. Five lines were added to the licence for this.
A102: Direct injection into the pipeline from a Durban terminal | B102: Sasol, Berth 9 | D102: 2026 | E102: Imports are received at Berth 9 into throughput tanks and transferred into the pipeline | S102: From source | T102: Report of five Portfolio Committees on the Island View directive, 11 March 2026 (Parliament) | U102: section 5.2 | V102: Sasol's statement to Parliament.
A103: Vopak Durban and the pipeline | B103: Vopak Terminal Durban, Island View | D103: 2026 | E103: Works with Transnet Pipelines on evacuation by pipeline; describes Durban and Lesedi as functionally integrated | S103: From source | T103: Report of five Portfolio Committees on the Island View directive, 11 March 2026 (Parliament) | U103: section 5.7 | V103: Vopak's statement to Parliament. It does not say whether Vopak's own lines reach Transnet's intake or whether product moves through a neighbour. Needs Vopak.
A104: Island View leases | B104: All ten operators, Vopak included | D104: directive announced 18 September 2025 | E104: Minister of Transport directed the port authority to renew every lease for 25 years | S104: From source | T104: Report of five Portfolio Committees on the Island View directive, 11 March 2026 (Parliament) | U104: section 2.2 | V104: Operators must agree a framework for third-party access to storage. New conditions are to require more use of the pipeline.
A106: Competing routes
A107: Item | B107: Asset or route | C107: Unit | D107: Basis | E107: 2019 | F107: 2020 | G107: 2021 | H107: 2022 | I107: 2023 | J107: 2024 | K107: 2025 | S107: Status | T107: Source | U107: Page | V107: Note
A108: Diesel imported by road from Mozambique | B108: Maputo and Matola, through Komatipoort | C108: billion litres | D108: calendar years | E108: 0.21 | F108: 0.21 | G108: 0.2 | H108: 0.27 | I108: 0.25 | J108: 0.19 | K108: 0.08 | S108: From source | T108: SARS customs, by office | V108: Falling since 2022. Diesel and petrol together were 0.5% of petrol and diesel imports in 2025.
A109: Petrol imported by road from Mozambique | B109: Maputo and Matola, through Komatipoort | C109: billion litres | D109: calendar years | E109: 0.039 | F109: 0.031 | G109: 0.039 | H109: 0.029 | I109: 0 | J109: 0.001 | K109: 0.004 | S109: From source | T109: SARS customs, by office | V109: Small and almost nil since 2023.
A110: Item | B110: Asset or route | C110: Unit | D110: Period | E110: Value | S110: Status | T110: Source | U110: Page | V110: Note
A111: Petrol and diesel imported through Namibian and Botswanan border posts | B111: Walvis Bay and the Trans-Kalahari road | C111: billion litres | D111: 2019-2025 | E111: 0.00 in every year | S111: From source | T111: SARS customs, by office | V111: Nakop (Narogas), Kopfontein, Skilpadshek, Groblersbrug and Ramatlabama record none. The route is not used for supply into South Africa.
A112: Diesel and petrol storage planned at Walvis Bay | B112: diesel | C112: million litres | D112: as planned; news item undated | E112: 45 | S112: From source | T112: Namibian Ports Authority news item | V112: Of 75 million litres in all; the rest is fuel oil and aviation fuel. Built for Namibia's own supply. Current operating capacity not confirmed.
A113: Diesel and petrol storage planned at Walvis Bay | B113: petrol | C113: million litres | D113: as planned; news item undated | E113: 20 | S113: From source | T113: Namibian Ports Authority news item | V113: Of 75 million litres in all; the rest is fuel oil and aviation fuel. Built for Namibia's own supply. Current operating capacity not confirmed.
...

Sheet DR04 entry points
A1: DR04 Where petrol and diesel imports enter
A2: Billion litres, calendar years. Petrol and diesel only. The office is where the fuel was cleared through customs: the nearest public record of the entry point, not a berth or terminal record.
A4: Entry point | B4: Route | C4: 2014 | D4: 2015 | E4: 2016 | F4: 2017 | G4: 2018 | H4: 2019 | I4: 2020 | J4: 2021 | K4: 2022 | L4: 2023 | M4: 2024 | N4: 2025 | O4: Source | P4: Note
A5: Diesel
A6: Durban | B6: Sea | C6: 3.4012934 | D6: 4.0427003 | E6: 3.441357 | F6: 4.8765373 | G6: 3.9859041 | H6: 3.8091433 | I6: 3.8259377 | J6: 5.8348732 | K6: 7.881248 | L6: 9.1250365 | M6: 8.0328899 | N6: 8.9315354 | O6: SARS customs, imports by office of clearance (fuel_trade_sars_by_office.csv) | P6: Includes fuel for the inland pipeline and for the coast.
A7: Cape Town | B7: Sea | C7: 0.56348507 | D7: 0.99664213 | E7: 0.21495197 | F7: 0.39464311 | G7: 0.51313339 | H7: 0.60156129 | I7: 1.8427224 | J7: 2.3507153 | K7: 2.485097 | L7: 1.3875841 | M7: 0.95747643 | N7: 1.3353922 | O7: SARS customs, imports by office of clearance (fuel_trade_sars_by_office.csv)
A8: Mossel Bay | B8: Sea | C8: 0.77085345 | D8: 0.95190812 | E8: 0.39227171 | F8: 0.29025052 | G8: 0.13823706 | H8: 0.71375255 | I8: 0.40019393 | J8: 0.67467583 | K8: 0.56689835 | L8: 1.0931506 | M8: 0.57338465 | N8: 0.5217978 | O8: SARS customs, imports by office of clearance (fuel_trade_sars_by_office.csv)
A9: East London | B9: Sea | C9: 0.059488792 | D9: 0.10177181 | E9: 0.07380239 | F9: 0.083400489 | G9: 0.066186531 | H9: 0.073540293 | I9: 0.19997504 | J9: 0.20686197 | K9: 0.18968079 | L9: 0.35138882 | M9: 0.51376771 | N9: 0.40330738 | O9: SARS customs, imports by office of clearance (fuel_trade_sars_by_office.csv)
A10: Port Elizabeth | B10: Sea | C10: 0.045097549 | D10: 0.095793462 | E10: 0.06197985 | F10: 0.05229008 | G10: 0.099219997 | H10: 0.085687549 | I10: 0.19170736 | J10: 0.2561779 | K10: 0.22513035 | L10: 0.33666737 | M10: 0.13769844 | N10: 0.31335745 | O10: SARS customs, imports by office of clearance (fuel_trade_sars_by_office.csv)
A11: Richards Bay | B11: Sea | C11: 0 | D11: 0 | E11: 0 | F11: 0.10571482 | G11: 0.091830959 | H11: 0.093812929 | I11: 0.14679285 | J11: 0.23403682 | K11: 0.33131979 | L11: 0.3207667 | M11: 0.39078248 | N11: 0.6579146 | O11: SARS customs, imports by office of clearance (fuel_trade_sars_by_office.csv)
A12: Komatipoort | B12: Road, from Mozambique | C12: 0.1510623 | D12: 0.257288 | E12: 0.23679602 | F12: 0.23388003 | G12: 0.22802977 | H12: 0.2127269 | I12: 0.20753876 | J12: 0.20133574 | K12: 0.27415852 | L12: 0.25457084 | M12: 0.18582006 | N12: 0.082022506 | O12: SARS customs, imports by office of clearance (fuel_trade_sars_by_office.csv) | P12: The only recorded entry from the Maputo and Matola side.
A13: Other offices | B13: Land borders and inland offices | C13: 0.00043176669 | D13: 0.0046752559 | E13: 0.0031359737 | F13: 0.00074357618 | G13: 0.00041767239 | H13: 4.726407e-05 | I13: 0.00011745485 | J13: 0.0027185497 | K13: 0.000723718 | L13: 0.00086713425 | M13: 0.00072742656 | N13: 0.0033929065 | O13: SARS customs, imports by office of clearance (fuel_trade_sars_by_office.csv)
A14: All offices | C14: =SUM(C6:C13) | D14: =SUM(D6:D13) | E14: =SUM(E6:E13) | F14: =SUM(F6:F13) | G14: =SUM(G6:G13) | H14: =SUM(H6:H13) | I14: =SUM(I6:I13) | J14: =SUM(J6:J13) | ... N14: =SUM(N6:N13) | O14: Sum of the rows above; equals SARS national imports on the History sheet
A15: Durban share | C15: =IF(C14=0,"",C6/C14) | D15: =IF(D14=0,"",D6/D14) | E15: =IF(E14=0,"",E6/E14) | F15: =IF(F14=0,"",F6/F14) | G15: =IF(G14=0,"",G6/G14) | H15: =IF(H14=0,"",H6/H14) | I15: =IF(I14=0,"",I6/I14) | J15: =IF(J14=0,"",J6/J14) | ... N15: =IF(N14=0,"",N6/N14) | O15: Calculated: Durban over all offices
A17: Petrol
A18: Durban | B18: Sea | C18: 0.85247094 | D18: 1.4425428 | E18: 1.13647 | F18: 1.7292857 | G18: 1.5364388 | H18: 1.2563484 | I18: 0.66409273 | J18: 2.4365647 | K18: 3.8826694 | L18: 4.1655992 | M18: 3.8047252 | N18: 4.2289797 | O18: SARS customs, imports by office of clearance (fuel_trade_sars_by_office.csv) | P18: Includes fuel for the inland pipeline and for the coast.
A19: Cape Town | B19: Sea | C19: 0.18750103 | D19: 0.26259419 | E19: 0.058894374 | F19: 0.21050907 | G19: 0.18265634 | H19: 0.11619286 | I19: 1.0027419 | J19: 1.4319451 | K19: 1.5003409 | L19: 0.23304926 | M19: 0.131091 | N19: 0.18559754 | O19: SARS customs, imports by office of clearance (fuel_trade_sars_by_office.csv)
A20: Mossel Bay | B20: Sea | C20: 0 | D20: 0 | E20: 0.010228015 | F20: 0 | G20: 0 | H20: 0.046954148 | I20: 0 | J20: 0.099757575 | K20: 0.034555764 | L20: 0.068691824 | M20: 0.049694999 | N20: 0 | O20: SARS customs, imports by office of clearance (fuel_trade_sars_by_office.csv)
A21: East London | B21: Sea | C21: 0.069111017 | D21: 0.10173686 | E21: 0.083706491 | F21: 0.069640116 | G21: 0.018334526 | H21: 0 | I21: 0.0118587 | J21: 0 | K21: 0.005168638 | L21: 0.008596477 | M21: 0.013139503 | N21: 0.031405816 | O21: SARS customs, imports by office of clearance (fuel_trade_sars_by_office.csv)
A22: Port Elizabeth | B22: Sea | C22: 0.041048641 | D22: 0.062738178 | E22: 0.070599366 | F22: 0.019982608 | G22: 0.014892632 | H22: 0.0010843011 | I22: 0.00077485668 | J22: 0.00078124021 | K22: 0.0037131559 | L22: 0.0067097924 | M22: 0.0011940559 | N22: 0.0030697401 | O22: SARS customs, imports by office of clearance (fuel_trade_sars_by_office.csv)
A23: Richards Bay | B23: Sea | C23: 0 | D23: 0 | E23: 0 | F23: 0.038417234 | G23: 0.03354092 | H23: 0.018129952 | I23: 0.009266228 | J23: 0 | K23: 0 | L23: 0 | M23: 0 | N23: 0 | O23: SARS customs, imports by office of clearance (fuel_trade_sars_by_office.csv)
A24: Komatipoort | B24: Road, from Mozambique | C24: 0 | D24: 0 | E24: 0.034672613 | F24: 0.046040565 | G24: 0.04390319 | H24: 0.038667509 | I24: 0.030842959 | J24: 0.039454367 | K24: 0.028805741 | L24: 0.000125422 | M24: 0.001009567 | N24: 0.004416485 | O24: SARS customs, imports by office of clearance (fuel_trade_sars_by_office.csv) | P24: The only recorded entry from the Maputo and Matola side.
A25: Other offices | B25: Land borders and inland offices | C25: 6.319224e-05 | D25: 3.317238e-05 | E25: 0.0010675928 | F25: 0.0002811756 | G25: 4.86485e-06 | H25: 8.68e-06 | I25: 9.5671e-05 | J25: 0.00010978057 | K25: 8.26079e-06 | L25: 2.756e-06 | M25: 8.455e-08 | N25: 1.854e-06 | O25: SARS customs, imports by office of clearance (fuel_trade_sars_by_office.csv)
A26: All offices | C26: =SUM(C18:C25) | D26: =SUM(D18:D25) | E26: =SUM(E18:E25) | F26: =SUM(F18:F25) | G26: =SUM(G18:G25) | H26: =SUM(H18:H25) | I26: =SUM(I18:I25) | J26: =SUM(J18:J25) | ... N26: =SUM(N18:N25) | O26: Sum of the rows above; equals SARS national imports on the History sheet
A27: Durban share | C27: =IF(C26=0,"",C18/C26) | D27: =IF(D26=0,"",D18/D26) | E27: =IF(E26=0,"",E18/E26) | F27: =IF(F26=0,"",F18/F26) | G27: =IF(G26=0,"",G18/G26) | H27: =IF(H26=0,"",H18/H26) | I27: =IF(I26=0,"",I18/I26) | J27: =IF(J26=0,"",J18/J26) | ... N27: =IF(N26=0,"",N18/N26) | O27: Calculated: Durban over all offices
A29: Diesel and petrol
A30: Durban | B30: Sea | C30: 4.2537643 | D30: 5.4852431 | E30: 4.5778271 | F30: 6.605823 | G30: 5.5223429 | H30: 5.0654917 | I30: 4.4900304 | J30: 8.2714379 | K30: 11.763917 | L30: 13.290636 | M30: 11.837615 | N30: 13.160515 | O30: SARS customs, imports by office of clearance (fuel_trade_sars_by_office.csv) | P30: Includes fuel for the inland pipeline and for the coast.
A31: Cape Town | B31: Sea | C31: 0.7509861 | D31: 1.2592363 | E31: 0.27384635 | F31: 0.60515219 | G31: 0.69578973 | H31: 0.71775415 | I31: 2.8454643 | J31: 3.7826604 | K31: 3.9854379 | L31: 1.6206334 | M31: 1.0885674 | N31: 1.5209897 | O31: SARS customs, imports by office of clearance (fuel_trade_sars_by_office.csv)
A32: Mossel Bay | B32: Sea | C32: 0.77085345 | D32: 0.95190812 | E32: 0.40249973 | F32: 0.29025052 | G32: 0.13823706 | H32: 0.7607067 | I32: 0.40019393 | J32: 0.7744334 | K32: 0.60145411 | L32: 1.1618424 | M32: 0.62307965 | N32: 0.5217978 | O32: SARS customs, imports by office of clearance (fuel_trade_sars_by_office.csv)
A33: East London | B33: Sea | C33: 0.12859981 | D33: 0.20350867 | E33: 0.15750888 | F33: 0.15304061 | G33: 0.084521057 | H33: 0.073540293 | I33: 0.21183374 | J33: 0.20686197 | K33: 0.19484943 | L33: 0.3599853 | M33: 0.52690721 | N33: 0.43471319 | O33: SARS customs, imports by office of clearance (fuel_trade_sars_by_office.csv)
A34: Port Elizabeth | B34: Sea | C34: 0.08614619 | D34: 0.15853164 | E34: 0.13257922 | F34: 0.072272688 | G34: 0.11411263 | H34: 0.08677185 | I34: 0.19248222 | J34: 0.25695914 | K34: 0.2288435 | L34: 0.34337717 | M34: 0.1388925 | N34: 0.31642719 | O34: SARS customs, imports by office of clearance (fuel_trade_sars_by_office.csv)
A35: Richards Bay | B35: Sea | C35: 0 | D35: 0 | E35: 0 | F35: 0.14413206 | G35: 0.12537188 | H35: 0.11194288 | I35: 0.15605907 | J35: 0.23403682 | K35: 0.33131979 | L35: 0.3207667 | M35: 0.39078248 | N35: 0.6579146 | O35: SARS customs, imports by office of clearance (fuel_trade_sars_by_office.csv)
A36: Komatipoort | B36: Road, from Mozambique | C36: 0.1510623 | D36: 0.257288 | E36: 0.27146864 | F36: 0.2799206 | G36: 0.27193296 | H36: 0.25139441 | I36: 0.23838172 | J36: 0.24079011 | K36: 0.30296427 | L36: 0.25469626 | M36: 0.18682963 | N36: 0.086438991 | O36: SARS customs, imports by office of clearance (fuel_trade_sars_by_office.csv) | P36: The only recorded entry from the Maputo and Matola side.
A37: Other offices | B37: Land borders and inland offices | C37: 0.00049495893 | D37: 0.0047084283 | E37: 0.0042035665 | F37: 0.0010247518 | G37: 0.00042253724 | H37: 5.594407e-05 | I37: 0.00021312585 | J37: 0.0028283303 | K37: 0.00073197879 | L37: 0.00086989025 | M37: 0.00072751111 | N37: 0.0033947605 | O37: SARS customs, imports by office of clearance (fuel_trade_sars_by_office.csv)
A38: All offices | C38: =SUM(C30:C37) | D38: =SUM(D30:D37) | E38: =SUM(E30:E37) | F38: =SUM(F30:F37) | G38: =SUM(G30:G37) | H38: =SUM(H30:H37) | I38: =SUM(I30:I37) | J38: =SUM(J30:J37) | ... N38: =SUM(N30:N37) | O38: Sum of the rows above; equals SARS national imports on the History sheet
A39: Durban share | C39: =IF(C38=0,"",C30/C38) | D39: =IF(D38=0,"",D30/D38) | E39: =IF(E38=0,"",E30/E38) | F39: =IF(F38=0,"",F30/F38) | G39: =IF(G38=0,"",G30/G38) | H39: =IF(H38=0,"",H30/H38) | I39: =IF(I38=0,"",I30/I38) | J39: =IF(J38=0,"",J30/J38) | ... N39: =IF(N38=0,"",N30/N38) | O39: Calculated: Durban over all offices

Sheet DR04 transport cost
A1: DR04 Regulated cost of moving petrol and diesel
A2: Cents a litre. These are regulated allowances in the fuel price, set by the department and the energy regulator. They are not what a haulier or Transnet charges a shipper: commercial road and rail rates are not published.
A4: Durban to Gauteng, by element
A5: Element | B5: 2024/25 | C5: 2025/26 | D5: 2026/27 | E5: Basis | H5: Source
A6: Pipeline tariff, Durban to Alrode | B6: 67.99 | C6: 73.22 | D6: 77.02 | E6: 2024/25 as reported; later years calculated by adding NERSA's stated increases | H6: NERSA statements of 15 March 2024 (as quoted by Engineering News) and 15 April 2025
A7: Regulated transport differential, Gauteng (zone 9C) | B7: 82.8 | D7: 91.1 | E7: Regulated allowance in the petrol and diesel price for transport from the coast | H7: Department zone list, April 2024; Central Energy Fund price composition, 1 April 2026
A8: Regulated secondary storage | B8: 36.6 | D8: 39 | E8: Regulated allowance for depot storage; one national figure | H8: Department diesel margins, 2024; Central Energy Fund price composition, 1 April 2026
A9: Regulated secondary distribution | B9: 17.2 | D9: 19.1 | E9: Regulated allowance for road delivery from depot to service station; one national figure | H9: Department diesel margins, 2024; Central Energy Fund price composition, 1 April 2026
A10: Commercial road tanker rate, Durban to Gauteng | E10: Not published | H10: None found; needs Vopak or a haulier
A11: Rail rate, Durban to Gauteng | E11: Not published | H11: None found; needs Transnet or Vopak
A13: Regulated transport differential by pricing zone (the same for petrol and diesel in 2014; diesel list for 2024)
A14: Zone | B14: Provinces | C14: Districts | D14: Examples | E14: 2014 | F14: 2024 | G14: Change | H14: Source
A15: 9C (Gauteng) | B15: Gauteng, Mpumalanga, Free State, North West | C15: 51 | D15: Alberton, Bafokeng, Balfour, Benoni, Bethal, Boksburg | E15: 33.1 | F15: 82.8 | G15: =IF(COUNT(E15,F15)<2,"",F15-E15) | H15: Department of Mineral and Petroleum Resources, zone lists effective 2 April 2014 and 3 April 2024
A16: 57C | B16: Mpumalanga, KwaZulu Natal | C16: 3 | D16: Paulpietersburg, Utrecht, Volksrust | E16: 30.5 | F16: 75.7 | G16: =IF(COUNT(E16,F16)<2,"",F16-E16) | H16: Department of Mineral and Petroleum Resources, zone lists effective 2 April 2014 and 3 April 2024
A17: 58C | B17: Mpumalanga, KwaZulu Natal | C17: 3 | D17: Piet Retief, Simdlangentsha, Wakkerstroom | E17: 35.4 | F17: 93.1 | G17: =IF(COUNT(E17,F17)<2,"",F17-E17) | H17: Department of Mineral and Petroleum Resources, zone lists effective 2 April 2014 and 3 April 2024
A18: 8C | B18: Mpumalanga, Free State | C18: 14 | D18: Amersfoort, Clocolan, Ermelo, Ficksburg, Frankfort, Heilbron | E18: 35.4 | F18: 93.1 | G18: =IF(COUNT(E18,F18)<2,"",F18-E18) | H18: Department of Mineral and Petroleum Resources, zone lists effective 2 April 2014 and 3 April 2024
A19: 10C | B19: Mpumalanga, Free State, North West, Limpopo | C19: 28 | D19: Bela-Bela (Warmbad), Belfast, Bloemhof, Brandfort, Bultfontein, Carolina | E19: 44.3 | F19: 104 | G19: =IF(COUNT(E19,F19)<2,"",F19-E19) | H19: Department of Mineral and Petroleum Resources, zone lists effective 2 April 2014 and 3 April 2024
A20: 61C | B20: Mpumalanga, Limpopo | C20: 8 | D20: Barberton, Mapulaneng, Mhala, Nelspruit, Nkomazi (Kamhulshwa), Nsikazi (Kangwane) | E20: 59.2 | F20: 128 | G20: =IF(COUNT(E20,F20)<2,"",F20-E20) | H20: Department of Mineral and Petroleum Resources, zone lists effective 2 April 2014 and 3 April 2024
A21: 6C | B21: Free State, KwaZulu Natal | C21: 8 | D21: Bergville, Dannhauser, Dundee, Glencoe, Harrismith, Newcastle | E21: 24.2 | F21: 59.1 | G21: =IF(COUNT(E21,F21)<2,"",F21-E21) | H21: Department of Mineral and Petroleum Resources, zone lists effective 2 April 2014 and 3 April 2024
A22: 7C | B22: Free State | C22: 3 | D22: Bethlehem, Fouriesburg, Witsieshoek | E22: 30.5 | F22: 75.7 | G22: =IF(COUNT(E22,F22)<2,"",F22-E22) | H22: Department of Mineral and Petroleum Resources, zone lists effective 2 April 2014 and 3 April 2024
A23: 8A | B23: Free State, Eastern Cape, Northern Cape | C23: 20 | D23: Barkly East, Bethulie, Colesberg, De Aar, Edenburg, Elliot | E23: 55.2 | F23: 87.6 | G23: =IF(COUNT(E23,F23)<2,"",F23-E23) | H23: Department of Mineral and Petroleum Resources, zone lists effective 2 April 2014 and 3 April 2024
A24: 9A | B24: Free State, Northern Cape | C24: 6 | D24: Britstown, Fauresmith, Hopetown, Koffiefontein, Philipstown, Prieska | E24: 72.1 | F24: 114.4 | G24: =IF(COUNT(E24,F24)<2,"",F24-E24) | H24: Department of Mineral and Petroleum Resources, zone lists effective 2 April 2014 and 3 April 2024
A25: 11C | B25: Free State, North West, Limpopo, Northern Cape | C25: 23 | D25: Barkly West, Bloemfontein, Boshof, Botshabelo, Delareyville, Dewetsdorp | E25: 59.2 | F25: 128 | G25: =IF(COUNT(E25,F25)<2,"",F25-E25) | H25: Department of Mineral and Petroleum Resources, zone lists effective 2 April 2014 and 3 April 2024
A26: 12C | B26: North West, Limpopo | C26: 6 | D26: Ditsobotla, Polokwane (Pietersburg) (south of tropic of capricorn), Seshego, Thabamoopo, Thabazimbi (east of 27o longitude), Vryburg (south of 26o30' latitude) | E26: 65 | F26: 132.8 | G26: =IF(COUNT(E26,F26)<2,"",F26-E26) | H26: Department of Mineral and Petroleum Resources, zone lists effective 2 April 2014 and 3 April 2024
... A66: 17A | B66: Northern Cape | C66: 1 | D66: Gordonia Central (between 27o30' and 28o latituded) | E66: 99.8 | F66: 179.6 | G66: =IF(COUNT(E66,F66)<2,"",F66-E66) | H66: Department of Mineral and Petroleum Resources, zone lists effective 2 April 2014 and 3 April 2024
A67: 60C | B67: Not in the 2014 district list | E67: 44.3 | F67: 104 | G67: =IF(COUNT(E67,F67)<2,"",F67-E67) | H67: Department of Mineral and Petroleum Resources, zone lists effective 2 April 2014 and 3 April 2024
A68: 10A | B68: Not in the 2014 district list | E68: 82.6 | F68: 121.5 | G68: =IF(COUNT(E68,F68)<2,"",F68-E68) | H68: Department of Mineral and Petroleum Resources, zone lists effective 2 April 2014 and 3 April 2024

Sheet DR07 demand evidence
A1: DR07 Demand evidence
A2: 75 facts from sources (blue), 21 calculated (white), 5 not available (yellow). Petrol and diesel only. Figures reported for several years are set out one column a year; every row names its source.
A5: Power generation
A6: Item | B6: Covers | C6: Unit | D6: Basis | E6: 2016 | F6: 2017 | G6: 2018 | H6: 2019 | I6: 2020 | J6: 2021 | K6: 2022 | L6: 2023 | M6: 2024 | N6: 2025 | O6: 2026 | P6: Status | Q6: Source | R6: Page | S6: Note
A7: Fuel burned at Eskom's turbines, as reported | B7: Eskom: Ankerlig, Gourikwa, Acacia, Port Rex | C7: million litres | D7: years to March | E7: 1247.8 | F7: 10 | G7: 37.8 | H7: 385 | I7: 426.2 | J7: 458.7 | K7: 580.4 | L7: 937.5 | M7: 1129.5 | N7: 679.1 | P7: From source | Q7: Eskom Integrated Report 2025, technical statistics | R7: PDF p.141 | S7: Eskom reports diesel and kerosene together. Acacia and Port Rex burn kerosene and are 342 MW of Eskom's 2,426 MW, so nearly all of it is diesel. 2026 is not yet reported.
A8: Electricity generated at Eskom's turbines | B8: Eskom | C8: GWh | D8: years to March | K8: 1826 | L8: 3018 | M8: 3634 | N8: 2176 | O8: 811 | P8: From source | Q8: Eskom data portal and reports
A9: Litres burned per kWh, implied | B9: Eskom | C9: litres per kWh | D9: years to March | K9: 0.318 | L9: 0.311 | M9: 0.311 | N9: 0.312 | P9: Calculated | Q9: Reported fuel divided by reported generation | S9: Confirms the 0.31 litres per kWh used on the Power fleet sheet.
A10: Electricity generated at independent diesel plants | B10: Avon and Dedisa | C10: GWh | D10: years to March | L10: 1098 | M10: 1509 | N10: 662 | O10: 268 | P10: From source | Q10: Eskom data portal and reports
A11: Diesel burned at independent plants, estimated | B11: Avon and Dedisa | C11: million litres | D11: years to March | L11: 340 | M11: 468 | N11: 205 | O11: 83 | P11: Calculated | Q11: Generation x 0.31 litres per kWh | S11: The producers do not report litres. Uses Eskom's implied rate.
A12: Electricity not supplied through load-shedding | B12: Electricity not supplied through load-shedding | C12: TWh | D12: calendar years | L12: 10.6 | M12: 2.5 | P12: From source | Q12: CSIR, Utility-scale power generation statistics in South Africa 2024 | R12: PDF p.4 | S12: An upper limit: each stage is counted as its full megawatts for the full hour.
A13: Item | B13: Covers | C13: Unit | D13: Period | E13: Value | P13: Status | Q13: Source | R13: Page | S13: Note
A14: Diesel burned in private backup generators | B14: Businesses and households | C14: million litres | E14: Not available | P14: Not available | Q14: None found | S14: No source measures it: checked the Reserve Bank, the CSIR, Eskom and the system operator. It is inside recorded diesel sales and cannot be separated.
A15: Diesel stations and capacity | B15: Ankerlig | C15: MW | D15: current | E15: 1338 | P15: From source | Q15: Eskom fact sheet GX 0001 (July 2024); African Energy (2015) | S15: Avon began in July 2016 and Dedisa in October 2015.
A16: Diesel stations and capacity | B16: Gourikwa | C16: MW | D16: current | E16: 746 | P16: From source | Q16: Eskom fact sheet GX 0001 (July 2024); African Energy (2015) | S16: Avon began in July 2016 and Dedisa in October 2015.
A17: Diesel stations and capacity | B17: Avon | C17: MW | D17: current | E17: 670 | P17: From source | Q17: Eskom fact sheet GX 0001 (July 2024); African Energy (2015) | S17: Avon began in July 2016 and Dedisa in October 2015.
A18: Diesel stations and capacity | B18: Dedisa | C18: MW | D18: current | E18: 335 | P18: From source | Q18: Eskom fact sheet GX 0001 (July 2024); African Energy (2015) | S18: Avon began in July 2016 and Dedisa in October 2015.
A19: Coal station shutdown | B19: Komati | D19: October 2022 | E19: Shut down | P19: From source | Q19: Eskom, coal-fired power stations page | S19: The last unit, unit 9.
A20: Coal station shutdown | B20: Camden | D20: by 31 March 2030 | E20: Scheduled to shut down | P20: From source | Q20: Eskom Integrated Report 2025; system operator outlook | R20: Eskom PDF pp.32, 44; outlook PDF pp.17, 19 | S20: Eskom: the four older stations 'will now continue operating until FY2030'. System operator: all five run to the end of 2028, then shut in phases from 2029.
A21: Coal station shutdown | B21: Hendrina | D21: by 31 March 2030 | E21: Scheduled to shut down | P21: From source | Q21: Eskom Integrated Report 2025; system operator outlook | R21: Eskom PDF pp.32, 44; outlook PDF pp.17, 19 | S21: Eskom: the four older stations 'will now continue operating until FY2030'. System operator: all five run to the end of 2028, then shut in phases from 2029.
A22: Coal station shutdown | B22: Grootvlei | D22: by 31 March 2030 | E22: Scheduled to shut down | P22: From source | Q22: Eskom Integrated Report 2025; system operator outlook | R22: Eskom PDF pp.32, 44; outlook PDF pp.17, 19 | S22: Eskom: the four older stations 'will now continue operating until FY2030'. System operator: all five run to the end of 2028, then shut in phases from 2029.
A23: Coal station shutdown | B23: Arnot | D23: by 31 March 2030 | E23: Scheduled to shut down | P23: From source | Q23: Eskom Integrated Report 2025; system operator outlook | R23: Eskom PDF pp.32, 44; outlook PDF pp.17, 19 | S23: Eskom: the four older stations 'will now continue operating until FY2030'. System operator: all five run to the end of 2028, then shut in phases from 2029.
A24: Coal station shutdown | B24: Kriel | D24: by 31 March 2030 | E24: Scheduled to shut down | P24: From source | Q24: Eskom Integrated Report 2025; system operator outlook | R24: Eskom PDF pp.32, 44; outlook PDF pp.17, 19 | S24: Eskom: the four older stations 'will now continue operating until FY2030'. System operator: all five run to the end of 2028, then shut in phases from 2029.
A25: Coal station shutdown | B25: Duvha | D25: February 2034 | E25: Planned shutdown | P25: From source | Q25: System operator, Medium-Term System Adequacy Outlook 2026-2030 (30 October 2025) | R25: PDF p.19 | S25: Its emissions exemption runs to this date.
A26: Coal station shutdown | B26: Matla | D26: July 2034 | E26: Planned shutdown | P26: From source | Q26: System operator, Medium-Term System Adequacy Outlook 2026-2030 (30 October 2025) | R26: PDF p.19 | S26: Its emissions exemption runs to this date.
A27: Coal station shutdown | B27: Tutuka | D27: by 2030 | E27: Scheduled for closure under Eskom's Generation 2035 plan | P27: From source | Q27: Eskom, coal-fired power stations page | S27: The system operator's outlook does not count Tutuka among the stations shutting by 2030, so this may be an older plan.
A28: Coal station shutdown | B28: Kendal | D28: no shutdown date given | E28: Emissions exemption to 31 March 2030 | P28: From source | Q28: System operator, Medium-Term System Adequacy Outlook 2026-2030 (30 October 2025) | R28: PDF p.19 | S28: An exemption, not a shutdown date. Eskom may apply for more.
A29: Coal station shutdown | B29: Lethabo | D29: no shutdown date given | E29: Emissions exemption to 31 March 2030 | P29: From source | Q29: System operator, Medium-Term System Adequacy Outlook 2026-2030 (30 October 2025) | R29: PDF p.19 | S29: An exemption, not a shutdown date. Eskom may apply for more.
A30: Coal station shutdown | B30: Majuba | D30: no shutdown date given | E30: Emissions exemption to 31 March 2030 | P30: From source | Q30: System operator, Medium-Term System Adequacy Outlook 2026-2030 (30 October 2025) | R30: PDF p.19 | S30: An exemption, not a shutdown date. Eskom may apply for more.
A31: Coal station shutdown | B31: Matimba | D31: no shutdown date given | E31: Emissions exemption to 31 March 2030 | P31: From source | Q31: System operator, Medium-Term System Adequacy Outlook 2026-2030 (30 October 2025) | R31: PDF p.19 | S31: An exemption, not a shutdown date. Eskom may apply for more.
A32: Coal station shutdown | B32: Medupi | D32: no shutdown date given | E32: Emissions exemption to 31 March 2030 | P32: From source | Q32: System operator, Medium-Term System Adequacy Outlook 2026-2030 (30 October 2025) | R32: PDF p.19 | S32: An exemption, not a shutdown date. Eskom may apply for more.
A33: Coal station shutdown | B33: Nine coal stations, about 22 GW | D33: by 2035 | E33: To be shut down | P33: From source | Q33: Eskom, input on emission standards (24 November 2022) | R33: PDF p.12 | S33: Eskom's 2035 plan as it stood in 2022, before the shutdowns were delayed.
A34: Coal stations: last full year used on the Power fleet sheet | B34: Komati | C34: last full year | E34: 2022 | P34: Calculated | Q34: Read from the shutdown dates above | S34: Eskom's decision on five of them, due end September 2026, had not been announced by 8 October.
A35: Coal stations: last full year used on the Power fleet sheet | B35: Camden | C35: last full year | E35: 2029 | P35: Calculated | Q35: Read from the shutdown dates above | S35: Eskom's decision on five of them, due end September 2026, had not been announced by 8 October.
A36: Coal stations: last full year used on the Power fleet sheet | B36: Grootvlei | C36: last full year | E36: 2029 | P36: Calculated | Q36: Read from the shutdown dates above | S36: Eskom's decision on five of them, due end September 2026, had not been announced by 8 October.
A37: Coal stations: last full year used on the Power fleet sheet | B37: Hendrina | C37: last full year | E37: 2029 | P37: Calculated | Q37: Read from the shutdown dates above | S37: Eskom's decision on five of them, due end September 2026, had not been announced by 8 October.
A38: Coal stations: last full year used on the Power fleet sheet | B38: Arnot | C38: last full year | E38: 2029 | P38: Calculated | Q38: Read from the shutdown dates above | S38: Eskom's decision on five of them, due end September 2026, had not been announced by 8 October.
A39: Coal stations: last full year used on the Power fleet sheet | B39: Kriel | C39: last full year | E39: 2029 | P39: Calculated | Q39: Read from the shutdown dates above | S39: Eskom's decision on five of them, due end September 2026, had not been announced by 8 October.
A40: Coal stations: last full year used on the Power fleet sheet | B40: Duvha | C40: last full year | E40: 2033 | P40: Calculated | Q40: Read from the shutdown dates above | S40: Eskom's decision on five of them, due end September 2026, had not been announced by 8 October.
A41: Coal stations: last full year used on the Power fleet sheet | B41: Matla | C41: last full year | E41: 2033 | P41: Calculated | Q41: Read from the shutdown dates above | S41: Eskom's decision on five of them, due end September 2026, had not been announced by 8 October.
A42: Independent diesel plants: contract end | B42: Dedisa | D42: August or September 2030 | E42: Contract expires | P42: From source | Q42: System operator, Medium-Term System Adequacy Outlook 2026-2030 (30 October 2025) | R42: PDF p.22 | S42: The department's two diesel peaking plants. The outlook gives August and September 2030 for Dedisa and Avon together.
A43: Independent diesel plants: contract end | B43: Avon | D43: August or September 2030 | E43: Contract expires | P43: From source | Q43: System operator, Medium-Term System Adequacy Outlook 2026-2030 (30 October 2025) | R43: PDF p.22 | S43: The department's two diesel peaking plants. The outlook gives August and September 2030 for Dedisa and Avon together.
A44: Kerosene stations: shutdown | B44: Acacia | D44: 2030 | E44: Scheduled for shutdown | P44: From source | Q44: System operator, Medium-Term System Adequacy Outlook 2026-2030 (30 October 2025) | R44: PDF p.18
A45: Kerosene stations: shutdown | B45: Port Rex | D45: 2030 | E45: Scheduled for shutdown | P45: From source | Q45: System operator, Medium-Term System Adequacy Outlook 2026-2030 (30 October 2025) | R45: PDF p.18
A46: New gas plant: commissioning | B46: Eskom combined-cycle gas turbines | C46: GW | D46: 2030 | E46: 3 | P46: From source | Q46: System operator, Medium-Term System Adequacy Outlook 2026-2030 (30 October 2025) | R46: PDF p.25 | S46: Assumed, not in construction. The outlook studies a delay beyond 2030 as a risk.
A47: New gas plant: commissioning | B47: Independent producers' combined-cycle gas turbines (gas bid windows 1 and 2) | C47: GW | D47: 2030 | E47: 3 | P47: From source | Q47: System operator, Medium-Term System Adequacy Outlook 2026-2030 (30 October 2025) | R47: PDF p.25 | S47: Assumed, not in construction. The outlook studies a delay beyond 2030 as a risk.
A48: Diesel turbine use expected by the system operator | B48: Diesel turbines (Ankerlig, Gourikwa, Dedisa, Avon) | D48: 2026-2030 | E48: Minimal, below 6% in most cases; higher in 2029, and in 2030 if the gas plant is late | P48: From source | Q48: System operator, Medium-Term System Adequacy Outlook 2026-2030 (30 October 2025) | R48: PDF p.35 | S48: The system operator's own modelling.
A49: Coal capacity shutting down | B49: Eskom coal fleet | C49: GW | D49: 2029 | E49: 5.26 | P49: From source | Q49: System operator, Medium-Term System Adequacy Outlook 2026-2030 (30 October 2025) | R49: PDF p.18 | S49: Camden, Hendrina, Arnot, Grootvlei and Kriel run to the end of 2028; phased shutdown from 2029. Eskom's coal fleet falls from 40.1 GW to 31.7 GW.
A50: Coal capacity shutting down | B50: Eskom coal fleet | C50: GW | D50: 2030, by March | E50: 3.14 | P50: From source | Q50: System operator, Medium-Term System Adequacy Outlook 2026-2030 (30 October 2025) | R50: PDF p.18 | S50: Camden, Hendrina, Arnot, Grootvlei and Kriel run to the end of 2028; phased shutdown from 2029. Eskom's coal fleet falls from 40.1 GW to 31.7 GW.
A51: New gas plant, by project | B51: Eskom, Richards Bay combined-cycle plant (3,000 MW) | D51: not beyond 2028 | E51: Minister's determination: connect as soon as possible and not beyond 2028 | P51: From source | Q51: NERSA, reasons for decision on the 3,000 MW gas determination (November 2024) | R51: PDF pp.1, 11 | S51: Eskom's feasibility study had all four units commissioned by the end of 2028 (p.49). The system operator now assumes 2030.
A52: New gas plant, by project | B52: Independent producers, gas bid window 1 (2,000 MW) | D52: request for proposals issued 14 December 2023 | E52: No bidder appointed; no commissioning date | P52: From source | Q52: Independent Power Producers Office, gas programme site | S52: Sites anywhere in the country except Coega, which has a separate process. Bids closed on 29 May 2026: see the rows below.
A53: New gas plant, by project | B53: Eskom, Richards Bay combined-cycle plant (3,000 MW) | D53: from 2031 | E53: Eskom plans to begin producing electricity from 2031 | P53: From source | Q53: Engineering News, 5 June 2026, reporting Eskom and the Independent Power Producers Office | S53: Three years after the determination's 2028 and a year after the system operator's 2030. The environmental assessment must be redone: the Supreme Court of Appeal set the authorisation aside in 2025. A press report of Eskom's statement.
A54: New gas plant, by project | B54: Eskom, Richards Bay plant: gas supply | D54: 5 June 2026 | E54: Heads of agreement signed with Zululand Energy Terminal; Eskom is foundation customer of the proposed import terminal at Richards Bay | P54: From source | Q54: Eskom and Zululand Energy Terminal, joint media statement, 5 June 2026 | S54: The terminal is not built and the statement gives no date for it or for the plant.
A55: New gas plant, by project | B55: Independent producers, gas bid window 1: bids | D55: bids closed 29 May 2026 | E55: Four bids, 2,830 MW against 2,000 MW sought | P55: From source | Q55: Independent Power Producers Office, list of bids received on 29 May 2026 (published by the Development Bank of Southern Africa) | R55: PDF p.1 | S55: No preferred bidder named. The evaluation was not concluded at 7 October 2026 (Engineering News, reporting the Minister).
A56: New gas plant, by project | B56: Khanyazwe Flexpower (FlexED), Mpumalanga | D56: bid of 29 May 2026 | E56: 440 MW, liquefied natural gas | P56: From source | Q56: Independent Power Producers Office, list of bids received on 29 May 2026 (published by the Development Bank of Southern Africa) | R56: PDF p.1 | S56: A bid, not an award. No commissioning date is published for it.
A57: New gas plant, by project | B57: Acwa (listed as the Pictor consortium), KwaZulu-Natal | D57: bid of 29 May 2026 | E57: 990 MW, liquefied natural gas | P57: From source | Q57: Independent Power Producers Office, list of bids received on 29 May 2026 (published by the Development Bank of Southern Africa) | R57: PDF p.1 | S57: A bid, not an award. No commissioning date is published for it. The bid list names only Pictor; identified as Acwa's project by Manish, 9 October 2026.
A58: New gas plant, by project | B58: Kelvin Redevelopment (Kelvin Gas Power), Gauteng | D58: bid of 29 May 2026 | E58: 600 MW, natural gas | P58: From source | Q58: Independent Power Producers Office, list of bids received on 29 May 2026 (published by the Development Bank of Southern Africa) | R58: PDF p.1 | S58: A bid, not an award. No commissioning date is published for it.
A59: New gas plant, by project | B59: Komatipoort Power (Vutomi Energy), Mpumalanga | D59: bid of 29 May 2026 | E59: 800 MW, natural gas | P59: From source | Q59: Independent Power Producers Office, list of bids received on 29 May 2026 (published by the Development Bank of Southern Africa) | R59: PDF p.1 | S59: A bid, not an award. No commissioning date is published for it.
A60: New gas plant, by project | B60: Independent producers, gas bid window 1: timetable | D60: as reported June 2026 | E60: After preferred bidders are named: more than a year to financial close, then 36 months of construction | P60: From source | Q60: Engineering News, 5 June 2026, reporting Eskom and the Independent Power Producers Office | S60: Preferred bidders were expected in August 2026 and had not been named by 7 October. On this timetable no plant from the round runs before about 2031 (my reading).
A61: New gas plant, by project | B61: New gas determination (5,000 MW) | D61: announced 7 October 2026 | E61: 5,000 MW of gas-to-power prioritised for new bidding rounds, open to Eskom as well | P61: From source | Q61: Engineering News, 7 October 2026, reporting the Minister of Electricity and Energy | S61: No dates, sites or capacity factor given. Whether it adds to or replaces the earlier 3,000 MW and 2,000 MW is not stated.
A62: New gas plant, by project | B62: Integrated Resource Plan 2025: Eskom gas | D62: 2029 | E62: 3,000 MW added in 2029 | P62: From source | Q62: Department of Electricity and Energy, Integrated Resource Plan 2025 (October 2025) | R62: PDF p.41, Table 1 | S62: The plan's schedule, not a project date. Eskom itself now says 2031.
A63: New gas plant, by project | B63: Integrated Resource Plan 2025: independent producers' gas | D63: 2030 | E63: 3,000 MW added in 2030 | P63: From source | Q63: Department of Electricity and Energy, Integrated Resource Plan 2025 (October 2025) | R63: PDF pp.27, 41 | S63: The plan assumes all 3,000 MW is on the grid by 2030 although only 2,000 MW had been offered to the market. It also studies a case where the gas does not arrive.
A64: New gas plant, by project | B64: Integrated Resource Plan 2025: independent producers' gas, later years | D64: 2031 to 2042 | E64: 12,250 MW added | P64: From source | Q64: Department of Electricity and Energy, Integrated Resource Plan 2025 (October 2025) | R64: PDF p.41, Table 1 | S64: The plan's schedule.
A65: New gas plant, by project | B65: Integrated Resource Plan 2025: existing diesel peaking plants | D65: no date | E65: Converting them to natural gas should be considered; plans are being developed at most of them | P65: From source | Q65: Department of Electricity and Energy, Integrated Resource Plan 2025 (October 2025) | R65: PDF p.46 | S65: Covers Avon and the other diesel turbines. No plant is named and no date is given.
A66: New gas plant, by project | B66: AIA working timeline: Acwa (not a published source) | D66: 2030 | E66: 990 MW | P66: From source | Q66: AIA chart, Gas-to-power demand timeline, supplied by Manish on 9 October 2026; its own sources are not stated | S66: For comparison; no published source confirms the date.
A67: New gas plant, by project | B67: AIA working timeline: Avon (not a published source) | D67: 2030 | E67: 670 MW | P67: From source | Q67: AIA chart, Gas-to-power demand timeline, supplied by Manish on 9 October 2026; its own sources are not stated | S67: For comparison; no published source confirms the date. Avon is not on the bid list.
A68: New gas plant, by project | B68: AIA working timeline: FlexED (not a published source) | D68: 2030 | E68: 440 MW | P68: From source | Q68: AIA chart, Gas-to-power demand timeline, supplied by Manish on 9 October 2026; its own sources are not stated | S68: For comparison; no published source confirms the date. The chart shows 450 MW; the bid list's 440 MW is used.
A69: New gas plant, by project | B69: AIA working timeline: Vutomi (not a published source) | D69: 2030 | E69: 800 MW | P69: From source | Q69: AIA chart, Gas-to-power demand timeline, supplied by Manish on 9 October 2026; its own sources are not stated | S69: For comparison; no published source confirms the date. High case only.
A70: New gas plant, by project | B70: AIA working timeline: Eskom (not a published source) | D70: 2032 | E70: 3,000 MW | P70: From source | Q70: AIA chart, Gas-to-power demand timeline, supplied by Manish on 9 October 2026; its own sources are not stated | S70: For comparison; no published source confirms the date.
A71: New gas plant: dates in use | B71: Eskom gas | C71: year | E71: 2029 | P71: From source | Q71: Department of Electricity and Energy, Integrated Resource Plan 2025 (October 2025) | R71: PDF p.41, Table 1 | S71: The plan's schedule, used on Manish's instruction of 9 October (decision D24). No project has a preferred bidder, financial close or construction start, and Eskom itself says 2031, so these are the earliest dates.
A72: New gas plant: dates in use | B72: independent producers' gas | C72: year | E72: 2030 | P72: From source | Q72: Department of Electricity and Energy, Integrated Resource Plan 2025 (October 2025) | R72: PDF p.41, Table 1 | S72: The plan's schedule, used on Manish's instruction of 9 October (decision D24). No project has a preferred bidder, financial close or construction start, and Eskom itself says 2031, so these are the earliest dates.
A74: Vehicle fleet
A75: Item | B75: Covers | C75: Unit | D75: Period | E75: Value | P75: Status | Q75: Source | R75: Page | S75: Note
A76: Registered vehicles by class | B76: cars | C76: vehicles | D76: 2026-06 | E76: 8340592 | P76: From source | Q76: eNaTIS live vehicle population by class and province | S76: By province on the DR07 fleet by province sheet. Monthly from February 2021.
A77: Registered vehicles by class | B77: light commercial | C77: vehicles | D77: 2026-06 | E77: 2816547 | P77: From source | Q77: eNaTIS live vehicle population by class and province | S77: By province on the DR07 fleet by province sheet. Monthly from February 2021.
A78: Registered vehicles by class | B78: trucks | C78: vehicles | D78: 2026-06 | E78: 409049 | P78: From source | Q78: eNaTIS live vehicle population by class and province | S78: By province on the DR07 fleet by province sheet. Monthly from February 2021.
A79: Registered vehicles by class | B79: buses | C79: vehicles | D79: 2026-06 | E79: 66872 | P79: From source | Q79: eNaTIS live vehicle population by class and province | S79: By province on the DR07 fleet by province sheet. Monthly from February 2021.
A80: Registered vehicles by class | B80: minibuses | C80: vehicles | D80: 2026-06 | E80: 356997 | P80: From source | Q80: eNaTIS live vehicle population by class and province | S80: By province on the DR07 fleet by province sheet. Monthly from February 2021.
A81: Largest provinces, share of registered vehicles | B81: Gauteng | C81: % | D81: 2026-06 | E81: 39 | P81: Calculated | Q81: Calculated from eNaTIS
A82: Largest provinces, share of registered vehicles | B82: Western Cape | C82: % | D82: 2026-06 | E82: 16.3 | P82: Calculated | Q82: Calculated from eNaTIS
A83: Largest provinces, share of registered vehicles | B83: KwaZulu-Natal | C83: % | D83: 2026-06 | E83: 14.1 | P83: Calculated | Q83: Calculated from eNaTIS
A84: Registered vehicles by fuel | B84: petrol | C84: vehicles | D84: December 2023 | E84: 8555772 | P84: From source | Q84: Department of Transport, Transport Statistics Bulletin 2023 | S84: National only, and not split by class. No later edition found.
A85: Registered vehicles by fuel | B85: diesel | C85: vehicles | D85: December 2023 | E85: 3335546 | P85: From source | Q85: Department of Transport, Transport Statistics Bulletin 2023 | S85: National only, and not split by class. No later edition found.
A86: Diesel vehicles by province | B86: Gauteng | C86: vehicles | D86: December 2023 | E86: 1142275 | P86: From source | Q86: Department of Transport, Transport Statistics Bulletin 2023, Table 2.8 | R86: PDF p.40 | S86: All nine provinces, petrol and diesel, are on the DR07 fleet by province sheet.
A87: Diesel vehicles by province | B87: Western Cape | C87: vehicles | D87: December 2023 | E87: 507006 | P87: From source | Q87: Department of Transport, Transport Statistics Bulletin 2023, Table 2.8 | R87: PDF p.40 | S87: All nine provinces, petrol and diesel, are on the DR07 fleet by province sheet.
A88: Diesel vehicles by province | B88: KwaZulu-Natal | C88: vehicles | D88: December 2023 | E88: 459888 | P88: From source | Q88: Department of Transport, Transport Statistics Bulletin 2023, Table 2.8 | R88: PDF p.40 | S88: All nine provinces, petrol and diesel, are on the DR07 fleet by province sheet.
A89: Diesel share of petrol and diesel vehicles, by province | B89: Northern Cape | C89: % | D89: December 2023 | E89: 38 | P89: Calculated | Q89: Calculated from the bulletin
A90: Diesel share of petrol and diesel vehicles, by province | B90: Gauteng | C90: % | D90: December 2023 | E90: 24.8 | P90: Calculated | Q90: Calculated from the bulletin
A91: Diesel vehicles by class, estimated | B91: cars | C91: vehicles | D91: December 2023 | E91: 1080644 | P91: Calculated | Q91: Calculated from the register (December 2023), the transport bulletin (December 2023) and Stone et al. (2018) | S91: Estimated, not published: each class's diesel share in the 2010 fleet (Stone et al. 2018) moved by one common factor so the classes add up to the bulletin's diesel total. Nothing published crosses fuel with class.
A92: Diesel vehicles by class, estimated | B92: light commercial | C92: vehicles | D92: December 2023 | E92: 1506107 | P92: Calculated | Q92: Calculated from the register (December 2023), the transport bulletin (December 2023) and Stone et al. (2018) | S92: Estimated, not published: each class's diesel share in the 2010 fleet (Stone et al. 2018) moved by one common factor so the classes add up to the bulletin's diesel total. Nothing published crosses fuel with class.
A93: Diesel vehicles by class, estimated | B93: trucks | C93: vehicles | D93: December 2023 | E93: 388778 | P93: Calculated | Q93: Calculated from the register (December 2023), the transport bulletin (December 2023) and Stone et al. (2018) | S93: Estimated, not published: each class's diesel share in the 2010 fleet (Stone et al. 2018) moved by one common factor so the classes add up to the bulletin's diesel total. Nothing published crosses fuel with class.
A94: Diesel vehicles by class, estimated | B94: buses | C94: vehicles | D94: December 2023 | E94: 64982 | P94: Calculated | Q94: Calculated from the register (December 2023), the transport bulletin (December 2023) and Stone et al. (2018) | S94: Estimated, not published: each class's diesel share in the 2010 fleet (Stone et al. 2018) moved by one common factor so the classes add up to the bulletin's diesel total. Nothing published crosses fuel with class.
A95: Diesel vehicles by class, estimated | B95: minibuses | C95: vehicles | D95: December 2023 | E95: 54087 | P95: Calculated | Q95: Calculated from the register (December 2023), the transport bulletin (December 2023) and Stone et al. (2018) | S95: Estimated, not published: each class's diesel share in the 2010 fleet (Stone et al. 2018) moved by one common factor so the classes add up to the bulletin's diesel total. Nothing published crosses fuel with class.
A96: Diesel vehicles by class, estimated | B96: motorcycles | C96: vehicles | D96: December 2023 | E96: 0 | P96: Calculated | Q96: Calculated from the register (December 2023), the transport bulletin (December 2023) and Stone et al. (2018) | S96: Estimated, not published: each class's diesel share in the 2010 fleet (Stone et al. 2018) moved by one common factor so the classes add up to the bulletin's diesel total. Nothing published crosses fuel with class.
A97: Diesel vehicles by class, estimated | B97: other self propelled | C97: vehicles | D97: December 2023 | E97: 238955 | P97: Calculated | Q97: Calculated from the register (December 2023), the transport bulletin (December 2023) and Stone et al. (2018) | S97: Estimated, not published: each class's diesel share in the 2010 fleet (Stone et al. 2018) moved by one common factor so the classes add up to the bulletin's diesel total. Nothing published crosses fuel with class.
A98: Petrol vehicles by class, estimated | B98: cars | C98: vehicles | D98: December 2023 | E98: 6713520 | P98: Calculated | Q98: Calculated from the register (December 2023), the transport bulletin (December 2023) and Stone et al. (2018) | S98: Estimated, not published: each class's diesel share in the 2010 fleet (Stone et al. 2018) moved by one common factor so the classes add up to the bulletin's diesel total. Nothing published crosses fuel with class.
A99: Petrol vehicles by class, estimated | B99: light commercial | C99: vehicles | D99: December 2023 | E99: 1183203 | P99: Calculated | Q99: Calculated from the register (December 2023), the transport bulletin (December 2023) and Stone et al. (2018) | S99: Estimated, not published: each class's diesel share in the 2010 fleet (Stone et al. 2018) moved by one common factor so the classes add up to the bulletin's diesel total. Nothing published crosses fuel with class.
A100: Petrol vehicles by class, estimated | B100: trucks | C100: vehicles | D100: December 2023 | E100: 3571 | P100: Calculated | Q100: Calculated from the register (December 2023), the transport bulletin (December 2023) and Stone et al. (2018) | S100: Estimated, not published: each class's diesel share in the 2010 fleet (Stone et al. 2018) moved by one common factor so the classes add up to the bulletin's diesel total. Nothing published crosses fuel with class.
A101: Petrol vehicles by class, estimated | B101: buses | C101: vehicles | D101: December 2023 | E101: 0 | P101: Calculated | Q101: Calculated from the register (December 2023), the transport bulletin (December 2023) and Stone et al. (2018) | S101: Estimated, not published: each class's diesel share in the 2010 fleet (Stone et al. 2018) moved by one common factor so the classes add up to the bulletin's diesel total. Nothing published crosses fuel with class.
A102: Petrol vehicles by class, estimated | B102: minibuses | C102: vehicles | D102: December 2023 | E102: 301148 | P102: Calculated | Q102: Calculated from the register (December 2023), the transport bulletin (December 2023) and Stone et al. (2018) | S102: Estimated, not published: each class's diesel share in the 2010 fleet (Stone et al. 2018) moved by one common factor so the classes add up to the bulletin's diesel total. Nothing published crosses fuel with class.
... A112: Average age of vehicles | B112: All vehicles and passenger vehicles | C112: years | D112: 2022 | E112: 10.5 | P112: From source | Q112: Lightstone Auto Insights, April 2022 | S112: Ten years and six months, up from nine years and four months for passenger vehicles in 2014 and 2015.
...

Sheet DR07 fleet by province
A1: DR07 Registered vehicles by province and class, 2026-06
A2: Vehicles on the register at month end, by class; then petrol and diesel vehicles by province at December 2023. Nothing published crosses fuel with class.
A4: Province | B4: Cars | C4: Light commercial | D4: Trucks | E4: Buses | F4: Minibuses | G4: Motorcycles | H4: All self-propelled | I4: Share of all vehicles | J4: Source
A5: Gauteng | B5: 3485272 | C5: 936521 | D5: 150862 | E5: 20937 | F5: 127451 | G5: 158810 | H5: 4919011 | I5: =H5/H$14 | J5: eNaTIS live vehicle population by class and province (vehicle_population_natis.csv)
A6: KwaZulu-Natal | B6: 1171505 | C6: 411049 | D6: 59557 | E6: 8253 | F6: 61665 | G6: 39411 | H6: 1783517 | I6: =H6/H$14 | J6: eNaTIS live vehicle population by class and province (vehicle_population_natis.csv)
A7: Western Cape | B7: 1448715 | C7: 371420 | D7: 50960 | E7: 7463 | F7: 41603 | G7: 96388 | H7: 2060254 | I7: =H7/H$14 | J7: eNaTIS live vehicle population by class and province (vehicle_population_natis.csv)
A8: Eastern Cape | B8: 506193 | C8: 212296 | D8: 23146 | E8: 4894 | F8: 27406 | G8: 21876 | H8: 813557 | I8: =H8/H$14 | J8: eNaTIS live vehicle population by class and province (vehicle_population_natis.csv)
A9: Mpumalanga | B9: 477358 | C9: 231790 | D9: 41125 | E9: 7812 | F9: 28469 | G9: 17205 | H9: 830714 | I9: =H9/H$14 | J9: eNaTIS live vehicle population by class and province (vehicle_population_natis.csv)
A10: Limpopo | B10: 419050 | C10: 260224 | D10: 28357 | E10: 7774 | F10: 28651 | G10: 9060 | H10: 771478 | I10: =H10/H$14 | J10: eNaTIS live vehicle population by class and province (vehicle_population_natis.csv)
A11: North West | B11: 365628 | C11: 168694 | D11: 18997 | E11: 4326 | F11: 22262 | G11: 13126 | H11: 614380 | I11: =H11/H$14 | J11: eNaTIS live vehicle population by class and province (vehicle_population_natis.csv)
A12: Free State | B12: 328418 | C12: 138820 | D12: 26190 | E12: 3425 | F12: 12679 | G12: 16810 | H12: 561774 | I12: =H12/H$14 | J12: eNaTIS live vehicle population by class and province (vehicle_population_natis.csv)
A13: Northern Cape | B13: 138453 | C13: 85733 | D13: 9855 | E13: 1988 | F13: 6811 | G13: 7123 | H13: 259795 | I13: =H13/H$14 | J13: eNaTIS live vehicle population by class and province (vehicle_population_natis.csv)
A14: South Africa | B14: =SUM(B5:B13) | C14: =SUM(C5:C13) | D14: =SUM(D5:D13) | E14: =SUM(E5:E13) | F14: =SUM(F5:F13) | G14: =SUM(G5:G13) | H14: =SUM(H5:H13) | I14: =H14/H$14 | J14: Sum of the nine provinces
A16: Petrol and diesel vehicles by province, December 2023
A17: Province | B17: Petrol | C17: Diesel | D17: Petrol and diesel | E17: Diesel share | J17: Source
A18: Gauteng | B18: 3466725 | C18: 1142275 | D18: =B18+C18 | E18: =C18/D18 | J18: Department of Transport, Transport Statistics Bulletin 2023, Table 2.8 (PDF p.40)
A19: KwaZulu-Natal | B19: 1181017 | C19: 459888 | D19: =B19+C19 | E19: =C19/D19 | J19: Department of Transport, Transport Statistics Bulletin 2023, Table 2.8 (PDF p.40)
A20: Western Cape | B20: 1426954 | C20: 507006 | D20: =B20+C20 | E20: =C20/D20 | J20: Department of Transport, Transport Statistics Bulletin 2023, Table 2.8 (PDF p.40)
A21: Eastern Cape | B21: 550085 | C21: 233959 | D21: =B21+C21 | E21: =C21/D21 | J21: Department of Transport, Transport Statistics Bulletin 2023, Table 2.8 (PDF p.40)
A22: Mpumalanga | B22: 529640 | C22: 281750 | D22: =B22+C22 | E22: =C22/D22 | J22: Department of Transport, Transport Statistics Bulletin 2023, Table 2.8 (PDF p.40)
A23: Limpopo | B23: 482248 | C23: 240595 | D23: =B23+C23 | E23: =C23/D23 | J23: Department of Transport, Transport Statistics Bulletin 2023, Table 2.8 (PDF p.40)
A24: North West | B24: 404398 | C24: 184614 | D24: =B24+C24 | E24: =C24/D24 | J24: Department of Transport, Transport Statistics Bulletin 2023, Table 2.8 (PDF p.40)
A25: Free State | B25: 358000 | C25: 189266 | D25: =B25+C25 | E25: =C25/D25 | J25: Department of Transport, Transport Statistics Bulletin 2023, Table 2.8 (PDF p.40)
A26: Northern Cape | B26: 156705 | C26: 96193 | D26: =B26+C26 | E26: =C26/D26 | J26: Department of Transport, Transport Statistics Bulletin 2023, Table 2.8 (PDF p.40)
A27: South Africa | B27: =SUM(B18:B26) | C27: =SUM(C18:C26) | D27: =B27+C27 | E27: =C27/D27 | J27: Sum of the nine provinces; equals the bulletin's national totals

Sheet DR08 refinery supply
A1: DR08 Refinery supply
A2: 43 facts from sources (blue), 19 calculated (white), 2 not available (yellow). Petrol and diesel only. Figures reported for several years are set out one column a year; every row names its source.
A5: Capacity
A6: Item | B6: Plant | C6: Unit | D6: Period | E6: Value | P6: Status | Q6: Source | R6: Page | S6: Note
A7: Published capacity | B7: Secunda | C7: barrels a day | D7: as published in 2023 | E7: 150000 | P7: From source | Q7: Department of Mineral Resources and Energy, South African Energy Sector Report 2023, Table 1 | R7: PDF p.17 | S7: Coal to liquids. The department's table names the industry association (SAPIA, now FIASA) as its source. Crude equivalent.
A8: Published capacity | B8: Natref | C8: barrels a day | D8: as published in 2023 | E8: 108000 | P8: From source | Q8: Department of Mineral Resources and Energy, South African Energy Sector Report 2023, Table 1 | R8: PDF p.17 | S8: Crude oil. Sasol 64%, TotalEnergies 36%. The department's table names the industry association (SAPIA, now FIASA) as its source. Crude equivalent.
A9: Published capacity | B9: Astron Energy | C9: barrels a day | D9: as published in 2023 | E9: 100000 | P9: From source | Q9: Department of Mineral Resources and Energy, South African Energy Sector Report 2023, Table 1 | R9: PDF p.17 | S9: Crude oil, Cape Town. The department's table names the industry association (SAPIA, now FIASA) as its source. Crude equivalent.
A10: Published capacity | B10: Sapref | C10: barrels a day | D10: as published in 2023 | E10: 180000 | P10: From source | Q10: Department of Mineral Resources and Energy, South African Energy Sector Report 2023, Table 1 | R10: PDF p.17 | S10: Crude oil, Durban. Listed at full capacity although not refining. The department's table names the industry association (SAPIA, now FIASA) as its source. Crude equivalent.
A11: Published capacity | B11: Enref | C11: barrels a day | D11: as published in 2023 | E11: 0 | P11: From source | Q11: Department of Mineral Resources and Energy, South African Energy Sector Report 2023, Table 1 | R11: PDF p.17 | S11: Crude oil, Durban. Shown as nil. The department's table names the industry association (SAPIA, now FIASA) as its source. Crude equivalent.
A12: Published capacity | B12: PetroSA | C12: barrels a day | D12: as published in 2023 | E12: 0 | P12: From source | Q12: Department of Mineral Resources and Energy, South African Energy Sector Report 2023, Table 1 | R12: PDF p.17 | S12: Gas to liquids, Mossel Bay. Shown as nil. The department's table names the industry association (SAPIA, now FIASA) as its source. Crude equivalent.
A13: Published capacity before the closures | B13: Enref | C13: barrels a day | D13: as published in 2021 | E13: 135000 | P13: From source | Q13: Department of Mineral Resources and Energy, South African Energy Sector Report 2021, Table 1-1 | R13: PDF p.15 | S13: The department's table names the industry association (SAPIA, now FIASA) as its source. Crude equivalent.
A14: Published capacity before the closures | B14: PetroSA | C14: barrels a day | D14: as published in 2021 | E14: 45000 | P14: From source | Q14: Department of Mineral Resources and Energy, South African Energy Sector Report 2021, Table 1-1 | R14: PDF p.15 | S14: The department's table names the industry association (SAPIA, now FIASA) as its source. Crude equivalent.
A15: Published capacity before the closures | B15: All six plants | C15: barrels a day | D15: as published in 2021 | E15: 718000 | P15: From source | Q15: Department of Mineral Resources and Energy, South African Energy Sector Report 2021, Table 1-1 | R15: PDF p.15 | S15: The department's table names the industry association (SAPIA, now FIASA) as its source. Crude equivalent.
A16: Capacity stated by the operator | B16: Astron Energy | C16: barrels a day, steady state | D16: 2023 and 2025 | E16: 100000 | P16: From source | Q16: Glencore annual reports 2023 and 2025 | R16: 2023 PDF p.195; 2025 PDF p.150 | S16: Agrees with the department's table.
A17: Capacity stated by the operator | B17: Secunda | C17: barrels a day | D17: as stated April 2021 | E17: 150000 | P17: From source | Q17: Sasol Limited, Business Overview, April 2021 | R17: PDF p.12 | S17: Sasol: about 7.5 to 7.7 million tonnes a year, of which about 60% is energy products and 40% chemicals. Agrees with the department's table.
A18: Capacity stated by the operator | B18: Natref | C18: barrels a day | D18: as stated April 2021 | E18: 108500 | P18: From source | Q18: Sasol Limited, Business Overview, April 2021 | R18: PDF p.12 | S18: The department's table shows 108,000.
A19: Capacity stated by the operator | B19: Secunda | C19: barrels of oil equivalent a day, fuels and chemicals | D19: as stated in a site-visit pack, 2023 | E19: About 160,000 | P19: From source | Q19: Sasol Limited, Secunda Operations investor site visit | R19: PDF p.3 | S19: About 7.5 million tonnes a year: about 60% fuels (diesel, petrol, jet fuel, LPG) and 40% chemicals. No split between petrol and diesel.
A20: Capacity stated by the operator | B20: Astron Energy | C20: barrels a day, nameplate crude processing | D20: as on the company's site, October 2026 | E20: 100000 | P20: From source | Q20: Astron Energy, About us page | S20: Agrees with Glencore and with the department's table.
A21: Capacity in operation | B21: Secunda, Natref and Astron Energy | C21: barrels a day, crude equivalent | D21: 2023 onward | E21: 358000 | P21: Calculated | Q21: Sum of the three plants operating | S21: Half of the 718,000 published in 2021. Sapref is still listed at 180,000 by the department although it is not refining.
A23: Status and dates
A24: Item | B24: Plant | C24: Unit | D24: Period | E24: Value | P24: Status | Q24: Source | R24: Page | S24: Note
A25: Refining in 2026 | B25: Secunda | D25: 2026 | E25: Yes | P25: Calculated | Q25: Sasol business performance metrics, June 2026 | S25: Read from the status rows below.
A26: Refining in 2026 | B26: Natref | D26: 2026; planned shutdown and a unit outage, August to September | E26: Yes | P26: Calculated | Q26: Sasol business performance metrics, June 2026; Natref update, 1 September 2026 | S26: Read from the status rows below. Natref is its own crude refinery at Sasolburg, part-owned by Sasol; its output is not part of Secunda's.
A27: Refining in 2026 | B27: Astron Energy | D27: since the restart in early 2023 | E27: Yes | P27: Calculated | Q27: Glencore annual reports 2023 to 2025 | S27: Read from the status rows below.
A28: Refining in 2026 | B28: Sapref | D28: since the pause at the end of March 2022 | E28: No | P28: Calculated | Q28: Shell South Africa release, 10 February 2022; Central Energy Fund, September 2026 | S28: Read from the status rows below.
A29: Refining in 2026 | B29: Enref | D29: since the fire of 4 December 2020 | E29: No | P29: Calculated | Q29: Engen's account to Parliament, 8 December 2020; department's 2023 report | S29: Read from the status rows below.
A30: Refining in 2026 | B30: PetroSA | D30: since December 2020 | E30: No | P30: Calculated | Q30: PetroSA tender scope of work; department's 2023 report | S30: Read from the status rows below.
A31: Status | B31: Astron Energy | D31: early 2023 | E31: Restarted after a multi-year rebuild | P31: From source | Q31: Glencore Annual Report 2023 | R31: PDF pp.101, 106 | S31: It had not operated since a 2020 incident; the department's 2023 report still describes it as not operating.
A32: Status | B32: Enref (Engen) | D32: as at 2023 | E32: Not operating after a major fire; capacity shown as nil | P32: From source | Q32: Department of Mineral Resources and Energy, South African Energy Sector Report 2023 | R32: PDF p.17 | S32: The fire and the decision to close are dated in the two rows below.
A33: Status | B33: PetroSA (Mossel Bay) | D33: since December 2020 | E33: Not operating: no feedstock | P33: From source | Q33: PetroSA tender scope of work; department's 2023 report | R33: department PDF p.17 | S33: PetroSA's tender proposes restarting the liquids refinery without the offshore gas sections.
A34: Status | B34: Sapref | D34: as at September 2026 | E34: Not refining; acquired by the Central Energy Fund | P34: From source | Q34: Central Energy Fund statements, September 2026 | S34: The two statements confirm the acquisition and that the site is not refining. The pause is dated in the Shell release below.
A35: Status | B35: Natref | D35: August to September 2026 | E35: A downstream unit outage alongside a planned shutdown | P35: From source | Q35: Sasol, Natref operational update, 1 September 2026 | S35: An operating risk, not a closure.
A36: Status | B36: Three crude refineries | D36: as at 2023 | E36: Not in operation for the past two years | P36: From source | Q36: Department of Mineral Resources and Energy, South African Energy Sector Report 2023 | R36: PDF p.17 | S36: The department's wording; it does not name them in that sentence.
A37: Status | B37: Enref (Engen) | D37: 4 December 2020 | E37: Fire and explosion at 07:08 in Unit 44; the refinery was shut | P37: From source | Q37: Engen's account to Parliament's Portfolio Committee on Environment, Forestry and Fisheries, 8 December 2020 (Parliamentary Monitoring Group record) | S37: It did not refine again: see the next row.
A38: Status | B38: Enref (Engen) | D38: 23 April 2021 | E38: Engen announced it would shut the refinery and convert the site to an import terminal by the end of 2023 | P38: From source | Q38: Engineering News, 23 April 2021, reporting Engen's statement | S38: A press report of Engen's statement; the statement itself is not held. Engen gives nameplate capacity as 120,000 barrels a day, against 135,000 in the department's table.
A39: Status | B39: Sapref | D39: 10 February 2022 | E39: Shell and bp announced a spend freeze and a pause of refinery operations no later than the end of March 2022, for an indefinite period | P39: From source | Q39: Shell South Africa media release, SAPREF to pause refinery operations | S39: Gives the latest date for the pause, not the day the last unit stopped.
A41: Output by plant
A42: Item | B42: Plant | C42: Unit | D42: Basis | E42: 2020 | F42: 2021 | G42: 2022 | H42: 2023 | I42: 2024 | J42: 2025 | K42: 2026 | P42: Status | Q42: Source | R42: Page | S42: Note
A43: Output reported by the operator | B43: Secunda, all refined products | C43: million barrels | D43: years to June | E43: 31.2 | F43: 32.1 | G43: 29.2 | H43: 29.9 | I43: 29.1 | J43: 27.6 | K43: 30.6 | P43: From source | Q43: Sasol production and sales metrics | S43: All products together. No operator reports petrol and diesel separately.
A44: Output reported by the operator | B44: Natref, Sasol's share | C44: million barrels | D44: years to June | E44: 16.8 | F44: 17.7 | G44: 18.9 | H44: 17.2 | I44: 17.8 | J44: 14.7 | K44: 25.8 | P44: From source | Q44: Sasol production and sales metrics | S44: All products together. No operator reports petrol and diesel separately. Sasol's 63.64% share only; the year to June 2026 includes output above that share.
A45: Output reported by the operator | B45: Astron Energy, all refined products | C45: billion Btu | D45: calendar years | H45: 136665 | I45: 166204 | J45: 164365 | P45: From source | Q45: Glencore annual reports | S45: All products together. No operator reports petrol and diesel separately. Reported as energy content, not volume.
A46: Petrol output, estimated | B46: Natref, whole refinery | C46: billion litres | D46: years to June | E46: 1.22 to 1.34 | F46: 1.28 to 1.41 | G46: 1.37 to 1.51 | H46: 1.25 to 1.38 | I46: 1.29 to 1.42 | J46: 1.06 to 1.18 | P46: Calculated | Q46: Sasol's reported Natref production, scaled to the whole refinery, times Sasol's stated product split | S46: An estimate: the split is a range Sasol stated in April 2021, applied to every year. The year to June 2026 is left out.
A47: Diesel output, estimated | B47: Natref, whole refinery | C47: billion litres | D47: years to June | E47: 1.30 to 1.55 | F47: 1.37 to 1.64 | G47: 1.46 to 1.75 | H47: 1.33 to 1.59 | I47: 1.38 to 1.65 | J47: 1.14 to 1.36 | P47: Calculated | Q47: Sasol's reported Natref production, scaled to the whole refinery, times Sasol's stated product split | S47: An estimate: the split is a range Sasol stated in April 2021, applied to every year. The year to June 2026 is left out.
A48: Item | B48: Plant | C48: Unit | D48: Period | E48: Value | P48: Status | Q48: Source | R48: Page | S48: Note
A49: Secunda fuels output | B49: Secunda, fuels (white and black products) | C49: thousand tonnes | D49: year to June 2024 | E49: 3472 | P49: From source | Q49: Sasol business performance metrics, 30 June 2026 | R49: PDF p.4 | S49: Of total Secunda production of 6,990, 6,721 and 7,260 thousand tonnes; the rest is chemicals and other products.
A50: Secunda fuels output | B50: Secunda, fuels (white and black products) | C50: thousand tonnes | D50: year to June 2025 | E50: 3293 | P50: From source | Q50: Sasol business performance metrics, 30 June 2026 | R50: PDF p.4 | S50: Of total Secunda production of 6,990, 6,721 and 7,260 thousand tonnes; the rest is chemicals and other products.
A51: Secunda fuels output | B51: Secunda, fuels (white and black products) | C51: thousand tonnes | D51: year to June 2026 | E51: 3634 | P51: From source | Q51: Sasol business performance metrics, 30 June 2026 | R51: PDF p.4 | S51: Of total Secunda production of 6,990, 6,721 and 7,260 thousand tonnes; the rest is chemicals and other products.
A52: Petrol and diesel output by plant | B52: Secunda and Astron Energy | C52: litres | E52: Not available | P52: Not available | Q52: None published | S52: Sasol states Secunda's split (65% petrol, 35% diesel) but not the total it applies to. Glencore publishes no split for Astron. Sasol's annual filing and both companies' sites were checked on 9 October. Needs the operators.
A53: Output while not operating | B53: Sapref | C53: barrels a day | D53: since the pause at the end of March 2022 | E53: 0 | P53: Calculated | Q53: From the status rows
A54: Output while not operating | B54: Enref | C54: barrels a day | D54: since the fire of 4 December 2020 | E54: 0 | P54: Calculated | Q54: From the status rows
A55: Output while not operating | B55: PetroSA | C55: barrels a day | D55: since December 2020 | E55: 0 | P55: Calculated | Q55: From the status rows
A57: National output by product
A58: Item | B58: Plant | C58: Unit | D58: Basis | E58: 2014 | F58: 2015 | G58: 2016 | H58: 2017 | I58: 2018 | J58: 2019 | K58: 2020 | L58: 2021 | M58: 2022 | N58: 2023 | P58: Status | Q58: Source | R58: Page | S58: Note
A59: Petrol produced, all plants | B59: South Africa | C59: billion litres | D59: calendar years | E59: 10.83 | F59: 10.46 | G59: 10.39 | H59: 9.43 | I59: 9.97 | J59: 10.42 | K59: 7.89 | L59: 6.35 | P59: From source | Q59: Department of Mineral and Petroleum Resources, energy balances | S59: The only output by product. Ends at 2021, the last balance published.
A60: Diesel produced, all plants | B60: South Africa | C60: billion litres | D60: calendar years | E60: 9.59 | F60: 9.37 | G60: 9.01 | H60: 7.92 | I60: 8.43 | J60: 9.08 | K60: 6.45 | L60: 5.31 | P60: From source | Q60: Department of Mineral and Petroleum Resources, energy balances | S60: The only output by product. Ends at 2021, the last balance published.
A61: Petrol produced, United Nations series (not used) | B61: South Africa | C61: thousand tonnes | D61: calendar years | J61: 5030 | K61: 3491 | L61: 2488 | M61: 1323 | N61: 1827 | P61: From source | Q61: United Nations Statistics Division, Energy Statistics Database (retrieved 8 October 2026) | R61: transaction 013, production from refineries | S61: Comparison only, not used. It does not match the department in the years they share: set against the department's litres it implies 0.39 to 0.48 kg a litre, and petrol weighs about 0.75.
A62: Diesel produced, United Nations series (not used) | B62: South Africa | C62: thousand tonnes | D62: calendar years | J62: 7535 | K62: 4676 | L62: 4282 | M62: 2383 | N62: 2222 | P62: From source | Q62: United Nations Statistics Division, Energy Statistics Database (retrieved 8 October 2026) | R62: transaction 013, production from refineries | S62: Comparison only, not used. Close to the department in 2019 and 2021 (0.83 and 0.81 kg a litre implied, against about 0.84) but low in 2020 (0.73). The petrol series from the same source does not match, so neither is relied on.
A63: Item | B63: Plant | C63: Unit | D63: Period | E63: Value | P63: Status | Q63: Source | R63: Page | S63: Note
A64: Petrol and diesel produced after 2021, on the department's basis | B64: South Africa | C64: billion litres | D64: 2022 onward | E64: Not available | P64: Not available | Q64: None published | S64: The department has published no balance after 2021. The United Nations series runs to 2023 but does not match the department in the years they share.
A66: Yields
A67: Item | B67: Plant | C67: Unit | D67: Basis | E67: 2014 | F67: 2015 | G67: 2016 | H67: 2017 | I67: 2018 | J67: 2019 | K67: 2020 | L67: 2021 | M67: 2022 | N67: 2023 | O67: 2024 | P67: Status | Q67: Source | R67: Page | S67: Note
A68: Petrol share of the four main fuels produced | B68: South Africa, all plants | C68: % of petrol, diesel, jet and paraffin | D68: calendar years | E68: 46.1 | F68: 44.8 | G68: 45 | H68: 48.1 | I68: 48.8 | J68: 49.5 | K68: 50.3 | L68: 50.6 | P68: Calculated | Q68: Calculated from the energy balances | S68: A national mix, not a plant yield. It will have shifted since the Durban refineries closed.
A69: Diesel share of the four main fuels produced | B69: South Africa, all plants | C69: % of petrol, diesel, jet and paraffin | D69: calendar years | E69: 40.8 | F69: 40.1 | G69: 39 | H69: 40.4 | I69: 41.2 | J69: 43.1 | K69: 41.1 | L69: 42.3 | P69: Calculated | Q69: Calculated from the energy balances | S69: A national mix, not a plant yield. It will have shifted since the Durban refineries closed.
A70: Natref white product yield | B70: Natref | C70: % of crude processed | D70: years to June | K70: 89.4 | L70: 88.5 | M70: 87.3 | N70: 88.1 | O70: 87.5 | P70: From source | Q70: Sasol production and sales metrics, June 2022 and June 2024 | R70: 2022 PDF p.4; 2024 PDF p.5 | S70: White products are petrol, diesel, jet and other light products together. Total yield was 97 to 98%. Not reported in the 2025 and 2026 metrics.
A71: Item | B71: Plant | C71: Unit | D71: Period | E71: Value | P71: Status | Q71: Source | R71: Page | S71: Note
A72: Petrol share of output | B72: Natref | C72: % of production | D72: as stated April 2021 | E72: 29 to 32 | P72: From source | Q72: Sasol Limited, Business Overview, April 2021 | R72: PDF p.12 | S72: A stated range, not a yearly figure. Jet is 9 to 21% and black products 5 to 8%.
A73: Diesel share of output | B73: Natref | C73: % of production | D73: as stated April 2021 | E73: 31 to 37 | P73: From source | Q73: Sasol Limited, Business Overview, April 2021 | R73: PDF p.12 | S73: A stated range, not a yearly figure. Jet is 9 to 21% and black products 5 to 8%.
A74: Petrol share of output | B74: Secunda | C74: % of petrol and diesel | D74: as stated April 2021 | E74: 65 | P74: From source | Q74: Sasol Limited, Business Overview, April 2021 | R74: PDF p.12 | S74: Sasol states the split as approximately 65% petrol, 35% diesel and does not say which total it applies to, so no volume is calculated.
A75: Diesel share of output | B75: Secunda | C75: % of petrol and diesel | D75: as stated April 2021 | E75: 35 | P75: From source | Q75: Sasol Limited, Business Overview, April 2021 | R75: PDF p.12 | S75: Sasol states the split as approximately 65% petrol, 35% diesel and does not say which total it applies to, so no volume is calculated.
A76: Petrol share of output, assumed | B76: Astron Energy | C76: % of petrol and diesel | D76: assumption | E76: 50 | P76: Calculated | Q76: Assumption agreed with Nigel on the call of 9 October 2026 | S76: Nothing is published for Astron. An even split, so the model responds sensibly when the plant is switched on or off; not a measured figure.
A77: Diesel share of output, assumed | B77: Astron Energy | C77: % of petrol and diesel | D77: assumption | E77: 50 | P77: Calculated | Q77: Assumption agreed with Nigel on the call of 9 October 2026 | S77: Nothing is published for Astron. An even split, so the model responds sensibly when the plant is switched on or off; not a measured figure.
A79: Utilisation
A80: Item | B80: Plant | C80: Unit | D80: Basis | E80: 2020 | F80: 2021 | G80: 2022 | H80: 2023 | I80: 2024 | J80: 2025 | K80: 2026 | P80: Status | Q80: Source | R80: Page | S80: Note
A81: Output as a share of published capacity | B81: Secunda | C81: % | D81: years to June | E81: 57 | F81: 59 | G81: 53 | H81: 55 | I81: 53 | J81: 50 | K81: 56 | P81: Calculated | Q81: Reported output over published capacity | S81: Capacity is crude equivalent and output is refined product, so this understates how hard the plant runs.
A82: Output as a share of published capacity | B82: Natref | C82: % | D82: years to June | E82: 67 | F82: 71 | G82: 75 | H82: 69 | I82: 71 | J82: 59 | P82: Calculated | Q82: Reported output over published capacity, Sasol's share scaled to the whole refinery | S82: Capacity is crude equivalent and output is refined product, so this understates how hard the plant runs. The year to June 2026 is left out because Sasol's figure includes output above its share.
A83: Output as a share of published capacity, estimated | B83: Astron Energy | C83: % | D83: calendar years | H83: 65 | I83: 78 | J83: 78 | P83: Calculated | Q83: Glencore's energy content at 5.8 million Btu a barrel of oil equivalent, over published capacity | S83: An estimate: no throughput in barrels is published. Refined products hold a little less energy per barrel than the standard, so true utilisation is somewhat higher. 2023 is the restart year.
A84: Item | B84: Plant | C84: Unit | D84: Period | E84: Value | P84: Status | Q84: Source | R84: Page | S84: Note
A85: Utilisation as stated by the operator | B85: Astron Energy | D85: 2025 | E85: Operating at full capacity, producing petrol, diesel, jet fuel and low-sulphur marine fuel | P85: From source | Q85: Astron Energy chief executive, in a company article in Engineering News | S85: The operator's own statement; no volume is given. Glencore's energy figure implies less than full: see the estimate below.
A87: Outlook
A88: Item | B88: Plant | C88: Unit | D88: Period | E88: Value | P88: Status | Q88: Source | R88: Page | S88: Note
A89: Outlook | B89: Sapref site (Central Energy Fund) | D89: no dates given | E89: Three phases: imports through existing tanks; a refinery of about 400,000 barrels a day; then 400,000 to 650,000 | P89: From source | Q89: Central Energy Fund, roadmap statement of 10 September 2026 | S89: No investment decision, dates or product slate. Phase one is an import terminal in Durban, which competes with existing terminals.
A90: Outlook | B90: Secunda | D90: July 2028 to June 2030 | E90: Sasol finds it technically feasible to supply Secunda's methane-rich gas to outside customers as Mozambican gas declines | P90: From source | Q90: Sasol media release, 6 November 2025 | S90: No liquid fuels penalty is quantified. Depends on approvals and investment.
A91: Outlook | B91: PetroSA (Mossel Bay) | D91: no dates given | E91: Tender to recommission the liquids refinery and adapt the terminal to import finished products | P91: From source | Q91: PetroSA tender scope of work | S91: No restart date or output.
A92: Outlook | B92: Secunda | D92: year to June 2026 | E92: Production 8% up and above guidance; Natref 76% up using a co-owner's capacity | P92: From source | Q92: Sasol business performance metrics, 30 June 2026 | R92: PDF p.4 | S92: Natref's rise includes Sasol using Prax SA's share during that company's business rescue.

Sheet Market sizing
A1: Market sizing: what each Vopak site can reach
A2: Billion litres a year unless the unit says otherwise. Public data only: no client throughput is assumed. Every litre Lesedi receives by pipeline lands at Durban first, so the two site markets are never added together.
A4: Site | B4: Measure | C4: Petrol | D4: Diesel | E4: Both | F4: Unit | G4: Period | H4: Status | I4: Source | J4: Note
A5: Durban | B5: Landed at Durban | C5: 4.229 | D5: 8.932 | E5: 13.161 | F5: billion litres a year | G5: 2025 | H5: Observed | I5: SARS customs, imports by office of clearance (fuel_trade_sars_by_office.csv) | J5: 95% of the 4.45 imported through every office. The most any Durban terminal can handle.
A6: Durban | B6: Coastal catchment: KwaZulu-Natal sales | C6: 1.499 | D6: 2.786 | E6: 4.284 | F6: billion litres a year | G6: 2022 | H6: Observed | I6: Department of Mineral and Petroleum Resources, sales by magisterial district added up by province | J6: Assumes KwaZulu-Natal is supplied from Durban, as both Durban refineries have stopped refining (DR08). The lower end of the Durban market.
A7: Durban | B7: Inland-bound through Durban | C7: 2.73 | D7: 6.146 | E7: 8.876 | F7: billion litres a year | G7: 2025 imports, 2022 sales | H7: Estimated | I7: SARS customs, imports by office of clearance (fuel_trade_sars_by_office.csv); Department of Mineral and Petroleum Resources, sales by magisterial district added up by province | J7: Mixes two years, and ignores coastwise shipments and exports by road from KwaZulu-Natal.
A8: Lesedi | B8: Near catchment: Gauteng sales | C8: 3.53 | D8: 3.279 | E8: 6.809 | F8: billion litres a year | G8: 2022 | H8: Observed | I8: Department of Mineral and Petroleum Resources, sales by magisterial district added up by province | J8: The market on Lesedi's doorstep. Part of it is supplied by Natref and Secunda, whose output by product is not published after 2021.
A9: Lesedi | B9: Inland catchment: six inland provinces | C9: 5.552 | D9: 6.4 | E9: 11.951 | F9: billion litres a year | G9: 2022 | H9: Observed | I9: Department of Mineral and Petroleum Resources, sales by magisterial district added up by province | J9: The upper end: everything sold inland, whoever supplies it.
A10: Lesedi | B10: Inland-bound through Durban | C10: 2.73 | D10: 6.146 | E10: 8.876 | F10: billion litres a year | G10: 2025 imports, 2022 sales | H10: Estimated | I10: SARS customs, imports by office of clearance (fuel_trade_sars_by_office.csv); Department of Mineral and Petroleum Resources, sales by magisterial district added up by province | J10: The imported fuel that moves inland, by pipeline, road or rail. Lesedi receives by pipeline only.
A11: Durban and Lesedi | B11: Both sites, counted once | C11: 4.229 | D11: 8.932 | E11: 13.161 | F11: billion litres a year | G11: 2025 | H11: Observed | I11: SARS customs, imports by office of clearance (fuel_trade_sars_by_office.csv) | J11: Every litre Lesedi receives by pipeline landed at Durban first, so the two site markets are not added together.
A12: Durban and Lesedi | B12: Trunk line capacity, Durban to Jameson Park | E12: 7.696 | F12: billion litres a year | G12: years to March 2021 to 2024 | H12: Observed | I12: Transnet Pipelines Report 2024, key performance indicators | J12: Every shipper and refined product. Unchanged from the 2020 figure.
A13: Durban and Lesedi | B13: Trunk line use, Durban to Jameson Park | E13: 5.044 | F13: billion litres a year | G13: year to March 2024 | H13: Observed | I13: Transnet Pipelines Report 2024, key performance indicators | J13: About two thirds of capacity. Not split by product.
A14: Durban and Lesedi | B14: Inland-bound fuel beyond the trunk line's capacity | E14: 1.18 | F14: billion litres a year | G14: 2025 imports, 2022 sales | H14: Estimated | I14: Calculated from the rows above | J14: At least this much must leave Durban by road or rail even with the line full.
A15: Durban and Lesedi | B15: Inland-bound fuel beyond what the trunk line carried | E15: 3.832 | F15: billion litres a year | G15: 2025 imports, 2022 sales, pipeline year to March 2024 | H15: Estimated | I15: Calculated from the rows above | J15: The fuel that left Durban for the interior by road or rail, on these figures. Mixes three periods, so read as an order of size.
A16: Durban | B16: Operational tank capacity | E16: 0.146 | F16: million m3 | G16: 2026 | H16: Estimated | I16: infrastructure/terminal_site_assumptions.csv (NERSA licence, Vopak statements and analyst estimates, each marked) | J16: Durban is 90% of the design capacity Vopak announced; Lesedi is from the licence, with two new tanks estimated.
A17: Durban | B17: Throughput the tanks allow at 1 turns a month | E17: 1.752 | F17: billion litres a year | G17: assumed turns | H17: Assumed | I17: infrastructure/terminal_site_assumptions.csv (NERSA licence, Vopak statements and analyst estimates, each marked) | J17: A ceiling, not a share: 13% of the site's market of 13.2. The turns are analyst estimates; actual throughput needs the client (DR02/05).
A18: Durban | B18: Throughput the tanks allow at 2 turns a month | E18: 3.504 | F18: billion litres a year | G18: assumed turns | H18: Assumed | I18: infrastructure/terminal_site_assumptions.csv (NERSA licence, Vopak statements and analyst estimates, each marked) | J18: A ceiling, not a share: 27% of the site's market of 13.2. The turns are analyst estimates; actual throughput needs the client (DR02/05).
A19: Durban | B19: Throughput the tanks allow at 3 turns a month | E19: 5.256 | F19: billion litres a year | G19: assumed turns | H19: Assumed | I19: infrastructure/terminal_site_assumptions.csv (NERSA licence, Vopak statements and analyst estimates, each marked) | J19: A ceiling, not a share: 40% of the site's market of 13.2. The turns are analyst estimates; actual throughput needs the client (DR02/05).
A20: Lesedi | B20: Operational tank capacity | E20: 0.124 | F20: million m3 | G20: 2026 | H20: Observed | I20: infrastructure/terminal_site_assumptions.csv (NERSA licence, Vopak statements and analyst estimates, each marked) | J20: Durban is 90% of the design capacity Vopak announced; Lesedi is from the licence, with two new tanks estimated.
A21: Lesedi | B21: Throughput the tanks allow at 1 turns a month | E21: 1.488 | F21: billion litres a year | G21: assumed turns | H21: Assumed | I21: infrastructure/terminal_site_assumptions.csv (NERSA licence, Vopak statements and analyst estimates, each marked) | J21: A ceiling, not a share: 17% of the site's market of 8.9. The turns are analyst estimates; actual throughput needs the client (DR02/05).
A22: Lesedi | B22: Throughput the tanks allow at 2 turns a month | E22: 2.976 | F22: billion litres a year | G22: assumed turns | H22: Assumed | I22: infrastructure/terminal_site_assumptions.csv (NERSA licence, Vopak statements and analyst estimates, each marked) | J22: A ceiling, not a share: 34% of the site's market of 8.9. The turns are analyst estimates; actual throughput needs the client (DR02/05).
A23: Lesedi | B23: Throughput the tanks allow at 2.4 turns a month | E23: 3.571 | F23: billion litres a year | G23: assumed turns | H23: Assumed | I23: infrastructure/terminal_site_assumptions.csv (NERSA licence, Vopak statements and analyst estimates, each marked) | J23: A ceiling, not a share: 40% of the site's market of 8.9. The turns are analyst estimates; actual throughput needs the client (DR02/05).

Sheet Not available
A1: What could not be found
A2: 17 items across the four requests. Each was searched for in published sources; the reason is given.
A4: Request | B4: What is missing | C4: Covers | D4: Why it is not available
A5: DR01 | B5: Production after 2021 | C5: South Africa | D5: The department's last energy balance is 2021. Confirmed not available on 9 October.
A6: DR01 | B6: Sales for 2024 and 2025 | C6: South Africa | D6: The department's sales data stops at 2023. Confirmed not available on 9 October.
A7: DR01 | B7: Stocks, for any year | C7: South Africa | D7: Not published by any source used.
A8: DR04 | B8: Tariff on routes other than Durban to Alrode | C8: Other inland routes | D8: Needed to compare destinations other than Gauteng. NERSA's decisions pages were searched again on 9 October; the route table was not found online. Owner: Manish.
A9: DR04 | B9: Commercial road tanker rate, Durban to Gauteng | C9: Road | D9: No fuel tanker rate is published. The rows above are the nearest published figures: a container rate and an all-goods average. Needs Vopak or a haulier quote.
A10: DR04 | B10: Rail rate, Durban to Gauteng | C10: Rail | D10: Transnet does not publish a fuel rate. The rows above give its container rate and its track access charge for tankers. Needs Transnet or Vopak.
A11: DR04 | B11: Liquid bulk capacity and tankage | C11: Durban, Island View | D11: Parliament's report gives berths and tenants but no capacity. Earlier search summaries quoting 19.5 million kilolitres a year were not traced to a document. Needs the port authority or Vopak.
A12: DR04 | B12: Road rate and border cost, Matola to Gauteng | C12: Maputo and Matola, through Komatipoort | D12: Needed for a matched delivered cost. Needs a haulier or Vopak.
A13: DR04 | B13: Petrol and diesel supplied inland by Natref and Secunda | C13: Sasolburg and Secunda | D13: No production by product after 2021. Belongs with DR08.
A14: DR04 | B14: Matched delivered cost, Durban to Gauteng, by mode | C14: Pipeline against road and rail | D14: Pipeline: 77.02 (tariff) or 91.1 (regulated allowance) in 2026/27. No fuel tanker or rail rate is published, so the modes cannot be set side by side. Looked in: Transnet's tariff proposal, Stats SA, NERSA, Parliament. Needs Vopak or a haulier.
A15: DR07 | B15: Diesel burned in private backup generators | C15: Businesses and households | D15: No source measures it: checked the Reserve Bank, the CSIR, Eskom and the system operator. It is inside recorded diesel sales and cannot be separated.
... A21: DR08 | B21: Petrol and diesel produced after 2021, on the department's basis | C21: South Africa | D21: The department has published no balance after 2021. The United Nations series runs to 2023 but does not match the department in the years they share.
