Workbook
Name Crude_oil_litresPerBarrel: [1]Assumptions!$G$91
Name Crude_oil_litresPerBarrel: [1]Assumptions!$G$91
Name Crude_oil_litresPerBarrel: [1]Assumptions!$G$91
Name Crude_oil_litresPerBarrel: Assumptions!$G$91
Name DieselDemandPowerGen_High: Assumptions!$O$171:$P$200
Name DieselDemandPowerGen_Low: Assumptions!$L$171:$M$200
Name DieselDemandSupply: '[1]Diesel - DemandSupply'!$C:$N
Name DieselDemandSupply: '[1]Diesel - DemandSupply'!$C:$N
Name DieselDemandSupply: '[1]Diesel - DemandSupply'!$C:$N
Name DieselDemandSupply: 'Diesel - DemandSupply'!$C:$N
Name DieselPayloads: [1]Assumptions!$L$299:$N$342
Name DieselPayloads: [1]Assumptions!$L$299:$N$342
Name DieselPayloads: [1]Assumptions!$L$299:$N$342
Name DieselPayloads: Assumptions!$L$299:$N$342
Name EskomDieselDemand: [1]Assumptions!$C$189:$H$232
Name EskomDieselDemand: [1]Assumptions!$C$189:$H$232
Name EskomDieselDemand: [1]Assumptions!$C$189:$H$232
Name EskomDieselDemand: Assumptions!$C$189:$H$232
Name EV_High_Penetration: [1]Assumptions!$E$286:$E$289
Name EV_High_Penetration: [1]Assumptions!$E$286:$E$289
Name EV_High_Penetration: [1]Assumptions!$E$286:$E$289
Name EV_High_Penetration: Assumptions!$E$286:$E$289
Name EV_Low_Penetration: [1]Assumptions!$D$286:$D$289
Name EV_Low_Penetration: [1]Assumptions!$D$286:$D$289
Name EV_Low_Penetration: [1]Assumptions!$D$286:$D$289
Name EV_Low_Penetration: Assumptions!$D$286:$D$289
Name GasolineDemandSupply: '[1]Gasoline - DemandSupply'!$C:$AB
Name GasolineDemandSupply: '[1]Gasoline - DemandSupply'!$C:$AB
Name GasolineDemandSupply: '[1]Gasoline - DemandSupply'!$C:$AB
Name GasolineDemandSupply: 'Gasoline - DemandSupply'!$C:$AB
Name GDP: [1]Assumptions!$Z$8:$AH$54
Name GDP: [1]Assumptions!$Z$8:$AH$54
Name GDP: [1]Assumptions!$Z$8:$AH$54
Name GDP: Assumptions!$Z$8:$AH$54
Name GDP_high_growth: [1]Assumptions!$C$8:$E$39
Name GDP_high_growth: [1]Assumptions!$C$8:$E$39
Name GDP_high_growth: [1]Assumptions!$C$8:$E$39
Name GDP_high_growth: Assumptions!$C$8:$E$39
Name GDP_low_growth: [1]Assumptions!$G$8:$I$39
Name GDP_low_growth: [1]Assumptions!$G$8:$I$39
Name GDP_low_growth: [1]Assumptions!$G$8:$I$39
Name GDP_low_growth: Assumptions!$G$8:$I$39
Name HighEfficiency_Improvement_Diesel: [1]Assumptions!$E$8:$E$39
Name HighEfficiency_Improvement_Diesel: [1]Assumptions!$E$8:$E$39
Name HighEfficiency_Improvement_Diesel: [1]Assumptions!$E$8:$E$39
Name HighEfficiency_Improvement_Diesel: Assumptions!$E$8:$E$39
Name HighEfficiency_Improvement_Gasoline: [1]Assumptions!$F$8:$F$39
Name HighEfficiency_Improvement_Gasoline: [1]Assumptions!$F$8:$F$39
Name HighEfficiency_Improvement_Gasoline: [1]Assumptions!$F$8:$F$39
Name HighEfficiency_Improvement_Gasoline: Assumptions!$F$8:$F$39
Name JetDemandSupply: '[1]Jet - DemandSupply'!$D:$L
Name JetDemandSupply: '[1]Jet - DemandSupply'!$D:$L
Name JetDemandSupply: '[1]Jet - DemandSupply'!$D:$L
Name JetDemandSupply: 'Jet - DemandSupply'!$D:$L
Name LoadFactor_High: Assumptions!$M$172:$M$200
Name LoadFactor_Low: Assumptions!$M$204:$M$232
Name LoadShedding_High: Assumptions!$O$236:$P$263
Name LoadShedding_Low: Assumptions!$O$266:$P$293
Name LowEfficiency_Improvement_Diesel: [1]Assumptions!$I$8:$I$39
Name LowEfficiency_Improvement_Diesel: [1]Assumptions!$I$8:$I$39

Sheet Notes
B2: Note:
B3: 1. Jet Fuel Supply and Demand:
B4: - Data ranges from 1st April to 2nd March (full calendar year) the corresponding year for the passengers and airplanes
B5: - For 2023, data ranges from March to October 2023 for the airplanes and passengers
B6: - 2023* contains annualized figures
B7: - Imports and exports data from DMRE runs upto June 2023
B8: - As per SARS, Kerosene, Jet Fuel and Aviation Fuel are classified together, but we only considered Jet Fuel and Aviation fuel in our data
B9: - Jet Fuel regression the independent variables that were found to best explain Jet Fuel demand are: GDP/Capita and Total Passenger Departures
B10: - This regression achieves a 95% R2. The coefficients for GDP per Capita and Passenger Departure Numbers are positive as expected
B11: - Regressing GDP and Passenger Depature numbers vs Jet Fuel demand gives a 93% R2, but GDP has a negative coefficient hence we opt to go for the prior model
B12: - Prior regressions will be hidden worksheets, only chosen regresson sheets will remain active
B14: 2. Gasoline Supply and Demand:
... B25: Regressions

Sheet Summary

Sheet Assumptions
C3: Source: MTBPS Wednesday, 30 October 2024 | H3: SCENARIOS AND ASSUMPTIONS | Z3: MACRO ASSUMPTIONS
C4: Chapter 2 (treasury.gov.za)
C5: (Add sheets that use these assumptions)
C7: High demand scenario | G7: Low demand scenario | Z7: Source: | AA7: StatsSA – GDP P0441 | AE7: UNDP WPP 2023 | AL7: UNDP WPP Forecasts
C8: Year | D8: Real GDP growth | E8: Efficiency Improvement Diesel | F8: Efficiency Improvement Gasoline | G8: Year | H8: Real GDP growth | I8: Efficiency Improvement Diesel | J8: Efficiency Improvement Gasoline | L8: Year | M8: IMF | N8: MTBPS 2024 | O8: MTBPS high | P8: MTBPS low | Z8: Year | AA8: GDP | AB8: GDP High | AC8: GDP Low | AD8: GDP/capita (constant 2015) | AE8: Population high | AF8: Population low | AG8: GDP/capita high | AH8: GDP/capita low | AN8: 47880595 | AO8: 1
C9: 2020 | D9: -0.064319748 | E9: 0.005 | F9: 0.01 | G9: 2020 | I9: 0.01 | J9: 0.015 | Z9: 2005 | AA9: 3.4114099e+12 | AB9: =AA9 -> 3.4114099e+12 | AC9: =AA9 -> 3.4114099e+12 | AD9: 71248.277 | AE9: =$AL9 -> 47880595 | AF9: =$AL9 -> 47880595 | AG9: =AD9 -> 71248.277 | AH9: =AD9 -> 71248.277 | AL9: 47880595 | AN9: =AN8*AO9 -> 48417875 | AO9: 1.0112213
C10: 2021 | D10: 0.049 | E10: 0.005 | F10: 0.01 | G10: 2021 | H10: 0.049 | I10: 0.01 | J10: 0.015 | L10: 2021 | M10: 0.049 | N10: 0.047 | O10: =N10 -> 0.047 | P10: =M10 -> 0.049 | Z10: 2006 | AA10: 3.6025787e+12 | AB10: =AA10 -> 3.6025787e+12 | AC10: =AA10 -> 3.6025787e+12 | AD10: 74296.113 | AE10: =$AL10 -> 48489464 | AF10: =$AL10 -> 48489464 | AG10: =AD10 -> 74296.113 | AH10: =AD10 -> 74296.113 | AL10: 48489464 | AM10: =AL10/AL9-1 -> 0.012716404 | AN10: =AN9*AO10 -> 48961185 | AO10: 1.0112213
C11: 2022 | D11: 0.019 | E11: 0.005 | F11: 0.01 | G11: 2022 | H11: 0.016 | I11: 0.01 | J11: 0.015 | L11: 2022 | M11: 0.02 | N11: 0.019 | O11: =N11+0 -> 0.019 | P11: =N11-0.003 -> 0.016 | Z11: 2007 | AA11: 3.6025787e+12 | AB11: =AA11 -> 3.6025787e+12 | AC11: =AA11 -> 3.6025787e+12 | AD11: 77274.268 | AE11: =$AL11 -> 49119766 | AF11: =$AL11 -> 49119766 | AG11: =AD11 -> 77274.268 | AH11: =AD11 -> 77274.268 | AL11: 49119766 | AM11: =AL11/AL10-1 -> 0.012998741 | AN11: =AN10*AO11 -> 49510591 | AO11: 1.0112213
C12: 2023 | D12: 0.01 | E12: 0.005 | F12: 0.01 | G12: 2023 | H12: 0.005 | I12: 0.01 | J12: 0.015 | L12: 2023 | M12: 0.001 | N12: 0.008 | O12: =N12+M12 -> 0.009 | P12: =N12-0.004 -> 0.004 | Z12: 2008 | AA12: 3.9168163e+12 | AB12: =AA12 -> 3.9168163e+12 | AC12: =AA12 -> 3.9168163e+12 | AD12: 78683.363 | AE12: =$AL12 -> 49779472 | AF12: =$AL12 -> 49779472 | AG12: =AD12 -> 78683.363 | AH12: =AD12 -> 78683.363 | AL12: 49779472 | AM12: =AL12/AL11-1 -> 0.013430561 | AN12: =AN11*AO12 -> 50066161 | AO12: 1.0112213
C13: 2024 | D13: 0.015 | E13: 0.005 | F13: 0.01 | G13: 2024 | H13: 0.015 | I13: 0.01 | J13: 0.015 | L13: 2024 | M13: 0.008 | N13: 0.011 | O13: =N13 -> 0.011 | P13: =N13/2 -> 0.0055 | Z13: 2009 | AA13: 3.8565721e+12 | AB13: =AA13 -> 3.8565721e+12 | AC13: =AA13 -> 3.8565721e+12 | AD13: 76402.543 | AE13: =$AL13 -> 50477013 | AF13: =$AL13 -> 50477013 | AG13: =AD13 -> 76402.543 | AH13: =AD13 -> 76402.543 | AL13: 50477013 | AM13: =AL13/AL12-1 -> 0.014012624 | AN13: =AN12*AO13 -> 50627967 | AO13: 1.0112213
C14: 2025 | D14: 0.017 | E14: 0.005 | F14: 0.01 | G14: 2025 | H14: 0.017 | I14: 0.01 | J14: 0.015 | L14: 2025 | M14: 0.015 | N14: 0.017 | O14: =N14 -> 0.017 | P14: =P13 -> 0.0055 | Z14: 2010 | AA14: 3.9738016e+12 | AB14: =AA14 -> 3.9738016e+12 | AC14: =AA14 -> 3.9738016e+12 | AD14: 77587.601 | AE14: =$AL14 -> 51216967 | AF14: =$AL14 -> 51216967 | AG14: =AD14 -> 77587.601 | AH14: =AD14 -> 77587.601 | AL14: 51216967 | AM14: =AL14/AL13-1 -> 0.014659227 | AN14: =AN13*AO14 -> 51196076 | AO14: 1.0112213
C15: 2026 | D15: 0.016 | E15: 0.005 | F15: 0.01 | G15: 2026 | H15: 0.01 | I15: 0.01 | J15: 0.015 | L15: 2026 | M15: 0.014 | N15: =AVERAGE($N$12:$N$14) -> 0.012 | O15: =O14 -> 0.017 | P15: =P14 -> 0.0055 | Z15: 2011 | AA15: 4.0997137e+12 | AB15: =AA15 -> 4.0997137e+12 | AC15: =AA15 -> 4.0997137e+12 | AD15: 78834.95 | AE15: =$AL15 -> 52003759 | AF15: =$AL15 -> 52003759 | AG15: =AD15 -> 78834.95 | AH15: =AD15 -> 78834.95 | AL15: 52003759 | AM15: =AL15/AL14-1 -> 0.015361941 | AN15: =AN14*AO15 -> 52023040 | AO15: 1.0161529
C16: 2027 | D16: =D15 -> 0.016 | E16: 0.005 | F16: 0.01 | G16: 2027 | H16: 0.01 | I16: 0.01 | J16: 0.015 | L16: 2027 | M16: 0.014 | N16: =AVERAGE($N$12:$N$14) -> 0.012 | O16: =O15 -> 0.017 | P16: =P15 -> 0.0055 | Z16: 2012 | AA16: 4.1979524e+12 | AB16: =AA16 -> 4.1979524e+12 | AC16: =AA16 -> 4.1979524e+12 | AD16: 79457.527 | AE16: =$AL16 -> 52832659 | AF16: =$AL16 -> 52832659 | AG16: =AD16 -> 79457.527 | AH16: =AD16 -> 79457.527 | AL16: 52832659 | AM16: =AL16/AL15-1 -> 0.015939232 | AN16: =AN15*AO16 -> 52863361 | AO16: 1.0161529
C17: 2028 | D17: =D16 -> 0.016 | E17: 0.005 | F17: 0.01 | G17: 2028 | H17: 0.01 | I17: 0.01 | J17: 0.015 | L17: 2028 | M17: 0.014 | N17: =AVERAGE($N$12:$N$14) -> 0.012 | O17: =O16 -> 0.017 | P17: =P16 -> 0.0055 | Z17: 2013 | AA17: 4.3022912e+12 | AB17: =AA17 -> 4.3022912e+12 | AC17: =AA17 -> 4.3022912e+12 | AD17: 80136.367 | AE17: =$AL17 -> 53687125 | AF17: =$AL17 -> 53687125 | AG17: =AD17 -> 80136.367 | AH17: =AD17 -> 80136.367 | AL17: 53687125 | AM17: =AL17/AL16-1 -> 0.016173064 | AN17: =AN16*AO17 -> 53717257 | AO17: 1.0161529
C18: 2029 | D18: =D17 -> 0.016 | E18: 0.005 | F18: 0.01 | G18: 2029 | H18: 0.01 | I18: 0.01 | J18: 0.015 | L18: 2029 | M18: 0.013 | N18: =AVERAGE($N$12:$N$14) -> 0.012 | O18: =O17 -> 0.017 | P18: =P17 -> 0.0055 | Z18: 2014 | AA18: 4.3631181e+12 | AB18: =AA18 -> 4.3631181e+12 | AC18: =AA18 -> 4.3631181e+12 | AD18: 79992.362 | AE18: =$AL18 -> 54544184 | AF18: =$AL18 -> 54544184 | AG18: =AD18 -> 79992.362 | AH18: =AD18 -> 79992.362 | AL18: 54544184 | AM18: =AL18/AL17-1 -> 0.015963958 | AN18: =AN17*AO18 -> 54584945 | AO18: 1.0161529
C19: 2030 | D19: =D18 -> 0.016 | E19: 0.005 | F19: 0.01 | G19: 2030 | H19: 0.01 | I19: 0.01 | J19: 0.015 | L19: 2030 | M19: 0.013 | N19: =AVERAGE($N$12:$N$14) -> 0.012 | O19: =O18 -> 0.017 | P19: =P18 -> 0.0055 | Z19: 2015 | AA19: 4.4207925e+12 | AB19: =AA19 -> 4.4207925e+12 | AC19: =AA19 -> 4.4207925e+12 | AD19: 79117.2 | AE19: =$AL19 -> 55876504 | AF19: =$AL19 -> 55876504 | AG19: =AD19 -> 79117.2 | AH19: =AD19 -> 79117.2 | AL19: 55876504 | AM19: =AL19/AL18-1 -> 0.024426436 | AN19: =AN18*AO19 -> 55466649 | AO19: 1.0161529
C20: 2031 | D20: =D19 -> 0.016 | E20: 0.005 | F20: 0.01 | G20: 2031 | H20: 0.01 | I20: 0.01 | J20: 0.015 | L20: 2031 | M20: =M19 -> 0.013 | N20: =AVERAGE($N$12:$N$14) -> 0.012 | O20: =O19 -> 0.017 | P20: =P19 -> 0.0055 | Z20: 2016 | AA20: 4.450171e+12 | AB20: =AA20 -> 4.450171e+12 | AC20: =AA20 -> 4.450171e+12 | AD20: 78872.592 | AE20: =$AL20 -> 56422274 | AF20: =$AL20 -> 56422274 | AG20: =AD20 -> 78872.592 | AH20: =AD20 -> 78872.592 | AL20: 56422274 | AM20: =AL20/AL19-1 -> 0.0097674328 | AN20: =AN19*AO20 -> 56362595 | AO20: 1.0161529
C21: 2032 | D21: =D20 -> 0.016 | E21: 0.005 | F21: 0.01 | G21: 2032 | H21: 0.01 | I21: 0.01 | J21: 0.015 | L21: 2032 | M21: =M20 -> 0.013 | N21: =AVERAGE($N$12:$N$14) -> 0.012 | O21: =O20 -> 0.017 | P21: =P20 -> 0.0055 | Z21: 2017 | AA21: 4.5017016e+12 | AB21: =AA21 -> 4.5017016e+12 | AC21: =AA21 -> 4.5017016e+12 | AD21: 79477.497 | AE21: =$AL21 -> 56641210 | AF21: =$AL21 -> 56641210 | AG21: =AD21 -> 79477.497 | AH21: =AD21 -> 79477.497 | AL21: 56641210 | AM21: =AL21/AL20-1 -> 0.0038803115 | AN21: =AN20*AO21 -> 57273013 | AO21: 1.0161529
C22: 2033 | D22: =D21 -> 0.016 | E22: 0.005 | F22: 0.01 | G22: 2033 | H22: 0.01 | I22: 0.01 | J22: 0.015 | L22: 2033 | M22: =M21 -> 0.013 | N22: =AVERAGE($N$12:$N$14) -> 0.012 | O22: =O21 -> 0.017 | P22: =P21 -> 0.0055 | Z22: 2018 | AA22: 4.5686697e+12 | AB22: =AA22 -> 4.5686697e+12 | AC22: =AA22 -> 4.5686697e+12 | AD22: 79677.342 | AE22: =$AL22 -> 57339635 | AF22: =$AL22 -> 57339635 | AG22: =AD22 -> 79677.342 | AH22: =AD22 -> 79677.342 | AL22: 57339635 | AM22: =AL22/AL21-1 -> 0.012330686 | AN22: =AN21*AO22 -> 58198137 | AO22: 1.0161529
C23: 2034 | D23: =D22 -> 0.016 | E23: 0.005 | F23: 0.01 | G23: 2034 | H23: 0.01 | I23: 0.01 | J23: 0.015 | L23: 2034 | M23: =M22 -> 0.013 | N23: =AVERAGE($N$12:$N$14) -> 0.012 | O23: =O22 -> 0.017 | P23: =P22 -> 0.0055 | Z23: 2019 | AA23: 4.5738348e+12 | AB23: =AA23 -> 4.5738348e+12 | AC23: =AA23 -> 4.5738348e+12 | AD23: 78741.034 | AE23: =$AL23 -> 58087055 | AF23: =$AL23 -> 58087055 | AG23: =AD23 -> 78741.034 | AH23: =AD23 -> 78741.034 | AL23: 58087055 | AM23: =AL23/AL22-1 -> 0.013034963 | AN23: =AN22*AO23 -> 59138204 | AO23: 1.0161529
C24: 2035 | D24: =D23 -> 0.016 | E24: 0.005 | F24: 0.01 | G24: 2035 | H24: 0.01 | I24: 0.01 | J24: 0.015 | L24: 2035 | M24: =M23 -> 0.013 | N24: =AVERAGE($N$12:$N$14) -> 0.012 | O24: =O23 -> 0.017 | P24: =P23 -> 0.0055 | Z24: 2020 | AA24: 4.2796469e+12 | AB24: =AA24 -> 4.2796469e+12 | AC24: =AA24 -> 4.2796469e+12 | AD24: 72780.725 | AE24: =$AL24 -> 58801927 | AF24: =$AL24 -> 58801927 | AG24: =AD24 -> 72780.725 | AH24: =AD24 -> 72780.725 | AL24: 58801927 | AM24: =AL24/AL23-1 -> 0.012306907 | AN24: =AN23*AO24 -> 60093456 | AO24: 1.0161529
C25: 2036 | D25: =D24 -> 0.016 | E25: 0.005 | F25: 0.01 | G25: 2036 | H25: 0.01 | I25: 0.01 | J25: 0.015 | L25: 2036 | M25: =M24 -> 0.013 | N25: =AVERAGE($N$12:$N$14) -> 0.012 | O25: =O24 -> 0.017 | P25: =P24 -> 0.0055 | Z25: 2021 | AA25: 4.5130439e+12 | AB25: =AA25 -> 4.5130439e+12 | AC25: =AA25 -> 4.5130439e+12 | AD25: 75987.078 | AE25: =$AL25 -> 59392255 | AF25: =$AL25 -> 59392255 | AG25: =AD25 -> 75987.078 | AH25: =AD25 -> 75987.078 | AL25: 59392255 | AM25: =AL25/AL24-1 -> 0.010039263 | AN25: =AN24*AO25 -> 61064139 | AO25: 1.0161529
C26: 2037 | D26: =D25 -> 0.016 | E26: 0.005 | F26: 0.01 | G26: 2037 | H26: 0.01 | I26: 0.01 | J26: 0.015 | L26: 2037 | M26: =M25 -> 0.013 | N26: =AVERAGE($N$12:$N$14) -> 0.012 | O26: =O25 -> 0.017 | P26: =P25 -> 0.0055 | Z26: 2022 | AA26: 4.5992614e+12 | AB26: =AA26 -> 4.5992614e+12 | AC26: =AA26 -> 4.5992614e+12 | AD26: 76790.165 | AE26: =$AL26 -> 59893886 | AF26: =$AL26 -> 59893886 | AG26: =AD26 -> 76790.165 | AH26: =AD26 -> 76790.165 | AL26: 59893886 | AM26: =AL26/AL25-1 -> 0.0084460676 | AN26: =AN25*AO26 -> 62050500 | AO26: 1.0161529
C27: 2038 | D27: =D26 -> 0.016 | E27: 0.005 | F27: 0.01 | G27: 2038 | H27: 0.01 | I27: 0.01 | J27: 0.015 | L27: 2038 | M27: =M26 -> 0.013 | N27: =AVERAGE($N$12:$N$14) -> 0.012 | O27: =O26 -> 0.017 | P27: =P26 -> 0.0055 | Z27: 2023 | AA27: 4.6384996e+12 | AB27: =AA27 -> 4.6384996e+12 | AC27: =AA27 -> 4.6384996e+12 | AD27: 76777.926 | AE27: =$AL27 -> 60414495 | AF27: =$AL27 -> 60414495 | AG27: =AD27 -> 76777.926 | AH27: =AD27 -> 76777.926 | AL27: 60414495 | AM27: =AL27/AL26-1 -> 0.0086921894 | AN27: =AN26*AO27 -> 63052794 | AO27: 1.0161529
C28: 2039 | D28: =D27 -> 0.016 | E28: 0.005 | F28: 0.01 | G28: 2039 | H28: 0.01 | I28: 0.01 | J28: 0.015 | L28: 2039 | M28: =M27 -> 0.013 | N28: =AVERAGE($N$12:$N$14) -> 0.012 | O28: =O27 -> 0.017 | P28: =P27 -> 0.0055 | Z28: 2024 | AA28: 4659294000000 | AB28: 4659294000000 | AC28: 4659294000000 | AD28: =AG28 -> 76356.557 | AE28: =$AL28 -> 61020221 | AF28: =$AL28 -> 61020221 | AG28: =AB28/AE28 -> 76356.557 | AH28: =AC28/AF28 -> 76356.557 | AL28: 61020221 | AM28: =AL28/AL27-1 -> 0.01002617 | AN28: =AN27*AO28 -> 64071278 | AO28: 1.0161529
C29: 2040 | D29: =D28 -> 0.016 | E29: 0.005 | F29: 0.01 | G29: 2040 | H29: 0.01 | I29: 0.01 | J29: 0.015 | L29: 2040 | M29: =M28 -> 0.013 | N29: =AVERAGE($N$12:$N$14) -> 0.012 | O29: =O28 -> 0.017 | P29: =P28 -> 0.0055 | Z29: 2025 | AA29: 4679355000000 | AB29: 4679355000000 | AC29: 4679355000000 | AD29: =AG29 -> 75873.54 | AE29: =$AL29 -> 61673081 | AF29: =$AL29 -> 61673081 | AG29: =AB29/AE29 -> 75873.54 | AH29: =AC29/AF29 -> 75873.54 | AL29: 61673081 | AM29: =AL29/AL28-1 -> 0.010699076 | AN29: =AN28*AO29 -> 65106214 | AO29: 1.0161529
C30: 2041 | D30: =D29 -> 0.016 | E30: 0.005 | F30: 0.01 | G30: 2041 | H30: 0.01 | I30: 0.01 | J30: 0.015 | L30: 2041 | M30: =M29 -> 0.013 | N30: =AVERAGE($N$12:$N$14) -> 0.012 | O30: =O29 -> 0.017 | P30: =P29 -> 0.0055 | Z30: 2026 | AB30: =$AB29*(VLOOKUP($Z30,GDP_high_growth,2,0)+1) -> 4754224680000 | AC30: =$AC29*(VLOOKUP($Z30,GDP_low_growth,2,0)+1) -> 4726148550000 | AD30: =AG30 -> 76305.621 | AE30: =$AL30 -> 62305039 | AF30: =$AL30 -> 62305039 | AG30: =AB30/AE30 -> 76305.621 | AH30: =AC30/AF30 -> 75854.997 | AL30: 62305039 | AM30: =AL30/AL29-1 -> 0.010246902 | AN30: =AN29*AO30 -> 66157866 | AO30: 1.0161529
C31: 2042 | D31: =D30 -> 0.016 | E31: 0.005 | F31: 0.01 | G31: 2042 | H31: 0.01 | I31: 0.01 | J31: 0.015 | L31: 2042 | M31: =M30 -> 0.013 | N31: =AVERAGE($N$12:$N$14) -> 0.012 | O31: =O30 -> 0.017 | P31: =P30 -> 0.0055 | Z31: 2027 | AB31: =$AB30*(VLOOKUP($Z31,GDP_high_growth,2,0)+1) -> 4830292274880 | AC31: =$AC30*(VLOOKUP($Z31,GDP_low_growth,2,0)+1) -> 4773410035500 | AD31: =AG31 -> 76770.113 | AE31: =$AL31 -> 62918916 | AF31: =$AL31 -> 62918916 | AG31: =AB31/AE31 -> 76770.113 | AH31: =AC31/AF31 -> 75866.056 | AL31: 62918916 | AM31: =AL31/AL30-1 -> 0.0098527665 | AN31: =AN30*AO31 -> 67226506 | AO31: 1.0161529
C32: 2043 | D32: =D31 -> 0.016 | E32: 0.005 | F32: 0.01 | G32: 2043 | H32: 0.01 | I32: 0.01 | J32: 0.015 | L32: 2043 | M32: =M31 -> 0.013 | N32: =AVERAGE($N$12:$N$14) -> 0.012 | O32: =O31 -> 0.017 | P32: =P31 -> 0.0055 | Z32: 2028 | AB32: =$AB31*(VLOOKUP($Z32,GDP_high_growth,2,0)+1) -> 4.907577e+12 | AC32: =$AC31*(VLOOKUP($Z32,GDP_low_growth,2,0)+1) -> 4821144135855 | AD32: =AG32 -> 77267.03 | AE32: =$AL32 -> 63514502 | AF32: =$AL32 -> 63514502 | AG32: =AB32/AE32 -> 77267.03 | AH32: =AC32/AF32 -> 75906.194 | AL32: 63514502 | AM32: =AL32/AL31-1 -> 0.0094659291 | AN32: =AN31*AO32 -> 68312408 | AO32: 1.0161529
C33: 2044 | D33: =D32 -> 0.016 | E33: 0.005 | F33: 0.01 | G33: 2044 | H33: 0.01 | I33: 0.01 | J33: 0.015 | L33: 2044 | M33: =M32 -> 0.013 | N33: =AVERAGE($N$12:$N$14) -> 0.012 | O33: =O32 -> 0.017 | P33: =P32 -> 0.0055 | Z33: 2029 | AB33: =$AB32*(VLOOKUP($Z33,GDP_high_growth,2,0)+1) -> 4.9860982e+12 | AC33: =$AC32*(VLOOKUP($Z33,GDP_low_growth,2,0)+1) -> 4.8693556e+12 | AD33: =AG33 -> 77793.85 | AE33: =$AL33 -> 64093732 | AF33: =$AL33 -> 64093732 | AG33: =AB33/AE33 -> 77793.85 | AH33: =AC33/AF33 -> 75972.415 | AL33: 64093732 | AM33: =AL33/AL32-1 -> 0.0091196496 | AN33: =AN32*AO33 -> 69415850 | AO33: 1.0161529
C34: 2045 | D34: =D33 -> 0.016 | E34: 0.005 | F34: 0.01 | G34: 2045 | H34: 0.01 | I34: 0.01 | J34: 0.015 | L34: 2045 | M34: =M33 -> 0.013 | N34: =AVERAGE($N$12:$N$14) -> 0.012 | O34: =O33 -> 0.017 | P34: =P33 -> 0.0055 | Z34: 2030 | AB34: =$AB33*(VLOOKUP($Z34,GDP_high_growth,2,0)+1) -> 5.0658758e+12 | AC34: =$AC33*(VLOOKUP($Z34,GDP_low_growth,2,0)+1) -> 4.9180491e+12 | AD34: =AG34 -> 78347.237 | AE34: =$AL34 -> 64659278 | AF34: =$AL34 -> 64659278 | AG34: =AB34/AE34 -> 78347.237 | AH34: =AC34/AF34 -> 76060.997 | AL34: 64659278 | AM34: =AL34/AL33-1 -> 0.0088237333 | AN34: =AN33*AO34 -> 70537115 | AO34: 1.0161529
C35: 2046 | D35: =D34 -> 0.016 | E35: 0.005 | F35: 0.01 | G35: 2046 | H35: 0.01 | I35: 0.01 | J35: 0.015 | L35: 2046 | M35: =M34 -> 0.013 | N35: =AVERAGE($N$12:$N$14) -> 0.012 | O35: =O34 -> 0.017 | P35: =P34 -> 0.0055 | Z35: 2031 | AB35: =$AB34*(VLOOKUP($Z35,GDP_high_growth,2,0)+1) -> 5.1469298e+12 | AC35: =$AC34*(VLOOKUP($Z35,GDP_low_growth,2,0)+1) -> 4.9672296e+12 | AD35: =AG35 -> 78904.56 | AE35: =$AL35 -> 65229814 | AF35: =$AL35 -> 65229814 | AG35: =AB35/AE35 -> 78904.56 | AH35: =AC35/AF35 -> 76149.682 | AL35: =AL34*(1+AM34) -> 65229814 | AM35: =AL35/AL34-1 -> 0.0088237333 | AN35: =AN34*AO35 -> 71676493 | AO35: 1.0161529
C36: 2047 | D36: =D35 -> 0.016 | E36: 0.005 | F36: 0.01 | G36: 2047 | H36: 0.01 | I36: 0.01 | J36: 0.015 | L36: 2047 | M36: =M35 -> 0.013 | N36: =AVERAGE($N$12:$N$14) -> 0.012 | O36: =O35 -> 0.017 | P36: =P35 -> 0.0055 | Z36: 2032 | AB36: =$AB35*(VLOOKUP($Z36,GDP_high_growth,2,0)+1) -> 5.2292806e+12 | AC36: =$AC35*(VLOOKUP($Z36,GDP_low_growth,2,0)+1) -> 5.0169019e+12 | AD36: =AG36 -> 79465.847 | AE36: =$AL36 -> 65805385 | AF36: =$AL36 -> 65805385 | AG36: =AB36/AE36 -> 79465.847 | AH36: =AC36/AF36 -> 76238.471 | AL36: =AL35*(1+AM35) -> 65805385 | AM36: =AL36/AL35-1 -> 0.0088237333 | AN36: =AN35*AO36 -> 72834274 | AO36: 1.0161529
C37: 2048 | D37: =D36 -> 0.016 | E37: 0.005 | F37: 0.01 | G37: 2048 | H37: 0.01 | I37: 0.01 | J37: 0.015 | L37: 2048 | M37: =M36 -> 0.013 | N37: =AVERAGE($N$12:$N$14) -> 0.012 | O37: =O36 -> 0.017 | P37: =P36 -> 0.0055 | Z37: 2033 | AB37: =$AB36*(VLOOKUP($Z37,GDP_high_growth,2,0)+1) -> 5.3129491e+12 | AC37: =$AC36*(VLOOKUP($Z37,GDP_low_growth,2,0)+1) -> 5.0670709e+12 | AD37: =AG37 -> 80031.127 | AE37: =$AL37 -> 66386034 | AF37: =$AL37 -> 66386034 | AG37: =AB37/AE37 -> 80031.127 | AH37: =AC37/AF37 -> 76327.364 | AL37: =AL36*(1+AM36) -> 66386034 | AM37: =AL37/AL36-1 -> 0.0088237333 | AN37: =AN36*AO37 -> 74010757 | AO37: 1.0161529
C38: 2049 | D38: =D37 -> 0.016 | E38: 0.005 | F38: 0.01 | G38: 2049 | H38: 0.01 | I38: 0.01 | J38: 0.015 | L38: 2049 | M38: =M37 -> 0.013 | N38: =AVERAGE($N$12:$N$14) -> 0.012 | O38: =O37 -> 0.017 | P38: =P37 -> 0.0055 | Z38: 2034 | AB38: =$AB37*(VLOOKUP($Z38,GDP_high_growth,2,0)+1) -> 5.3979563e+12 | AC38: =$AC37*(VLOOKUP($Z38,GDP_low_growth,2,0)+1) -> 5.1177416e+12 | AD38: =AG38 -> 80600.429 | AE38: =$AL38 -> 66971807 | AF38: =$AL38 -> 66971807 | AG38: =AB38/AE38 -> 80600.429 | AH38: =AC38/AF38 -> 76416.36 | AL38: =AL37*(1+AM37) -> 66971807 | AM38: =AL38/AL37-1 -> 0.0088237333 | AN38: =AN37*AO38 -> 75206244 | AO38: 1.0161529
C39: 2050 | D39: =D38 -> 0.016 | E39: 0.005 | F39: 0.01 | G39: 2050 | H39: 0.01 | I39: 0.01 | J39: 0.015 | L39: 2050 | M39: =M38 -> 0.013 | N39: =AVERAGE($N$12:$N$14) -> 0.012 | O39: =O38 -> 0.017 | P39: =P38 -> 0.0055 | Z39: 2035 | AB39: =$AB38*(VLOOKUP($Z39,GDP_high_growth,2,0)+1) -> 5.4843236e+12 | AC39: =$AC38*(VLOOKUP($Z39,GDP_low_growth,2,0)+1) -> 5.1689191e+12 | AD39: =AG39 -> 81173.78 | AE39: =$AL39 -> 67562748 | AF39: =$AL39 -> 67562748 | AG39: =AB39/AE39 -> 81173.78 | AH39: =AC39/AF39 -> 76505.459 | AL39: =AL38*(1+AM38) -> 67562748 | AM39: =AL39/AL38-1 -> 0.0088237333 | AN39: =AN38*AO39 -> 76421041 | AO39: 1.0161529
Z40: 2036 | AB40: =$AB39*(VLOOKUP($Z40,GDP_high_growth,2,0)+1) -> 5.5720728e+12 | AC40: =$AC39*(VLOOKUP($Z40,GDP_low_growth,2,0)+1) -> 5.2206083e+12 | AD40: =AG40 -> 81751.209 | AE40: =$AL40 -> 68158904 | AF40: =$AL40 -> 68158904 | AG40: =AB40/AE40 -> 81751.209 | AH40: =AC40/AF40 -> 76594.663 | AL40: =AL39*(1+AM39) -> 68158904 | AM40: =AL40/AL39-1 -> 0.0088237333 | AN40: =AN39*AO40 -> 77655461 | AO40: 1.0161529
Z41: 2037 | AB41: =$AB40*(VLOOKUP($Z41,GDP_high_growth,2,0)+1) -> 5.661226e+12 | AC41: =$AC40*(VLOOKUP($Z41,GDP_low_growth,2,0)+1) -> 5.2728143e+12 | AD41: =AG41 -> 82332.747 | AE41: =$AL41 -> 68760320 | AF41: =$AL41 -> 68760320 | AG41: =AB41/AE41 -> 82332.747 | AH41: =AC41/AF41 -> 76683.971 | AL41: =AL40*(1+AM40) -> 68760320 | AM41: =AL41/AL40-1 -> 0.0088237333 | AN41: =AN40*AO41 -> 78909820 | AO41: 1.0161529
Z42: 2038 | AB42: =$AB41*(VLOOKUP($Z42,GDP_high_growth,2,0)+1) -> 5.7518056e+12 | AC42: =$AC41*(VLOOKUP($Z42,GDP_low_growth,2,0)+1) -> 5.3255425e+12 | AD42: =AG42 -> 82918.42 | AE42: =$AL42 -> 69367042 | AF42: =$AL42 -> 69367042 | AG42: =AB42/AE42 -> 82918.42 | AH42: =AC42/AF42 -> 76773.383 | AL42: =AL41*(1+AM41) -> 69367042 | AM42: =AL42/AL41-1 -> 0.0088237333 | AN42: =AN41*AO42 -> 80184440 | AO42: 1.0161529
C43: Data Sheet Lists | Z43: 2039 | AB43: =$AB42*(VLOOKUP($Z43,GDP_high_growth,2,0)+1) -> 5.8438345e+12 | AC43: =$AC42*(VLOOKUP($Z43,GDP_low_growth,2,0)+1) -> 5.3787979e+12 | AD43: =AG43 -> 83508.261 | AE43: =$AL43 -> 69979119 | AF43: =$AL43 -> 69979119 | AG43: =AB43/AE43 -> 83508.261 | AH43: =AC43/AF43 -> 76862.899 | AL43: =AL42*(1+AM42) -> 69979119 | AM43: =AL43/AL42-1 -> 0.0088237333 | AN43: =AN42*AO43 -> 81479650 | AO43: 1.0161529
C44: Arrivals_Ap | E44: Airplane arrivals | H44: Specified Market Demand | J44: RSA Demand Vol | L44: RSA incl. OSP Demand/#Vehicles | N44: Total | Z44: 2040 | AB44: =$AB43*(VLOOKUP($Z44,GDP_high_growth,2,0)+1) -> 5.9373358e+12 | AC44: =$AC43*(VLOOKUP($Z44,GDP_low_growth,2,0)+1) -> 5.4325859e+12 | AD44: =AG44 -> 84102.296 | AE44: =$AL44 -> 70596596 | AF44: =$AL44 -> 70596596 | AG44: =AB44/AE44 -> 84102.296 | AH44: =AC44/AF44 -> 76952.519 | AL44: =AL43*(1+AM43) -> 70596596 | AM44: =AL44/AL43-1 -> 0.0088237333 | AN44: =AN43*AO44 -> 82795781 | AO44: 1.0161529
C45: Arrivals_Pass | E45: Passenger arrivals | H45: RSA Demand | J45: Specified Market Vol | L45: Specified Market incl. OSP Demand/#Vehicles | N45: Domestic | Z45: 2041 | AB45: =$AB44*(VLOOKUP($Z45,GDP_high_growth,2,0)+1) -> 6.0323332e+12 | AC45: =$AC44*(VLOOKUP($Z45,GDP_low_growth,2,0)+1) -> 5.4869117e+12 | AD45: =AG45 -> 84700.558 | AE45: =$AL45 -> 71219521 | AF45: =$AL45 -> 71219521 | AG45: =AB45/AE45 -> 84700.558 | AH45: =AC45/AF45 -> 77042.244 | AL45: =AL44*(1+AM44) -> 71219521 | AM45: =AL45/AL44-1 -> 0.0088237333 | AN45: =AN44*AO45 -> 84133171 | AO45: 1.0161529
C46: Departures_AP | E46: Airplane departures | H46: RSA Demand (excluding Power Gen) | J46: Trucks (HGVs) | L46: RSA excl. OSP Demand/#Vehicles | N46: International | Z46: 2042 | AB46: =$AB45*(VLOOKUP($Z46,GDP_high_growth,2,0)+1) -> 6.1288505e+12 | AC46: =$AC45*(VLOOKUP($Z46,GDP_low_growth,2,0)+1) -> 5.5417809e+12 | AD46: =AG46 -> 85303.075 | AE46: =$AL46 -> 71847943 | AF46: =$AL46 -> 71847943 | AG46: =AB46/AE46 -> 85303.075 | AH46: =AC46/AF46 -> 77132.074 | AL46: =AL45*(1+AM45) -> 71847943 | AM46: =AL46/AL45-1 -> 0.0088237333 | AN46: =AN45*AO46 -> 85492163 | AO46: 1.0161529
C47: Departures_Pass | E47: Passenger departures | H47: Specified Market Demand (excluding Power Gen) | L47: Specified Market excl. OSP Demand/#Vehicles | N47: Regional | Z47: 2043 | AB47: =$AB46*(VLOOKUP($Z47,GDP_high_growth,2,0)+1) -> 6.2269121e+12 | AC47: =$AC46*(VLOOKUP($Z47,GDP_low_growth,2,0)+1) -> 5.5971987e+12 | AD47: =AG47 -> 85909.879 | AE47: =$AL47 -> 72481910 | AF47: =$AL47 -> 72481910 | AG47: =AB47/AE47 -> 85909.879 | AH47: =AC47/AF47 -> 77222.008 | AL47: =AL46*(1+AM46) -> 72481910 | AM47: =AL47/AL46-1 -> 0.0088237333 | AN47: =AN46*AO47 -> 86873108 | AO47: 1.0161529
N48: Unscheduled | Z48: 2044 | AB48: =$AB47*(VLOOKUP($Z48,GDP_high_growth,2,0)+1) -> 6.3265427e+12 | AC48: =$AC47*(VLOOKUP($Z48,GDP_low_growth,2,0)+1) -> 5.6531707e+12 | AD48: =AG48 -> 86520.999 | AE48: =$AL48 -> 73121471 | AF48: =$AL48 -> 73121471 | AG48: =AB48/AE48 -> 86520.999 | AH48: =AC48/AF48 -> 77312.047 | AL48: =AL47*(1+AM47) -> 73121471 | AM48: =AL48/AL47-1 -> 0.0088237333 | AN48: =AN47*AO48 -> 88276358 | AO48: 1.0161529
Z49: 2045 | AB49: =$AB48*(VLOOKUP($Z49,GDP_high_growth,2,0)+1) -> 6.4277674e+12 | AC49: =$AC48*(VLOOKUP($Z49,GDP_low_growth,2,0)+1) -> 5.7097024e+12 | AD49: =AG49 -> 87136.466 | AE49: =$AL49 -> 73766676 | AF49: =$AL49 -> 73766676 | AG49: =AB49/AE49 -> 87136.466 | AH49: =AC49/AF49 -> 77402.192 | AL49: =AL48*(1+AM48) -> 73766676 | AM49: =AL49/AL48-1 -> 0.0088237333 | AN49: =AN48*AO49 -> 89702275 | AO49: 1.0161529
C50: Source: | D50: Base Scenario - ACSA Stakeholder Engagement Report April 2023 | Z50: 2046 | AB50: =$AB49*(VLOOKUP($Z50,GDP_high_growth,2,0)+1) -> 6.5306117e+12 | AC50: =$AC49*(VLOOKUP($Z50,GDP_low_growth,2,0)+1) -> 5.7667994e+12 | AD50: =AG50 -> 87756.311 | AE50: =$AL50 -> 74417573 | AF50: =$AL50 -> 74417573 | AG50: =AB50/AE50 -> 87756.311 | AH50: =AC50/AF50 -> 77492.441 | AL50: =AL49*(1+AM49) -> 74417573 | AM50: =AL50/AL49-1 -> 0.0088237333 | AN50: =AN49*AO50 -> 91151225 | AO50: 1.0161529
C51: Source: | D51: High and Low Scenarios - the Importance of Air Transport to South Africa - IATA | Z51: 2047 | AB51: =$AB50*(VLOOKUP($Z51,GDP_high_growth,2,0)+1) -> 6.6351015e+12 | AC51: =$AC50*(VLOOKUP($Z51,GDP_low_growth,2,0)+1) -> 5.8244674e+12 | AD51: =AG51 -> 88380.565 | AE51: =$AL51 -> 75074214 | AF51: =$AL51 -> 75074214 | AG51: =AB51/AE51 -> 88380.565 | AH51: =AC51/AF51 -> 77582.795 | AL51: =AL50*(1+AM50) -> 75074214 | AM51: =AL51/AL50-1 -> 0.0088237333 | AN51: =AN50*AO51 -> 92623580 | AO51: 1.0161529
Z52: 2048 | AB52: =$AB51*(VLOOKUP($Z52,GDP_high_growth,2,0)+1) -> 6.7412631e+12 | AC52: =$AC51*(VLOOKUP($Z52,GDP_low_growth,2,0)+1) -> 5.8827121e+12 | AD52: =AG52 -> 89009.26 | AE52: =$AL52 -> 75736649 | AF52: =$AL52 -> 75736649 | AG52: =AB52/AE52 -> 89009.26 | AH52: =AC52/AF52 -> 77673.255 | AL52: =AL51*(1+AM51) -> 75736649 | AM52: =AL52/AL51-1 -> 0.0088237333 | AN52: =AN51*AO52 -> 94119717 | AO52: 1.0161529
C53: High demand scenario | G53: Low demand scenario | Z53: 2049 | AB53: =$AB52*(VLOOKUP($Z53,GDP_high_growth,2,0)+1) -> 6.8491233e+12 | AC53: =$AC52*(VLOOKUP($Z53,GDP_low_growth,2,0)+1) -> 5.9415392e+12 | AD53: =AG53 -> 89642.428 | AE53: =$AL53 -> 76404929 | AF53: =$AL53 -> 76404929 | AG53: =AB53/AE53 -> 89642.428 | AH53: =AC53/AF53 -> 77763.821 | AL53: =AL52*(1+AM52) -> 76404929 | AM53: =AL53/AL52-1 -> 0.0088237333 | AN53: =AN52*AO53 -> 95640021 | AO53: 1.0161529
C54: Year | D54: GDP_per_Capita Growth | E54: Passenger Growth | G54: Year | H54: GDP_per_Capita Growth | I54: Passenger Growth | L54: Year | M54: ACSA Pax Base | N54: Growth Base | O54: IATA Pax High | P54: Growth High | Q54: IATA Pax Low | R54: Growth Low | S54: GDP_per_Capita Growth High | T54: GDP_per_Capita Growth Low | Z54: 2050 | AB54: =$AB53*(VLOOKUP($Z54,GDP_high_growth,2,0)+1) -> 6.9587093e+12 | AC54: =$AC53*(VLOOKUP($Z54,GDP_low_growth,2,0)+1) -> 6.0009546e+12 | AD54: =AG54 -> 90280.099 | AE54: =$AL54 -> 77079106 | AF54: =$AL54 -> 77079106 | AG54: =AB54/AE54 -> 90280.099 | AH54: =AC54/AF54 -> 77854.491 | AL54: =AL53*(1+AM53) -> 77079106 | AM54: =AL54/AL53-1 -> 0.0088237333 | AN54: =AN53*AO54 -> 97184883 | AO54: 1.0161529
C55: 2020 | G55: 2020 | L55: 2020 | M55: 21000000 | O55: 21000000 | Q55: 21000000
C56: 2021 | D56: =AG25/AG24-1 -> 0.044054981 | E56: =P56 -> -0.76190476 | G56: 2021 | H56: =AH25/AH24-1 -> 0.044054981 | I56: =R56 -> -0.76190476 | L56: 2021 | M56: 5000000 | N56: -0.76190476 | O56: 5000000 | P56: -0.76190476 | Q56: 5000000 | R56: -0.76190476
C57: 2022 | D57: =AG26/AG25-1 -> 0.01056873 | E57: =P57 -> 1.2 | G57: 2022 | H57: =AH26/AH25-1 -> 0.01056873 | I57: =R57 -> 1.2 | L57: 2022 | M57: 11000000 | N57: 1.2 | O57: 11000000 | P57: 1.2 | Q57: 11000000 | R57: 1.2
C58: 2023 | D58: =AG27/AG26-1 -> -0.00015937981 | E58: =P58 -> 0.45454545 | G58: 2023 | H58: =AH27/AH26-1 -> -0.00015937981 | I58: =R58 -> 0.45454545 | L58: 2023 | M58: 16000000 | N58: 0.45454545 | O58: 16000000 | P58: 0.45454545 | Q58: 16000000 | R58: 0.45454545 | AF58: GDP | AG58: Pop High | AH58: Pop Low
C59: 2024 | D59: =AG28/AG27-1 -> -0.005488152 | E59: =P59 -> 0.0625 | G59: 2024 | H59: =AH28/AH27-1 -> -0.005488152 | I59: =R59 -> 0.0625 | L59: 2024 | M59: 17000000 | N59: 0.0625 | O59: =O58*(1+P59) -> 17000000 | P59: 0.0625 | Q59: =Q58*(1+R59) -> 17000000 | R59: 0.0625 | AF59: =VLOOKUP($Z28,GDP_high_growth,2,0) -> 0.015 | AG59: =AE27/AE26-1 -> 0.0086921894 | AH59: =AF27/AF26-1 -> 0.0086921894
C60: 2025 | D60: =AG29/AG28-1 -> -0.0063258081 | E60: =P60 -> 0.11764706 | G60: 2025 | H60: =AH29/AH28-1 -> -0.0063258081 | I60: =R60 -> 0.11764706 | L60: 2025 | M60: =M59*(1+N60) -> 19000000 | N60: 0.11764706 | O60: =O59*(1+P60) -> 19000000 | P60: 0.11764706 | Q60: =Q59*(1+R60) -> 19000000 | R60: 0.11764706 | AF60: =VLOOKUP($Z29,GDP_high_growth,2,0) -> 0.017 | AG60: =AE28/AE27-1 -> 0.01002617 | AH60: =AF28/AF27-1 -> 0.01002617
C61: 2026 | D61: =AG30/AG29-1 -> 0.0056947448 | E61: =P61 -> 0.10526316 | G61: 2026 | H61: =AH30/AH29-1 -> -0.00024439741 | I61: =R61 -> 0.10526316 | L61: 2026 | M61: =M60*(1+N61) -> 21000000 | N61: 0.10526316 | O61: =O60*(1+P61) -> 21000000 | P61: 0.10526316 | Q61: =Q60*(1+R61) -> 21000000 | R61: 0.10526316 | AF61: =VLOOKUP($Z30,GDP_high_growth,2,0) -> 0.016 | AG61: =AE29/AE28-1 -> 0.010699076 | AH61: =AF29/AF28-1 -> 0.010699076
C62: 2027 | D62: =AG31/AG30-1 -> 0.0060872572 | E62: =P62 -> 0.071996877 | G62: 2027 | H62: =AH31/AH30-1 -> 0.00014579701 | I62: =R62 -> 0.048843141 | L62: 2027 | M62: =M61*(1+N62) -> 22366223 | N62: 0.06505822 | O62: =O61*(1+P62) -> 22511934 | P62: 0.071996877 | Q62: =Q61*(1+R62) -> 22025706 | R62: 0.048843141 | U62: =M63-M62 -> 1466004.2 | V62: =O63-O62 -> 1598347.3 | W62: =Q63-Q62 -> 121781.51 | AF62: =VLOOKUP($Z31,GDP_high_growth,2,0) -> 0.016 | AG62: =AE30/AE29-1 -> 0.010246902 | AH62: =AF30/AF29-1 -> 0.010246902
C63: 2028 | D63: =AG32/AG31-1 -> 0.0064727998 | E63: =P63 -> 0.071 | G63: 2028 | H63: =AH32/AH31-1 -> 0.0005290628 | I63: =H63+0.5% -> 0.0055290628 | L63: 2028 | M63: =M62*(1+N63) -> 23832227 | N63: 0.065545455 | O63: =O62*(1+P63) -> 24110282 | P63: 0.071 | Q63: =Q62*(1+R63) -> 22147487 | R63: =I63 -> 0.0055290628 | U63: =M64-M63 -> 1562094.1 | V63: =O64-O63 -> 1711830 | W63: =Q64-Q63 -> 122454.85 | AF63: =VLOOKUP($Z32,GDP_high_growth,2,0) -> 0.016 | AG63: =AE31/AE30-1 -> 0.0098527665 | AH63: =AF31/AF30-1 -> 0.0098527665
C64: 2029 | D64: =AG33/AG32-1 -> 0.0068181711 | E64: =P64 -> 0.071 | G64: 2029 | H64: =AH33/AH32-1 -> 0.00087239451 | I64: =H63+0.5% -> 0.0055290628 | L64: 2029 | M64: =M63*(1+N64) -> 25394321 | N64: =N63 -> 0.065545455 | O64: =O63*(1+P64) -> 25822112 | P64: =P63 -> 0.071 | Q64: =Q63*(1+R64) -> 22269942 | R64: =I64 -> 0.0055290628 | U64: =M65-M64 -> 1664482.3 | V64: =O65-O64 -> 1833369.9 | W64: =Q65-Q64 -> 130777.89 | AF64: =VLOOKUP($Z33,GDP_high_growth,2,0) -> 0.016 | AG64: =AE32/AE31-1 -> 0.0094659291 | AH64: =AF32/AF31-1 -> 0.0094659291
C65: 2030 | D65: =AG34/AG33-1 -> 0.007113499 | E65: =P65 -> 0.071 | G65: 2030 | H65: =AH34/AH33-1 -> 0.0011659784 | I65: =H64+0.5% -> 0.0058723945 | L65: 2030 | M65: =M64*(1+N65) -> 27058803 | N65: =N64 -> 0.065545455 | O65: =O64*(1+P65) -> 27655482 | P65: =P64 -> 0.071 | Q65: =Q64*(1+R65) -> 22400720 | R65: =I65 -> 0.0058723945 | U65: =M66-M65 -> 1773581.6 | V65: =O66-O65 -> 553109.63 | W65: =Q66-Q65 -> 138122.36 | AF65: =VLOOKUP($Z34,GDP_high_growth,2,0) -> 0.016 | AG65: =AE33/AE32-1 -> 0.0091196496 | AH65: =AF33/AF32-1 -> 0.0091196496
C66: 2031 | D66: =$D$65 -> 0.007113499 | E66: 0.02 | G66: 2031 | H66: =$H$65 -> 0.0011659784 | I66: =H65+0.5% -> 0.0061659784 | L66: 2031 | M66: =M65*(1+N66) -> 28832385 | N66: =N65 -> 0.065545455 | O66: =O65*(1+P66) -> 28208591 | P66: =E66 -> 0.02 | Q66: =Q65*(1+R66) -> 22538843 | R66: =I66 -> 0.0061659784 | U66: =M67-M66 -> 1889831.8 | V66: =O67-O66 -> 564171.83 | W66: =Q67-Q66 -> 138974.02
C67: 2032 | D67: =$D$65 -> 0.007113499 | E67: 0.02 | G67: 2032 | H67: =$H$65 -> 0.0011659784 | I67: =H66+0.5% -> 0.0061659784 | L67: 2032 | M67: =M66*(1+N67) -> 30722217 | N67: =N66 -> 0.065545455 | O67: =O66*(1+P67) -> 28772763 | P67: =P66 -> 0.02 | Q67: =Q66*(1+R67) -> 22677817 | R67: =I67 -> 0.0061659784 | U67: =M68-M67 -> 2013701.7 | V67: =O68-O67 -> 575455.26 | W67: =Q68-Q67 -> 139830.93
C68: 2033 | D68: =$D$65 -> 0.007113499 | E68: 0.02 | G68: 2033 | H68: =$H$65 -> 0.0011659784 | I68: =H67+0.5% -> 0.0061659784 | L68: 2033 | M68: =M67*(1+N68) -> 32735918 | N68: =N67 -> 0.065545455 | O68: =O67*(1+P68) -> 29348218 | P68: =P67 -> 0.02 | Q68: =Q67*(1+R68) -> 22817647 | R68: =I68 -> 0.0061659784 | U68: =M69-M68 -> 2145690.6 | V68: =O69-O68 -> 586964.37 | W68: =Q69-Q68 -> 140693.12
C69: 2034 | D69: =$D$65 -> 0.007113499 | E69: 0.02 | G69: 2034 | H69: =$H$65 -> 0.0011659784 | I69: =H68+0.5% -> 0.0061659784 | L69: 2034 | M69: =M68*(1+N69) -> 34881609 | N69: =N68 -> 0.065545455 | O69: =O68*(1+P69) -> 29935183 | P69: =P68 -> 0.02 | Q69: =Q68*(1+R69) -> 22958341 | R69: =I69 -> 0.0061659784 | U69: =M70-M69 -> 2286330.9 | V69: =O70-O69 -> 598703.66 | W69: =Q70-Q69 -> 141560.63
C70: 2035 | D70: =$D$65 -> 0.007113499 | E70: 0.02 | G70: 2035 | H70: =$H$65 -> 0.0011659784 | I70: =H69+0.5% -> 0.0061659784 | L70: 2035 | M70: =M69*(1+N70) -> 37167940 | N70: =N69 -> 0.065545455 | O70: =O69*(1+P70) -> 30533886 | P70: =P69 -> 0.02 | Q70: =Q69*(1+R70) -> 23099901 | R70: =I70 -> 0.0061659784 | U70: =M71-M70 -> 2436189.5 | V70: =O71-O70 -> 610677.73 | W70: =Q71-Q70 -> 142433.49
C71: 2036 | D71: =$D$65 -> 0.007113499 | E71: 0.02 | G71: 2036 | H71: =$H$65 -> 0.0011659784 | I71: =H70+0.5% -> 0.0061659784 | L71: 2036 | M71: =M70*(1+N71) -> 39604129 | N71: =N70 -> 0.065545455 | O71: =O70*(1+P71) -> 31144564 | P71: =P70 -> 0.02 | Q71: =Q70*(1+R71) -> 23242335 | R71: =I71 -> 0.0061659784 | U71: =M72-M71 -> 2595870.7 | V71: =O72-O71 -> 622891.28 | W71: =Q72-Q71 -> 143311.73
C72: 2037 | D72: =$D$65 -> 0.007113499 | E72: 0.02 | G72: 2037 | H72: =$H$65 -> 0.0011659784 | I72: =H71+0.5% -> 0.0061659784 | L72: 2037 | M72: =M71*(1+N72) -> 42200000 | N72: =N71 -> 0.065545455 | O72: =O71*(1+P72) -> 31767455 | P72: =P71 -> 0.02 | Q72: =Q71*(1+R72) -> 23385646 | R72: =I72 -> 0.0061659784 | U72: =M73-M72 -> 2766018.2 | V72: =O73-O72 -> 635349.11 | W72: =Q73-Q72 -> 144195.39
C73: 2038 | D73: =$D$65 -> 0.007113499 | E73: 0.02 | G73: 2038 | H73: =$H$65 -> 0.0011659784 | I73: =H72+0.5% -> 0.0061659784 | L73: 2038 | M73: =M72*(1+N73) -> 44966018 | N73: =N72 -> 0.065545455 | O73: =O72*(1+P73) -> 32402805 | P73: =P72 -> 0.02 | Q73: =Q72*(1+R73) -> 23529842 | R73: =R72 -> 0.0061659784 | U73: =M74-M73 -> 2947318.1 | V73: =O74-O73 -> 648056.09 | W73: =Q74-Q73 -> 145084.5
C74: 2039 | D74: =$D$65 -> 0.007113499 | E74: 0.02 | G74: 2039 | H74: =$H$65 -> 0.0011659784 | I74: =H73+0.5% -> 0.0061659784 | L74: 2039 | M74: =M73*(1+N74) -> 47913336 | N74: =N73 -> 0.065545455 | O74: =O73*(1+P74) -> 33050861 | P74: =P73 -> 0.02 | Q74: =Q73*(1+R74) -> 23674926 | R74: =R73 -> 0.0061659784 | U74: =M75-M74 -> 3140501.4 | V74: =O75-O74 -> 661017.21 | W74: =Q75-Q74 -> 145979.08
C75: 2040 | D75: =$D$65 -> 0.007113499 | E75: 0.02 | G75: 2040 | H75: =$H$65 -> 0.0011659784 | I75: =H74+0.5% -> 0.0061659784 | L75: 2040 | M75: =M74*(1+N75) -> 51053838 | N75: =N74 -> 0.065545455 | O75: =O74*(1+P75) -> 33711878 | P75: =P74 -> 0.02 | Q75: =Q74*(1+R75) -> 23820905 | R75: =R74 -> 0.0061659784 | U75: =M76-M75 -> 3346347 | V75: =O76-O75 -> 674237.56 | W75: =Q76-Q75 -> 146879.19
C76: 2041 | D76: =$D$65 -> 0.007113499 | E76: 0.02 | G76: 2041 | H76: =$H$65 -> 0.0011659784 | I76: =H75+0.5% -> 0.0061659784 | L76: 2041 | M76: =M75*(1+N76) -> 54400185 | N76: =N75 -> 0.065545455 | O76: =O75*(1+P76) -> 34386115 | P76: =P75 -> 0.02 | Q76: =Q75*(1+R76) -> 23967785 | R76: =R75 -> 0.0061659784 | U76: =M77-M76 -> 3565684.8 | V76: =O77-O76 -> 687722.31 | W76: =Q77-Q76 -> 147784.84
C77: 2042 | D77: =$D$65 -> 0.007113499 | E77: 0.02 | G77: 2042 | H77: =$H$65 -> 0.0011659784 | I77: =H76+0.5% -> 0.0061659784 | L77: 2042 | M77: =M76*(1+N77) -> 57965870 | N77: =N76 -> 0.065545455 | O77: =O76*(1+P77) -> 35073838 | P77: =P76 -> 0.02 | Q77: =Q76*(1+R77) -> 24115569 | R77: =R76 -> 0.0061659784 | U77: =M78-M77 -> 3799399.3 | V77: =O78-O77 -> 701476.75 | W77: =Q78-Q77 -> 148696.08
C78: 2043 | D78: =$D$65 -> 0.007113499 | E78: 0.02 | G78: 2043 | H78: =$H$65 -> 0.0011659784 | I78: =H77+0.5% -> 0.0061659784 | L78: 2043 | M78: =M77*(1+N78) -> 61765269 | N78: =N77 -> 0.065545455 | O78: =O77*(1+P78) -> 35775314 | P78: =P77 -> 0.02 | Q78: =Q77*(1+R78) -> 24264266 | R78: =R77 -> 0.0061659784 | U78: =M79-M78 -> 4048432.6 | V78: =O79-O78 -> 715506.29 | W78: =Q79-Q78 -> 149612.94
C79: 2044 | D79: =$D$65 -> 0.007113499 | E79: 0.02 | G79: 2044 | H79: =$H$65 -> 0.0011659784 | I79: =H78+0.5% -> 0.0061659784 | L79: 2044 | M79: =M78*(1+N79) -> 65813701 | N79: =N78 -> 0.065545455 | O79: =O78*(1+P79) -> 36490821 | P79: =P78 -> 0.02 | Q79: =Q78*(1+R79) -> 24413878 | R79: =R78 -> 0.0061659784 | U79: =M80-M79 -> 4313789 | V79: =O80-O79 -> 729816.42 | W79: =Q80-Q79 -> 150535.45
C80: 2045 | D80: =$D$65 -> 0.007113499 | E80: 0.02 | G80: 2045 | H80: =$H$65 -> 0.0011659784 | I80: =H79+0.5% -> 0.0061659784 | L80: 2045 | M80: =M79*(1+N80) -> 70127490 | N80: =N79 -> 0.065545455 | O80: =O79*(1+P80) -> 37220637 | P80: =P79 -> 0.02 | Q80: =Q79*(1+R80) -> 24564414 | R80: =R79 -> 0.0061659784 | U80: =M81-M80 -> 4596538.2 | V80: =O81-O80 -> 744412.74 | W80: =Q81-Q80 -> 151463.65
C81: 2046 | D81: =$D$65 -> 0.007113499 | E81: 0.02 | G81: 2046 | H81: =$H$65 -> 0.0011659784 | I81: =H80+0.5% -> 0.0061659784 | L81: 2046 | M81: =M80*(1+N81) -> 74724029 | N81: =N80 -> 0.065545455 | O81: =O80*(1+P81) -> 37965050 | P81: =P80 -> 0.02 | Q81: =Q80*(1+R81) -> 24715878 | R81: =R80 -> 0.0061659784 | U81: =M82-M81 -> 4897820.4 | V81: =O82-O81 -> 759301 | W81: =Q82-Q81 -> 152397.57
C82: 2047 | D82: =$D$65 -> 0.007113499 | E82: 0.02 | G82: 2047 | H82: =$H$65 -> 0.0011659784 | I82: =H81+0.5% -> 0.0061659784 | L82: 2047 | M82: =M81*(1+N82) -> 79621849 | N82: =N81 -> 0.065545455 | O82: =O81*(1+P82) -> 38724351 | P82: =P81 -> 0.02 | Q82: =Q81*(1+R82) -> 24868275 | R82: =R81 -> 0.0061659784 | U82: =M83-M82 -> 5218850.3 | V82: =O83-O82 -> 774487.02 | W82: =Q83-Q82 -> 153337.25
C83: 2048 | D83: =$D$65 -> 0.007113499 | E83: 0.02 | G83: 2048 | H83: =$H$65 -> 0.0011659784 | I83: =H82+0.5% -> 0.0061659784 | L83: 2048 | M83: =M82*(1+N83) -> 84840699 | N83: =N82 -> 0.065545455 | O83: =O82*(1+P83) -> 39498838 | P83: =P82 -> 0.02 | Q83: =Q82*(1+R83) -> 25021612 | R83: =R82 -> 0.0061659784 | U83: =M84-M83 -> 5560922.2 | V83: =O84-O83 -> 789976.76 | W83: =Q84-Q83 -> 154282.72
C84: 2049 | D84: =$D$65 -> 0.007113499 | E84: 0.02 | G84: 2049 | H84: =$H$65 -> 0.0011659784 | I84: =H83+0.5% -> 0.0061659784 | L84: 2049 | M84: =M83*(1+N84) -> 90401622 | N84: =N83 -> 0.065545455 | O84: =O83*(1+P84) -> 40288815 | P84: =P83 -> 0.02 | Q84: =Q83*(1+R84) -> 25175895 | R84: =R83 -> 0.0061659784 | U84: =M85-M84 -> 5925415.4 | V84: =O85-O84 -> 805776.29 | W84: =Q85-Q84 -> 155234.02
C85: 2050 | D85: =$D$65 -> 0.007113499 | E85: 0.02 | G85: 2050 | H85: =$H$65 -> 0.0011659784 | I85: =H84+0.5% -> 0.0061659784 | L85: 2050 | M85: =M84*(1+N85) -> 96327037 | N85: =N84 -> 0.065545455 | O85: =O84*(1+P85) -> 41094591 | P85: =P84 -> 0.02 | Q85: =Q84*(1+R85) -> 25331129 | R85: =R84 -> 0.0061659784
C88: Refineries:
C89: Source: | D89: https://www.sapia.org.za/Overview/
C91: Crude Oil Litres per barrel -> | G91: 158.987 | L91: Ownership | M91: Engen Petroleum | N91: Shell/BP (50%/50%) | O91: Sasol/Total (64%/36%) | P91: Sasol (Secunda) | Q91: Astron Energy | R91: PetroSA
C92: Refinery availability -> | G92: 0.9 | L92: Location | M92: KZN | N92: KZN | O92: Free State | P92: MP | Q92: WC | R92: WC
C93: Days Available | G93: 365 | I93: News: Sapref to come back online | L93: Refinery | M93: Enref | N93: SAPREF | O93: Natref | P93: Sasol | Q93: Astron | R93: PetroSA
I94: Mantashe wants private investors for Sapref refinery rebuild (businesslive.co.za) | L94: Capacity (kbpd) | M94: 120 | N94: 180 | O94: 108.5 | P94: 75 | Q94: 100 | R94: 45
L95: Gasoline | M95: 0.45 | N95: 0.45 | O95: 0.45 | P95: 0.85 | Q95: 0.45 | R95: 0.85
L96: Diesel | M96: 0.25 | N96: 0.25 | O96: 0.25 | P96: =1-P95 -> 0.15 | Q96: 0.25 | R96: 0.15
L97: Jet Fuel | M97: 0 | N97: 0.1 | O97: 0.1 | P97: 0 | Q97: 0.1 | R97: 0
L98: Total | M98: =SUM(M95:M97) -> 0.7 | N98: =SUM(N95:N97) -> 0.8 | O98: =SUM(O95:O97) -> 0.8 | P98: =SUM(P95:P97) -> 1 | Q98: =SUM(Q95:Q97) -> 0.8 | R98: =SUM(R95:R97) -> 1
D99: Source: Used 10% from https://www.sapia.org.za/wp-content/uploads/2022/04/SAPIA_Economic-Impact-Assessment.pdf
L101: High production scenario (low imports)
L102: Production | M102: Enref | N102: SAPREF | O102: Natref | P102: Sasol | Q102: Astron | R102: PetroSA
L103: 2022 | M103: 0 | N103: 0 | O103: 0.873 | P103: 0.9 | Q103: 0 | R103: 0
L104: 2023 | M104: 0 | N104: 0 | O104: 0.875 | P104: 0.9123 | Q104: 0.5 | R104: 0
L105: 2024 | M105: 0 | N105: 0 | O105: 0.88 | P105: 0.9246 | Q105: 0.9 | R105: 0
L106: 2025 | M106: 0 | N106: 0 | O106: 0.85 | P106: 0.9369 | Q106: 0.9 | R106: 0
L107: 2026 | M107: 0 | N107: 0 | O107: 0.85 | P107: 0.9492 | Q107: 0.9 | R107: 0
...

Sheet Supply Forecast
B3: Nameplate capacity (litres) | C3: Enref | D3: SAPREF | E3: Natref | F3: Sasol | G3: Astron | H3: PetroSA
B4: Gasoline | C4: =INDEX(Refinery,MATCH($B4,Assumptions!$L$93:$L$98,0),MATCH(C$3,Assumptions!$L$93:$R$93,0))*Crude_oil_litresPerBarrel*(INDEX(Refinery_capacity,2,MATCH(C$3,Assumptions!$L$93:$R$93,0)))*Operational_days*1000 -> 3133633770 | D4: =INDEX(Refinery,MATCH($B4,Assumptions!$L$93:$L$98,0),MATCH(D$3,Assumptions!$L$93:$R$93,0))*Crude_oil_litresPerBarrel*(INDEX(Refinery_capacity,2,MATCH(D$3,Assumptions!$L$93:$R$93,0)))*Operational_days*1000 -> 4700450655 | E4: =INDEX(Refinery,MATCH($B4,Assumptions!$L$93:$L$98,0),MATCH(E$3,Assumptions!$L$93:$R$93,0))*Crude_oil_litresPerBarrel*(INDEX(Refinery_capacity,2,MATCH(E$3,Assumptions!$L$93:$R$93,0)))*Operational_days*1000 -> 2.8333272e+09 | F4: =INDEX(Refinery,MATCH($B4,Assumptions!$L$93:$L$98,0),MATCH(F$3,Assumptions!$L$93:$R$93,0))*Crude_oil_litresPerBarrel*(INDEX(Refinery_capacity,2,MATCH(F$3,Assumptions!$L$93:$R$93,0)))*Operational_days*1000 -> 3.6994288e+09 | G4: =INDEX(Refinery,MATCH($B4,Assumptions!$L$93:$L$98,0),MATCH(G$3,Assumptions!$L$93:$R$93,0))*Crude_oil_litresPerBarrel*(INDEX(Refinery_capacity,2,MATCH(G$3,Assumptions!$L$93:$R$93,0)))*Operational_days*1000 -> 2611361475 | H4: =INDEX(Refinery,MATCH($B4,Assumptions!$L$93:$L$98,0),MATCH(H$3,Assumptions!$L$93:$R$93,0))*Crude_oil_litresPerBarrel*(INDEX(Refinery_capacity,2,MATCH(H$3,Assumptions!$L$93:$R$93,0)))*Operational_days*1000 -> 2.2196573e+09
B5: Diesel | C5: =INDEX(Refinery,MATCH($B5,Assumptions!$L$93:$L$98,0),MATCH(C$3,Assumptions!$L$93:$R$93,0))*Crude_oil_litresPerBarrel*(INDEX(Refinery_capacity,2,MATCH(C$3,Assumptions!$L$93:$R$93,0)))*Operational_days*1000 -> 1740907650 | D5: =INDEX(Refinery,MATCH($B5,Assumptions!$L$93:$L$98,0),MATCH(D$3,Assumptions!$L$93:$R$93,0))*Crude_oil_litresPerBarrel*(INDEX(Refinery_capacity,2,MATCH(D$3,Assumptions!$L$93:$R$93,0)))*Operational_days*1000 -> 2611361475 | E5: =INDEX(Refinery,MATCH($B5,Assumptions!$L$93:$L$98,0),MATCH(E$3,Assumptions!$L$93:$R$93,0))*Crude_oil_litresPerBarrel*(INDEX(Refinery_capacity,2,MATCH(E$3,Assumptions!$L$93:$R$93,0)))*Operational_days*1000 -> 1.5740707e+09 | F5: =INDEX(Refinery,MATCH($B5,Assumptions!$L$93:$L$98,0),MATCH(F$3,Assumptions!$L$93:$R$93,0))*Crude_oil_litresPerBarrel*(INDEX(Refinery_capacity,2,MATCH(F$3,Assumptions!$L$93:$R$93,0)))*Operational_days*1000 -> 6.5284037e+08 | G5: =INDEX(Refinery,MATCH($B5,Assumptions!$L$93:$L$98,0),MATCH(G$3,Assumptions!$L$93:$R$93,0))*Crude_oil_litresPerBarrel*(INDEX(Refinery_capacity,2,MATCH(G$3,Assumptions!$L$93:$R$93,0)))*Operational_days*1000 -> 1450756375 | H5: =INDEX(Refinery,MATCH($B5,Assumptions!$L$93:$L$98,0),MATCH(H$3,Assumptions!$L$93:$R$93,0))*Crude_oil_litresPerBarrel*(INDEX(Refinery_capacity,2,MATCH(H$3,Assumptions!$L$93:$R$93,0)))*Operational_days*1000 -> 3.9170422e+08
B6: Jet Fuel | C6: =INDEX(Refinery,MATCH($B6,Assumptions!$L$93:$L$98,0),MATCH(C$3,Assumptions!$L$93:$R$93,0))*Crude_oil_litresPerBarrel*(INDEX(Refinery_capacity,2,MATCH(C$3,Assumptions!$L$93:$R$93,0)))*Operational_days*1000 -> 0 | D6: =INDEX(Refinery,MATCH($B6,Assumptions!$L$93:$L$98,0),MATCH(D$3,Assumptions!$L$93:$R$93,0))*Crude_oil_litresPerBarrel*(INDEX(Refinery_capacity,2,MATCH(D$3,Assumptions!$L$93:$R$93,0)))*Operational_days*1000 -> 1.0445446e+09 | E6: =INDEX(Refinery,MATCH($B6,Assumptions!$L$93:$L$98,0),MATCH(E$3,Assumptions!$L$93:$R$93,0))*Crude_oil_litresPerBarrel*(INDEX(Refinery_capacity,2,MATCH(E$3,Assumptions!$L$93:$R$93,0)))*Operational_days*1000 -> 6.2962827e+08 | F6: =INDEX(Refinery,MATCH($B6,Assumptions!$L$93:$L$98,0),MATCH(F$3,Assumptions!$L$93:$R$93,0))*Crude_oil_litresPerBarrel*(INDEX(Refinery_capacity,2,MATCH(F$3,Assumptions!$L$93:$R$93,0)))*Operational_days*1000 -> 0 | G6: =INDEX(Refinery,MATCH($B6,Assumptions!$L$93:$L$98,0),MATCH(G$3,Assumptions!$L$93:$R$93,0))*Crude_oil_litresPerBarrel*(INDEX(Refinery_capacity,2,MATCH(G$3,Assumptions!$L$93:$R$93,0)))*Operational_days*1000 -> 5.8030255e+08 | H6: =INDEX(Refinery,MATCH($B6,Assumptions!$L$93:$L$98,0),MATCH(H$3,Assumptions!$L$93:$R$93,0))*Crude_oil_litresPerBarrel*(INDEX(Refinery_capacity,2,MATCH(H$3,Assumptions!$L$93:$R$93,0)))*Operational_days*1000 -> 0
B7: Total | C7: =INDEX(Refinery,MATCH($B7,Assumptions!$L$93:$L$98,0),MATCH(C$3,Assumptions!$L$93:$R$93,0))*Crude_oil_litresPerBarrel*(INDEX(Refinery_capacity,2,MATCH(C$3,Assumptions!$L$93:$R$93,0)))*Operational_days*1000 -> 4874541420 | D7: =INDEX(Refinery,MATCH($B7,Assumptions!$L$93:$L$98,0),MATCH(D$3,Assumptions!$L$93:$R$93,0))*Crude_oil_litresPerBarrel*(INDEX(Refinery_capacity,2,MATCH(D$3,Assumptions!$L$93:$R$93,0)))*Operational_days*1000 -> 8.3563567e+09 | E7: =INDEX(Refinery,MATCH($B7,Assumptions!$L$93:$L$98,0),MATCH(E$3,Assumptions!$L$93:$R$93,0))*Crude_oil_litresPerBarrel*(INDEX(Refinery_capacity,2,MATCH(E$3,Assumptions!$L$93:$R$93,0)))*Operational_days*1000 -> 5.0370261e+09 | F7: =INDEX(Refinery,MATCH($B7,Assumptions!$L$93:$L$98,0),MATCH(F$3,Assumptions!$L$93:$R$93,0))*Crude_oil_litresPerBarrel*(INDEX(Refinery_capacity,2,MATCH(F$3,Assumptions!$L$93:$R$93,0)))*Operational_days*1000 -> 4352269125 | G7: =INDEX(Refinery,MATCH($B7,Assumptions!$L$93:$L$98,0),MATCH(G$3,Assumptions!$L$93:$R$93,0))*Crude_oil_litresPerBarrel*(INDEX(Refinery_capacity,2,MATCH(G$3,Assumptions!$L$93:$R$93,0)))*Operational_days*1000 -> 4.6424204e+09 | H7: =INDEX(Refinery,MATCH($B7,Assumptions!$L$93:$L$98,0),MATCH(H$3,Assumptions!$L$93:$R$93,0))*Crude_oil_litresPerBarrel*(INDEX(Refinery_capacity,2,MATCH(H$3,Assumptions!$L$93:$R$93,0)))*Operational_days*1000 -> 2611361475
B9: Check | C9: 2 | D9: 3 | E9: 4 | F9: 5 | G9: 6 | H9: 7
B10: 2028 | C10: =C$7*VLOOKUP($B10,Assumptions!$L$103:$R$131,C$9)*Refinery_availability -> 0 | D10: =D$7*VLOOKUP($B10,Assumptions!$L$103:$R$131,D$9)*Refinery_availability -> 0 | E10: =E$7*VLOOKUP($B10,Assumptions!$L$103:$R$131,E$9)*Refinery_availability -> 3.853325e+09 | F10: =F$7*VLOOKUP($B10,Assumptions!$L$103:$R$131,F$9)*Refinery_availability -> 3.814024e+09 | G10: =G$7*VLOOKUP($B10,Assumptions!$L$103:$R$131,G$9)*Refinery_availability -> 3.7603605e+09 | H10: =H$7*VLOOKUP($B10,Assumptions!$L$103:$R$131,H$9)*Refinery_availability -> 0
C11: =C10=VLOOKUP($B$10,$B$17:$H$45,C$9) -> TRUE | D11: =D10=VLOOKUP($B$10,$B$17:$H$45,D$9) -> TRUE | E11: =E10=VLOOKUP($B$10,$B$17:$H$45,E$9) -> FALSE | F11: =F10=VLOOKUP($B$10,$B$17:$H$45,F$9) -> FALSE | G11: =G10=VLOOKUP($B$10,$B$17:$H$45,G$9) -> FALSE | H11: =H10=VLOOKUP($B$10,$B$17:$H$45,H$9) -> TRUE
E13: =IF((Product_select="Total"),(INDEX(Refinery,MATCH("Jet Fuel",Assumptions!$L$93:$L$98,0),MATCH(E$16,Assumptions!$L$93:$R$93,0))*Crude_oil_litresPerBarrel*(INDEX(Refinery_capacity,2,MATCH(E$16,Assumptions!$L$93:$R$93,0)))*Operational_days*1000*Refinery_availability*INDEX(Production_High,MATCH($B$23,Assumptions!$L$102:$L$131,0),MATCH(E$16,Assumptions!$L$102:$R$102,0))),0) -> 0 | F13: Don't delete this
B14: Gasoline | C14: Choose product
B15: High production scenario (low imports) | X15: 2022 | Y15: =I50 -> 5.2050362e+09 | Z15: =I17 -> 5.2226825e+09
B16: Year | C16: =C3 -> Enref | D16: =D3 -> SAPREF | E16: =E3 -> Natref | F16: Sasol | G16: =G3 -> Astron | H16: =H3 -> PetroSA | I16: =IF(Product_select="Total", "Total Liquid Fuels", "Total ")&IF(Product_select="Total","",Product_select)&" High Supply (Litres)" -> Total Gasoline High Supply (Litres) | J16: =IF(Product_select="Total", "Total Liquid Fuels", "Total ")&IF(Product_select="Total","",Product_select)&" High Supply (kbpd)" -> Total Gasoline High Supply (kbpd) | K16: =IF(Product_select="Total", "Specified Market Total Liquid Fuels", "Total ")&IF(Product_select="Total","",Product_select)&" High Supply (Litres)" -> Total Gasoline High Supply (Litres) | L16: =IF(Product_select="Total", "Specified Market Total Liquid Fuels", "Total ")&IF(Product_select="Total","",Product_select)&" High Supply (kbpd)" -> Total Gasoline High Supply (kbpd) | N16: MOI | X16: 2023 | Y16: =I51 -> 6.4072235e+09 | Z16: =I18 -> 6.4438478e+09
B17: 2022 | C17: =INDEX(Refinery,MATCH(Product_select,Assumptions!$L$93:$L$98,0),MATCH("Enref",Assumptions!$L$93:$R$93,0))*Crude_oil_litresPerBarrel*(INDEX(Refinery_capacity,2,MATCH("Enref",Assumptions!$L$93:$R$93,0)))*Operational_days*1000*Refinery_availability*INDEX(Production_High,MATCH($B17,Assumptions!$L$102:$L$131,0),MATCH("Enref",Assumptions!$L$102:$R$102,0)) -> 0 | D17: =INDEX(Refinery,MATCH(Product_select,Assumptions!$L$93:$L$98,0),MATCH(D$16,Assumptions!$L$93:$R$93,0))*Crude_oil_litresPerBarrel*(INDEX(Refinery_capacity,2,MATCH(D$16,Assumptions!$L$93:$R$93,0)))*Operational_days*1000*Refinery_availability*INDEX(Production_High,MATCH($B17,Assumptions!$L$102:$L$131,0),MATCH(D$16,Assumptions!$L$102:$R$102,0)) -> 0 | E17: =INDEX(Refinery,MATCH(Product_select,Assumptions!$L$93:$L$98,0),MATCH(E$16,Assumptions!$L$93:$R$93,0))*Crude_oil_litresPerBarrel*(INDEX(Refinery_capacity,2,MATCH(E$16,Assumptions!$L$93:$R$93,0)))*Operational_days*1000*Refinery_availability*INDEX(Production_High,MATCH($B17,Assumptions!$L$102:$L$131,0),MATCH(E$16,Assumptions!$L$102:$R$102,0)) -> 2.2261452e+09 | F17: =INDEX(Refinery,MATCH(Product_select,Assumptions!$L$93:$L$98,0),MATCH(F$16,Assumptions!$L$93:$R$93,0))*Crude_oil_litresPerBarrel*(INDEX(Refinery_capacity,2,MATCH(F$16,Assumptions!$L$93:$R$93,0)))*Operational_days*1000*Refinery_availability*INDEX(Production_High,MATCH($B17,Assumptions!$L$102:$L$131,0),MATCH(F$16,Assumptions!$L$102:$R$102,0)) -> 2.9965373e+09 | G17: =INDEX(Refinery,MATCH(Product_select,Assumptions!$L$93:$L$98,0),MATCH(G$16,Assumptions!$L$93:$R$93,0))*Crude_oil_litresPerBarrel*(INDEX(Refinery_capacity,2,MATCH(G$16,Assumptions!$L$93:$R$93,0)))*Operational_days*1000*Refinery_availability*INDEX(Production_High,MATCH($B17,Assumptions!$L$102:$L$131,0),MATCH(G$16,Assumptions!$L$102:$R$102,0)) -> 0 | H17: =INDEX(Refinery,MATCH(Product_select,Assumptions!$L$93:$L$98,0),MATCH(H$16,Assumptions!$L$93:$R$93,0))*Crude_oil_litresPerBarrel*(INDEX(Refinery_capacity,2,MATCH(H$16,Assumptions!$L$93:$R$93,0)))*Operational_days*1000*Refinery_availability*INDEX(Production_High,MATCH($B17,Assumptions!$L$102:$L$131,0),MATCH(H$16,Assumptions!$L$102:$R$102,0)) -> 0 | I17: =SUM(C17:H17) -> 5.2226825e+09 | J17: =I17/Crude_oil_litresPerBarrel/Operational_days/1000 -> 89.999302 | K17: =SUM(C17:H17) -> 5.2226825e+09 | L17: =K17/Crude_oil_litresPerBarrel/Operational_days/1000 -> 89.999302 | N17: =E17+F17 -> 5.2226825e+09 | X17: 2024 | Y17: =I52 -> 6.6880166e+09 | Z17: =I19 -> 7.4376406e+09
B18: 2023 | C18: =INDEX(Refinery,MATCH(Product_select,Assumptions!$L$93:$L$98,0),MATCH(C$16,Assumptions!$L$93:$R$93,0))*Crude_oil_litresPerBarrel*(INDEX(Refinery_capacity,2,MATCH(C$16,Assumptions!$L$93:$R$93,0)))*Operational_days*1000*Refinery_availability*INDEX(Production_High,MATCH($B18,Assumptions!$L$102:$L$131,0),MATCH(C$16,Assumptions!$L$102:$R$102,0)) -> 0 | D18: =INDEX(Refinery,MATCH(Product_select,Assumptions!$L$93:$L$98,0),MATCH(D$16,Assumptions!$L$93:$R$93,0))*Crude_oil_litresPerBarrel*(INDEX(Refinery_capacity,2,MATCH(D$16,Assumptions!$L$93:$R$93,0)))*Operational_days*1000*Refinery_availability*INDEX(Production_High,MATCH($B18,Assumptions!$L$102:$L$131,0),MATCH(D$16,Assumptions!$L$102:$R$102,0)) -> 0 | E18: =INDEX(Refinery,MATCH(Product_select,Assumptions!$L$93:$L$98,0),MATCH(E$16,Assumptions!$L$93:$R$93,0))*Crude_oil_litresPerBarrel*(INDEX(Refinery_capacity,2,MATCH(E$16,Assumptions!$L$93:$R$93,0)))*Operational_days*1000*Refinery_availability*INDEX(Production_High,MATCH($B18,Assumptions!$L$102:$L$131,0),MATCH(E$16,Assumptions!$L$102:$R$102,0)) -> 2.2312452e+09 | F18: =INDEX(Refinery,MATCH(Product_select,Assumptions!$L$93:$L$98,0),MATCH(F$16,Assumptions!$L$93:$R$93,0))*Crude_oil_litresPerBarrel*(INDEX(Refinery_capacity,2,MATCH(F$16,Assumptions!$L$93:$R$93,0)))*Operational_days*1000*Refinery_availability*INDEX(Production_High,MATCH($B18,Assumptions!$L$102:$L$131,0),MATCH(F$16,Assumptions!$L$102:$R$102,0)) -> 3.03749e+09 | G18: =INDEX(Refinery,MATCH(Product_select,Assumptions!$L$93:$L$98,0),MATCH(G$16,Assumptions!$L$93:$R$93,0))*Crude_oil_litresPerBarrel*(INDEX(Refinery_capacity,2,MATCH(G$16,Assumptions!$L$93:$R$93,0)))*Operational_days*1000*Refinery_availability*INDEX(Production_High,MATCH($B18,Assumptions!$L$102:$L$131,0),MATCH(G$16,Assumptions!$L$102:$R$102,0)) -> 1.1751127e+09 | H18: =INDEX(Refinery,MATCH(Product_select,Assumptions!$L$93:$L$98,0),MATCH(H$16,Assumptions!$L$93:$R$93,0))*Crude_oil_litresPerBarrel*(INDEX(Refinery_capacity,2,MATCH(H$16,Assumptions!$L$93:$R$93,0)))*Operational_days*1000*Refinery_availability*INDEX(Production_High,MATCH($B18,Assumptions!$L$102:$L$131,0),MATCH(H$16,Assumptions!$L$102:$R$102,0)) -> 0 | I18: =SUM(C18:H18) -> 6.4438478e+09 | J18: =I18/Crude_oil_litresPerBarrel/Operational_days/1000 -> 111.0429 | K18: =SUM(C18:H18) -> 6.4438478e+09 | L18: =K18/Crude_oil_litresPerBarrel/Operational_days/1000 -> 111.0429 | N18: =E18+F18 -> 5.2687351e+09 | X18: 2025 | Y18: =I53 -> 6.7099912e+09 | Z18: =I20 -> 7.4020934e+09
B19: 2024 | C19: =INDEX(Refinery,MATCH(Product_select,Assumptions!$L$93:$L$98,0),MATCH(C$16,Assumptions!$L$93:$R$93,0))*Crude_oil_litresPerBarrel*(INDEX(Refinery_capacity,2,MATCH(C$16,Assumptions!$L$93:$R$93,0)))*Operational_days*1000*Refinery_availability*INDEX(Production_High,MATCH($B19,Assumptions!$L$102:$L$131,0),MATCH(C$16,Assumptions!$L$102:$R$102,0)) -> 0 | D19: =INDEX(Refinery,MATCH(Product_select,Assumptions!$L$93:$L$98,0),MATCH(D$16,Assumptions!$L$93:$R$93,0))*Crude_oil_litresPerBarrel*(INDEX(Refinery_capacity,2,MATCH(D$16,Assumptions!$L$93:$R$93,0)))*Operational_days*1000*Refinery_availability*INDEX(Production_High,MATCH($B19,Assumptions!$L$102:$L$131,0),MATCH(D$16,Assumptions!$L$102:$R$102,0)) -> 0 | E19: =INDEX(Refinery,MATCH(Product_select,Assumptions!$L$93:$L$98,0),MATCH(E$16,Assumptions!$L$93:$R$93,0))*Crude_oil_litresPerBarrel*(INDEX(Refinery_capacity,2,MATCH(E$16,Assumptions!$L$93:$R$93,0)))*Operational_days*1000*Refinery_availability*INDEX(Production_High,MATCH($B19,Assumptions!$L$102:$L$131,0),MATCH(E$16,Assumptions!$L$102:$R$102,0)) -> 2.2439951e+09 | F19: =INDEX(Refinery,MATCH(Product_select,Assumptions!$L$93:$L$98,0),MATCH(F$16,Assumptions!$L$93:$R$93,0))*Crude_oil_litresPerBarrel*(INDEX(Refinery_capacity,2,MATCH(F$16,Assumptions!$L$93:$R$93,0)))*Operational_days*1000*Refinery_availability*INDEX(Production_High,MATCH($B19,Assumptions!$L$102:$L$131,0),MATCH(F$16,Assumptions!$L$102:$R$102,0)) -> 3.0784426e+09 | G19: =INDEX(Refinery,MATCH(Product_select,Assumptions!$L$93:$L$98,0),MATCH(G$16,Assumptions!$L$93:$R$93,0))*Crude_oil_litresPerBarrel*(INDEX(Refinery_capacity,2,MATCH(G$16,Assumptions!$L$93:$R$93,0)))*Operational_days*1000*Refinery_availability*INDEX(Production_High,MATCH($B19,Assumptions!$L$102:$L$131,0),MATCH(G$16,Assumptions!$L$102:$R$102,0)) -> 2.1152028e+09 | H19: =INDEX(Refinery,MATCH(Product_select,Assumptions!$L$93:$L$98,0),MATCH(H$16,Assumptions!$L$93:$R$93,0))*Crude_oil_litresPerBarrel*(INDEX(Refinery_capacity,2,MATCH(H$16,Assumptions!$L$93:$R$93,0)))*Operational_days*1000*Refinery_availability*INDEX(Production_High,MATCH($B19,Assumptions!$L$102:$L$131,0),MATCH(H$16,Assumptions!$L$102:$R$102,0)) -> 0 | I19: =SUM(C19:H19) -> 7.4376406e+09 | J19: =I19/Crude_oil_litresPerBarrel/Operational_days/1000 -> 128.16833 | K19: =SUM(C19:H19) -> 7.4376406e+09 | L19: =K19/Crude_oil_litresPerBarrel/Operational_days/1000 -> 128.16833 | N19: =E19+F19 -> 5.3224378e+09 | X19: 2026 | Y19: =I54 -> 6.7319658e+09 | Z19: =I21 -> 7.4430461e+09
B20: 2025 | C20: =INDEX(Refinery,MATCH(Product_select,Assumptions!$L$93:$L$98,0),MATCH(C$16,Assumptions!$L$93:$R$93,0))*Crude_oil_litresPerBarrel*(INDEX(Refinery_capacity,2,MATCH(C$16,Assumptions!$L$93:$R$93,0)))*Operational_days*1000*Refinery_availability*INDEX(Production_High,MATCH($B20,Assumptions!$L$102:$L$131,0),MATCH(C$16,Assumptions!$L$102:$R$102,0)) -> 0 | D20: =INDEX(Refinery,MATCH(Product_select,Assumptions!$L$93:$L$98,0),MATCH(D$16,Assumptions!$L$93:$R$93,0))*Crude_oil_litresPerBarrel*(INDEX(Refinery_capacity,2,MATCH(D$16,Assumptions!$L$93:$R$93,0)))*Operational_days*1000*Refinery_availability*INDEX(Production_High,MATCH($B20,Assumptions!$L$102:$L$131,0),MATCH(D$16,Assumptions!$L$102:$R$102,0)) -> 0 | E20: =INDEX(Refinery,MATCH(Product_select,Assumptions!$L$93:$L$98,0),MATCH(E$16,Assumptions!$L$93:$R$93,0))*Crude_oil_litresPerBarrel*(INDEX(Refinery_capacity,2,MATCH(E$16,Assumptions!$L$93:$R$93,0)))*Operational_days*1000*Refinery_availability*INDEX(Production_High,MATCH($B20,Assumptions!$L$102:$L$131,0),MATCH(E$16,Assumptions!$L$102:$R$102,0)) -> 2.1674953e+09 | F20: =INDEX(Refinery,MATCH(Product_select,Assumptions!$L$93:$L$98,0),MATCH(F$16,Assumptions!$L$93:$R$93,0))*Crude_oil_litresPerBarrel*(INDEX(Refinery_capacity,2,MATCH(F$16,Assumptions!$L$93:$R$93,0)))*Operational_days*1000*Refinery_availability*INDEX(Production_High,MATCH($B20,Assumptions!$L$102:$L$131,0),MATCH(F$16,Assumptions!$L$102:$R$102,0)) -> 3.1193953e+09 | G20: =INDEX(Refinery,MATCH(Product_select,Assumptions!$L$93:$L$98,0),MATCH(G$16,Assumptions!$L$93:$R$93,0))*Crude_oil_litresPerBarrel*(INDEX(Refinery_capacity,2,MATCH(G$16,Assumptions!$L$93:$R$93,0)))*Operational_days*1000*Refinery_availability*INDEX(Production_High,MATCH($B20,Assumptions!$L$102:$L$131,0),MATCH(G$16,Assumptions!$L$102:$R$102,0)) -> 2.1152028e+09 | H20: =INDEX(Refinery,MATCH(Product_select,Assumptions!$L$93:$L$98,0),MATCH(H$16,Assumptions!$L$93:$R$93,0))*Crude_oil_litresPerBarrel*(INDEX(Refinery_capacity,2,MATCH(H$16,Assumptions!$L$93:$R$93,0)))*Operational_days*1000*Refinery_availability*INDEX(Production_High,MATCH($B20,Assumptions!$L$102:$L$131,0),MATCH(H$16,Assumptions!$L$102:$R$102,0)) -> 0 | I20: =SUM(C20:H20) -> 7.4020934e+09 | J20: =I20/Crude_oil_litresPerBarrel/Operational_days/1000 -> 127.55576 | K20: =SUM(C20:H20) -> 7.4020934e+09 | L20: =K20/Crude_oil_litresPerBarrel/Operational_days/1000 -> 127.55576 | N20: =E20+F20 -> 5.2868906e+09 | X20: 2027 | Y20: =I55 -> 6.7539404e+09 | Z20: =I22 -> 7.4839988e+09
B21: 2026 | C21: =INDEX(Refinery,MATCH(Product_select,Assumptions!$L$93:$L$98,0),MATCH(C$16,Assumptions!$L$93:$R$93,0))*Crude_oil_litresPerBarrel*(INDEX(Refinery_capacity,2,MATCH(C$16,Assumptions!$L$93:$R$93,0)))*Operational_days*1000*Refinery_availability*INDEX(Production_High,MATCH($B21,Assumptions!$L$102:$L$131,0),MATCH(C$16,Assumptions!$L$102:$R$102,0)) -> 0 | D21: =INDEX(Refinery,MATCH(Product_select,Assumptions!$L$93:$L$98,0),MATCH(D$16,Assumptions!$L$93:$R$93,0))*Crude_oil_litresPerBarrel*(INDEX(Refinery_capacity,2,MATCH(D$16,Assumptions!$L$93:$R$93,0)))*Operational_days*1000*Refinery_availability*INDEX(Production_High,MATCH($B21,Assumptions!$L$102:$L$131,0),MATCH(D$16,Assumptions!$L$102:$R$102,0)) -> 0 | E21: =INDEX(Refinery,MATCH(Product_select,Assumptions!$L$93:$L$98,0),MATCH(E$16,Assumptions!$L$93:$R$93,0))*Crude_oil_litresPerBarrel*(INDEX(Refinery_capacity,2,MATCH(E$16,Assumptions!$L$93:$R$93,0)))*Operational_days*1000*Refinery_availability*INDEX(Production_High,MATCH($B21,Assumptions!$L$102:$L$131,0),MATCH(E$16,Assumptions!$L$102:$R$102,0)) -> 2.1674953e+09 | F21: =INDEX(Refinery,MATCH(Product_select,Assumptions!$L$93:$L$98,0),MATCH(F$16,Assumptions!$L$93:$R$93,0))*Crude_oil_litresPerBarrel*(INDEX(Refinery_capacity,2,MATCH(F$16,Assumptions!$L$93:$R$93,0)))*Operational_days*1000*Refinery_availability*INDEX(Production_High,MATCH($B21,Assumptions!$L$102:$L$131,0),MATCH(F$16,Assumptions!$L$102:$R$102,0)) -> 3.160348e+09 | G21: =INDEX(Refinery,MATCH(Product_select,Assumptions!$L$93:$L$98,0),MATCH(G$16,Assumptions!$L$93:$R$93,0))*Crude_oil_litresPerBarrel*(INDEX(Refinery_capacity,2,MATCH(G$16,Assumptions!$L$93:$R$93,0)))*Operational_days*1000*Refinery_availability*INDEX(Production_High,MATCH($B21,Assumptions!$L$102:$L$131,0),MATCH(G$16,Assumptions!$L$102:$R$102,0)) -> 2.1152028e+09 | H21: =INDEX(Refinery,MATCH(Product_select,Assumptions!$L$93:$L$98,0),MATCH(H$16,Assumptions!$L$93:$R$93,0))*Crude_oil_litresPerBarrel*(INDEX(Refinery_capacity,2,MATCH(H$16,Assumptions!$L$93:$R$93,0)))*Operational_days*1000*Refinery_availability*INDEX(Production_High,MATCH($B21,Assumptions!$L$102:$L$131,0),MATCH(H$16,Assumptions!$L$102:$R$102,0)) -> 0 | I21: =SUM(C21:H21) -> 7.4430461e+09 | J21: =I21/Crude_oil_litresPerBarrel/Operational_days/1000 -> 128.26148 | K21: =SUM(C21:H21) -> 7.4430461e+09 | L21: =K21/Crude_oil_litresPerBarrel/Operational_days/1000 -> 128.26148 | N21: =E21+F21 -> 5.3278433e+09 | X21: 2028 | Y21: =I56 -> 6.7755821e+09 | Z21: =I23 -> 7.5246185e+09
B22: 2027 | C22: =INDEX(Refinery,MATCH(Product_select,Assumptions!$L$93:$L$98,0),MATCH(C$16,Assumptions!$L$93:$R$93,0))*Crude_oil_litresPerBarrel*(INDEX(Refinery_capacity,2,MATCH(C$16,Assumptions!$L$93:$R$93,0)))*Operational_days*1000*Refinery_availability*INDEX(Production_High,MATCH($B22,Assumptions!$L$102:$L$131,0),MATCH(C$16,Assumptions!$L$102:$R$102,0)) -> 0 | D22: =INDEX(Refinery,MATCH(Product_select,Assumptions!$L$93:$L$98,0),MATCH(D$16,Assumptions!$L$93:$R$93,0))*Crude_oil_litresPerBarrel*(INDEX(Refinery_capacity,2,MATCH(D$16,Assumptions!$L$93:$R$93,0)))*Operational_days*1000*Refinery_availability*INDEX(Production_High,MATCH($B22,Assumptions!$L$102:$L$131,0),MATCH(D$16,Assumptions!$L$102:$R$102,0)) -> 0 | E22: =INDEX(Refinery,MATCH(Product_select,Assumptions!$L$93:$L$98,0),MATCH(E$16,Assumptions!$L$93:$R$93,0))*Crude_oil_litresPerBarrel*(INDEX(Refinery_capacity,2,MATCH(E$16,Assumptions!$L$93:$R$93,0)))*Operational_days*1000*Refinery_availability*INDEX(Production_High,MATCH($B22,Assumptions!$L$102:$L$131,0),MATCH(E$16,Assumptions!$L$102:$R$102,0)) -> 2.1674953e+09 | F22: =INDEX(Refinery,MATCH(Product_select,Assumptions!$L$93:$L$98,0),MATCH(F$16,Assumptions!$L$93:$R$93,0))*Crude_oil_litresPerBarrel*(INDEX(Refinery_capacity,2,MATCH(F$16,Assumptions!$L$93:$R$93,0)))*Operational_days*1000*Refinery_availability*INDEX(Production_High,MATCH($B22,Assumptions!$L$102:$L$131,0),MATCH(F$16,Assumptions!$L$102:$R$102,0)) -> 3.2013007e+09 | G22: =INDEX(Refinery,MATCH(Product_select,Assumptions!$L$93:$L$98,0),MATCH(G$16,Assumptions!$L$93:$R$93,0))*Crude_oil_litresPerBarrel*(INDEX(Refinery_capacity,2,MATCH(G$16,Assumptions!$L$93:$R$93,0)))*Operational_days*1000*Refinery_availability*INDEX(Production_High,MATCH($B22,Assumptions!$L$102:$L$131,0),MATCH(G$16,Assumptions!$L$102:$R$102,0)) -> 2.1152028e+09 | H22: =INDEX(Refinery,MATCH(Product_select,Assumptions!$L$93:$L$98,0),MATCH(H$16,Assumptions!$L$93:$R$93,0))*Crude_oil_litresPerBarrel*(INDEX(Refinery_capacity,2,MATCH(H$16,Assumptions!$L$93:$R$93,0)))*Operational_days*1000*Refinery_availability*INDEX(Production_High,MATCH($B22,Assumptions!$L$102:$L$131,0),MATCH(H$16,Assumptions!$L$102:$R$102,0)) -> 0 | I22: =SUM(C22:H22) -> 7.4839988e+09 | J22: =I22/Crude_oil_litresPerBarrel/Operational_days/1000 -> 128.96719 | K22: =SUM(C22:H22) -> 7.4839988e+09 | L22: =K22/Crude_oil_litresPerBarrel/Operational_days/1000 -> 128.96719 | N22: =E22+F22 -> 5.368796e+09 | X22: 2029 | Y22: =I57 -> 6.588798e+09 | Z22: =I24 -> 7.4247339e+09
B23: 2028 | C23: =INDEX(Refinery,MATCH(Product_select,Assumptions!$L$93:$L$98,0),MATCH(C$16,Assumptions!$L$93:$R$93,0))*Crude_oil_litresPerBarrel*(INDEX(Refinery_capacity,2,MATCH(C$16,Assumptions!$L$93:$R$93,0)))*Operational_days*1000*Refinery_availability*INDEX(Production_High,MATCH($B23,Assumptions!$L$102:$L$131,0),MATCH(C$16,Assumptions!$L$102:$R$102,0)) -> 0 | D23: =INDEX(Refinery,MATCH(Product_select,Assumptions!$L$93:$L$98,0),MATCH(D$16,Assumptions!$L$93:$R$93,0))*Crude_oil_litresPerBarrel*(INDEX(Refinery_capacity,2,MATCH(D$16,Assumptions!$L$93:$R$93,0)))*Operational_days*1000*Refinery_availability*INDEX(Production_High,MATCH($B23,Assumptions!$L$102:$L$131,0),MATCH(D$16,Assumptions!$L$102:$R$102,0)) -> 0 | E23: =INDEX(Refinery,MATCH(Product_select,Assumptions!$L$93:$L$98,0),MATCH(E$16,Assumptions!$L$93:$R$93,0))*Crude_oil_litresPerBarrel*(INDEX(Refinery_capacity,2,MATCH(E$16,Assumptions!$L$93:$R$93,0)))*Operational_days*1000*Refinery_availability*INDEX(Production_High,MATCH($B23,Assumptions!$L$102:$L$131,0),MATCH(E$16,Assumptions!$L$102:$R$102,0)) -> 2.1674953e+09 | F23: =INDEX(Refinery,MATCH(Product_select,Assumptions!$L$93:$L$98,0),MATCH(F$16,Assumptions!$L$93:$R$93,0))*Crude_oil_litresPerBarrel*(INDEX(Refinery_capacity,2,MATCH(F$16,Assumptions!$L$93:$R$93,0)))*Operational_days*1000*Refinery_availability*INDEX(Production_High,MATCH($B23,Assumptions!$L$102:$L$131,0),MATCH(F$16,Assumptions!$L$102:$R$102,0)) -> 3.2419204e+09 | G23: =INDEX(Refinery,MATCH(Product_select,Assumptions!$L$93:$L$98,0),MATCH(G$16,Assumptions!$L$93:$R$93,0))*Crude_oil_litresPerBarrel*(INDEX(Refinery_capacity,2,MATCH(G$16,Assumptions!$L$93:$R$93,0)))*Operational_days*1000*Refinery_availability*INDEX(Production_High,MATCH($B23,Assumptions!$L$102:$L$131,0),MATCH(G$16,Assumptions!$L$102:$R$102,0)) -> 2.1152028e+09 | H23: =INDEX(Refinery,MATCH(Product_select,Assumptions!$L$93:$L$98,0),MATCH(H$16,Assumptions!$L$93:$R$93,0))*Crude_oil_litresPerBarrel*(INDEX(Refinery_capacity,2,MATCH(H$16,Assumptions!$L$93:$R$93,0)))*Operational_days*1000*Refinery_availability*INDEX(Production_High,MATCH($B23,Assumptions!$L$102:$L$131,0),MATCH(H$16,Assumptions!$L$102:$R$102,0)) -> 0 | I23: =SUM(C23:H23) -> 7.5246185e+09 | J23: =I23/Crude_oil_litresPerBarrel/Operational_days/1000 -> 129.66716 | K23: =SUM(C23:H23) -> 7.5246185e+09 | L23: =K23/Crude_oil_litresPerBarrel/Operational_days/1000 -> 129.66716 | N23: =E23+F23 -> 5.4094157e+09 | X23: 2030 | Y23: =I58 -> 6.588798e+09 | Z23: =I25 -> 7.4247339e+09
B24: 2029 | C24: =INDEX(Refinery,MATCH(Product_select,Assumptions!$L$93:$L$98,0),MATCH(C$16,Assumptions!$L$93:$R$93,0))*Crude_oil_litresPerBarrel*(INDEX(Refinery_capacity,2,MATCH(C$16,Assumptions!$L$93:$R$93,0)))*Operational_days*1000*Refinery_availability*INDEX(Production_High,MATCH($B24,Assumptions!$L$102:$L$131,0),MATCH(C$16,Assumptions!$L$102:$R$102,0)) -> 0 | D24: =INDEX(Refinery,MATCH(Product_select,Assumptions!$L$93:$L$98,0),MATCH(D$16,Assumptions!$L$93:$R$93,0))*Crude_oil_litresPerBarrel*(INDEX(Refinery_capacity,2,MATCH(D$16,Assumptions!$L$93:$R$93,0)))*Operational_days*1000*Refinery_availability*INDEX(Production_High,MATCH($B24,Assumptions!$L$102:$L$131,0),MATCH(D$16,Assumptions!$L$102:$R$102,0)) -> 0 | E24: =INDEX(Refinery,MATCH(Product_select,Assumptions!$L$93:$L$98,0),MATCH(E$16,Assumptions!$L$93:$R$93,0))*Crude_oil_litresPerBarrel*(INDEX(Refinery_capacity,2,MATCH(E$16,Assumptions!$L$93:$R$93,0)))*Operational_days*1000*Refinery_availability*INDEX(Production_High,MATCH($B24,Assumptions!$L$102:$L$131,0),MATCH(E$16,Assumptions!$L$102:$R$102,0)) -> 2.1674953e+09 | F24: =INDEX(Refinery,MATCH(Product_select,Assumptions!$L$93:$L$98,0),MATCH(F$16,Assumptions!$L$93:$R$93,0))*Crude_oil_litresPerBarrel*(INDEX(Refinery_capacity,2,MATCH(F$16,Assumptions!$L$93:$R$93,0)))*Operational_days*1000*Refinery_availability*INDEX(Production_High,MATCH($B24,Assumptions!$L$102:$L$131,0),MATCH(F$16,Assumptions!$L$102:$R$102,0)) -> 3.1420358e+09 | G24: =INDEX(Refinery,MATCH(Product_select,Assumptions!$L$93:$L$98,0),MATCH(G$16,Assumptions!$L$93:$R$93,0))*Crude_oil_litresPerBarrel*(INDEX(Refinery_capacity,2,MATCH(G$16,Assumptions!$L$93:$R$93,0)))*Operational_days*1000*Refinery_availability*INDEX(Production_High,MATCH($B24,Assumptions!$L$102:$L$131,0),MATCH(G$16,Assumptions!$L$102:$R$102,0)) -> 2.1152028e+09 | H24: =INDEX(Refinery,MATCH(Product_select,Assumptions!$L$93:$L$98,0),MATCH(H$16,Assumptions!$L$93:$R$93,0))*Crude_oil_litresPerBarrel*(INDEX(Refinery_capacity,2,MATCH(H$16,Assumptions!$L$93:$R$93,0)))*Operational_days*1000*Refinery_availability*INDEX(Production_High,MATCH($B24,Assumptions!$L$102:$L$131,0),MATCH(H$16,Assumptions!$L$102:$R$102,0)) -> 0 | I24: =SUM(C24:H24) -> 7.4247339e+09 | J24: =I24/Crude_oil_litresPerBarrel/Operational_days/1000 -> 127.94591 | K24: =SUM(C24:H24) -> 7.4247339e+09 | L24: =K24/Crude_oil_litresPerBarrel/Operational_days/1000 -> 127.94591 | N24: =E24+F24 -> 5.3095311e+09 | X24: 2031 | Y24: =I59 -> 4.8038018e+09 | Z24: =I26 -> 1.0552628e+10
B25: 2030 | C25: =INDEX(Refinery,MATCH(Product_select,Assumptions!$L$93:$L$98,0),MATCH(C$16,Assumptions!$L$93:$R$93,0))*Crude_oil_litresPerBarrel*(INDEX(Refinery_capacity,2,MATCH(C$16,Assumptions!$L$93:$R$93,0)))*Operational_days*1000*Refinery_availability*INDEX(Production_High,MATCH($B25,Assumptions!$L$102:$L$131,0),MATCH(C$16,Assumptions!$L$102:$R$102,0)) -> 0 | D25: =INDEX(Refinery,MATCH(Product_select,Assumptions!$L$93:$L$98,0),MATCH(D$16,Assumptions!$L$93:$R$93,0))*Crude_oil_litresPerBarrel*(INDEX(Refinery_capacity,2,MATCH(D$16,Assumptions!$L$93:$R$93,0)))*Operational_days*1000*Refinery_availability*INDEX(Production_High,MATCH($B25,Assumptions!$L$102:$L$131,0),MATCH(D$16,Assumptions!$L$102:$R$102,0)) -> 0 | E25: =INDEX(Refinery,MATCH(Product_select,Assumptions!$L$93:$L$98,0),MATCH(E$16,Assumptions!$L$93:$R$93,0))*Crude_oil_litresPerBarrel*(INDEX(Refinery_capacity,2,MATCH(E$16,Assumptions!$L$93:$R$93,0)))*Operational_days*1000*Refinery_availability*INDEX(Production_High,MATCH($B25,Assumptions!$L$102:$L$131,0),MATCH(E$16,Assumptions!$L$102:$R$102,0)) -> 2.1674953e+09 | F25: =INDEX(Refinery,MATCH(Product_select,Assumptions!$L$93:$L$98,0),MATCH(F$16,Assumptions!$L$93:$R$93,0))*Crude_oil_litresPerBarrel*(INDEX(Refinery_capacity,2,MATCH(F$16,Assumptions!$L$93:$R$93,0)))*Operational_days*1000*Refinery_availability*INDEX(Production_High,MATCH($B25,Assumptions!$L$102:$L$131,0),MATCH(F$16,Assumptions!$L$102:$R$102,0)) -> 3.1420358e+09 | G25: =INDEX(Refinery,MATCH(Product_select,Assumptions!$L$93:$L$98,0),MATCH(G$16,Assumptions!$L$93:$R$93,0))*Crude_oil_litresPerBarrel*(INDEX(Refinery_capacity,2,MATCH(G$16,Assumptions!$L$93:$R$93,0)))*Operational_days*1000*Refinery_availability*INDEX(Production_High,MATCH($B25,Assumptions!$L$102:$L$131,0),MATCH(G$16,Assumptions!$L$102:$R$102,0)) -> 2.1152028e+09 | H25: =INDEX(Refinery,MATCH(Product_select,Assumptions!$L$93:$L$98,0),MATCH(H$16,Assumptions!$L$93:$R$93,0))*Crude_oil_litresPerBarrel*(INDEX(Refinery_capacity,2,MATCH(H$16,Assumptions!$L$93:$R$93,0)))*Operational_days*1000*Refinery_availability*INDEX(Production_High,MATCH($B25,Assumptions!$L$102:$L$131,0),MATCH(H$16,Assumptions!$L$102:$R$102,0)) -> 0 | I25: =SUM(C25:H25) -> 7.4247339e+09 | J25: =I25/Crude_oil_litresPerBarrel/Operational_days/1000 -> 127.94591 | K25: =SUM(C25:H25) -> 7.4247339e+09 | L25: =K25/Crude_oil_litresPerBarrel/Operational_days/1000 -> 127.94591 | N25: =E25+F25 -> 5.3095311e+09 | X25: 2032 | Y25: =I60 -> 4.8038018e+09 | Z25: =I27 -> 1.0586311e+10
B26: 2031 | C26: =INDEX(Refinery,MATCH(Product_select,Assumptions!$L$93:$L$98,0),MATCH(C$16,Assumptions!$L$93:$R$93,0))*Crude_oil_litresPerBarrel*(INDEX(Refinery_capacity,2,MATCH(C$16,Assumptions!$L$93:$R$93,0)))*Operational_days*1000*Refinery_availability*INDEX(Production_High,MATCH($B26,Assumptions!$L$102:$L$131,0),MATCH(C$16,Assumptions!$L$102:$R$102,0))+ IF( INDEX(Production_High,MATCH($B26,Assumptions!$L$102:$L$131,0),MATCH(C$16,Assumptions!$L$102:$R$102,0))>0, IF(Product_select="Diesel", INDEX(fDiesel!$J$30:$J$45, MATCH($B26, fDiesel!$B$30:$B$45,0)) * INDEX(Assumptions!$U$110:$U$112, MATCH("Diesel", Assumptions!$T$110:$T$112,0)), IF(Product_select="Gasoline", INDEX(fGasoline!$L$30:$L$45, MATCH($B26, fGasoline!$B$30:$B$45,0)) * INDEX(Assumptions!$U$110:$U$112, MATCH("Gasoline", Assumptions!$T$110:$T$112,0)), IF(Product_select="Total", INDEX(fDiesel!$J$30:$J$45, MATCH($B26, fDiesel!$B$30:$B$45,0)) * INDEX(Assumptions!$U$110:$U$112, MATCH("Diesel", Assumptions!$T$110:$T$112,0)) + INDEX(fGasoline!$L$30:$L$45, MATCH($B26, fGasoline!$B$30:$B$45,0)) * INDEX(Assumptions!$U$110:$U$112, MATCH("Gasoline", Assumptions!$T$110:$T$112,0)) ) ) ), 0 ) -> 0 | D26: =INDEX(Refinery,MATCH(Product_select,Assumptions!$L$93:$L$98,0),MATCH(D$16,Assumptions!$L$93:$R$93,0))*Crude_oil_litresPerBarrel*(INDEX(Refinery_capacity,2,MATCH(D$16,Assumptions!$L$93:$R$93,0)))*Operational_days*1000*Refinery_availability*INDEX(Production_High,MATCH($B26,Assumptions!$L$102:$L$131,0),MATCH(D$16,Assumptions!$L$102:$R$102,0))+ IF( INDEX(Production_High,MATCH($B26,Assumptions!$L$102:$L$131,0),MATCH(D$16,Assumptions!$L$102:$R$102,0))>0, IF(Product_select="Diesel", INDEX(fDiesel!$J$30:$J$45, MATCH($B26, fDiesel!$B$30:$B$45,0)) * INDEX(Assumptions!$U$110:$U$112, MATCH("Diesel", Assumptions!$T$110:$T$112,0)), IF(Product_select="Gasoline", INDEX(fGasoline!$L$30:$L$45, MATCH($B26, fGasoline!$B$30:$B$45,0)) * INDEX(Assumptions!$U$110:$U$112, MATCH("Gasoline", Assumptions!$T$110:$T$112,0)), IF(Product_select="Total", INDEX(fDiesel!$J$30:$J$45, MATCH($B26, fDiesel!$B$30:$B$45,0)) * INDEX(Assumptions!$U$110:$U$112, MATCH("Diesel", Assumptions!$T$110:$T$112,0)) + INDEX(fGasoline!$L$30:$L$45, MATCH($B26, fGasoline!$B$30:$B$45,0)) * INDEX(Assumptions!$U$110:$U$112, MATCH("Gasoline", Assumptions!$T$110:$T$112,0)) ) ) ), 0 ) -> 0 | E26: =INDEX(Refinery,MATCH(Product_select,Assumptions!$L$93:$L$98,0),MATCH(E$16,Assumptions!$L$93:$R$93,0))*Crude_oil_litresPerBarrel*(INDEX(Refinery_capacity,2,MATCH(E$16,Assumptions!$L$93:$R$93,0)))*Operational_days*1000*Refinery_availability*INDEX(Production_High,MATCH($B26,Assumptions!$L$102:$L$131,0),MATCH(E$16,Assumptions!$L$102:$R$102,0))+ IF( INDEX(Production_High,MATCH($B26,Assumptions!$L$102:$L$131,0),MATCH(E$16,Assumptions!$L$102:$R$102,0))>0, IF(Product_select="Diesel", INDEX(fDiesel!$J$30:$J$45, MATCH($B26, fDiesel!$B$30:$B$45,0)) * INDEX(Assumptions!$U$110:$U$112, MATCH("Diesel", Assumptions!$T$110:$T$112,0)), IF(Product_select="Gasoline", INDEX(fGasoline!$L$30:$L$45, MATCH($B26, fGasoline!$B$30:$B$45,0)) * INDEX(Assumptions!$U$110:$U$112, MATCH("Gasoline", Assumptions!$T$110:$T$112,0)), IF(Product_select="Total", INDEX(fDiesel!$J$30:$J$45, MATCH($B26, fDiesel!$B$30:$B$45,0)) * INDEX(Assumptions!$U$110:$U$112, MATCH("Diesel", Assumptions!$T$110:$T$112,0)) + INDEX(fGasoline!$L$30:$L$45, MATCH($B26, fGasoline!$B$30:$B$45,0)) * INDEX(Assumptions!$U$110:$U$112, MATCH("Gasoline", Assumptions!$T$110:$T$112,0)) ) ) ), 0 ) -> 3.1768317e+09 | F26: =INDEX(Refinery,MATCH(Product_select,Assumptions!$L$93:$L$98,0),MATCH(F$16,Assumptions!$L$93:$R$93,0))*Crude_oil_litresPerBarrel*(INDEX(Refinery_capacity,2,MATCH(F$16,Assumptions!$L$93:$R$93,0)))*Operational_days*1000*Refinery_availability*INDEX(Production_High,MATCH($B26,Assumptions!$L$102:$L$131,0),MATCH(F$16,Assumptions!$L$102:$R$102,0))+ IF( INDEX(Production_High,MATCH($B26,Assumptions!$L$102:$L$131,0),MATCH(F$16,Assumptions!$L$102:$R$102,0))>0, IF(Product_select="Diesel", INDEX(fDiesel!$J$30:$J$45, MATCH($B26, fDiesel!$B$30:$B$45,0)) * INDEX(Assumptions!$U$110:$U$112, MATCH("Diesel", Assumptions!$T$110:$T$112,0)), IF(Product_select="Gasoline", INDEX(fGasoline!$L$30:$L$45, MATCH($B26, fGasoline!$B$30:$B$45,0)) * INDEX(Assumptions!$U$110:$U$112, MATCH("Gasoline", Assumptions!$T$110:$T$112,0)), IF(Product_select="Total", INDEX(fDiesel!$J$30:$J$45, MATCH($B26, fDiesel!$B$30:$B$45,0)) * INDEX(Assumptions!$U$110:$U$112, MATCH("Diesel", Assumptions!$T$110:$T$112,0)) + INDEX(fGasoline!$L$30:$L$45, MATCH($B26, fGasoline!$B$30:$B$45,0)) * INDEX(Assumptions!$U$110:$U$112, MATCH("Gasoline", Assumptions!$T$110:$T$112,0)) ) ) ), 0 ) -> 4.2512568e+09 | G26: =INDEX(Refinery,MATCH(Product_select,Assumptions!$L$93:$L$98,0),MATCH(G$16,Assumptions!$L$93:$R$93,0))*Crude_oil_litresPerBarrel*(INDEX(Refinery_capacity,2,MATCH(G$16,Assumptions!$L$93:$R$93,0)))*Operational_days*1000*Refinery_availability*INDEX(Production_High,MATCH($B26,Assumptions!$L$102:$L$131,0),MATCH(G$16,Assumptions!$L$102:$R$102,0))+ IF( INDEX(Production_High,MATCH($B26,Assumptions!$L$102:$L$131,0),MATCH(G$16,Assumptions!$L$102:$R$102,0))>0, IF(Product_select="Diesel", INDEX(fDiesel!$J$30:$J$45, MATCH($B26, fDiesel!$B$30:$B$45,0)) * INDEX(Assumptions!$U$110:$U$112, MATCH("Diesel", Assumptions!$T$110:$T$112,0)), IF(Product_select="Gasoline", INDEX(fGasoline!$L$30:$L$45, MATCH($B26, fGasoline!$B$30:$B$45,0)) * INDEX(Assumptions!$U$110:$U$112, MATCH("Gasoline", Assumptions!$T$110:$T$112,0)), IF(Product_select="Total", INDEX(fDiesel!$J$30:$J$45, MATCH($B26, fDiesel!$B$30:$B$45,0)) * INDEX(Assumptions!$U$110:$U$112, MATCH("Diesel", Assumptions!$T$110:$T$112,0)) + INDEX(fGasoline!$L$30:$L$45, MATCH($B26, fGasoline!$B$30:$B$45,0)) * INDEX(Assumptions!$U$110:$U$112, MATCH("Gasoline", Assumptions!$T$110:$T$112,0)) ) ) ), 0 ) -> 3.1245392e+09 | H26: =INDEX(Refinery,MATCH(Product_select,Assumptions!$L$93:$L$98,0),MATCH(H$16,Assumptions!$L$93:$R$93,0))*Crude_oil_litresPerBarrel*(INDEX(Refinery_capacity,2,MATCH(H$16,Assumptions!$L$93:$R$93,0)))*Operational_days*1000*Refinery_availability*INDEX(Production_High,MATCH($B26,Assumptions!$L$102:$L$131,0),MATCH(H$16,Assumptions!$L$102:$R$102,0))+ IF( INDEX(Production_High,MATCH($B26,Assumptions!$L$102:$L$131,0),MATCH(H$16,Assumptions!$L$102:$R$102,0))>0, IF(Product_select="Diesel", INDEX(fDiesel!$J$30:$J$45, MATCH($B26, fDiesel!$B$30:$B$45,0)) * INDEX(Assumptions!$U$110:$U$112, MATCH("Diesel", Assumptions!$T$110:$T$112,0)), IF(Product_select="Gasoline", INDEX(fGasoline!$L$30:$L$45, MATCH($B26, fGasoline!$B$30:$B$45,0)) * INDEX(Assumptions!$U$110:$U$112, MATCH("Gasoline", Assumptions!$T$110:$T$112,0)), IF(Product_select="Total", INDEX(fDiesel!$J$30:$J$45, MATCH($B26, fDiesel!$B$30:$B$45,0)) * INDEX(Assumptions!$U$110:$U$112, MATCH("Diesel", Assumptions!$T$110:$T$112,0)) + INDEX(fGasoline!$L$30:$L$45, MATCH($B26, fGasoline!$B$30:$B$45,0)) * INDEX(Assumptions!$U$110:$U$112, MATCH("Gasoline", Assumptions!$T$110:$T$112,0)) ) ) ), 0 ) -> 0 | I26: =SUM(C26:H26) -> 1.0552628e+10 | J26: =I26/Crude_oil_litresPerBarrel/Operational_days/1000 -> 181.847 | K26: =SUM(C26:H26) -> 1.0552628e+10 | L26: =K26/Crude_oil_litresPerBarrel/Operational_days/1000 -> 181.847 | N26: =E26+F26 -> 7.4280885e+09 | X26: 2033 | Y26: =I61 -> 4.6915981e+09 | Z26: =I28 -> 1.0521501e+10
B27: 2032 | C27: =INDEX(Refinery,MATCH(Product_select,Assumptions!$L$93:$L$98,0),MATCH(C$16,Assumptions!$L$93:$R$93,0))*Crude_oil_litresPerBarrel*(INDEX(Refinery_capacity,2,MATCH(C$16,Assumptions!$L$93:$R$93,0)))*Operational_days*1000*Refinery_availability*INDEX(Production_High,MATCH($B27,Assumptions!$L$102:$L$131,0),MATCH(C$16,Assumptions!$L$102:$R$102,0))+ IF( INDEX(Production_High,MATCH($B27,Assumptions!$L$102:$L$131,0),MATCH(C$16,Assumptions!$L$102:$R$102,0))>0, IF(Product_select="Diesel", INDEX(fDiesel!$J$30:$J$45, MATCH($B27, fDiesel!$B$30:$B$45,0)) * INDEX(Assumptions!$U$110:$U$112, MATCH("Diesel", Assumptions!$T$110:$T$112,0)), IF(Product_select="Gasoline", INDEX(fGasoline!$L$30:$L$45, MATCH($B27, fGasoline!$B$30:$B$45,0)) * INDEX(Assumptions!$U$110:$U$112, MATCH("Gasoline", Assumptions!$T$110:$T$112,0)), IF(Product_select="Total", INDEX(fDiesel!$J$30:$J$45, MATCH($B27, fDiesel!$B$30:$B$45,0)) * INDEX(Assumptions!$U$110:$U$112, MATCH("Diesel", Assumptions!$T$110:$T$112,0)) + INDEX(fGasoline!$L$30:$L$45, MATCH($B27, fGasoline!$B$30:$B$45,0)) * INDEX(Assumptions!$U$110:$U$112, MATCH("Gasoline", Assumptions!$T$110:$T$112,0)) ) ) ), 0 ) -> 0 | D27: =INDEX(Refinery,MATCH(Product_select,Assumptions!$L$93:$L$98,0),MATCH(D$16,Assumptions!$L$93:$R$93,0))*Crude_oil_litresPerBarrel*(INDEX(Refinery_capacity,2,MATCH(D$16,Assumptions!$L$93:$R$93,0)))*Operational_days*1000*Refinery_availability*INDEX(Production_High,MATCH($B27,Assumptions!$L$102:$L$131,0),MATCH(D$16,Assumptions!$L$102:$R$102,0))+ IF( INDEX(Production_High,MATCH($B27,Assumptions!$L$102:$L$131,0),MATCH(D$16,Assumptions!$L$102:$R$102,0))>0, IF(Product_select="Diesel", INDEX(fDiesel!$J$30:$J$45, MATCH($B27, fDiesel!$B$30:$B$45,0)) * INDEX(Assumptions!$U$110:$U$112, MATCH("Diesel", Assumptions!$T$110:$T$112,0)), IF(Product_select="Gasoline", INDEX(fGasoline!$L$30:$L$45, MATCH($B27, fGasoline!$B$30:$B$45,0)) * INDEX(Assumptions!$U$110:$U$112, MATCH("Gasoline", Assumptions!$T$110:$T$112,0)), IF(Product_select="Total", INDEX(fDiesel!$J$30:$J$45, MATCH($B27, fDiesel!$B$30:$B$45,0)) * INDEX(Assumptions!$U$110:$U$112, MATCH("Diesel", Assumptions!$T$110:$T$112,0)) + INDEX(fGasoline!$L$30:$L$45, MATCH($B27, fGasoline!$B$30:$B$45,0)) * INDEX(Assumptions!$U$110:$U$112, MATCH("Gasoline", Assumptions!$T$110:$T$112,0)) ) ) ), 0 ) -> 0 | E27: =INDEX(Refinery,MATCH(Product_select,Assumptions!$L$93:$L$98,0),MATCH(E$16,Assumptions!$L$93:$R$93,0))*Crude_oil_litresPerBarrel*(INDEX(Refinery_capacity,2,MATCH(E$16,Assumptions!$L$93:$R$93,0)))*Operational_days*1000*Refinery_availability*INDEX(Production_High,MATCH($B27,Assumptions!$L$102:$L$131,0),MATCH(E$16,Assumptions!$L$102:$R$102,0))+ IF( INDEX(Production_High,MATCH($B27,Assumptions!$L$102:$L$131,0),MATCH(E$16,Assumptions!$L$102:$R$102,0))>0, IF(Product_select="Diesel", INDEX(fDiesel!$J$30:$J$45, MATCH($B27, fDiesel!$B$30:$B$45,0)) * INDEX(Assumptions!$U$110:$U$112, MATCH("Diesel", Assumptions!$T$110:$T$112,0)), IF(Product_select="Gasoline", INDEX(fGasoline!$L$30:$L$45, MATCH($B27, fGasoline!$B$30:$B$45,0)) * INDEX(Assumptions!$U$110:$U$112, MATCH("Gasoline", Assumptions!$T$110:$T$112,0)), IF(Product_select="Total", INDEX(fDiesel!$J$30:$J$45, MATCH($B27, fDiesel!$B$30:$B$45,0)) * INDEX(Assumptions!$U$110:$U$112, MATCH("Diesel", Assumptions!$T$110:$T$112,0)) + INDEX(fGasoline!$L$30:$L$45, MATCH($B27, fGasoline!$B$30:$B$45,0)) * INDEX(Assumptions!$U$110:$U$112, MATCH("Gasoline", Assumptions!$T$110:$T$112,0)) ) ) ), 0 ) -> 3.1880596e+09 | F27: =INDEX(Refinery,MATCH(Product_select,Assumptions!$L$93:$L$98,0),MATCH(F$16,Assumptions!$L$93:$R$93,0))*Crude_oil_litresPerBarrel*(INDEX(Refinery_capacity,2,MATCH(F$16,Assumptions!$L$93:$R$93,0)))*Operational_days*1000*Refinery_availability*INDEX(Production_High,MATCH($B27,Assumptions!$L$102:$L$131,0),MATCH(F$16,Assumptions!$L$102:$R$102,0))+ IF( INDEX(Production_High,MATCH($B27,Assumptions!$L$102:$L$131,0),MATCH(F$16,Assumptions!$L$102:$R$102,0))>0, IF(Product_select="Diesel", INDEX(fDiesel!$J$30:$J$45, MATCH($B27, fDiesel!$B$30:$B$45,0)) * INDEX(Assumptions!$U$110:$U$112, MATCH("Diesel", Assumptions!$T$110:$T$112,0)), IF(Product_select="Gasoline", INDEX(fGasoline!$L$30:$L$45, MATCH($B27, fGasoline!$B$30:$B$45,0)) * INDEX(Assumptions!$U$110:$U$112, MATCH("Gasoline", Assumptions!$T$110:$T$112,0)), IF(Product_select="Total", INDEX(fDiesel!$J$30:$J$45, MATCH($B27, fDiesel!$B$30:$B$45,0)) * INDEX(Assumptions!$U$110:$U$112, MATCH("Diesel", Assumptions!$T$110:$T$112,0)) + INDEX(fGasoline!$L$30:$L$45, MATCH($B27, fGasoline!$B$30:$B$45,0)) * INDEX(Assumptions!$U$110:$U$112, MATCH("Gasoline", Assumptions!$T$110:$T$112,0)) ) ) ), 0 ) -> 4.2624847e+09 | G27: =INDEX(Refinery,MATCH(Product_select,Assumptions!$L$93:$L$98,0),MATCH(G$16,Assumptions!$L$93:$R$93,0))*Crude_oil_litresPerBarrel*(INDEX(Refinery_capacity,2,MATCH(G$16,Assumptions!$L$93:$R$93,0)))*Operational_days*1000*Refinery_availability*INDEX(Production_High,MATCH($B27,Assumptions!$L$102:$L$131,0),MATCH(G$16,Assumptions!$L$102:$R$102,0))+ IF( INDEX(Production_High,MATCH($B27,Assumptions!$L$102:$L$131,0),MATCH(G$16,Assumptions!$L$102:$R$102,0))>0, IF(Product_select="Diesel", INDEX(fDiesel!$J$30:$J$45, MATCH($B27, fDiesel!$B$30:$B$45,0)) * INDEX(Assumptions!$U$110:$U$112, MATCH("Diesel", Assumptions!$T$110:$T$112,0)), IF(Product_select="Gasoline", INDEX(fGasoline!$L$30:$L$45, MATCH($B27, fGasoline!$B$30:$B$45,0)) * INDEX(Assumptions!$U$110:$U$112, MATCH("Gasoline", Assumptions!$T$110:$T$112,0)), IF(Product_select="Total", INDEX(fDiesel!$J$30:$J$45, MATCH($B27, fDiesel!$B$30:$B$45,0)) * INDEX(Assumptions!$U$110:$U$112, MATCH("Diesel", Assumptions!$T$110:$T$112,0)) + INDEX(fGasoline!$L$30:$L$45, MATCH($B27, fGasoline!$B$30:$B$45,0)) * INDEX(Assumptions!$U$110:$U$112, MATCH("Gasoline", Assumptions!$T$110:$T$112,0)) ) ) ), 0 ) -> 3.1357671e+09 | H27: =INDEX(Refinery,MATCH(Product_select,Assumptions!$L$93:$L$98,0),MATCH(H$16,Assumptions!$L$93:$R$93,0))*Crude_oil_litresPerBarrel*(INDEX(Refinery_capacity,2,MATCH(H$16,Assumptions!$L$93:$R$93,0)))*Operational_days*1000*Refinery_availability*INDEX(Production_High,MATCH($B27,Assumptions!$L$102:$L$131,0),MATCH(H$16,Assumptions!$L$102:$R$102,0))+ IF( INDEX(Production_High,MATCH($B27,Assumptions!$L$102:$L$131,0),MATCH(H$16,Assumptions!$L$102:$R$102,0))>0, IF(Product_select="Diesel", INDEX(fDiesel!$J$30:$J$45, MATCH($B27, fDiesel!$B$30:$B$45,0)) * INDEX(Assumptions!$U$110:$U$112, MATCH("Diesel", Assumptions!$T$110:$T$112,0)), IF(Product_select="Gasoline", INDEX(fGasoline!$L$30:$L$45, MATCH($B27, fGasoline!$B$30:$B$45,0)) * INDEX(Assumptions!$U$110:$U$112, MATCH("Gasoline", Assumptions!$T$110:$T$112,0)), IF(Product_select="Total", INDEX(fDiesel!$J$30:$J$45, MATCH($B27, fDiesel!$B$30:$B$45,0)) * INDEX(Assumptions!$U$110:$U$112, MATCH("Diesel", Assumptions!$T$110:$T$112,0)) + INDEX(fGasoline!$L$30:$L$45, MATCH($B27, fGasoline!$B$30:$B$45,0)) * INDEX(Assumptions!$U$110:$U$112, MATCH("Gasoline", Assumptions!$T$110:$T$112,0)) ) ) ), 0 ) -> 0 | I27: =SUM(C27:H27) -> 1.0586311e+10 | J27: =I27/Crude_oil_litresPerBarrel/Operational_days/1000 -> 182.42745 | K27: =SUM(C27:H27) -> 1.0586311e+10 | L27: =K27/Crude_oil_litresPerBarrel/Operational_days/1000 -> 182.42745 | N27: =E27+F27 -> 7.4505444e+09 | X27: 2034 | Y27: =I62 -> 4.5793945e+09 | Z27: =I29 -> 1.0431509e+10
B28: 2033 | C28: =INDEX(Refinery,MATCH(Product_select,Assumptions!$L$93:$L$98,0),MATCH(C$16,Assumptions!$L$93:$R$93,0))*Crude_oil_litresPerBarrel*(INDEX(Refinery_capacity,2,MATCH(C$16,Assumptions!$L$93:$R$93,0)))*Operational_days*1000*Refinery_availability*INDEX(Production_High,MATCH($B28,Assumptions!$L$102:$L$131,0),MATCH(C$16,Assumptions!$L$102:$R$102,0))+ IF( INDEX(Production_High,MATCH($B28,Assumptions!$L$102:$L$131,0),MATCH(C$16,Assumptions!$L$102:$R$102,0))>0, IF(Product_select="Diesel", INDEX(fDiesel!$J$30:$J$45, MATCH($B28, fDiesel!$B$30:$B$45,0)) * INDEX(Assumptions!$U$110:$U$112, MATCH("Diesel", Assumptions!$T$110:$T$112,0)), IF(Product_select="Gasoline", INDEX(fGasoline!$L$30:$L$45, MATCH($B28, fGasoline!$B$30:$B$45,0)) * INDEX(Assumptions!$U$110:$U$112, MATCH("Gasoline", Assumptions!$T$110:$T$112,0)), IF(Product_select="Total", INDEX(fDiesel!$J$30:$J$45, MATCH($B28, fDiesel!$B$30:$B$45,0)) * INDEX(Assumptions!$U$110:$U$112, MATCH("Diesel", Assumptions!$T$110:$T$112,0)) + INDEX(fGasoline!$L$30:$L$45, MATCH($B28, fGasoline!$B$30:$B$45,0)) * INDEX(Assumptions!$U$110:$U$112, MATCH("Gasoline", Assumptions!$T$110:$T$112,0)) ) ) ), 0 ) -> 0 | D28: =INDEX(Refinery,MATCH(Product_select,Assumptions!$L$93:$L$98,0),MATCH(D$16,Assumptions!$L$93:$R$93,0))*Crude_oil_litresPerBarrel*(INDEX(Refinery_capacity,2,MATCH(D$16,Assumptions!$L$93:$R$93,0)))*Operational_days*1000*Refinery_availability*INDEX(Production_High,MATCH($B28,Assumptions!$L$102:$L$131,0),MATCH(D$16,Assumptions!$L$102:$R$102,0))+ IF( INDEX(Production_High,MATCH($B28,Assumptions!$L$102:$L$131,0),MATCH(D$16,Assumptions!$L$102:$R$102,0))>0, IF(Product_select="Diesel", INDEX(fDiesel!$J$30:$J$45, MATCH($B28, fDiesel!$B$30:$B$45,0)) * INDEX(Assumptions!$U$110:$U$112, MATCH("Diesel", Assumptions!$T$110:$T$112,0)), IF(Product_select="Gasoline", INDEX(fGasoline!$L$30:$L$45, MATCH($B28, fGasoline!$B$30:$B$45,0)) * INDEX(Assumptions!$U$110:$U$112, MATCH("Gasoline", Assumptions!$T$110:$T$112,0)), IF(Product_select="Total", INDEX(fDiesel!$J$30:$J$45, MATCH($B28, fDiesel!$B$30:$B$45,0)) * INDEX(Assumptions!$U$110:$U$112, MATCH("Diesel", Assumptions!$T$110:$T$112,0)) + INDEX(fGasoline!$L$30:$L$45, MATCH($B28, fGasoline!$B$30:$B$45,0)) * INDEX(Assumptions!$U$110:$U$112, MATCH("Gasoline", Assumptions!$T$110:$T$112,0)) ) ) ), 0 ) -> 0 | E28: =INDEX(Refinery,MATCH(Product_select,Assumptions!$L$93:$L$98,0),MATCH(E$16,Assumptions!$L$93:$R$93,0))*Crude_oil_litresPerBarrel*(INDEX(Refinery_capacity,2,MATCH(E$16,Assumptions!$L$93:$R$93,0)))*Operational_days*1000*Refinery_availability*INDEX(Production_High,MATCH($B28,Assumptions!$L$102:$L$131,0),MATCH(E$16,Assumptions!$L$102:$R$102,0))+ IF( INDEX(Production_High,MATCH($B28,Assumptions!$L$102:$L$131,0),MATCH(E$16,Assumptions!$L$102:$R$102,0))>0, IF(Product_select="Diesel", INDEX(fDiesel!$J$30:$J$45, MATCH($B28, fDiesel!$B$30:$B$45,0)) * INDEX(Assumptions!$U$110:$U$112, MATCH("Diesel", Assumptions!$T$110:$T$112,0)), IF(Product_select="Gasoline", INDEX(fGasoline!$L$30:$L$45, MATCH($B28, fGasoline!$B$30:$B$45,0)) * INDEX(Assumptions!$U$110:$U$112, MATCH("Gasoline", Assumptions!$T$110:$T$112,0)), IF(Product_select="Total", INDEX(fDiesel!$J$30:$J$45, MATCH($B28, fDiesel!$B$30:$B$45,0)) * INDEX(Assumptions!$U$110:$U$112, MATCH("Diesel", Assumptions!$T$110:$T$112,0)) + INDEX(fGasoline!$L$30:$L$45, MATCH($B28, fGasoline!$B$30:$B$45,0)) * INDEX(Assumptions!$U$110:$U$112, MATCH("Gasoline", Assumptions!$T$110:$T$112,0)) ) ) ), 0 ) -> 3.198752e+09 | F28: =INDEX(Refinery,MATCH(Product_select,Assumptions!$L$93:$L$98,0),MATCH(F$16,Assumptions!$L$93:$R$93,0))*Crude_oil_litresPerBarrel*(INDEX(Refinery_capacity,2,MATCH(F$16,Assumptions!$L$93:$R$93,0)))*Operational_days*1000*Refinery_availability*INDEX(Production_High,MATCH($B28,Assumptions!$L$102:$L$131,0),MATCH(F$16,Assumptions!$L$102:$R$102,0))+ IF( INDEX(Production_High,MATCH($B28,Assumptions!$L$102:$L$131,0),MATCH(F$16,Assumptions!$L$102:$R$102,0))>0, IF(Product_select="Diesel", INDEX(fDiesel!$J$30:$J$45, MATCH($B28, fDiesel!$B$30:$B$45,0)) * INDEX(Assumptions!$U$110:$U$112, MATCH("Diesel", Assumptions!$T$110:$T$112,0)), IF(Product_select="Gasoline", INDEX(fGasoline!$L$30:$L$45, MATCH($B28, fGasoline!$B$30:$B$45,0)) * INDEX(Assumptions!$U$110:$U$112, MATCH("Gasoline", Assumptions!$T$110:$T$112,0)), IF(Product_select="Total", INDEX(fDiesel!$J$30:$J$45, MATCH($B28, fDiesel!$B$30:$B$45,0)) * INDEX(Assumptions!$U$110:$U$112, MATCH("Diesel", Assumptions!$T$110:$T$112,0)) + INDEX(fGasoline!$L$30:$L$45, MATCH($B28, fGasoline!$B$30:$B$45,0)) * INDEX(Assumptions!$U$110:$U$112, MATCH("Gasoline", Assumptions!$T$110:$T$112,0)) ) ) ), 0 ) -> 4.1762891e+09 | G28: =INDEX(Refinery,MATCH(Product_select,Assumptions!$L$93:$L$98,0),MATCH(G$16,Assumptions!$L$93:$R$93,0))*Crude_oil_litresPerBarrel*(INDEX(Refinery_capacity,2,MATCH(G$16,Assumptions!$L$93:$R$93,0)))*Operational_days*1000*Refinery_availability*INDEX(Production_High,MATCH($B28,Assumptions!$L$102:$L$131,0),MATCH(G$16,Assumptions!$L$102:$R$102,0))+ IF( INDEX(Production_High,MATCH($B28,Assumptions!$L$102:$L$131,0),MATCH(G$16,Assumptions!$L$102:$R$102,0))>0, IF(Product_select="Diesel", INDEX(fDiesel!$J$30:$J$45, MATCH($B28, fDiesel!$B$30:$B$45,0)) * INDEX(Assumptions!$U$110:$U$112, MATCH("Diesel", Assumptions!$T$110:$T$112,0)), IF(Product_select="Gasoline", INDEX(fGasoline!$L$30:$L$45, MATCH($B28, fGasoline!$B$30:$B$45,0)) * INDEX(Assumptions!$U$110:$U$112, MATCH("Gasoline", Assumptions!$T$110:$T$112,0)), IF(Product_select="Total", INDEX(fDiesel!$J$30:$J$45, MATCH($B28, fDiesel!$B$30:$B$45,0)) * INDEX(Assumptions!$U$110:$U$112, MATCH("Diesel", Assumptions!$T$110:$T$112,0)) + INDEX(fGasoline!$L$30:$L$45, MATCH($B28, fGasoline!$B$30:$B$45,0)) * INDEX(Assumptions!$U$110:$U$112, MATCH("Gasoline", Assumptions!$T$110:$T$112,0)) ) ) ), 0 ) -> 3.1464595e+09 | H28: =INDEX(Refinery,MATCH(Product_select,Assumptions!$L$93:$L$98,0),MATCH(H$16,Assumptions!$L$93:$R$93,0))*Crude_oil_litresPerBarrel*(INDEX(Refinery_capacity,2,MATCH(H$16,Assumptions!$L$93:$R$93,0)))*Operational_days*1000*Refinery_availability*INDEX(Production_High,MATCH($B28,Assumptions!$L$102:$L$131,0),MATCH(H$16,Assumptions!$L$102:$R$102,0))+ IF( INDEX(Production_High,MATCH($B28,Assumptions!$L$102:$L$131,0),MATCH(H$16,Assumptions!$L$102:$R$102,0))>0, IF(Product_select="Diesel", INDEX(fDiesel!$J$30:$J$45, MATCH($B28, fDiesel!$B$30:$B$45,0)) * INDEX(Assumptions!$U$110:$U$112, MATCH("Diesel", Assumptions!$T$110:$T$112,0)), IF(Product_select="Gasoline", INDEX(fGasoline!$L$30:$L$45, MATCH($B28, fGasoline!$B$30:$B$45,0)) * INDEX(Assumptions!$U$110:$U$112, MATCH("Gasoline", Assumptions!$T$110:$T$112,0)), IF(Product_select="Total", INDEX(fDiesel!$J$30:$J$45, MATCH($B28, fDiesel!$B$30:$B$45,0)) * INDEX(Assumptions!$U$110:$U$112, MATCH("Diesel", Assumptions!$T$110:$T$112,0)) + INDEX(fGasoline!$L$30:$L$45, MATCH($B28, fGasoline!$B$30:$B$45,0)) * INDEX(Assumptions!$U$110:$U$112, MATCH("Gasoline", Assumptions!$T$110:$T$112,0)) ) ) ), 0 ) -> 0 | I28: =SUM(C28:H28) -> 1.0521501e+10 | J28: =I28/Crude_oil_litresPerBarrel/Operational_days/1000 -> 181.3106 | K28: =SUM(C28:H28) -> 1.0521501e+10 | L28: =K28/Crude_oil_litresPerBarrel/Operational_days/1000 -> 181.3106 | N28: =E28+F28 -> 7.3750411e+09 | X28: 2035 | Y28: =I63 -> 4.4671908e+09 | Z28: =I30 -> 1.0338854e+10
B29: 2034 | C29: =INDEX(Refinery,MATCH(Product_select,Assumptions!$L$93:$L$98,0),MATCH(C$16,Assumptions!$L$93:$R$93,0))*Crude_oil_litresPerBarrel*(INDEX(Refinery_capacity,2,MATCH(C$16,Assumptions!$L$93:$R$93,0)))*Operational_days*1000*Refinery_availability*INDEX(Production_High,MATCH($B29,Assumptions!$L$102:$L$131,0),MATCH(C$16,Assumptions!$L$102:$R$102,0))+ IF( INDEX(Production_High,MATCH($B29,Assumptions!$L$102:$L$131,0),MATCH(C$16,Assumptions!$L$102:$R$102,0))>0, IF(Product_select="Diesel", INDEX(fDiesel!$J$30:$J$45, MATCH($B29, fDiesel!$B$30:$B$45,0)) * INDEX(Assumptions!$U$110:$U$112, MATCH("Diesel", Assumptions!$T$110:$T$112,0)), IF(Product_select="Gasoline", INDEX(fGasoline!$L$30:$L$45, MATCH($B29, fGasoline!$B$30:$B$45,0)) * INDEX(Assumptions!$U$110:$U$112, MATCH("Gasoline", Assumptions!$T$110:$T$112,0)), IF(Product_select="Total", INDEX(fDiesel!$J$30:$J$45, MATCH($B29, fDiesel!$B$30:$B$45,0)) * INDEX(Assumptions!$U$110:$U$112, MATCH("Diesel", Assumptions!$T$110:$T$112,0)) + INDEX(fGasoline!$L$30:$L$45, MATCH($B29, fGasoline!$B$30:$B$45,0)) * INDEX(Assumptions!$U$110:$U$112, MATCH("Gasoline", Assumptions!$T$110:$T$112,0)) ) ) ), 0 ) -> 0 | D29: =INDEX(Refinery,MATCH(Product_select,Assumptions!$L$93:$L$98,0),MATCH(D$16,Assumptions!$L$93:$R$93,0))*Crude_oil_litresPerBarrel*(INDEX(Refinery_capacity,2,MATCH(D$16,Assumptions!$L$93:$R$93,0)))*Operational_days*1000*Refinery_availability*INDEX(Production_High,MATCH($B29,Assumptions!$L$102:$L$131,0),MATCH(D$16,Assumptions!$L$102:$R$102,0))+ IF( INDEX(Production_High,MATCH($B29,Assumptions!$L$102:$L$131,0),MATCH(D$16,Assumptions!$L$102:$R$102,0))>0, IF(Product_select="Diesel", INDEX(fDiesel!$J$30:$J$45, MATCH($B29, fDiesel!$B$30:$B$45,0)) * INDEX(Assumptions!$U$110:$U$112, MATCH("Diesel", Assumptions!$T$110:$T$112,0)), IF(Product_select="Gasoline", INDEX(fGasoline!$L$30:$L$45, MATCH($B29, fGasoline!$B$30:$B$45,0)) * INDEX(Assumptions!$U$110:$U$112, MATCH("Gasoline", Assumptions!$T$110:$T$112,0)), IF(Product_select="Total", INDEX(fDiesel!$J$30:$J$45, MATCH($B29, fDiesel!$B$30:$B$45,0)) * INDEX(Assumptions!$U$110:$U$112, MATCH("Diesel", Assumptions!$T$110:$T$112,0)) + INDEX(fGasoline!$L$30:$L$45, MATCH($B29, fGasoline!$B$30:$B$45,0)) * INDEX(Assumptions!$U$110:$U$112, MATCH("Gasoline", Assumptions!$T$110:$T$112,0)) ) ) ), 0 ) -> 0 | E29: =INDEX(Refinery,MATCH(Product_select,Assumptions!$L$93:$L$98,0),MATCH(E$16,Assumptions!$L$93:$R$93,0))*Crude_oil_litresPerBarrel*(INDEX(Refinery_capacity,2,MATCH(E$16,Assumptions!$L$93:$R$93,0)))*Operational_days*1000*Refinery_availability*INDEX(Production_High,MATCH($B29,Assumptions!$L$102:$L$131,0),MATCH(E$16,Assumptions!$L$102:$R$102,0))+ IF( INDEX(Production_High,MATCH($B29,Assumptions!$L$102:$L$131,0),MATCH(E$16,Assumptions!$L$102:$R$102,0))>0, IF(Product_select="Diesel", INDEX(fDiesel!$J$30:$J$45, MATCH($B29, fDiesel!$B$30:$B$45,0)) * INDEX(Assumptions!$U$110:$U$112, MATCH("Diesel", Assumptions!$T$110:$T$112,0)), IF(Product_select="Gasoline", INDEX(fGasoline!$L$30:$L$45, MATCH($B29, fGasoline!$B$30:$B$45,0)) * INDEX(Assumptions!$U$110:$U$112, MATCH("Gasoline", Assumptions!$T$110:$T$112,0)), IF(Product_select="Total", INDEX(fDiesel!$J$30:$J$45, MATCH($B29, fDiesel!$B$30:$B$45,0)) * INDEX(Assumptions!$U$110:$U$112, MATCH("Diesel", Assumptions!$T$110:$T$112,0)) + INDEX(fGasoline!$L$30:$L$45, MATCH($B29, fGasoline!$B$30:$B$45,0)) * INDEX(Assumptions!$U$110:$U$112, MATCH("Gasoline", Assumptions!$T$110:$T$112,0)) ) ) ), 0 ) -> 3.201051e+09 | F29: =INDEX(Refinery,MATCH(Product_select,Assumptions!$L$93:$L$98,0),MATCH(F$16,Assumptions!$L$93:$R$93,0))*Crude_oil_litresPerBarrel*(INDEX(Refinery_capacity,2,MATCH(F$16,Assumptions!$L$93:$R$93,0)))*Operational_days*1000*Refinery_availability*INDEX(Production_High,MATCH($B29,Assumptions!$L$102:$L$131,0),MATCH(F$16,Assumptions!$L$102:$R$102,0))+ IF( INDEX(Production_High,MATCH($B29,Assumptions!$L$102:$L$131,0),MATCH(F$16,Assumptions!$L$102:$R$102,0))>0, IF(Product_select="Diesel", INDEX(fDiesel!$J$30:$J$45, MATCH($B29, fDiesel!$B$30:$B$45,0)) * INDEX(Assumptions!$U$110:$U$112, MATCH("Diesel", Assumptions!$T$110:$T$112,0)), IF(Product_select="Gasoline", INDEX(fGasoline!$L$30:$L$45, MATCH($B29, fGasoline!$B$30:$B$45,0)) * INDEX(Assumptions!$U$110:$U$112, MATCH("Gasoline", Assumptions!$T$110:$T$112,0)), IF(Product_select="Total", INDEX(fDiesel!$J$30:$J$45, MATCH($B29, fDiesel!$B$30:$B$45,0)) * INDEX(Assumptions!$U$110:$U$112, MATCH("Diesel", Assumptions!$T$110:$T$112,0)) + INDEX(fGasoline!$L$30:$L$45, MATCH($B29, fGasoline!$B$30:$B$45,0)) * INDEX(Assumptions!$U$110:$U$112, MATCH("Gasoline", Assumptions!$T$110:$T$112,0)) ) ) ), 0 ) -> 4.0817e+09 | G29: =INDEX(Refinery,MATCH(Product_select,Assumptions!$L$93:$L$98,0),MATCH(G$16,Assumptions!$L$93:$R$93,0))*Crude_oil_litresPerBarrel*(INDEX(Refinery_capacity,2,MATCH(G$16,Assumptions!$L$93:$R$93,0)))*Operational_days*1000*Refinery_availability*INDEX(Production_High,MATCH($B29,Assumptions!$L$102:$L$131,0),MATCH(G$16,Assumptions!$L$102:$R$102,0))+ IF( INDEX(Production_High,MATCH($B29,Assumptions!$L$102:$L$131,0),MATCH(G$16,Assumptions!$L$102:$R$102,0))>0, IF(Product_select="Diesel", INDEX(fDiesel!$J$30:$J$45, MATCH($B29, fDiesel!$B$30:$B$45,0)) * INDEX(Assumptions!$U$110:$U$112, MATCH("Diesel", Assumptions!$T$110:$T$112,0)), IF(Product_select="Gasoline", INDEX(fGasoline!$L$30:$L$45, MATCH($B29, fGasoline!$B$30:$B$45,0)) * INDEX(Assumptions!$U$110:$U$112, MATCH("Gasoline", Assumptions!$T$110:$T$112,0)), IF(Product_select="Total", INDEX(fDiesel!$J$30:$J$45, MATCH($B29, fDiesel!$B$30:$B$45,0)) * INDEX(Assumptions!$U$110:$U$112, MATCH("Diesel", Assumptions!$T$110:$T$112,0)) + INDEX(fGasoline!$L$30:$L$45, MATCH($B29, fGasoline!$B$30:$B$45,0)) * INDEX(Assumptions!$U$110:$U$112, MATCH("Gasoline", Assumptions!$T$110:$T$112,0)) ) ) ), 0 ) -> 3.1487585e+09 | H29: =INDEX(Refinery,MATCH(Product_select,Assumptions!$L$93:$L$98,0),MATCH(H$16,Assumptions!$L$93:$R$93,0))*Crude_oil_litresPerBarrel*(INDEX(Refinery_capacity,2,MATCH(H$16,Assumptions!$L$93:$R$93,0)))*Operational_days*1000*Refinery_availability*INDEX(Production_High,MATCH($B29,Assumptions!$L$102:$L$131,0),MATCH(H$16,Assumptions!$L$102:$R$102,0))+ IF( INDEX(Production_High,MATCH($B29,Assumptions!$L$102:$L$131,0),MATCH(H$16,Assumptions!$L$102:$R$102,0))>0, IF(Product_select="Diesel", INDEX(fDiesel!$J$30:$J$45, MATCH($B29, fDiesel!$B$30:$B$45,0)) * INDEX(Assumptions!$U$110:$U$112, MATCH("Diesel", Assumptions!$T$110:$T$112,0)), IF(Product_select="Gasoline", INDEX(fGasoline!$L$30:$L$45, MATCH($B29, fGasoline!$B$30:$B$45,0)) * INDEX(Assumptions!$U$110:$U$112, MATCH("Gasoline", Assumptions!$T$110:$T$112,0)), IF(Product_select="Total", INDEX(fDiesel!$J$30:$J$45, MATCH($B29, fDiesel!$B$30:$B$45,0)) * INDEX(Assumptions!$U$110:$U$112, MATCH("Diesel", Assumptions!$T$110:$T$112,0)) + INDEX(fGasoline!$L$30:$L$45, MATCH($B29, fGasoline!$B$30:$B$45,0)) * INDEX(Assumptions!$U$110:$U$112, MATCH("Gasoline", Assumptions!$T$110:$T$112,0)) ) ) ), 0 ) -> 0 | I29: =SUM(C29:H29) -> 1.0431509e+10 | J29: =I29/Crude_oil_litresPerBarrel/Operational_days/1000 -> 179.75984 | K29: =SUM(C29:H29) -> 1.0431509e+10 | L29: =K29/Crude_oil_litresPerBarrel/Operational_days/1000 -> 179.75984 | N29: =E29+F29 -> 7.282751e+09 | X29: 2036 | Y29: =I64 -> 4.4671908e+09 | Z29: =I31 -> 1.0026379e+10
B30: 2035 | C30: =INDEX(Refinery,MATCH(Product_select,Assumptions!$L$93:$L$98,0),MATCH(C$16,Assumptions!$L$93:$R$93,0))*Crude_oil_litresPerBarrel*(INDEX(Refinery_capacity,2,MATCH(C$16,Assumptions!$L$93:$R$93,0)))*Operational_days*1000*Refinery_availability*INDEX(Production_High,MATCH($B30,Assumptions!$L$102:$L$131,0),MATCH(C$16,Assumptions!$L$102:$R$102,0))+ IF( INDEX(Production_High,MATCH($B30,Assumptions!$L$102:$L$131,0),MATCH(C$16,Assumptions!$L$102:$R$102,0))>0, IF(Product_select="Diesel", INDEX(fDiesel!$J$30:$J$45, MATCH($B30, fDiesel!$B$30:$B$45,0)) * INDEX(Assumptions!$U$110:$U$112, MATCH("Diesel", Assumptions!$T$110:$T$112,0)), IF(Product_select="Gasoline", INDEX(fGasoline!$L$30:$L$45, MATCH($B30, fGasoline!$B$30:$B$45,0)) * INDEX(Assumptions!$U$110:$U$112, MATCH("Gasoline", Assumptions!$T$110:$T$112,0)), IF(Product_select="Total", INDEX(fDiesel!$J$30:$J$45, MATCH($B30, fDiesel!$B$30:$B$45,0)) * INDEX(Assumptions!$U$110:$U$112, MATCH("Diesel", Assumptions!$T$110:$T$112,0)) + INDEX(fGasoline!$L$30:$L$45, MATCH($B30, fGasoline!$B$30:$B$45,0)) * INDEX(Assumptions!$U$110:$U$112, MATCH("Gasoline", Assumptions!$T$110:$T$112,0)) ) ) ), 0 ) -> 0 | D30: =INDEX(Refinery,MATCH(Product_select,Assumptions!$L$93:$L$98,0),MATCH(D$16,Assumptions!$L$93:$R$93,0))*Crude_oil_litresPerBarrel*(INDEX(Refinery_capacity,2,MATCH(D$16,Assumptions!$L$93:$R$93,0)))*Operational_days*1000*Refinery_availability*INDEX(Production_High,MATCH($B30,Assumptions!$L$102:$L$131,0),MATCH(D$16,Assumptions!$L$102:$R$102,0))+ IF( INDEX(Production_High,MATCH($B30,Assumptions!$L$102:$L$131,0),MATCH(D$16,Assumptions!$L$102:$R$102,0))>0, IF(Product_select="Diesel", INDEX(fDiesel!$J$30:$J$45, MATCH($B30, fDiesel!$B$30:$B$45,0)) * INDEX(Assumptions!$U$110:$U$112, MATCH("Diesel", Assumptions!$T$110:$T$112,0)), IF(Product_select="Gasoline", INDEX(fGasoline!$L$30:$L$45, MATCH($B30, fGasoline!$B$30:$B$45,0)) * INDEX(Assumptions!$U$110:$U$112, MATCH("Gasoline", Assumptions!$T$110:$T$112,0)), IF(Product_select="Total", INDEX(fDiesel!$J$30:$J$45, MATCH($B30, fDiesel!$B$30:$B$45,0)) * INDEX(Assumptions!$U$110:$U$112, MATCH("Diesel", Assumptions!$T$110:$T$112,0)) + INDEX(fGasoline!$L$30:$L$45, MATCH($B30, fGasoline!$B$30:$B$45,0)) * INDEX(Assumptions!$U$110:$U$112, MATCH("Gasoline", Assumptions!$T$110:$T$112,0)) ) ) ), 0 ) -> 0 | E30: =INDEX(Refinery,MATCH(Product_select,Assumptions!$L$93:$L$98,0),MATCH(E$16,Assumptions!$L$93:$R$93,0))*Crude_oil_litresPerBarrel*(INDEX(Refinery_capacity,2,MATCH(E$16,Assumptions!$L$93:$R$93,0)))*Operational_days*1000*Refinery_availability*INDEX(Production_High,MATCH($B30,Assumptions!$L$102:$L$131,0),MATCH(E$16,Assumptions!$L$102:$R$102,0))+ IF( INDEX(Production_High,MATCH($B30,Assumptions!$L$102:$L$131,0),MATCH(E$16,Assumptions!$L$102:$R$102,0))>0, IF(Product_select="Diesel", INDEX(fDiesel!$J$30:$J$45, MATCH($B30, fDiesel!$B$30:$B$45,0)) * INDEX(Assumptions!$U$110:$U$112, MATCH("Diesel", Assumptions!$T$110:$T$112,0)), IF(Product_select="Gasoline", INDEX(fGasoline!$L$30:$L$45, MATCH($B30, fGasoline!$B$30:$B$45,0)) * INDEX(Assumptions!$U$110:$U$112, MATCH("Gasoline", Assumptions!$T$110:$T$112,0)), IF(Product_select="Total", INDEX(fDiesel!$J$30:$J$45, MATCH($B30, fDiesel!$B$30:$B$45,0)) * INDEX(Assumptions!$U$110:$U$112, MATCH("Diesel", Assumptions!$T$110:$T$112,0)) + INDEX(fGasoline!$L$30:$L$45, MATCH($B30, fGasoline!$B$30:$B$45,0)) * INDEX(Assumptions!$U$110:$U$112, MATCH("Gasoline", Assumptions!$T$110:$T$112,0)) ) ) ), 0 ) -> 3.2025727e+09 | F30: =INDEX(Refinery,MATCH(Product_select,Assumptions!$L$93:$L$98,0),MATCH(F$16,Assumptions!$L$93:$R$93,0))*Crude_oil_litresPerBarrel*(INDEX(Refinery_capacity,2,MATCH(F$16,Assumptions!$L$93:$R$93,0)))*Operational_days*1000*Refinery_availability*INDEX(Production_High,MATCH($B30,Assumptions!$L$102:$L$131,0),MATCH(F$16,Assumptions!$L$102:$R$102,0))+ IF( INDEX(Production_High,MATCH($B30,Assumptions!$L$102:$L$131,0),MATCH(F$16,Assumptions!$L$102:$R$102,0))>0, IF(Product_select="Diesel", INDEX(fDiesel!$J$30:$J$45, MATCH($B30, fDiesel!$B$30:$B$45,0)) * INDEX(Assumptions!$U$110:$U$112, MATCH("Diesel", Assumptions!$T$110:$T$112,0)), IF(Product_select="Gasoline", INDEX(fGasoline!$L$30:$L$45, MATCH($B30, fGasoline!$B$30:$B$45,0)) * INDEX(Assumptions!$U$110:$U$112, MATCH("Gasoline", Assumptions!$T$110:$T$112,0)), IF(Product_select="Total", INDEX(fDiesel!$J$30:$J$45, MATCH($B30, fDiesel!$B$30:$B$45,0)) * INDEX(Assumptions!$U$110:$U$112, MATCH("Diesel", Assumptions!$T$110:$T$112,0)) + INDEX(fGasoline!$L$30:$L$45, MATCH($B30, fGasoline!$B$30:$B$45,0)) * INDEX(Assumptions!$U$110:$U$112, MATCH("Gasoline", Assumptions!$T$110:$T$112,0)) ) ) ), 0 ) -> 3.9860008e+09 | G30: =INDEX(Refinery,MATCH(Product_select,Assumptions!$L$93:$L$98,0),MATCH(G$16,Assumptions!$L$93:$R$93,0))*Crude_oil_litresPerBarrel*(INDEX(Refinery_capacity,2,MATCH(G$16,Assumptions!$L$93:$R$93,0)))*Operational_days*1000*Refinery_availability*INDEX(Production_High,MATCH($B30,Assumptions!$L$102:$L$131,0),MATCH(G$16,Assumptions!$L$102:$R$102,0))+ IF( INDEX(Production_High,MATCH($B30,Assumptions!$L$102:$L$131,0),MATCH(G$16,Assumptions!$L$102:$R$102,0))>0, IF(Product_select="Diesel", INDEX(fDiesel!$J$30:$J$45, MATCH($B30, fDiesel!$B$30:$B$45,0)) * INDEX(Assumptions!$U$110:$U$112, MATCH("Diesel", Assumptions!$T$110:$T$112,0)), IF(Product_select="Gasoline", INDEX(fGasoline!$L$30:$L$45, MATCH($B30, fGasoline!$B$30:$B$45,0)) * INDEX(Assumptions!$U$110:$U$112, MATCH("Gasoline", Assumptions!$T$110:$T$112,0)), IF(Product_select="Total", INDEX(fDiesel!$J$30:$J$45, MATCH($B30, fDiesel!$B$30:$B$45,0)) * INDEX(Assumptions!$U$110:$U$112, MATCH("Diesel", Assumptions!$T$110:$T$112,0)) + INDEX(fGasoline!$L$30:$L$45, MATCH($B30, fGasoline!$B$30:$B$45,0)) * INDEX(Assumptions!$U$110:$U$112, MATCH("Gasoline", Assumptions!$T$110:$T$112,0)) ) ) ), 0 ) -> 3.1502802e+09 | H30: =INDEX(Refinery,MATCH(Product_select,Assumptions!$L$93:$L$98,0),MATCH(H$16,Assumptions!$L$93:$R$93,0))*Crude_oil_litresPerBarrel*(INDEX(Refinery_capacity,2,MATCH(H$16,Assumptions!$L$93:$R$93,0)))*Operational_days*1000*Refinery_availability*INDEX(Production_High,MATCH($B30,Assumptions!$L$102:$L$131,0),MATCH(H$16,Assumptions!$L$102:$R$102,0))+ IF( INDEX(Production_High,MATCH($B30,Assumptions!$L$102:$L$131,0),MATCH(H$16,Assumptions!$L$102:$R$102,0))>0, IF(Product_select="Diesel", INDEX(fDiesel!$J$30:$J$45, MATCH($B30, fDiesel!$B$30:$B$45,0)) * INDEX(Assumptions!$U$110:$U$112, MATCH("Diesel", Assumptions!$T$110:$T$112,0)), IF(Product_select="Gasoline", INDEX(fGasoline!$L$30:$L$45, MATCH($B30, fGasoline!$B$30:$B$45,0)) * INDEX(Assumptions!$U$110:$U$112, MATCH("Gasoline", Assumptions!$T$110:$T$112,0)), IF(Product_select="Total", INDEX(fDiesel!$J$30:$J$45, MATCH($B30, fDiesel!$B$30:$B$45,0)) * INDEX(Assumptions!$U$110:$U$112, MATCH("Diesel", Assumptions!$T$110:$T$112,0)) + INDEX(fGasoline!$L$30:$L$45, MATCH($B30, fGasoline!$B$30:$B$45,0)) * INDEX(Assumptions!$U$110:$U$112, MATCH("Gasoline", Assumptions!$T$110:$T$112,0)) ) ) ), 0 ) -> 0 | I30: =SUM(C30:H30) -> 1.0338854e+10 | J30: =I30/Crude_oil_litresPerBarrel/Operational_days/1000 -> 178.16316 | K30: =SUM(C30:H30) -> 1.0338854e+10 | L30: =K30/Crude_oil_litresPerBarrel/Operational_days/1000 -> 178.16316 | N30: =E30+F30 -> 7.1885735e+09 | X30: 2037 | Y30: =I65 -> 4.4671908e+09 | Z30: =I32 -> 1.0024001e+10
B31: 2036 | C31: =INDEX(Refinery,MATCH(Product_select,Assumptions!$L$93:$L$98,0),MATCH(C$16,Assumptions!$L$93:$R$93,0))*Crude_oil_litresPerBarrel*(INDEX(Refinery_capacity,2,MATCH(C$16,Assumptions!$L$93:$R$93,0)))*Operational_days*1000*Refinery_availability*INDEX(Production_High,MATCH($B31,Assumptions!$L$102:$L$131,0),MATCH(C$16,Assumptions!$L$102:$R$102,0))+ IF( INDEX(Production_High,MATCH($B31,Assumptions!$L$102:$L$131,0),MATCH(C$16,Assumptions!$L$102:$R$102,0))>0, IF(Product_select="Diesel", INDEX(fDiesel!$J$30:$J$45, MATCH($B31, fDiesel!$B$30:$B$45,0)) * INDEX(Assumptions!$U$110:$U$112, MATCH("Diesel", Assumptions!$T$110:$T$112,0)), IF(Product_select="Gasoline", INDEX(fGasoline!$L$30:$L$45, MATCH($B31, fGasoline!$B$30:$B$45,0)) * INDEX(Assumptions!$U$110:$U$112, MATCH("Gasoline", Assumptions!$T$110:$T$112,0)), IF(Product_select="Total", INDEX(fDiesel!$J$30:$J$45, MATCH($B31, fDiesel!$B$30:$B$45,0)) * INDEX(Assumptions!$U$110:$U$112, MATCH("Diesel", Assumptions!$T$110:$T$112,0)) + INDEX(fGasoline!$L$30:$L$45, MATCH($B31, fGasoline!$B$30:$B$45,0)) * INDEX(Assumptions!$U$110:$U$112, MATCH("Gasoline", Assumptions!$T$110:$T$112,0)) ) ) ), 0 ) -> 0 | D31: =INDEX(Refinery,MATCH(Product_select,Assumptions!$L$93:$L$98,0),MATCH(D$16,Assumptions!$L$93:$R$93,0))*Crude_oil_litresPerBarrel*(INDEX(Refinery_capacity,2,MATCH(D$16,Assumptions!$L$93:$R$93,0)))*Operational_days*1000*Refinery_availability*INDEX(Production_High,MATCH($B31,Assumptions!$L$102:$L$131,0),MATCH(D$16,Assumptions!$L$102:$R$102,0))+ IF( INDEX(Production_High,MATCH($B31,Assumptions!$L$102:$L$131,0),MATCH(D$16,Assumptions!$L$102:$R$102,0))>0, IF(Product_select="Diesel", INDEX(fDiesel!$J$30:$J$45, MATCH($B31, fDiesel!$B$30:$B$45,0)) * INDEX(Assumptions!$U$110:$U$112, MATCH("Diesel", Assumptions!$T$110:$T$112,0)), IF(Product_select="Gasoline", INDEX(fGasoline!$L$30:$L$45, MATCH($B31, fGasoline!$B$30:$B$45,0)) * INDEX(Assumptions!$U$110:$U$112, MATCH("Gasoline", Assumptions!$T$110:$T$112,0)), IF(Product_select="Total", INDEX(fDiesel!$J$30:$J$45, MATCH($B31, fDiesel!$B$30:$B$45,0)) * INDEX(Assumptions!$U$110:$U$112, MATCH("Diesel", Assumptions!$T$110:$T$112,0)) + INDEX(fGasoline!$L$30:$L$45, MATCH($B31, fGasoline!$B$30:$B$45,0)) * INDEX(Assumptions!$U$110:$U$112, MATCH("Gasoline", Assumptions!$T$110:$T$112,0)) ) ) ), 0 ) -> 0 | E31: =INDEX(Refinery,MATCH(Product_select,Assumptions!$L$93:$L$98,0),MATCH(E$16,Assumptions!$L$93:$R$93,0))*Crude_oil_litresPerBarrel*(INDEX(Refinery_capacity,2,MATCH(E$16,Assumptions!$L$93:$R$93,0)))*Operational_days*1000*Refinery_availability*INDEX(Production_High,MATCH($B31,Assumptions!$L$102:$L$131,0),MATCH(E$16,Assumptions!$L$102:$R$102,0))+ IF( INDEX(Production_High,MATCH($B31,Assumptions!$L$102:$L$131,0),MATCH(E$16,Assumptions!$L$102:$R$102,0))>0, IF(Product_select="Diesel", INDEX(fDiesel!$J$30:$J$45, MATCH($B31, fDiesel!$B$30:$B$45,0)) * INDEX(Assumptions!$U$110:$U$112, MATCH("Diesel", Assumptions!$T$110:$T$112,0)), IF(Product_select="Gasoline", INDEX(fGasoline!$L$30:$L$45, MATCH($B31, fGasoline!$B$30:$B$45,0)) * INDEX(Assumptions!$U$110:$U$112, MATCH("Gasoline", Assumptions!$T$110:$T$112,0)), IF(Product_select="Total", INDEX(fDiesel!$J$30:$J$45, MATCH($B31, fDiesel!$B$30:$B$45,0)) * INDEX(Assumptions!$U$110:$U$112, MATCH("Diesel", Assumptions!$T$110:$T$112,0)) + INDEX(fGasoline!$L$30:$L$45, MATCH($B31, fGasoline!$B$30:$B$45,0)) * INDEX(Assumptions!$U$110:$U$112, MATCH("Gasoline", Assumptions!$T$110:$T$112,0)) ) ) ), 0 ) -> 3.2030715e+09 | F31: =INDEX(Refinery,MATCH(Product_select,Assumptions!$L$93:$L$98,0),MATCH(F$16,Assumptions!$L$93:$R$93,0))*Crude_oil_litresPerBarrel*(INDEX(Refinery_capacity,2,MATCH(F$16,Assumptions!$L$93:$R$93,0)))*Operational_days*1000*Refinery_availability*INDEX(Production_High,MATCH($B31,Assumptions!$L$102:$L$131,0),MATCH(F$16,Assumptions!$L$102:$R$102,0))+ IF( INDEX(Production_High,MATCH($B31,Assumptions!$L$102:$L$131,0),MATCH(F$16,Assumptions!$L$102:$R$102,0))>0, IF(Product_select="Diesel", INDEX(fDiesel!$J$30:$J$45, MATCH($B31, fDiesel!$B$30:$B$45,0)) * INDEX(Assumptions!$U$110:$U$112, MATCH("Diesel", Assumptions!$T$110:$T$112,0)), IF(Product_select="Gasoline", INDEX(fGasoline!$L$30:$L$45, MATCH($B31, fGasoline!$B$30:$B$45,0)) * INDEX(Assumptions!$U$110:$U$112, MATCH("Gasoline", Assumptions!$T$110:$T$112,0)), IF(Product_select="Total", INDEX(fDiesel!$J$30:$J$45, MATCH($B31, fDiesel!$B$30:$B$45,0)) * INDEX(Assumptions!$U$110:$U$112, MATCH("Diesel", Assumptions!$T$110:$T$112,0)) + INDEX(fGasoline!$L$30:$L$45, MATCH($B31, fGasoline!$B$30:$B$45,0)) * INDEX(Assumptions!$U$110:$U$112, MATCH("Gasoline", Assumptions!$T$110:$T$112,0)) ) ) ), 0 ) -> 3.672529e+09 | G31: =INDEX(Refinery,MATCH(Product_select,Assumptions!$L$93:$L$98,0),MATCH(G$16,Assumptions!$L$93:$R$93,0))*Crude_oil_litresPerBarrel*(INDEX(Refinery_capacity,2,MATCH(G$16,Assumptions!$L$93:$R$93,0)))*Operational_days*1000*Refinery_availability*INDEX(Production_High,MATCH($B31,Assumptions!$L$102:$L$131,0),MATCH(G$16,Assumptions!$L$102:$R$102,0))+ IF( INDEX(Production_High,MATCH($B31,Assumptions!$L$102:$L$131,0),MATCH(G$16,Assumptions!$L$102:$R$102,0))>0, IF(Product_select="Diesel", INDEX(fDiesel!$J$30:$J$45, MATCH($B31, fDiesel!$B$30:$B$45,0)) * INDEX(Assumptions!$U$110:$U$112, MATCH("Diesel", Assumptions!$T$110:$T$112,0)), IF(Product_select="Gasoline", INDEX(fGasoline!$L$30:$L$45, MATCH($B31, fGasoline!$B$30:$B$45,0)) * INDEX(Assumptions!$U$110:$U$112, MATCH("Gasoline", Assumptions!$T$110:$T$112,0)), IF(Product_select="Total", INDEX(fDiesel!$J$30:$J$45, MATCH($B31, fDiesel!$B$30:$B$45,0)) * INDEX(Assumptions!$U$110:$U$112, MATCH("Diesel", Assumptions!$T$110:$T$112,0)) + INDEX(fGasoline!$L$30:$L$45, MATCH($B31, fGasoline!$B$30:$B$45,0)) * INDEX(Assumptions!$U$110:$U$112, MATCH("Gasoline", Assumptions!$T$110:$T$112,0)) ) ) ), 0 ) -> 3.150779e+09 | H31: =INDEX(Refinery,MATCH(Product_select,Assumptions!$L$93:$L$98,0),MATCH(H$16,Assumptions!$L$93:$R$93,0))*Crude_oil_litresPerBarrel*(INDEX(Refinery_capacity,2,MATCH(H$16,Assumptions!$L$93:$R$93,0)))*Operational_days*1000*Refinery_availability*INDEX(Production_High,MATCH($B31,Assumptions!$L$102:$L$131,0),MATCH(H$16,Assumptions!$L$102:$R$102,0))+ IF( INDEX(Production_High,MATCH($B31,Assumptions!$L$102:$L$131,0),MATCH(H$16,Assumptions!$L$102:$R$102,0))>0, IF(Product_select="Diesel", INDEX(fDiesel!$J$30:$J$45, MATCH($B31, fDiesel!$B$30:$B$45,0)) * INDEX(Assumptions!$U$110:$U$112, MATCH("Diesel", Assumptions!$T$110:$T$112,0)), IF(Product_select="Gasoline", INDEX(fGasoline!$L$30:$L$45, MATCH($B31, fGasoline!$B$30:$B$45,0)) * INDEX(Assumptions!$U$110:$U$112, MATCH("Gasoline", Assumptions!$T$110:$T$112,0)), IF(Product_select="Total", INDEX(fDiesel!$J$30:$J$45, MATCH($B31, fDiesel!$B$30:$B$45,0)) * INDEX(Assumptions!$U$110:$U$112, MATCH("Diesel", Assumptions!$T$110:$T$112,0)) + INDEX(fGasoline!$L$30:$L$45, MATCH($B31, fGasoline!$B$30:$B$45,0)) * INDEX(Assumptions!$U$110:$U$112, MATCH("Gasoline", Assumptions!$T$110:$T$112,0)) ) ) ), 0 ) -> 0 | I31: =SUM(C31:H31) -> 1.0026379e+10 | J31: =I31/Crude_oil_litresPerBarrel/Operational_days/1000 -> 172.77848 | K31: =SUM(C31:H31) -> 1.0026379e+10 | L31: =K31/Crude_oil_litresPerBarrel/Operational_days/1000 -> 172.77848 | N31: =E31+F31 -> 6.8756005e+09 | X31: 2038 | Y31: =I66 -> 4.4671908e+09 | Z31: =I33 -> 1.0016949e+10
B32: 2037 | C32: =INDEX(Refinery,MATCH(Product_select,Assumptions!$L$93:$L$98,0),MATCH(C$16,Assumptions!$L$93:$R$93,0))*Crude_oil_litresPerBarrel*(INDEX(Refinery_capacity,2,MATCH(C$16,Assumptions!$L$93:$R$93,0)))*Operational_days*1000*Refinery_availability*INDEX(Production_High,MATCH($B32,Assumptions!$L$102:$L$131,0),MATCH(C$16,Assumptions!$L$102:$R$102,0))+ IF( INDEX(Production_High,MATCH($B32,Assumptions!$L$102:$L$131,0),MATCH(C$16,Assumptions!$L$102:$R$102,0))>0, IF(Product_select="Diesel", INDEX(fDiesel!$J$30:$J$45, MATCH($B32, fDiesel!$B$30:$B$45,0)) * INDEX(Assumptions!$U$110:$U$112, MATCH("Diesel", Assumptions!$T$110:$T$112,0)), IF(Product_select="Gasoline", INDEX(fGasoline!$L$30:$L$45, MATCH($B32, fGasoline!$B$30:$B$45,0)) * INDEX(Assumptions!$U$110:$U$112, MATCH("Gasoline", Assumptions!$T$110:$T$112,0)), IF(Product_select="Total", INDEX(fDiesel!$J$30:$J$45, MATCH($B32, fDiesel!$B$30:$B$45,0)) * INDEX(Assumptions!$U$110:$U$112, MATCH("Diesel", Assumptions!$T$110:$T$112,0)) + INDEX(fGasoline!$L$30:$L$45, MATCH($B32, fGasoline!$B$30:$B$45,0)) * INDEX(Assumptions!$U$110:$U$112, MATCH("Gasoline", Assumptions!$T$110:$T$112,0)) ) ) ), 0 ) -> 0 | D32: =INDEX(Refinery,MATCH(Product_select,Assumptions!$L$93:$L$98,0),MATCH(D$16,Assumptions!$L$93:$R$93,0))*Crude_oil_litresPerBarrel*(INDEX(Refinery_capacity,2,MATCH(D$16,Assumptions!$L$93:$R$93,0)))*Operational_days*1000*Refinery_availability*INDEX(Production_High,MATCH($B32,Assumptions!$L$102:$L$131,0),MATCH(D$16,Assumptions!$L$102:$R$102,0))+ IF( INDEX(Production_High,MATCH($B32,Assumptions!$L$102:$L$131,0),MATCH(D$16,Assumptions!$L$102:$R$102,0))>0, IF(Product_select="Diesel", INDEX(fDiesel!$J$30:$J$45, MATCH($B32, fDiesel!$B$30:$B$45,0)) * INDEX(Assumptions!$U$110:$U$112, MATCH("Diesel", Assumptions!$T$110:$T$112,0)), IF(Product_select="Gasoline", INDEX(fGasoline!$L$30:$L$45, MATCH($B32, fGasoline!$B$30:$B$45,0)) * INDEX(Assumptions!$U$110:$U$112, MATCH("Gasoline", Assumptions!$T$110:$T$112,0)), IF(Product_select="Total", INDEX(fDiesel!$J$30:$J$45, MATCH($B32, fDiesel!$B$30:$B$45,0)) * INDEX(Assumptions!$U$110:$U$112, MATCH("Diesel", Assumptions!$T$110:$T$112,0)) + INDEX(fGasoline!$L$30:$L$45, MATCH($B32, fGasoline!$B$30:$B$45,0)) * INDEX(Assumptions!$U$110:$U$112, MATCH("Gasoline", Assumptions!$T$110:$T$112,0)) ) ) ), 0 ) -> 0 | E32: =INDEX(Refinery,MATCH(Product_select,Assumptions!$L$93:$L$98,0),MATCH(E$16,Assumptions!$L$93:$R$93,0))*Crude_oil_litresPerBarrel*(INDEX(Refinery_capacity,2,MATCH(E$16,Assumptions!$L$93:$R$93,0)))*Operational_days*1000*Refinery_availability*INDEX(Production_High,MATCH($B32,Assumptions!$L$102:$L$131,0),MATCH(E$16,Assumptions!$L$102:$R$102,0))+ IF( INDEX(Production_High,MATCH($B32,Assumptions!$L$102:$L$131,0),MATCH(E$16,Assumptions!$L$102:$R$102,0))>0, IF(Product_select="Diesel", INDEX(fDiesel!$J$30:$J$45, MATCH($B32, fDiesel!$B$30:$B$45,0)) * INDEX(Assumptions!$U$110:$U$112, MATCH("Diesel", Assumptions!$T$110:$T$112,0)), IF(Product_select="Gasoline", INDEX(fGasoline!$L$30:$L$45, MATCH($B32, fGasoline!$B$30:$B$45,0)) * INDEX(Assumptions!$U$110:$U$112, MATCH("Gasoline", Assumptions!$T$110:$T$112,0)), IF(Product_select="Total", INDEX(fDiesel!$J$30:$J$45, MATCH($B32, fDiesel!$B$30:$B$45,0)) * INDEX(Assumptions!$U$110:$U$112, MATCH("Diesel", Assumptions!$T$110:$T$112,0)) + INDEX(fGasoline!$L$30:$L$45, MATCH($B32, fGasoline!$B$30:$B$45,0)) * INDEX(Assumptions!$U$110:$U$112, MATCH("Gasoline", Assumptions!$T$110:$T$112,0)) ) ) ), 0 ) -> 3.2022786e+09 | F32: =INDEX(Refinery,MATCH(Product_select,Assumptions!$L$93:$L$98,0),MATCH(F$16,Assumptions!$L$93:$R$93,0))*Crude_oil_litresPerBarrel*(INDEX(Refinery_capacity,2,MATCH(F$16,Assumptions!$L$93:$R$93,0)))*Operational_days*1000*Refinery_availability*INDEX(Production_High,MATCH($B32,Assumptions!$L$102:$L$131,0),MATCH(F$16,Assumptions!$L$102:$R$102,0))+ IF( INDEX(Production_High,MATCH($B32,Assumptions!$L$102:$L$131,0),MATCH(F$16,Assumptions!$L$102:$R$102,0))>0, IF(Product_select="Diesel", INDEX(fDiesel!$J$30:$J$45, MATCH($B32, fDiesel!$B$30:$B$45,0)) * INDEX(Assumptions!$U$110:$U$112, MATCH("Diesel", Assumptions!$T$110:$T$112,0)), IF(Product_select="Gasoline", INDEX(fGasoline!$L$30:$L$45, MATCH($B32, fGasoline!$B$30:$B$45,0)) * INDEX(Assumptions!$U$110:$U$112, MATCH("Gasoline", Assumptions!$T$110:$T$112,0)), IF(Product_select="Total", INDEX(fDiesel!$J$30:$J$45, MATCH($B32, fDiesel!$B$30:$B$45,0)) * INDEX(Assumptions!$U$110:$U$112, MATCH("Diesel", Assumptions!$T$110:$T$112,0)) + INDEX(fGasoline!$L$30:$L$45, MATCH($B32, fGasoline!$B$30:$B$45,0)) * INDEX(Assumptions!$U$110:$U$112, MATCH("Gasoline", Assumptions!$T$110:$T$112,0)) ) ) ), 0 ) -> 3.6717361e+09 | G32: =INDEX(Refinery,MATCH(Product_select,Assumptions!$L$93:$L$98,0),MATCH(G$16,Assumptions!$L$93:$R$93,0))*Crude_oil_litresPerBarrel*(INDEX(Refinery_capacity,2,MATCH(G$16,Assumptions!$L$93:$R$93,0)))*Operational_days*1000*Refinery_availability*INDEX(Production_High,MATCH($B32,Assumptions!$L$102:$L$131,0),MATCH(G$16,Assumptions!$L$102:$R$102,0))+ IF( INDEX(Production_High,MATCH($B32,Assumptions!$L$102:$L$131,0),MATCH(G$16,Assumptions!$L$102:$R$102,0))>0, IF(Product_select="Diesel", INDEX(fDiesel!$J$30:$J$45, MATCH($B32, fDiesel!$B$30:$B$45,0)) * INDEX(Assumptions!$U$110:$U$112, MATCH("Diesel", Assumptions!$T$110:$T$112,0)), IF(Product_select="Gasoline", INDEX(fGasoline!$L$30:$L$45, MATCH($B32, fGasoline!$B$30:$B$45,0)) * INDEX(Assumptions!$U$110:$U$112, MATCH("Gasoline", Assumptions!$T$110:$T$112,0)), IF(Product_select="Total", INDEX(fDiesel!$J$30:$J$45, MATCH($B32, fDiesel!$B$30:$B$45,0)) * INDEX(Assumptions!$U$110:$U$112, MATCH("Diesel", Assumptions!$T$110:$T$112,0)) + INDEX(fGasoline!$L$30:$L$45, MATCH($B32, fGasoline!$B$30:$B$45,0)) * INDEX(Assumptions!$U$110:$U$112, MATCH("Gasoline", Assumptions!$T$110:$T$112,0)) ) ) ), 0 ) -> 3.1499861e+09 | H32: =INDEX(Refinery,MATCH(Product_select,Assumptions!$L$93:$L$98,0),MATCH(H$16,Assumptions!$L$93:$R$93,0))*Crude_oil_litresPerBarrel*(INDEX(Refinery_capacity,2,MATCH(H$16,Assumptions!$L$93:$R$93,0)))*Operational_days*1000*Refinery_availability*INDEX(Production_High,MATCH($B32,Assumptions!$L$102:$L$131,0),MATCH(H$16,Assumptions!$L$102:$R$102,0))+ IF( INDEX(Production_High,MATCH($B32,Assumptions!$L$102:$L$131,0),MATCH(H$16,Assumptions!$L$102:$R$102,0))>0, IF(Product_select="Diesel", INDEX(fDiesel!$J$30:$J$45, MATCH($B32, fDiesel!$B$30:$B$45,0)) * INDEX(Assumptions!$U$110:$U$112, MATCH("Diesel", Assumptions!$T$110:$T$112,0)), IF(Product_select="Gasoline", INDEX(fGasoline!$L$30:$L$45, MATCH($B32, fGasoline!$B$30:$B$45,0)) * INDEX(Assumptions!$U$110:$U$112, MATCH("Gasoline", Assumptions!$T$110:$T$112,0)), IF(Product_select="Total", INDEX(fDiesel!$J$30:$J$45, MATCH($B32, fDiesel!$B$30:$B$45,0)) * INDEX(Assumptions!$U$110:$U$112, MATCH("Diesel", Assumptions!$T$110:$T$112,0)) + INDEX(fGasoline!$L$30:$L$45, MATCH($B32, fGasoline!$B$30:$B$45,0)) * INDEX(Assumptions!$U$110:$U$112, MATCH("Gasoline", Assumptions!$T$110:$T$112,0)) ) ) ), 0 ) -> 0 | I32: =SUM(C32:H32) -> 1.0024001e+10 | J32: =I32/Crude_oil_litresPerBarrel/Operational_days/1000 -> 172.73749 | K32: =SUM(C32:H32) -> 1.0024001e+10 | L32: =K32/Crude_oil_litresPerBarrel/Operational_days/1000 -> 172.73749 | N32: =E32+F32 -> 6.8740146e+09 | X32: 2039 | Y32: =I67 -> 4.4671908e+09 | Z32: =I34 -> 1.000454e+10
B33: 2038 | C33: =INDEX(Refinery,MATCH(Product_select,Assumptions!$L$93:$L$98,0),MATCH(C$16,Assumptions!$L$93:$R$93,0))*Crude_oil_litresPerBarrel*(INDEX(Refinery_capacity,2,MATCH(C$16,Assumptions!$L$93:$R$93,0)))*Operational_days*1000*Refinery_availability*INDEX(Production_High,MATCH($B33,Assumptions!$L$102:$L$131,0),MATCH(C$16,Assumptions!$L$102:$R$102,0))+ IF( INDEX(Production_High,MATCH($B33,Assumptions!$L$102:$L$131,0),MATCH(C$16,Assumptions!$L$102:$R$102,0))>0, IF(Product_select="Diesel", INDEX(fDiesel!$J$30:$J$45, MATCH($B33, fDiesel!$B$30:$B$45,0)) * INDEX(Assumptions!$U$110:$U$112, MATCH("Diesel", Assumptions!$T$110:$T$112,0)), IF(Product_select="Gasoline", INDEX(fGasoline!$L$30:$L$45, MATCH($B33, fGasoline!$B$30:$B$45,0)) * INDEX(Assumptions!$U$110:$U$112, MATCH("Gasoline", Assumptions!$T$110:$T$112,0)), IF(Product_select="Total", INDEX(fDiesel!$J$30:$J$45, MATCH($B33, fDiesel!$B$30:$B$45,0)) * INDEX(Assumptions!$U$110:$U$112, MATCH("Diesel", Assumptions!$T$110:$T$112,0)) + INDEX(fGasoline!$L$30:$L$45, MATCH($B33, fGasoline!$B$30:$B$45,0)) * INDEX(Assumptions!$U$110:$U$112, MATCH("Gasoline", Assumptions!$T$110:$T$112,0)) ) ) ), 0 ) -> 0 | D33: =INDEX(Refinery,MATCH(Product_select,Assumptions!$L$93:$L$98,0),MATCH(D$16,Assumptions!$L$93:$R$93,0))*Crude_oil_litresPerBarrel*(INDEX(Refinery_capacity,2,MATCH(D$16,Assumptions!$L$93:$R$93,0)))*Operational_days*1000*Refinery_availability*INDEX(Production_High,MATCH($B33,Assumptions!$L$102:$L$131,0),MATCH(D$16,Assumptions!$L$102:$R$102,0))+ IF( INDEX(Production_High,MATCH($B33,Assumptions!$L$102:$L$131,0),MATCH(D$16,Assumptions!$L$102:$R$102,0))>0, IF(Product_select="Diesel", INDEX(fDiesel!$J$30:$J$45, MATCH($B33, fDiesel!$B$30:$B$45,0)) * INDEX(Assumptions!$U$110:$U$112, MATCH("Diesel", Assumptions!$T$110:$T$112,0)), IF(Product_select="Gasoline", INDEX(fGasoline!$L$30:$L$45, MATCH($B33, fGasoline!$B$30:$B$45,0)) * INDEX(Assumptions!$U$110:$U$112, MATCH("Gasoline", Assumptions!$T$110:$T$112,0)), IF(Product_select="Total", INDEX(fDiesel!$J$30:$J$45, MATCH($B33, fDiesel!$B$30:$B$45,0)) * INDEX(Assumptions!$U$110:$U$112, MATCH("Diesel", Assumptions!$T$110:$T$112,0)) + INDEX(fGasoline!$L$30:$L$45, MATCH($B33, fGasoline!$B$30:$B$45,0)) * INDEX(Assumptions!$U$110:$U$112, MATCH("Gasoline", Assumptions!$T$110:$T$112,0)) ) ) ), 0 ) -> 0 | E33: =INDEX(Refinery,MATCH(Product_select,Assumptions!$L$93:$L$98,0),MATCH(E$16,Assumptions!$L$93:$R$93,0))*Crude_oil_litresPerBarrel*(INDEX(Refinery_capacity,2,MATCH(E$16,Assumptions!$L$93:$R$93,0)))*Operational_days*1000*Refinery_availability*INDEX(Production_High,MATCH($B33,Assumptions!$L$102:$L$131,0),MATCH(E$16,Assumptions!$L$102:$R$102,0))+ IF( INDEX(Production_High,MATCH($B33,Assumptions!$L$102:$L$131,0),MATCH(E$16,Assumptions!$L$102:$R$102,0))>0, IF(Product_select="Diesel", INDEX(fDiesel!$J$30:$J$45, MATCH($B33, fDiesel!$B$30:$B$45,0)) * INDEX(Assumptions!$U$110:$U$112, MATCH("Diesel", Assumptions!$T$110:$T$112,0)), IF(Product_select="Gasoline", INDEX(fGasoline!$L$30:$L$45, MATCH($B33, fGasoline!$B$30:$B$45,0)) * INDEX(Assumptions!$U$110:$U$112, MATCH("Gasoline", Assumptions!$T$110:$T$112,0)), IF(Product_select="Total", INDEX(fDiesel!$J$30:$J$45, MATCH($B33, fDiesel!$B$30:$B$45,0)) * INDEX(Assumptions!$U$110:$U$112, MATCH("Diesel", Assumptions!$T$110:$T$112,0)) + INDEX(fGasoline!$L$30:$L$45, MATCH($B33, fGasoline!$B$30:$B$45,0)) * INDEX(Assumptions!$U$110:$U$112, MATCH("Gasoline", Assumptions!$T$110:$T$112,0)) ) ) ), 0 ) -> 3.199928e+09 | F33: =INDEX(Refinery,MATCH(Product_select,Assumptions!$L$93:$L$98,0),MATCH(F$16,Assumptions!$L$93:$R$93,0))*Crude_oil_litresPerBarrel*(INDEX(Refinery_capacity,2,MATCH(F$16,Assumptions!$L$93:$R$93,0)))*Operational_days*1000*Refinery_availability*INDEX(Production_High,MATCH($B33,Assumptions!$L$102:$L$131,0),MATCH(F$16,Assumptions!$L$102:$R$102,0))+ IF( INDEX(Production_High,MATCH($B33,Assumptions!$L$102:$L$131,0),MATCH(F$16,Assumptions!$L$102:$R$102,0))>0, IF(Product_select="Diesel", INDEX(fDiesel!$J$30:$J$45, MATCH($B33, fDiesel!$B$30:$B$45,0)) * INDEX(Assumptions!$U$110:$U$112, MATCH("Diesel", Assumptions!$T$110:$T$112,0)), IF(Product_select="Gasoline", INDEX(fGasoline!$L$30:$L$45, MATCH($B33, fGasoline!$B$30:$B$45,0)) * INDEX(Assumptions!$U$110:$U$112, MATCH("Gasoline", Assumptions!$T$110:$T$112,0)), IF(Product_select="Total", INDEX(fDiesel!$J$30:$J$45, MATCH($B33, fDiesel!$B$30:$B$45,0)) * INDEX(Assumptions!$U$110:$U$112, MATCH("Diesel", Assumptions!$T$110:$T$112,0)) + INDEX(fGasoline!$L$30:$L$45, MATCH($B33, fGasoline!$B$30:$B$45,0)) * INDEX(Assumptions!$U$110:$U$112, MATCH("Gasoline", Assumptions!$T$110:$T$112,0)) ) ) ), 0 ) -> 3.6693855e+09 | G33: =INDEX(Refinery,MATCH(Product_select,Assumptions!$L$93:$L$98,0),MATCH(G$16,Assumptions!$L$93:$R$93,0))*Crude_oil_litresPerBarrel*(INDEX(Refinery_capacity,2,MATCH(G$16,Assumptions!$L$93:$R$93,0)))*Operational_days*1000*Refinery_availability*INDEX(Production_High,MATCH($B33,Assumptions!$L$102:$L$131,0),MATCH(G$16,Assumptions!$L$102:$R$102,0))+ IF( INDEX(Production_High,MATCH($B33,Assumptions!$L$102:$L$131,0),MATCH(G$16,Assumptions!$L$102:$R$102,0))>0, IF(Product_select="Diesel", INDEX(fDiesel!$J$30:$J$45, MATCH($B33, fDiesel!$B$30:$B$45,0)) * INDEX(Assumptions!$U$110:$U$112, MATCH("Diesel", Assumptions!$T$110:$T$112,0)), IF(Product_select="Gasoline", INDEX(fGasoline!$L$30:$L$45, MATCH($B33, fGasoline!$B$30:$B$45,0)) * INDEX(Assumptions!$U$110:$U$112, MATCH("Gasoline", Assumptions!$T$110:$T$112,0)), IF(Product_select="Total", INDEX(fDiesel!$J$30:$J$45, MATCH($B33, fDiesel!$B$30:$B$45,0)) * INDEX(Assumptions!$U$110:$U$112, MATCH("Diesel", Assumptions!$T$110:$T$112,0)) + INDEX(fGasoline!$L$30:$L$45, MATCH($B33, fGasoline!$B$30:$B$45,0)) * INDEX(Assumptions!$U$110:$U$112, MATCH("Gasoline", Assumptions!$T$110:$T$112,0)) ) ) ), 0 ) -> 3.1476355e+09 | H33: =INDEX(Refinery,MATCH(Product_select,Assumptions!$L$93:$L$98,0),MATCH(H$16,Assumptions!$L$93:$R$93,0))*Crude_oil_litresPerBarrel*(INDEX(Refinery_capacity,2,MATCH(H$16,Assumptions!$L$93:$R$93,0)))*Operational_days*1000*Refinery_availability*INDEX(Production_High,MATCH($B33,Assumptions!$L$102:$L$131,0),MATCH(H$16,Assumptions!$L$102:$R$102,0))+ IF( INDEX(Production_High,MATCH($B33,Assumptions!$L$102:$L$131,0),MATCH(H$16,Assumptions!$L$102:$R$102,0))>0, IF(Product_select="Diesel", INDEX(fDiesel!$J$30:$J$45, MATCH($B33, fDiesel!$B$30:$B$45,0)) * INDEX(Assumptions!$U$110:$U$112, MATCH("Diesel", Assumptions!$T$110:$T$112,0)), IF(Product_select="Gasoline", INDEX(fGasoline!$L$30:$L$45, MATCH($B33, fGasoline!$B$30:$B$45,0)) * INDEX(Assumptions!$U$110:$U$112, MATCH("Gasoline", Assumptions!$T$110:$T$112,0)), IF(Product_select="Total", INDEX(fDiesel!$J$30:$J$45, MATCH($B33, fDiesel!$B$30:$B$45,0)) * INDEX(Assumptions!$U$110:$U$112, MATCH("Diesel", Assumptions!$T$110:$T$112,0)) + INDEX(fGasoline!$L$30:$L$45, MATCH($B33, fGasoline!$B$30:$B$45,0)) * INDEX(Assumptions!$U$110:$U$112, MATCH("Gasoline", Assumptions!$T$110:$T$112,0)) ) ) ), 0 ) -> 0 | I33: =SUM(C33:H33) -> 1.0016949e+10 | J33: =I33/Crude_oil_litresPerBarrel/Operational_days/1000 -> 172.61598 | K33: =SUM(C33:H33) -> 1.0016949e+10 | L33: =K33/Crude_oil_litresPerBarrel/Operational_days/1000 -> 172.61598 | N33: =E33+F33 -> 6.8693136e+09 | X33: 2040 | Y33: =I68 -> 4.4671908e+09 | Z33: =I35 -> 9.9863122e+09
B34: 2039 | C34: =INDEX(Refinery,MATCH(Product_select,Assumptions!$L$93:$L$98,0),MATCH(C$16,Assumptions!$L$93:$R$93,0))*Crude_oil_litresPerBarrel*(INDEX(Refinery_capacity,2,MATCH(C$16,Assumptions!$L$93:$R$93,0)))*Operational_days*1000*Refinery_availability*INDEX(Production_High,MATCH($B34,Assumptions!$L$102:$L$131,0),MATCH(C$16,Assumptions!$L$102:$R$102,0))+ IF( INDEX(Production_High,MATCH($B34,Assumptions!$L$102:$L$131,0),MATCH(C$16,Assumptions!$L$102:$R$102,0))>0, IF(Product_select="Diesel", INDEX(fDiesel!$J$30:$J$45, MATCH($B34, fDiesel!$B$30:$B$45,0)) * INDEX(Assumptions!$U$110:$U$112, MATCH("Diesel", Assumptions!$T$110:$T$112,0)), IF(Product_select="Gasoline", INDEX(fGasoline!$L$30:$L$45, MATCH($B34, fGasoline!$B$30:$B$45,0)) * INDEX(Assumptions!$U$110:$U$112, MATCH("Gasoline", Assumptions!$T$110:$T$112,0)), IF(Product_select="Total", INDEX(fDiesel!$J$30:$J$45, MATCH($B34, fDiesel!$B$30:$B$45,0)) * INDEX(Assumptions!$U$110:$U$112, MATCH("Diesel", Assumptions!$T$110:$T$112,0)) + INDEX(fGasoline!$L$30:$L$45, MATCH($B34, fGasoline!$B$30:$B$45,0)) * INDEX(Assumptions!$U$110:$U$112, MATCH("Gasoline", Assumptions!$T$110:$T$112,0)) ) ) ), 0 ) -> 0 | D34: =INDEX(Refinery,MATCH(Product_select,Assumptions!$L$93:$L$98,0),MATCH(D$16,Assumptions!$L$93:$R$93,0))*Crude_oil_litresPerBarrel*(INDEX(Refinery_capacity,2,MATCH(D$16,Assumptions!$L$93:$R$93,0)))*Operational_days*1000*Refinery_availability*INDEX(Production_High,MATCH($B34,Assumptions!$L$102:$L$131,0),MATCH(D$16,Assumptions!$L$102:$R$102,0))+ IF( INDEX(Production_High,MATCH($B34,Assumptions!$L$102:$L$131,0),MATCH(D$16,Assumptions!$L$102:$R$102,0))>0, IF(Product_select="Diesel", INDEX(fDiesel!$J$30:$J$45, MATCH($B34, fDiesel!$B$30:$B$45,0)) * INDEX(Assumptions!$U$110:$U$112, MATCH("Diesel", Assumptions!$T$110:$T$112,0)), IF(Product_select="Gasoline", INDEX(fGasoline!$L$30:$L$45, MATCH($B34, fGasoline!$B$30:$B$45,0)) * INDEX(Assumptions!$U$110:$U$112, MATCH("Gasoline", Assumptions!$T$110:$T$112,0)), IF(Product_select="Total", INDEX(fDiesel!$J$30:$J$45, MATCH($B34, fDiesel!$B$30:$B$45,0)) * INDEX(Assumptions!$U$110:$U$112, MATCH("Diesel", Assumptions!$T$110:$T$112,0)) + INDEX(fGasoline!$L$30:$L$45, MATCH($B34, fGasoline!$B$30:$B$45,0)) * INDEX(Assumptions!$U$110:$U$112, MATCH("Gasoline", Assumptions!$T$110:$T$112,0)) ) ) ), 0 ) -> 0 | E34: =INDEX(Refinery,MATCH(Product_select,Assumptions!$L$93:$L$98,0),MATCH(E$16,Assumptions!$L$93:$R$93,0))*Crude_oil_litresPerBarrel*(INDEX(Refinery_capacity,2,MATCH(E$16,Assumptions!$L$93:$R$93,0)))*Operational_days*1000*Refinery_availability*INDEX(Production_High,MATCH($B34,Assumptions!$L$102:$L$131,0),MATCH(E$16,Assumptions!$L$102:$R$102,0))+ IF( INDEX(Production_High,MATCH($B34,Assumptions!$L$102:$L$131,0),MATCH(E$16,Assumptions!$L$102:$R$102,0))>0, IF(Product_select="Diesel", INDEX(fDiesel!$J$30:$J$45, MATCH($B34, fDiesel!$B$30:$B$45,0)) * INDEX(Assumptions!$U$110:$U$112, MATCH("Diesel", Assumptions!$T$110:$T$112,0)), IF(Product_select="Gasoline", INDEX(fGasoline!$L$30:$L$45, MATCH($B34, fGasoline!$B$30:$B$45,0)) * INDEX(Assumptions!$U$110:$U$112, MATCH("Gasoline", Assumptions!$T$110:$T$112,0)), IF(Product_select="Total", INDEX(fDiesel!$J$30:$J$45, MATCH($B34, fDiesel!$B$30:$B$45,0)) * INDEX(Assumptions!$U$110:$U$112, MATCH("Diesel", Assumptions!$T$110:$T$112,0)) + INDEX(fGasoline!$L$30:$L$45, MATCH($B34, fGasoline!$B$30:$B$45,0)) * INDEX(Assumptions!$U$110:$U$112, MATCH("Gasoline", Assumptions!$T$110:$T$112,0)) ) ) ), 0 ) -> 3.1957916e+09 | F34: =INDEX(Refinery,MATCH(Product_select,Assumptions!$L$93:$L$98,0),MATCH(F$16,Assumptions!$L$93:$R$93,0))*Crude_oil_litresPerBarrel*(INDEX(Refinery_capacity,2,MATCH(F$16,Assumptions!$L$93:$R$93,0)))*Operational_days*1000*Refinery_availability*INDEX(Production_High,MATCH($B34,Assumptions!$L$102:$L$131,0),MATCH(F$16,Assumptions!$L$102:$R$102,0))+ IF( INDEX(Production_High,MATCH($B34,Assumptions!$L$102:$L$131,0),MATCH(F$16,Assumptions!$L$102:$R$102,0))>0, IF(Product_select="Diesel", INDEX(fDiesel!$J$30:$J$45, MATCH($B34, fDiesel!$B$30:$B$45,0)) * INDEX(Assumptions!$U$110:$U$112, MATCH("Diesel", Assumptions!$T$110:$T$112,0)), IF(Product_select="Gasoline", INDEX(fGasoline!$L$30:$L$45, MATCH($B34, fGasoline!$B$30:$B$45,0)) * INDEX(Assumptions!$U$110:$U$112, MATCH("Gasoline", Assumptions!$T$110:$T$112,0)), IF(Product_select="Total", INDEX(fDiesel!$J$30:$J$45, MATCH($B34, fDiesel!$B$30:$B$45,0)) * INDEX(Assumptions!$U$110:$U$112, MATCH("Diesel", Assumptions!$T$110:$T$112,0)) + INDEX(fGasoline!$L$30:$L$45, MATCH($B34, fGasoline!$B$30:$B$45,0)) * INDEX(Assumptions!$U$110:$U$112, MATCH("Gasoline", Assumptions!$T$110:$T$112,0)) ) ) ), 0 ) -> 3.6652491e+09 | G34: =INDEX(Refinery,MATCH(Product_select,Assumptions!$L$93:$L$98,0),MATCH(G$16,Assumptions!$L$93:$R$93,0))*Crude_oil_litresPerBarrel*(INDEX(Refinery_capacity,2,MATCH(G$16,Assumptions!$L$93:$R$93,0)))*Operational_days*1000*Refinery_availability*INDEX(Production_High,MATCH($B34,Assumptions!$L$102:$L$131,0),MATCH(G$16,Assumptions!$L$102:$R$102,0))+ IF( INDEX(Production_High,MATCH($B34,Assumptions!$L$102:$L$131,0),MATCH(G$16,Assumptions!$L$102:$R$102,0))>0, IF(Product_select="Diesel", INDEX(fDiesel!$J$30:$J$45, MATCH($B34, fDiesel!$B$30:$B$45,0)) * INDEX(Assumptions!$U$110:$U$112, MATCH("Diesel", Assumptions!$T$110:$T$112,0)), IF(Product_select="Gasoline", INDEX(fGasoline!$L$30:$L$45, MATCH($B34, fGasoline!$B$30:$B$45,0)) * INDEX(Assumptions!$U$110:$U$112, MATCH("Gasoline", Assumptions!$T$110:$T$112,0)), IF(Product_select="Total", INDEX(fDiesel!$J$30:$J$45, MATCH($B34, fDiesel!$B$30:$B$45,0)) * INDEX(Assumptions!$U$110:$U$112, MATCH("Diesel", Assumptions!$T$110:$T$112,0)) + INDEX(fGasoline!$L$30:$L$45, MATCH($B34, fGasoline!$B$30:$B$45,0)) * INDEX(Assumptions!$U$110:$U$112, MATCH("Gasoline", Assumptions!$T$110:$T$112,0)) ) ) ), 0 ) -> 3.1434991e+09 | H34: =INDEX(Refinery,MATCH(Product_select,Assumptions!$L$93:$L$98,0),MATCH(H$16,Assumptions!$L$93:$R$93,0))*Crude_oil_litresPerBarrel*(INDEX(Refinery_capacity,2,MATCH(H$16,Assumptions!$L$93:$R$93,0)))*Operational_days*1000*Refinery_availability*INDEX(Production_High,MATCH($B34,Assumptions!$L$102:$L$131,0),MATCH(H$16,Assumptions!$L$102:$R$102,0))+ IF( INDEX(Production_High,MATCH($B34,Assumptions!$L$102:$L$131,0),MATCH(H$16,Assumptions!$L$102:$R$102,0))>0, IF(Product_select="Diesel", INDEX(fDiesel!$J$30:$J$45, MATCH($B34, fDiesel!$B$30:$B$45,0)) * INDEX(Assumptions!$U$110:$U$112, MATCH("Diesel", Assumptions!$T$110:$T$112,0)), IF(Product_select="Gasoline", INDEX(fGasoline!$L$30:$L$45, MATCH($B34, fGasoline!$B$30:$B$45,0)) * INDEX(Assumptions!$U$110:$U$112, MATCH("Gasoline", Assumptions!$T$110:$T$112,0)), IF(Product_select="Total", INDEX(fDiesel!$J$30:$J$45, MATCH($B34, fDiesel!$B$30:$B$45,0)) * INDEX(Assumptions!$U$110:$U$112, MATCH("Diesel", Assumptions!$T$110:$T$112,0)) + INDEX(fGasoline!$L$30:$L$45, MATCH($B34, fGasoline!$B$30:$B$45,0)) * INDEX(Assumptions!$U$110:$U$112, MATCH("Gasoline", Assumptions!$T$110:$T$112,0)) ) ) ), 0 ) -> 0 | I34: =SUM(C34:H34) -> 1.000454e+10 | J34: =I34/Crude_oil_litresPerBarrel/Operational_days/1000 -> 172.40214 | K34: =SUM(C34:H34) -> 1.000454e+10 | L34: =K34/Crude_oil_litresPerBarrel/Operational_days/1000 -> 172.40214 | N34: =E34+F34 -> 6.8610408e+09
B35: 2040 | C35: =INDEX(Refinery,MATCH(Product_select,Assumptions!$L$93:$L$98,0),MATCH(C$16,Assumptions!$L$93:$R$93,0))*Crude_oil_litresPerBarrel*(INDEX(Refinery_capacity,2,MATCH(C$16,Assumptions!$L$93:$R$93,0)))*Operational_days*1000*Refinery_availability*INDEX(Production_High,MATCH($B35,Assumptions!$L$102:$L$131,0),MATCH(C$16,Assumptions!$L$102:$R$102,0))+ IF( INDEX(Production_High,MATCH($B35,Assumptions!$L$102:$L$131,0),MATCH(C$16,Assumptions!$L$102:$R$102,0))>0, IF(Product_select="Diesel", INDEX(fDiesel!$J$30:$J$45, MATCH($B35, fDiesel!$B$30:$B$45,0)) * INDEX(Assumptions!$U$110:$U$112, MATCH("Diesel", Assumptions!$T$110:$T$112,0)), IF(Product_select="Gasoline", INDEX(fGasoline!$L$30:$L$45, MATCH($B35, fGasoline!$B$30:$B$45,0)) * INDEX(Assumptions!$U$110:$U$112, MATCH("Gasoline", Assumptions!$T$110:$T$112,0)), IF(Product_select="Total", INDEX(fDiesel!$J$30:$J$45, MATCH($B35, fDiesel!$B$30:$B$45,0)) * INDEX(Assumptions!$U$110:$U$112, MATCH("Diesel", Assumptions!$T$110:$T$112,0)) + INDEX(fGasoline!$L$30:$L$45, MATCH($B35, fGasoline!$B$30:$B$45,0)) * INDEX(Assumptions!$U$110:$U$112, MATCH("Gasoline", Assumptions!$T$110:$T$112,0)) ) ) ), 0 ) -> 0 | D35: =INDEX(Refinery,MATCH(Product_select,Assumptions!$L$93:$L$98,0),MATCH(D$16,Assumptions!$L$93:$R$93,0))*Crude_oil_litresPerBarrel*(INDEX(Refinery_capacity,2,MATCH(D$16,Assumptions!$L$93:$R$93,0)))*Operational_days*1000*Refinery_availability*INDEX(Production_High,MATCH($B35,Assumptions!$L$102:$L$131,0),MATCH(D$16,Assumptions!$L$102:$R$102,0))+ IF( INDEX(Production_High,MATCH($B35,Assumptions!$L$102:$L$131,0),MATCH(D$16,Assumptions!$L$102:$R$102,0))>0, IF(Product_select="Diesel", INDEX(fDiesel!$J$30:$J$45, MATCH($B35, fDiesel!$B$30:$B$45,0)) * INDEX(Assumptions!$U$110:$U$112, MATCH("Diesel", Assumptions!$T$110:$T$112,0)), IF(Product_select="Gasoline", INDEX(fGasoline!$L$30:$L$45, MATCH($B35, fGasoline!$B$30:$B$45,0)) * INDEX(Assumptions!$U$110:$U$112, MATCH("Gasoline", Assumptions!$T$110:$T$112,0)), IF(Product_select="Total", INDEX(fDiesel!$J$30:$J$45, MATCH($B35, fDiesel!$B$30:$B$45,0)) * INDEX(Assumptions!$U$110:$U$112, MATCH("Diesel", Assumptions!$T$110:$T$112,0)) + INDEX(fGasoline!$L$30:$L$45, MATCH($B35, fGasoline!$B$30:$B$45,0)) * INDEX(Assumptions!$U$110:$U$112, MATCH("Gasoline", Assumptions!$T$110:$T$112,0)) ) ) ), 0 ) -> 0 | E35: =INDEX(Refinery,MATCH(Product_select,Assumptions!$L$93:$L$98,0),MATCH(E$16,Assumptions!$L$93:$R$93,0))*Crude_oil_litresPerBarrel*(INDEX(Refinery_capacity,2,MATCH(E$16,Assumptions!$L$93:$R$93,0)))*Operational_days*1000*Refinery_availability*INDEX(Production_High,MATCH($B35,Assumptions!$L$102:$L$131,0),MATCH(E$16,Assumptions!$L$102:$R$102,0))+ IF( INDEX(Production_High,MATCH($B35,Assumptions!$L$102:$L$131,0),MATCH(E$16,Assumptions!$L$102:$R$102,0))>0, IF(Product_select="Diesel", INDEX(fDiesel!$J$30:$J$45, MATCH($B35, fDiesel!$B$30:$B$45,0)) * INDEX(Assumptions!$U$110:$U$112, MATCH("Diesel", Assumptions!$T$110:$T$112,0)), IF(Product_select="Gasoline", INDEX(fGasoline!$L$30:$L$45, MATCH($B35, fGasoline!$B$30:$B$45,0)) * INDEX(Assumptions!$U$110:$U$112, MATCH("Gasoline", Assumptions!$T$110:$T$112,0)), IF(Product_select="Total", INDEX(fDiesel!$J$30:$J$45, MATCH($B35, fDiesel!$B$30:$B$45,0)) * INDEX(Assumptions!$U$110:$U$112, MATCH("Diesel", Assumptions!$T$110:$T$112,0)) + INDEX(fGasoline!$L$30:$L$45, MATCH($B35, fGasoline!$B$30:$B$45,0)) * INDEX(Assumptions!$U$110:$U$112, MATCH("Gasoline", Assumptions!$T$110:$T$112,0)) ) ) ), 0 ) -> 3.1897157e+09 | F35: =INDEX(Refinery,MATCH(Product_select,Assumptions!$L$93:$L$98,0),MATCH(F$16,Assumptions!$L$93:$R$93,0))*Crude_oil_litresPerBarrel*(INDEX(Refinery_capacity,2,MATCH(F$16,Assumptions!$L$93:$R$93,0)))*Operational_days*1000*Refinery_availability*INDEX(Production_High,MATCH($B35,Assumptions!$L$102:$L$131,0),MATCH(F$16,Assumptions!$L$102:$R$102,0))+ IF( INDEX(Production_High,MATCH($B35,Assumptions!$L$102:$L$131,0),MATCH(F$16,Assumptions!$L$102:$R$102,0))>0, IF(Product_select="Diesel", INDEX(fDiesel!$J$30:$J$45, MATCH($B35, fDiesel!$B$30:$B$45,0)) * INDEX(Assumptions!$U$110:$U$112, MATCH("Diesel", Assumptions!$T$110:$T$112,0)), IF(Product_select="Gasoline", INDEX(fGasoline!$L$30:$L$45, MATCH($B35, fGasoline!$B$30:$B$45,0)) * INDEX(Assumptions!$U$110:$U$112, MATCH("Gasoline", Assumptions!$T$110:$T$112,0)), IF(Product_select="Total", INDEX(fDiesel!$J$30:$J$45, MATCH($B35, fDiesel!$B$30:$B$45,0)) * INDEX(Assumptions!$U$110:$U$112, MATCH("Diesel", Assumptions!$T$110:$T$112,0)) + INDEX(fGasoline!$L$30:$L$45, MATCH($B35, fGasoline!$B$30:$B$45,0)) * INDEX(Assumptions!$U$110:$U$112, MATCH("Gasoline", Assumptions!$T$110:$T$112,0)) ) ) ), 0 ) -> 3.6591732e+09 | G35: =INDEX(Refinery,MATCH(Product_select,Assumptions!$L$93:$L$98,0),MATCH(G$16,Assumptions!$L$93:$R$93,0))*Crude_oil_litresPerBarrel*(INDEX(Refinery_capacity,2,MATCH(G$16,Assumptions!$L$93:$R$93,0)))*Operational_days*1000*Refinery_availability*INDEX(Production_High,MATCH($B35,Assumptions!$L$102:$L$131,0),MATCH(G$16,Assumptions!$L$102:$R$102,0))+ IF( INDEX(Production_High,MATCH($B35,Assumptions!$L$102:$L$131,0),MATCH(G$16,Assumptions!$L$102:$R$102,0))>0, IF(Product_select="Diesel", INDEX(fDiesel!$J$30:$J$45, MATCH($B35, fDiesel!$B$30:$B$45,0)) * INDEX(Assumptions!$U$110:$U$112, MATCH("Diesel", Assumptions!$T$110:$T$112,0)), IF(Product_select="Gasoline", INDEX(fGasoline!$L$30:$L$45, MATCH($B35, fGasoline!$B$30:$B$45,0)) * INDEX(Assumptions!$U$110:$U$112, MATCH("Gasoline", Assumptions!$T$110:$T$112,0)), IF(Product_select="Total", INDEX(fDiesel!$J$30:$J$45, MATCH($B35, fDiesel!$B$30:$B$45,0)) * INDEX(Assumptions!$U$110:$U$112, MATCH("Diesel", Assumptions!$T$110:$T$112,0)) + INDEX(fGasoline!$L$30:$L$45, MATCH($B35, fGasoline!$B$30:$B$45,0)) * INDEX(Assumptions!$U$110:$U$112, MATCH("Gasoline", Assumptions!$T$110:$T$112,0)) ) ) ), 0 ) -> 3.1374232e+09 | H35: =INDEX(Refinery,MATCH(Product_select,Assumptions!$L$93:$L$98,0),MATCH(H$16,Assumptions!$L$93:$R$93,0))*Crude_oil_litresPerBarrel*(INDEX(Refinery_capacity,2,MATCH(H$16,Assumptions!$L$93:$R$93,0)))*Operational_days*1000*Refinery_availability*INDEX(Production_High,MATCH($B35,Assumptions!$L$102:$L$131,0),MATCH(H$16,Assumptions!$L$102:$R$102,0))+ IF( INDEX(Production_High,MATCH($B35,Assumptions!$L$102:$L$131,0),MATCH(H$16,Assumptions!$L$102:$R$102,0))>0, IF(Product_select="Diesel", INDEX(fDiesel!$J$30:$J$45, MATCH($B35, fDiesel!$B$30:$B$45,0)) * INDEX(Assumptions!$U$110:$U$112, MATCH("Diesel", Assumptions!$T$110:$T$112,0)), IF(Product_select="Gasoline", INDEX(fGasoline!$L$30:$L$45, MATCH($B35, fGasoline!$B$30:$B$45,0)) * INDEX(Assumptions!$U$110:$U$112, MATCH("Gasoline", Assumptions!$T$110:$T$112,0)), IF(Product_select="Total", INDEX(fDiesel!$J$30:$J$45, MATCH($B35, fDiesel!$B$30:$B$45,0)) * INDEX(Assumptions!$U$110:$U$112, MATCH("Diesel", Assumptions!$T$110:$T$112,0)) + INDEX(fGasoline!$L$30:$L$45, MATCH($B35, fGasoline!$B$30:$B$45,0)) * INDEX(Assumptions!$U$110:$U$112, MATCH("Gasoline", Assumptions!$T$110:$T$112,0)) ) ) ), 0 ) -> 0 | I35: =SUM(C35:H35) -> 9.9863122e+09 | J35: =I35/Crude_oil_litresPerBarrel/Operational_days/1000 -> 172.08803 | K35: =SUM(C35:H35) -> 9.9863122e+09 | L35: =K35/Crude_oil_litresPerBarrel/Operational_days/1000 -> 172.08803 | N35: =E35+F35 -> 6.848889e+09
B36: 2041 | C36: =INDEX(Refinery,MATCH(Product_select,Assumptions!$L$93:$L$98,0),MATCH(C$16,Assumptions!$L$93:$R$93,0))*Crude_oil_litresPerBarrel*(INDEX(Refinery_capacity,2,MATCH(C$16,Assumptions!$L$93:$R$93,0)))*Operational_days*1000*Refinery_availability*INDEX(Production_High,MATCH($B36,Assumptions!$L$102:$L$131,0),MATCH(C$16,Assumptions!$L$102:$R$102,0))+ IF( INDEX(Production_High,MATCH($B36,Assumptions!$L$102:$L$131,0),MATCH(C$16,Assumptions!$L$102:$R$102,0))>0, IF(Product_select="Diesel", INDEX(fDiesel!$J$30:$J$45, MATCH($B36, fDiesel!$B$30:$B$45,0)) * INDEX(Assumptions!$U$110:$U$112, MATCH("Diesel", Assumptions!$T$110:$T$112,0)), IF(Product_select="Gasoline", INDEX(fGasoline!$L$30:$L$45, MATCH($B36, fGasoline!$B$30:$B$45,0)) * INDEX(Assumptions!$U$110:$U$112, MATCH("Gasoline", Assumptions!$T$110:$T$112,0)), IF(Product_select="Total", INDEX(fDiesel!$J$30:$J$45, MATCH($B36, fDiesel!$B$30:$B$45,0)) * INDEX(Assumptions!$U$110:$U$112, MATCH("Diesel", Assumptions!$T$110:$T$112,0)) + INDEX(fGasoline!$L$30:$L$45, MATCH($B36, fGasoline!$B$30:$B$45,0)) * INDEX(Assumptions!$U$110:$U$112, MATCH("Gasoline", Assumptions!$T$110:$T$112,0)) ) ) ), 0 ) -> 0 | D36: =INDEX(Refinery,MATCH(Product_select,Assumptions!$L$93:$L$98,0),MATCH(D$16,Assumptions!$L$93:$R$93,0))*Crude_oil_litresPerBarrel*(INDEX(Refinery_capacity,2,MATCH(D$16,Assumptions!$L$93:$R$93,0)))*Operational_days*1000*Refinery_availability*INDEX(Production_High,MATCH($B36,Assumptions!$L$102:$L$131,0),MATCH(D$16,Assumptions!$L$102:$R$102,0))+ IF( INDEX(Production_High,MATCH($B36,Assumptions!$L$102:$L$131,0),MATCH(D$16,Assumptions!$L$102:$R$102,0))>0, IF(Product_select="Diesel", INDEX(fDiesel!$J$30:$J$45, MATCH($B36, fDiesel!$B$30:$B$45,0)) * INDEX(Assumptions!$U$110:$U$112, MATCH("Diesel", Assumptions!$T$110:$T$112,0)), IF(Product_select="Gasoline", INDEX(fGasoline!$L$30:$L$45, MATCH($B36, fGasoline!$B$30:$B$45,0)) * INDEX(Assumptions!$U$110:$U$112, MATCH("Gasoline", Assumptions!$T$110:$T$112,0)), IF(Product_select="Total", INDEX(fDiesel!$J$30:$J$45, MATCH($B36, fDiesel!$B$30:$B$45,0)) * INDEX(Assumptions!$U$110:$U$112, MATCH("Diesel", Assumptions!$T$110:$T$112,0)) + INDEX(fGasoline!$L$30:$L$45, MATCH($B36, fGasoline!$B$30:$B$45,0)) * INDEX(Assumptions!$U$110:$U$112, MATCH("Gasoline", Assumptions!$T$110:$T$112,0)) ) ) ), 0 ) -> 0 | E36: =INDEX(Refinery,MATCH(Product_select,Assumptions!$L$93:$L$98,0),MATCH(E$16,Assumptions!$L$93:$R$93,0))*Crude_oil_litresPerBarrel*(INDEX(Refinery_capacity,2,MATCH(E$16,Assumptions!$L$93:$R$93,0)))*Operational_days*1000*Refinery_availability*INDEX(Production_High,MATCH($B36,Assumptions!$L$102:$L$131,0),MATCH(E$16,Assumptions!$L$102:$R$102,0))+ IF( INDEX(Production_High,MATCH($B36,Assumptions!$L$102:$L$131,0),MATCH(E$16,Assumptions!$L$102:$R$102,0))>0, IF(Product_select="Diesel", INDEX(fDiesel!$J$30:$J$45, MATCH($B36, fDiesel!$B$30:$B$45,0)) * INDEX(Assumptions!$U$110:$U$112, MATCH("Diesel", Assumptions!$T$110:$T$112,0)), IF(Product_select="Gasoline", INDEX(fGasoline!$L$30:$L$45, MATCH($B36, fGasoline!$B$30:$B$45,0)) * INDEX(Assumptions!$U$110:$U$112, MATCH("Gasoline", Assumptions!$T$110:$T$112,0)), IF(Product_select="Total", INDEX(fDiesel!$J$30:$J$45, MATCH($B36, fDiesel!$B$30:$B$45,0)) * INDEX(Assumptions!$U$110:$U$112, MATCH("Diesel", Assumptions!$T$110:$T$112,0)) + INDEX(fGasoline!$L$30:$L$45, MATCH($B36, fGasoline!$B$30:$B$45,0)) * INDEX(Assumptions!$U$110:$U$112, MATCH("Gasoline", Assumptions!$T$110:$T$112,0)) ) ) ), 0 ) -> 3.1816484e+09 | F36: =INDEX(Refinery,MATCH(Product_select,Assumptions!$L$93:$L$98,0),MATCH(F$16,Assumptions!$L$93:$R$93,0))*Crude_oil_litresPerBarrel*(INDEX(Refinery_capacity,2,MATCH(F$16,Assumptions!$L$93:$R$93,0)))*Operational_days*1000*Refinery_availability*INDEX(Production_High,MATCH($B36,Assumptions!$L$102:$L$131,0),MATCH(F$16,Assumptions!$L$102:$R$102,0))+ IF( INDEX(Production_High,MATCH($B36,Assumptions!$L$102:$L$131,0),MATCH(F$16,Assumptions!$L$102:$R$102,0))>0, IF(Product_select="Diesel", INDEX(fDiesel!$J$30:$J$45, MATCH($B36, fDiesel!$B$30:$B$45,0)) * INDEX(Assumptions!$U$110:$U$112, MATCH("Diesel", Assumptions!$T$110:$T$112,0)), IF(Product_select="Gasoline", INDEX(fGasoline!$L$30:$L$45, MATCH($B36, fGasoline!$B$30:$B$45,0)) * INDEX(Assumptions!$U$110:$U$112, MATCH("Gasoline", Assumptions!$T$110:$T$112,0)), IF(Product_select="Total", INDEX(fDiesel!$J$30:$J$45, MATCH($B36, fDiesel!$B$30:$B$45,0)) * INDEX(Assumptions!$U$110:$U$112, MATCH("Diesel", Assumptions!$T$110:$T$112,0)) + INDEX(fGasoline!$L$30:$L$45, MATCH($B36, fGasoline!$B$30:$B$45,0)) * INDEX(Assumptions!$U$110:$U$112, MATCH("Gasoline", Assumptions!$T$110:$T$112,0)) ) ) ), 0 ) -> 3.6511059e+09 | G36: =INDEX(Refinery,MATCH(Product_select,Assumptions!$L$93:$L$98,0),MATCH(G$16,Assumptions!$L$93:$R$93,0))*Crude_oil_litresPerBarrel*(INDEX(Refinery_capacity,2,MATCH(G$16,Assumptions!$L$93:$R$93,0)))*Operational_days*1000*Refinery_availability*INDEX(Production_High,MATCH($B36,Assumptions!$L$102:$L$131,0),MATCH(G$16,Assumptions!$L$102:$R$102,0))+ IF( INDEX(Production_High,MATCH($B36,Assumptions!$L$102:$L$131,0),MATCH(G$16,Assumptions!$L$102:$R$102,0))>0, IF(Product_select="Diesel", INDEX(fDiesel!$J$30:$J$45, MATCH($B36, fDiesel!$B$30:$B$45,0)) * INDEX(Assumptions!$U$110:$U$112, MATCH("Diesel", Assumptions!$T$110:$T$112,0)), IF(Product_select="Gasoline", INDEX(fGasoline!$L$30:$L$45, MATCH($B36, fGasoline!$B$30:$B$45,0)) * INDEX(Assumptions!$U$110:$U$112, MATCH("Gasoline", Assumptions!$T$110:$T$112,0)), IF(Product_select="Total", INDEX(fDiesel!$J$30:$J$45, MATCH($B36, fDiesel!$B$30:$B$45,0)) * INDEX(Assumptions!$U$110:$U$112, MATCH("Diesel", Assumptions!$T$110:$T$112,0)) + INDEX(fGasoline!$L$30:$L$45, MATCH($B36, fGasoline!$B$30:$B$45,0)) * INDEX(Assumptions!$U$110:$U$112, MATCH("Gasoline", Assumptions!$T$110:$T$112,0)) ) ) ), 0 ) -> 3.1293559e+09 | H36: =INDEX(Refinery,MATCH(Product_select,Assumptions!$L$93:$L$98,0),MATCH(H$16,Assumptions!$L$93:$R$93,0))*Crude_oil_litresPerBarrel*(INDEX(Refinery_capacity,2,MATCH(H$16,Assumptions!$L$93:$R$93,0)))*Operational_days*1000*Refinery_availability*INDEX(Production_High,MATCH($B36,Assumptions!$L$102:$L$131,0),MATCH(H$16,Assumptions!$L$102:$R$102,0))+ IF( INDEX(Production_High,MATCH($B36,Assumptions!$L$102:$L$131,0),MATCH(H$16,Assumptions!$L$102:$R$102,0))>0, IF(Product_select="Diesel", INDEX(fDiesel!$J$30:$J$45, MATCH($B36, fDiesel!$B$30:$B$45,0)) * INDEX(Assumptions!$U$110:$U$112, MATCH("Diesel", Assumptions!$T$110:$T$112,0)), IF(Product_select="Gasoline", INDEX(fGasoline!$L$30:$L$45, MATCH($B36, fGasoline!$B$30:$B$45,0)) * INDEX(Assumptions!$U$110:$U$112, MATCH("Gasoline", Assumptions!$T$110:$T$112,0)), IF(Product_select="Total", INDEX(fDiesel!$J$30:$J$45, MATCH($B36, fDiesel!$B$30:$B$45,0)) * INDEX(Assumptions!$U$110:$U$112, MATCH("Diesel", Assumptions!$T$110:$T$112,0)) + INDEX(fGasoline!$L$30:$L$45, MATCH($B36, fGasoline!$B$30:$B$45,0)) * INDEX(Assumptions!$U$110:$U$112, MATCH("Gasoline", Assumptions!$T$110:$T$112,0)) ) ) ), 0 ) -> 0 | I36: =SUM(C36:H36) -> 9.9621102e+09 | J36: =I36/Crude_oil_litresPerBarrel/Operational_days/1000 -> 171.67097 | K36: =SUM(C36:H36) -> 9.9621102e+09 | L36: =K36/Crude_oil_litresPerBarrel/Operational_days/1000 -> 171.67097 | N36: =E36+F36 -> 6.8327543e+09 | O36: =E25 -> 2.1674953e+09 | P36: 4.7519093e+08 | Q36: =SUM(O36:P36) -> 2.6426862e+09
B37: 2042 | C37: =INDEX(Refinery,MATCH(Product_select,Assumptions!$L$93:$L$98,0),MATCH(C$16,Assumptions!$L$93:$R$93,0))*Crude_oil_litresPerBarrel*(INDEX(Refinery_capacity,2,MATCH(C$16,Assumptions!$L$93:$R$93,0)))*Operational_days*1000*Refinery_availability*INDEX(Production_High,MATCH($B37,Assumptions!$L$102:$L$131,0),MATCH(C$16,Assumptions!$L$102:$R$102,0))+ IF( INDEX(Production_High,MATCH($B37,Assumptions!$L$102:$L$131,0),MATCH(C$16,Assumptions!$L$102:$R$102,0))>0, IF(Product_select="Diesel", INDEX(fDiesel!$J$30:$J$45, MATCH($B37, fDiesel!$B$30:$B$45,0)) * INDEX(Assumptions!$U$110:$U$112, MATCH("Diesel", Assumptions!$T$110:$T$112,0)), IF(Product_select="Gasoline", INDEX(fGasoline!$L$30:$L$45, MATCH($B37, fGasoline!$B$30:$B$45,0)) * INDEX(Assumptions!$U$110:$U$112, MATCH("Gasoline", Assumptions!$T$110:$T$112,0)), IF(Product_select="Total", INDEX(fDiesel!$J$30:$J$45, MATCH($B37, fDiesel!$B$30:$B$45,0)) * INDEX(Assumptions!$U$110:$U$112, MATCH("Diesel", Assumptions!$T$110:$T$112,0)) + INDEX(fGasoline!$L$30:$L$45, MATCH($B37, fGasoline!$B$30:$B$45,0)) * INDEX(Assumptions!$U$110:$U$112, MATCH("Gasoline", Assumptions!$T$110:$T$112,0)) ) ) ), 0 ) -> 0 | D37: =INDEX(Refinery,MATCH(Product_select,Assumptions!$L$93:$L$98,0),MATCH(D$16,Assumptions!$L$93:$R$93,0))*Crude_oil_litresPerBarrel*(INDEX(Refinery_capacity,2,MATCH(D$16,Assumptions!$L$93:$R$93,0)))*Operational_days*1000*Refinery_availability*INDEX(Production_High,MATCH($B37,Assumptions!$L$102:$L$131,0),MATCH(D$16,Assumptions!$L$102:$R$102,0))+ IF( INDEX(Production_High,MATCH($B37,Assumptions!$L$102:$L$131,0),MATCH(D$16,Assumptions!$L$102:$R$102,0))>0, IF(Product_select="Diesel", INDEX(fDiesel!$J$30:$J$45, MATCH($B37, fDiesel!$B$30:$B$45,0)) * INDEX(Assumptions!$U$110:$U$112, MATCH("Diesel", Assumptions!$T$110:$T$112,0)), IF(Product_select="Gasoline", INDEX(fGasoline!$L$30:$L$45, MATCH($B37, fGasoline!$B$30:$B$45,0)) * INDEX(Assumptions!$U$110:$U$112, MATCH("Gasoline", Assumptions!$T$110:$T$112,0)), IF(Product_select="Total", INDEX(fDiesel!$J$30:$J$45, MATCH($B37, fDiesel!$B$30:$B$45,0)) * INDEX(Assumptions!$U$110:$U$112, MATCH("Diesel", Assumptions!$T$110:$T$112,0)) + INDEX(fGasoline!$L$30:$L$45, MATCH($B37, fGasoline!$B$30:$B$45,0)) * INDEX(Assumptions!$U$110:$U$112, MATCH("Gasoline", Assumptions!$T$110:$T$112,0)) ) ) ), 0 ) -> 0 | E37: =INDEX(Refinery,MATCH(Product_select,Assumptions!$L$93:$L$98,0),MATCH(E$16,Assumptions!$L$93:$R$93,0))*Crude_oil_litresPerBarrel*(INDEX(Refinery_capacity,2,MATCH(E$16,Assumptions!$L$93:$R$93,0)))*Operational_days*1000*Refinery_availability*INDEX(Production_High,MATCH($B37,Assumptions!$L$102:$L$131,0),MATCH(E$16,Assumptions!$L$102:$R$102,0))+ IF( INDEX(Production_High,MATCH($B37,Assumptions!$L$102:$L$131,0),MATCH(E$16,Assumptions!$L$102:$R$102,0))>0, IF(Product_select="Diesel", INDEX(fDiesel!$J$30:$J$45, MATCH($B37, fDiesel!$B$30:$B$45,0)) * INDEX(Assumptions!$U$110:$U$112, MATCH("Diesel", Assumptions!$T$110:$T$112,0)), IF(Product_select="Gasoline", INDEX(fGasoline!$L$30:$L$45, MATCH($B37, fGasoline!$B$30:$B$45,0)) * INDEX(Assumptions!$U$110:$U$112, MATCH("Gasoline", Assumptions!$T$110:$T$112,0)), IF(Product_select="Total", INDEX(fDiesel!$J$30:$J$45, MATCH($B37, fDiesel!$B$30:$B$45,0)) * INDEX(Assumptions!$U$110:$U$112, MATCH("Diesel", Assumptions!$T$110:$T$112,0)) + INDEX(fGasoline!$L$30:$L$45, MATCH($B37, fGasoline!$B$30:$B$45,0)) * INDEX(Assumptions!$U$110:$U$112, MATCH("Gasoline", Assumptions!$T$110:$T$112,0)) ) ) ), 0 ) -> 3.1716464e+09 | F37: =INDEX(Refinery,MATCH(Product_select,Assumptions!$L$93:$L$98,0),MATCH(F$16,Assumptions!$L$93:$R$93,0))*Crude_oil_litresPerBarrel*(INDEX(Refinery_capacity,2,MATCH(F$16,Assumptions!$L$93:$R$93,0)))*Operational_days*1000*Refinery_availability*INDEX(Production_High,MATCH($B37,Assumptions!$L$102:$L$131,0),MATCH(F$16,Assumptions!$L$102:$R$102,0))+ IF( INDEX(Production_High,MATCH($B37,Assumptions!$L$102:$L$131,0),MATCH(F$16,Assumptions!$L$102:$R$102,0))>0, IF(Product_select="Diesel", INDEX(fDiesel!$J$30:$J$45, MATCH($B37, fDiesel!$B$30:$B$45,0)) * INDEX(Assumptions!$U$110:$U$112, MATCH("Diesel", Assumptions!$T$110:$T$112,0)), IF(Product_select="Gasoline", INDEX(fGasoline!$L$30:$L$45, MATCH($B37, fGasoline!$B$30:$B$45,0)) * INDEX(Assumptions!$U$110:$U$112, MATCH("Gasoline", Assumptions!$T$110:$T$112,0)), IF(Product_select="Total", INDEX(fDiesel!$J$30:$J$45, MATCH($B37, fDiesel!$B$30:$B$45,0)) * INDEX(Assumptions!$U$110:$U$112, MATCH("Diesel", Assumptions!$T$110:$T$112,0)) + INDEX(fGasoline!$L$30:$L$45, MATCH($B37, fGasoline!$B$30:$B$45,0)) * INDEX(Assumptions!$U$110:$U$112, MATCH("Gasoline", Assumptions!$T$110:$T$112,0)) ) ) ), 0 ) -> 3.6411039e+09 | G37: =INDEX(Refinery,MATCH(Product_select,Assumptions!$L$93:$L$98,0),MATCH(G$16,Assumptions!$L$93:$R$93,0))*Crude_oil_litresPerBarrel*(INDEX(Refinery_capacity,2,MATCH(G$16,Assumptions!$L$93:$R$93,0)))*Operational_days*1000*Refinery_availability*INDEX(Production_High,MATCH($B37,Assumptions!$L$102:$L$131,0),MATCH(G$16,Assumptions!$L$102:$R$102,0))+ IF( INDEX(Production_High,MATCH($B37,Assumptions!$L$102:$L$131,0),MATCH(G$16,Assumptions!$L$102:$R$102,0))>0, IF(Product_select="Diesel", INDEX(fDiesel!$J$30:$J$45, MATCH($B37, fDiesel!$B$30:$B$45,0)) * INDEX(Assumptions!$U$110:$U$112, MATCH("Diesel", Assumptions!$T$110:$T$112,0)), IF(Product_select="Gasoline", INDEX(fGasoline!$L$30:$L$45, MATCH($B37, fGasoline!$B$30:$B$45,0)) * INDEX(Assumptions!$U$110:$U$112, MATCH("Gasoline", Assumptions!$T$110:$T$112,0)), IF(Product_select="Total", INDEX(fDiesel!$J$30:$J$45, MATCH($B37, fDiesel!$B$30:$B$45,0)) * INDEX(Assumptions!$U$110:$U$112, MATCH("Diesel", Assumptions!$T$110:$T$112,0)) + INDEX(fGasoline!$L$30:$L$45, MATCH($B37, fGasoline!$B$30:$B$45,0)) * INDEX(Assumptions!$U$110:$U$112, MATCH("Gasoline", Assumptions!$T$110:$T$112,0)) ) ) ), 0 ) -> 3.1193538e+09 | H37: =INDEX(Refinery,MATCH(Product_select,Assumptions!$L$93:$L$98,0),MATCH(H$16,Assumptions!$L$93:$R$93,0))*Crude_oil_litresPerBarrel*(INDEX(Refinery_capacity,2,MATCH(H$16,Assumptions!$L$93:$R$93,0)))*Operational_days*1000*Refinery_availability*INDEX(Production_High,MATCH($B37,Assumptions!$L$102:$L$131,0),MATCH(H$16,Assumptions!$L$102:$R$102,0))+ IF( INDEX(Production_High,MATCH($B37,Assumptions!$L$102:$L$131,0),MATCH(H$16,Assumptions!$L$102:$R$102,0))>0, IF(Product_select="Diesel", INDEX(fDiesel!$J$30:$J$45, MATCH($B37, fDiesel!$B$30:$B$45,0)) * INDEX(Assumptions!$U$110:$U$112, MATCH("Diesel", Assumptions!$T$110:$T$112,0)), IF(Product_select="Gasoline", INDEX(fGasoline!$L$30:$L$45, MATCH($B37, fGasoline!$B$30:$B$45,0)) * INDEX(Assumptions!$U$110:$U$112, MATCH("Gasoline", Assumptions!$T$110:$T$112,0)), IF(Product_select="Total", INDEX(fDiesel!$J$30:$J$45, MATCH($B37, fDiesel!$B$30:$B$45,0)) * INDEX(Assumptions!$U$110:$U$112, MATCH("Diesel", Assumptions!$T$110:$T$112,0)) + INDEX(fGasoline!$L$30:$L$45, MATCH($B37, fGasoline!$B$30:$B$45,0)) * INDEX(Assumptions!$U$110:$U$112, MATCH("Gasoline", Assumptions!$T$110:$T$112,0)) ) ) ), 0 ) -> 0 | I37: =SUM(C37:H37) -> 9.9321041e+09 | J37: =I37/Crude_oil_litresPerBarrel/Operational_days/1000 -> 171.15389 | K37: =SUM(C37:H37) -> 9.9321041e+09 | L37: =K37/Crude_oil_litresPerBarrel/Operational_days/1000 -> 171.15389 | N37: =E37+F37 -> 6.8127502e+09
B38: 2043 | C38: =INDEX(Refinery,MATCH(Product_select,Assumptions!$L$93:$L$98,0),MATCH(C$16,Assumptions!$L$93:$R$93,0))*Crude_oil_litresPerBarrel*(INDEX(Refinery_capacity,2,MATCH(C$16,Assumptions!$L$93:$R$93,0)))*Operational_days*1000*Refinery_availability*INDEX(Production_High,MATCH($B38,Assumptions!$L$102:$L$131,0),MATCH(C$16,Assumptions!$L$102:$R$102,0))+ IF( INDEX(Production_High,MATCH($B38,Assumptions!$L$102:$L$131,0),MATCH(C$16,Assumptions!$L$102:$R$102,0))>0, IF(Product_select="Diesel", INDEX(fDiesel!$J$30:$J$45, MATCH($B38, fDiesel!$B$30:$B$45,0)) * INDEX(Assumptions!$U$110:$U$112, MATCH("Diesel", Assumptions!$T$110:$T$112,0)), IF(Product_select="Gasoline", INDEX(fGasoline!$L$30:$L$45, MATCH($B38, fGasoline!$B$30:$B$45,0)) * INDEX(Assumptions!$U$110:$U$112, MATCH("Gasoline", Assumptions!$T$110:$T$112,0)), IF(Product_select="Total", INDEX(fDiesel!$J$30:$J$45, MATCH($B38, fDiesel!$B$30:$B$45,0)) * INDEX(Assumptions!$U$110:$U$112, MATCH("Diesel", Assumptions!$T$110:$T$112,0)) + INDEX(fGasoline!$L$30:$L$45, MATCH($B38, fGasoline!$B$30:$B$45,0)) * INDEX(Assumptions!$U$110:$U$112, MATCH("Gasoline", Assumptions!$T$110:$T$112,0)) ) ) ), 0 ) -> 0 | D38: =INDEX(Refinery,MATCH(Product_select,Assumptions!$L$93:$L$98,0),MATCH(D$16,Assumptions!$L$93:$R$93,0))*Crude_oil_litresPerBarrel*(INDEX(Refinery_capacity,2,MATCH(D$16,Assumptions!$L$93:$R$93,0)))*Operational_days*1000*Refinery_availability*INDEX(Production_High,MATCH($B38,Assumptions!$L$102:$L$131,0),MATCH(D$16,Assumptions!$L$102:$R$102,0))+ IF( INDEX(Production_High,MATCH($B38,Assumptions!$L$102:$L$131,0),MATCH(D$16,Assumptions!$L$102:$R$102,0))>0, IF(Product_select="Diesel", INDEX(fDiesel!$J$30:$J$45, MATCH($B38, fDiesel!$B$30:$B$45,0)) * INDEX(Assumptions!$U$110:$U$112, MATCH("Diesel", Assumptions!$T$110:$T$112,0)), IF(Product_select="Gasoline", INDEX(fGasoline!$L$30:$L$45, MATCH($B38, fGasoline!$B$30:$B$45,0)) * INDEX(Assumptions!$U$110:$U$112, MATCH("Gasoline", Assumptions!$T$110:$T$112,0)), IF(Product_select="Total", INDEX(fDiesel!$J$30:$J$45, MATCH($B38, fDiesel!$B$30:$B$45,0)) * INDEX(Assumptions!$U$110:$U$112, MATCH("Diesel", Assumptions!$T$110:$T$112,0)) + INDEX(fGasoline!$L$30:$L$45, MATCH($B38, fGasoline!$B$30:$B$45,0)) * INDEX(Assumptions!$U$110:$U$112, MATCH("Gasoline", Assumptions!$T$110:$T$112,0)) ) ) ), 0 ) -> 0 | E38: =INDEX(Refinery,MATCH(Product_select,Assumptions!$L$93:$L$98,0),MATCH(E$16,Assumptions!$L$93:$R$93,0))*Crude_oil_litresPerBarrel*(INDEX(Refinery_capacity,2,MATCH(E$16,Assumptions!$L$93:$R$93,0)))*Operational_days*1000*Refinery_availability*INDEX(Production_High,MATCH($B38,Assumptions!$L$102:$L$131,0),MATCH(E$16,Assumptions!$L$102:$R$102,0))+ IF( INDEX(Production_High,MATCH($B38,Assumptions!$L$102:$L$131,0),MATCH(E$16,Assumptions!$L$102:$R$102,0))>0, IF(Product_select="Diesel", INDEX(fDiesel!$J$30:$J$45, MATCH($B38, fDiesel!$B$30:$B$45,0)) * INDEX(Assumptions!$U$110:$U$112, MATCH("Diesel", Assumptions!$T$110:$T$112,0)), IF(Product_select="Gasoline", INDEX(fGasoline!$L$30:$L$45, MATCH($B38, fGasoline!$B$30:$B$45,0)) * INDEX(Assumptions!$U$110:$U$112, MATCH("Gasoline", Assumptions!$T$110:$T$112,0)), IF(Product_select="Total", INDEX(fDiesel!$J$30:$J$45, MATCH($B38, fDiesel!$B$30:$B$45,0)) * INDEX(Assumptions!$U$110:$U$112, MATCH("Diesel", Assumptions!$T$110:$T$112,0)) + INDEX(fGasoline!$L$30:$L$45, MATCH($B38, fGasoline!$B$30:$B$45,0)) * INDEX(Assumptions!$U$110:$U$112, MATCH("Gasoline", Assumptions!$T$110:$T$112,0)) ) ) ), 0 ) -> 3.1598598e+09 | F38: =INDEX(Refinery,MATCH(Product_select,Assumptions!$L$93:$L$98,0),MATCH(F$16,Assumptions!$L$93:$R$93,0))*Crude_oil_litresPerBarrel*(INDEX(Refinery_capacity,2,MATCH(F$16,Assumptions!$L$93:$R$93,0)))*Operational_days*1000*Refinery_availability*INDEX(Production_High,MATCH($B38,Assumptions!$L$102:$L$131,0),MATCH(F$16,Assumptions!$L$102:$R$102,0))+ IF( INDEX(Production_High,MATCH($B38,Assumptions!$L$102:$L$131,0),MATCH(F$16,Assumptions!$L$102:$R$102,0))>0, IF(Product_select="Diesel", INDEX(fDiesel!$J$30:$J$45, MATCH($B38, fDiesel!$B$30:$B$45,0)) * INDEX(Assumptions!$U$110:$U$112, MATCH("Diesel", Assumptions!$T$110:$T$112,0)), IF(Product_select="Gasoline", INDEX(fGasoline!$L$30:$L$45, MATCH($B38, fGasoline!$B$30:$B$45,0)) * INDEX(Assumptions!$U$110:$U$112, MATCH("Gasoline", Assumptions!$T$110:$T$112,0)), IF(Product_select="Total", INDEX(fDiesel!$J$30:$J$45, MATCH($B38, fDiesel!$B$30:$B$45,0)) * INDEX(Assumptions!$U$110:$U$112, MATCH("Diesel", Assumptions!$T$110:$T$112,0)) + INDEX(fGasoline!$L$30:$L$45, MATCH($B38, fGasoline!$B$30:$B$45,0)) * INDEX(Assumptions!$U$110:$U$112, MATCH("Gasoline", Assumptions!$T$110:$T$112,0)) ) ) ), 0 ) -> 3.6293173e+09 | G38: =INDEX(Refinery,MATCH(Product_select,Assumptions!$L$93:$L$98,0),MATCH(G$16,Assumptions!$L$93:$R$93,0))*Crude_oil_litresPerBarrel*(INDEX(Refinery_capacity,2,MATCH(G$16,Assumptions!$L$93:$R$93,0)))*Operational_days*1000*Refinery_availability*INDEX(Production_High,MATCH($B38,Assumptions!$L$102:$L$131,0),MATCH(G$16,Assumptions!$L$102:$R$102,0))+ IF( INDEX(Production_High,MATCH($B38,Assumptions!$L$102:$L$131,0),MATCH(G$16,Assumptions!$L$102:$R$102,0))>0, IF(Product_select="Diesel", INDEX(fDiesel!$J$30:$J$45, MATCH($B38, fDiesel!$B$30:$B$45,0)) * INDEX(Assumptions!$U$110:$U$112, MATCH("Diesel", Assumptions!$T$110:$T$112,0)), IF(Product_select="Gasoline", INDEX(fGasoline!$L$30:$L$45, MATCH($B38, fGasoline!$B$30:$B$45,0)) * INDEX(Assumptions!$U$110:$U$112, MATCH("Gasoline", Assumptions!$T$110:$T$112,0)), IF(Product_select="Total", INDEX(fDiesel!$J$30:$J$45, MATCH($B38, fDiesel!$B$30:$B$45,0)) * INDEX(Assumptions!$U$110:$U$112, MATCH("Diesel", Assumptions!$T$110:$T$112,0)) + INDEX(fGasoline!$L$30:$L$45, MATCH($B38, fGasoline!$B$30:$B$45,0)) * INDEX(Assumptions!$U$110:$U$112, MATCH("Gasoline", Assumptions!$T$110:$T$112,0)) ) ) ), 0 ) -> 3.1075672e+09 | H38: =INDEX(Refinery,MATCH(Product_select,Assumptions!$L$93:$L$98,0),MATCH(H$16,Assumptions!$L$93:$R$93,0))*Crude_oil_litresPerBarrel*(INDEX(Refinery_capacity,2,MATCH(H$16,Assumptions!$L$93:$R$93,0)))*Operational_days*1000*Refinery_availability*INDEX(Production_High,MATCH($B38,Assumptions!$L$102:$L$131,0),MATCH(H$16,Assumptions!$L$102:$R$102,0))+ IF( INDEX(Production_High,MATCH($B38,Assumptions!$L$102:$L$131,0),MATCH(H$16,Assumptions!$L$102:$R$102,0))>0, IF(Product_select="Diesel", INDEX(fDiesel!$J$30:$J$45, MATCH($B38, fDiesel!$B$30:$B$45,0)) * INDEX(Assumptions!$U$110:$U$112, MATCH("Diesel", Assumptions!$T$110:$T$112,0)), IF(Product_select="Gasoline", INDEX(fGasoline!$L$30:$L$45, MATCH($B38, fGasoline!$B$30:$B$45,0)) * INDEX(Assumptions!$U$110:$U$112, MATCH("Gasoline", Assumptions!$T$110:$T$112,0)), IF(Product_select="Total", INDEX(fDiesel!$J$30:$J$45, MATCH($B38, fDiesel!$B$30:$B$45,0)) * INDEX(Assumptions!$U$110:$U$112, MATCH("Diesel", Assumptions!$T$110:$T$112,0)) + INDEX(fGasoline!$L$30:$L$45, MATCH($B38, fGasoline!$B$30:$B$45,0)) * INDEX(Assumptions!$U$110:$U$112, MATCH("Gasoline", Assumptions!$T$110:$T$112,0)) ) ) ), 0 ) -> 0 | I38: =SUM(C38:H38) -> 9.8967443e+09 | J38: =I38/Crude_oil_litresPerBarrel/Operational_days/1000 -> 170.54456 | K38: =SUM(C38:H38) -> 9.8967443e+09 | L38: =K38/Crude_oil_litresPerBarrel/Operational_days/1000 -> 170.54456 | N38: =E38+F38 -> 6.789177e+09
B39: 2044 | C39: =INDEX(Refinery,MATCH(Product_select,Assumptions!$L$93:$L$98,0),MATCH(C$16,Assumptions!$L$93:$R$93,0))*Crude_oil_litresPerBarrel*(INDEX(Refinery_capacity,2,MATCH(C$16,Assumptions!$L$93:$R$93,0)))*Operational_days*1000*Refinery_availability*INDEX(Production_High,MATCH($B39,Assumptions!$L$102:$L$131,0),MATCH(C$16,Assumptions!$L$102:$R$102,0))+ IF( INDEX(Production_High,MATCH($B39,Assumptions!$L$102:$L$131,0),MATCH(C$16,Assumptions!$L$102:$R$102,0))>0, IF(Product_select="Diesel", INDEX(fDiesel!$J$30:$J$45, MATCH($B39, fDiesel!$B$30:$B$45,0)) * INDEX(Assumptions!$U$110:$U$112, MATCH("Diesel", Assumptions!$T$110:$T$112,0)), IF(Product_select="Gasoline", INDEX(fGasoline!$L$30:$L$45, MATCH($B39, fGasoline!$B$30:$B$45,0)) * INDEX(Assumptions!$U$110:$U$112, MATCH("Gasoline", Assumptions!$T$110:$T$112,0)), IF(Product_select="Total", INDEX(fDiesel!$J$30:$J$45, MATCH($B39, fDiesel!$B$30:$B$45,0)) * INDEX(Assumptions!$U$110:$U$112, MATCH("Diesel", Assumptions!$T$110:$T$112,0)) + INDEX(fGasoline!$L$30:$L$45, MATCH($B39, fGasoline!$B$30:$B$45,0)) * INDEX(Assumptions!$U$110:$U$112, MATCH("Gasoline", Assumptions!$T$110:$T$112,0)) ) ) ), 0 ) -> 0 | D39: =INDEX(Refinery,MATCH(Product_select,Assumptions!$L$93:$L$98,0),MATCH(D$16,Assumptions!$L$93:$R$93,0))*Crude_oil_litresPerBarrel*(INDEX(Refinery_capacity,2,MATCH(D$16,Assumptions!$L$93:$R$93,0)))*Operational_days*1000*Refinery_availability*INDEX(Production_High,MATCH($B39,Assumptions!$L$102:$L$131,0),MATCH(D$16,Assumptions!$L$102:$R$102,0))+ IF( INDEX(Production_High,MATCH($B39,Assumptions!$L$102:$L$131,0),MATCH(D$16,Assumptions!$L$102:$R$102,0))>0, IF(Product_select="Diesel", INDEX(fDiesel!$J$30:$J$45, MATCH($B39, fDiesel!$B$30:$B$45,0)) * INDEX(Assumptions!$U$110:$U$112, MATCH("Diesel", Assumptions!$T$110:$T$112,0)), IF(Product_select="Gasoline", INDEX(fGasoline!$L$30:$L$45, MATCH($B39, fGasoline!$B$30:$B$45,0)) * INDEX(Assumptions!$U$110:$U$112, MATCH("Gasoline", Assumptions!$T$110:$T$112,0)), IF(Product_select="Total", INDEX(fDiesel!$J$30:$J$45, MATCH($B39, fDiesel!$B$30:$B$45,0)) * INDEX(Assumptions!$U$110:$U$112, MATCH("Diesel", Assumptions!$T$110:$T$112,0)) + INDEX(fGasoline!$L$30:$L$45, MATCH($B39, fGasoline!$B$30:$B$45,0)) * INDEX(Assumptions!$U$110:$U$112, MATCH("Gasoline", Assumptions!$T$110:$T$112,0)) ) ) ), 0 ) -> 0 | E39: =INDEX(Refinery,MATCH(Product_select,Assumptions!$L$93:$L$98,0),MATCH(E$16,Assumptions!$L$93:$R$93,0))*Crude_oil_litresPerBarrel*(INDEX(Refinery_capacity,2,MATCH(E$16,Assumptions!$L$93:$R$93,0)))*Operational_days*1000*Refinery_availability*INDEX(Production_High,MATCH($B39,Assumptions!$L$102:$L$131,0),MATCH(E$16,Assumptions!$L$102:$R$102,0))+ IF( INDEX(Production_High,MATCH($B39,Assumptions!$L$102:$L$131,0),MATCH(E$16,Assumptions!$L$102:$R$102,0))>0, IF(Product_select="Diesel", INDEX(fDiesel!$J$30:$J$45, MATCH($B39, fDiesel!$B$30:$B$45,0)) * INDEX(Assumptions!$U$110:$U$112, MATCH("Diesel", Assumptions!$T$110:$T$112,0)), IF(Product_select="Gasoline", INDEX(fGasoline!$L$30:$L$45, MATCH($B39, fGasoline!$B$30:$B$45,0)) * INDEX(Assumptions!$U$110:$U$112, MATCH("Gasoline", Assumptions!$T$110:$T$112,0)), IF(Product_select="Total", INDEX(fDiesel!$J$30:$J$45, MATCH($B39, fDiesel!$B$30:$B$45,0)) * INDEX(Assumptions!$U$110:$U$112, MATCH("Diesel", Assumptions!$T$110:$T$112,0)) + INDEX(fGasoline!$L$30:$L$45, MATCH($B39, fGasoline!$B$30:$B$45,0)) * INDEX(Assumptions!$U$110:$U$112, MATCH("Gasoline", Assumptions!$T$110:$T$112,0)) ) ) ), 0 ) -> 3.1465015e+09 | F39: =INDEX(Refinery,MATCH(Product_select,Assumptions!$L$93:$L$98,0),MATCH(F$16,Assumptions!$L$93:$R$93,0))*Crude_oil_litresPerBarrel*(INDEX(Refinery_capacity,2,MATCH(F$16,Assumptions!$L$93:$R$93,0)))*Operational_days*1000*Refinery_availability*INDEX(Production_High,MATCH($B39,Assumptions!$L$102:$L$131,0),MATCH(F$16,Assumptions!$L$102:$R$102,0))+ IF( INDEX(Production_High,MATCH($B39,Assumptions!$L$102:$L$131,0),MATCH(F$16,Assumptions!$L$102:$R$102,0))>0, IF(Product_select="Diesel", INDEX(fDiesel!$J$30:$J$45, MATCH($B39, fDiesel!$B$30:$B$45,0)) * INDEX(Assumptions!$U$110:$U$112, MATCH("Diesel", Assumptions!$T$110:$T$112,0)), IF(Product_select="Gasoline", INDEX(fGasoline!$L$30:$L$45, MATCH($B39, fGasoline!$B$30:$B$45,0)) * INDEX(Assumptions!$U$110:$U$112, MATCH("Gasoline", Assumptions!$T$110:$T$112,0)), IF(Product_select="Total", INDEX(fDiesel!$J$30:$J$45, MATCH($B39, fDiesel!$B$30:$B$45,0)) * INDEX(Assumptions!$U$110:$U$112, MATCH("Diesel", Assumptions!$T$110:$T$112,0)) + INDEX(fGasoline!$L$30:$L$45, MATCH($B39, fGasoline!$B$30:$B$45,0)) * INDEX(Assumptions!$U$110:$U$112, MATCH("Gasoline", Assumptions!$T$110:$T$112,0)) ) ) ), 0 ) -> 3.615959e+09 | G39: =INDEX(Refinery,MATCH(Product_select,Assumptions!$L$93:$L$98,0),MATCH(G$16,Assumptions!$L$93:$R$93,0))*Crude_oil_litresPerBarrel*(INDEX(Refinery_capacity,2,MATCH(G$16,Assumptions!$L$93:$R$93,0)))*Operational_days*1000*Refinery_availability*INDEX(Production_High,MATCH($B39,Assumptions!$L$102:$L$131,0),MATCH(G$16,Assumptions!$L$102:$R$102,0))+ IF( INDEX(Production_High,MATCH($B39,Assumptions!$L$102:$L$131,0),MATCH(G$16,Assumptions!$L$102:$R$102,0))>0, IF(Product_select="Diesel", INDEX(fDiesel!$J$30:$J$45, MATCH($B39, fDiesel!$B$30:$B$45,0)) * INDEX(Assumptions!$U$110:$U$112, MATCH("Diesel", Assumptions!$T$110:$T$112,0)), IF(Product_select="Gasoline", INDEX(fGasoline!$L$30:$L$45, MATCH($B39, fGasoline!$B$30:$B$45,0)) * INDEX(Assumptions!$U$110:$U$112, MATCH("Gasoline", Assumptions!$T$110:$T$112,0)), IF(Product_select="Total", INDEX(fDiesel!$J$30:$J$45, MATCH($B39, fDiesel!$B$30:$B$45,0)) * INDEX(Assumptions!$U$110:$U$112, MATCH("Diesel", Assumptions!$T$110:$T$112,0)) + INDEX(fGasoline!$L$30:$L$45, MATCH($B39, fGasoline!$B$30:$B$45,0)) * INDEX(Assumptions!$U$110:$U$112, MATCH("Gasoline", Assumptions!$T$110:$T$112,0)) ) ) ), 0 ) -> 3.094209e+09 | H39: =INDEX(Refinery,MATCH(Product_select,Assumptions!$L$93:$L$98,0),MATCH(H$16,Assumptions!$L$93:$R$93,0))*Crude_oil_litresPerBarrel*(INDEX(Refinery_capacity,2,MATCH(H$16,Assumptions!$L$93:$R$93,0)))*Operational_days*1000*Refinery_availability*INDEX(Production_High,MATCH($B39,Assumptions!$L$102:$L$131,0),MATCH(H$16,Assumptions!$L$102:$R$102,0))+ IF( INDEX(Production_High,MATCH($B39,Assumptions!$L$102:$L$131,0),MATCH(H$16,Assumptions!$L$102:$R$102,0))>0, IF(Product_select="Diesel", INDEX(fDiesel!$J$30:$J$45, MATCH($B39, fDiesel!$B$30:$B$45,0)) * INDEX(Assumptions!$U$110:$U$112, MATCH("Diesel", Assumptions!$T$110:$T$112,0)), IF(Product_select="Gasoline", INDEX(fGasoline!$L$30:$L$45, MATCH($B39, fGasoline!$B$30:$B$45,0)) * INDEX(Assumptions!$U$110:$U$112, MATCH("Gasoline", Assumptions!$T$110:$T$112,0)), IF(Product_select="Total", INDEX(fDiesel!$J$30:$J$45, MATCH($B39, fDiesel!$B$30:$B$45,0)) * INDEX(Assumptions!$U$110:$U$112, MATCH("Diesel", Assumptions!$T$110:$T$112,0)) + INDEX(fGasoline!$L$30:$L$45, MATCH($B39, fGasoline!$B$30:$B$45,0)) * INDEX(Assumptions!$U$110:$U$112, MATCH("Gasoline", Assumptions!$T$110:$T$112,0)) ) ) ), 0 ) -> 0 | I39: =SUM(C39:H39) -> 9.8566696e+09 | J39: =I39/Crude_oil_litresPerBarrel/Operational_days/1000 -> 169.85398 | K39: =SUM(C39:H39) -> 9.8566696e+09 | L39: =K39/Crude_oil_litresPerBarrel/Operational_days/1000 -> 169.85398 | N39: =E39+F39 -> 6.7624606e+09
B40: 2045 | C40: =INDEX(Refinery,MATCH(Product_select,Assumptions!$L$93:$L$98,0),MATCH(C$16,Assumptions!$L$93:$R$93,0))*Crude_oil_litresPerBarrel*(INDEX(Refinery_capacity,2,MATCH(C$16,Assumptions!$L$93:$R$93,0)))*Operational_days*1000*Refinery_availability*INDEX(Production_High,MATCH($B40,Assumptions!$L$102:$L$131,0),MATCH(C$16,Assumptions!$L$102:$R$102,0))+ IF( INDEX(Production_High,MATCH($B40,Assumptions!$L$102:$L$131,0),MATCH(C$16,Assumptions!$L$102:$R$102,0))>0, IF(Product_select="Diesel", INDEX(fDiesel!$J$30:$J$45, MATCH($B40, fDiesel!$B$30:$B$45,0)) * INDEX(Assumptions!$U$110:$U$112, MATCH("Diesel", Assumptions!$T$110:$T$112,0)), IF(Product_select="Gasoline", INDEX(fGasoline!$L$30:$L$45, MATCH($B40, fGasoline!$B$30:$B$45,0)) * INDEX(Assumptions!$U$110:$U$112, MATCH("Gasoline", Assumptions!$T$110:$T$112,0)), IF(Product_select="Total", INDEX(fDiesel!$J$30:$J$45, MATCH($B40, fDiesel!$B$30:$B$45,0)) * INDEX(Assumptions!$U$110:$U$112, MATCH("Diesel", Assumptions!$T$110:$T$112,0)) + INDEX(fGasoline!$L$30:$L$45, MATCH($B40, fGasoline!$B$30:$B$45,0)) * INDEX(Assumptions!$U$110:$U$112, MATCH("Gasoline", Assumptions!$T$110:$T$112,0)) ) ) ), 0 ) -> 0 | D40: =INDEX(Refinery,MATCH(Product_select,Assumptions!$L$93:$L$98,0),MATCH(D$16,Assumptions!$L$93:$R$93,0))*Crude_oil_litresPerBarrel*(INDEX(Refinery_capacity,2,MATCH(D$16,Assumptions!$L$93:$R$93,0)))*Operational_days*1000*Refinery_availability*INDEX(Production_High,MATCH($B40,Assumptions!$L$102:$L$131,0),MATCH(D$16,Assumptions!$L$102:$R$102,0))+ IF( INDEX(Production_High,MATCH($B40,Assumptions!$L$102:$L$131,0),MATCH(D$16,Assumptions!$L$102:$R$102,0))>0, IF(Product_select="Diesel", INDEX(fDiesel!$J$30:$J$45, MATCH($B40, fDiesel!$B$30:$B$45,0)) * INDEX(Assumptions!$U$110:$U$112, MATCH("Diesel", Assumptions!$T$110:$T$112,0)), IF(Product_select="Gasoline", INDEX(fGasoline!$L$30:$L$45, MATCH($B40, fGasoline!$B$30:$B$45,0)) * INDEX(Assumptions!$U$110:$U$112, MATCH("Gasoline", Assumptions!$T$110:$T$112,0)), IF(Product_select="Total", INDEX(fDiesel!$J$30:$J$45, MATCH($B40, fDiesel!$B$30:$B$45,0)) * INDEX(Assumptions!$U$110:$U$112, MATCH("Diesel", Assumptions!$T$110:$T$112,0)) + INDEX(fGasoline!$L$30:$L$45, MATCH($B40, fGasoline!$B$30:$B$45,0)) * INDEX(Assumptions!$U$110:$U$112, MATCH("Gasoline", Assumptions!$T$110:$T$112,0)) ) ) ), 0 ) -> 0 | E40: =INDEX(Refinery,MATCH(Product_select,Assumptions!$L$93:$L$98,0),MATCH(E$16,Assumptions!$L$93:$R$93,0))*Crude_oil_litresPerBarrel*(INDEX(Refinery_capacity,2,MATCH(E$16,Assumptions!$L$93:$R$93,0)))*Operational_days*1000*Refinery_availability*INDEX(Production_High,MATCH($B40,Assumptions!$L$102:$L$131,0),MATCH(E$16,Assumptions!$L$102:$R$102,0))+ IF( INDEX(Production_High,MATCH($B40,Assumptions!$L$102:$L$131,0),MATCH(E$16,Assumptions!$L$102:$R$102,0))>0, IF(Product_select="Diesel", INDEX(fDiesel!$J$30:$J$45, MATCH($B40, fDiesel!$B$30:$B$45,0)) * INDEX(Assumptions!$U$110:$U$112, MATCH("Diesel", Assumptions!$T$110:$T$112,0)), IF(Product_select="Gasoline", INDEX(fGasoline!$L$30:$L$45, MATCH($B40, fGasoline!$B$30:$B$45,0)) * INDEX(Assumptions!$U$110:$U$112, MATCH("Gasoline", Assumptions!$T$110:$T$112,0)), IF(Product_select="Total", INDEX(fDiesel!$J$30:$J$45, MATCH($B40, fDiesel!$B$30:$B$45,0)) * INDEX(Assumptions!$U$110:$U$112, MATCH("Diesel", Assumptions!$T$110:$T$112,0)) + INDEX(fGasoline!$L$30:$L$45, MATCH($B40, fGasoline!$B$30:$B$45,0)) * INDEX(Assumptions!$U$110:$U$112, MATCH("Gasoline", Assumptions!$T$110:$T$112,0)) ) ) ), 0 ) -> 3.1318126e+09 | F40: =INDEX(Refinery,MATCH(Product_select,Assumptions!$L$93:$L$98,0),MATCH(F$16,Assumptions!$L$93:$R$93,0))*Crude_oil_litresPerBarrel*(INDEX(Refinery_capacity,2,MATCH(F$16,Assumptions!$L$93:$R$93,0)))*Operational_days*1000*Refinery_availability*INDEX(Production_High,MATCH($B40,Assumptions!$L$102:$L$131,0),MATCH(F$16,Assumptions!$L$102:$R$102,0))+ IF( INDEX(Production_High,MATCH($B40,Assumptions!$L$102:$L$131,0),MATCH(F$16,Assumptions!$L$102:$R$102,0))>0, IF(Product_select="Diesel", INDEX(fDiesel!$J$30:$J$45, MATCH($B40, fDiesel!$B$30:$B$45,0)) * INDEX(Assumptions!$U$110:$U$112, MATCH("Diesel", Assumptions!$T$110:$T$112,0)), IF(Product_select="Gasoline", INDEX(fGasoline!$L$30:$L$45, MATCH($B40, fGasoline!$B$30:$B$45,0)) * INDEX(Assumptions!$U$110:$U$112, MATCH("Gasoline", Assumptions!$T$110:$T$112,0)), IF(Product_select="Total", INDEX(fDiesel!$J$30:$J$45, MATCH($B40, fDiesel!$B$30:$B$45,0)) * INDEX(Assumptions!$U$110:$U$112, MATCH("Diesel", Assumptions!$T$110:$T$112,0)) + INDEX(fGasoline!$L$30:$L$45, MATCH($B40, fGasoline!$B$30:$B$45,0)) * INDEX(Assumptions!$U$110:$U$112, MATCH("Gasoline", Assumptions!$T$110:$T$112,0)) ) ) ), 0 ) -> 3.6012701e+09 | G40: =INDEX(Refinery,MATCH(Product_select,Assumptions!$L$93:$L$98,0),MATCH(G$16,Assumptions!$L$93:$R$93,0))*Crude_oil_litresPerBarrel*(INDEX(Refinery_capacity,2,MATCH(G$16,Assumptions!$L$93:$R$93,0)))*Operational_days*1000*Refinery_availability*INDEX(Production_High,MATCH($B40,Assumptions!$L$102:$L$131,0),MATCH(G$16,Assumptions!$L$102:$R$102,0))+ IF( INDEX(Production_High,MATCH($B40,Assumptions!$L$102:$L$131,0),MATCH(G$16,Assumptions!$L$102:$R$102,0))>0, IF(Product_select="Diesel", INDEX(fDiesel!$J$30:$J$45, MATCH($B40, fDiesel!$B$30:$B$45,0)) * INDEX(Assumptions!$U$110:$U$112, MATCH("Diesel", Assumptions!$T$110:$T$112,0)), IF(Product_select="Gasoline", INDEX(fGasoline!$L$30:$L$45, MATCH($B40, fGasoline!$B$30:$B$45,0)) * INDEX(Assumptions!$U$110:$U$112, MATCH("Gasoline", Assumptions!$T$110:$T$112,0)), IF(Product_select="Total", INDEX(fDiesel!$J$30:$J$45, MATCH($B40, fDiesel!$B$30:$B$45,0)) * INDEX(Assumptions!$U$110:$U$112, MATCH("Diesel", Assumptions!$T$110:$T$112,0)) + INDEX(fGasoline!$L$30:$L$45, MATCH($B40, fGasoline!$B$30:$B$45,0)) * INDEX(Assumptions!$U$110:$U$112, MATCH("Gasoline", Assumptions!$T$110:$T$112,0)) ) ) ), 0 ) -> 3.0795201e+09 | H40: =INDEX(Refinery,MATCH(Product_select,Assumptions!$L$93:$L$98,0),MATCH(H$16,Assumptions!$L$93:$R$93,0))*Crude_oil_litresPerBarrel*(INDEX(Refinery_capacity,2,MATCH(H$16,Assumptions!$L$93:$R$93,0)))*Operational_days*1000*Refinery_availability*INDEX(Production_High,MATCH($B40,Assumptions!$L$102:$L$131,0),MATCH(H$16,Assumptions!$L$102:$R$102,0))+ IF( INDEX(Production_High,MATCH($B40,Assumptions!$L$102:$L$131,0),MATCH(H$16,Assumptions!$L$102:$R$102,0))>0, IF(Product_select="Diesel", INDEX(fDiesel!$J$30:$J$45, MATCH($B40, fDiesel!$B$30:$B$45,0)) * INDEX(Assumptions!$U$110:$U$112, MATCH("Diesel", Assumptions!$T$110:$T$112,0)), IF(Product_select="Gasoline", INDEX(fGasoline!$L$30:$L$45, MATCH($B40, fGasoline!$B$30:$B$45,0)) * INDEX(Assumptions!$U$110:$U$112, MATCH("Gasoline", Assumptions!$T$110:$T$112,0)), IF(Product_select="Total", INDEX(fDiesel!$J$30:$J$45, MATCH($B40, fDiesel!$B$30:$B$45,0)) * INDEX(Assumptions!$U$110:$U$112, MATCH("Diesel", Assumptions!$T$110:$T$112,0)) + INDEX(fGasoline!$L$30:$L$45, MATCH($B40, fGasoline!$B$30:$B$45,0)) * INDEX(Assumptions!$U$110:$U$112, MATCH("Gasoline", Assumptions!$T$110:$T$112,0)) ) ) ), 0 ) -> 0 | I40: =SUM(C40:H40) -> 9.8126027e+09 | J40: =I40/Crude_oil_litresPerBarrel/Operational_days/1000 -> 169.0946 | K40: =SUM(C40:H40) -> 9.8126027e+09 | L40: =K40/Crude_oil_litresPerBarrel/Operational_days/1000 -> 169.0946 | N40: =E40+F40 -> 6.7330826e+09
B41: 2046 | C41: =INDEX(Refinery,MATCH(Product_select,Assumptions!$L$93:$L$98,0),MATCH(C$16,Assumptions!$L$93:$R$93,0))*Crude_oil_litresPerBarrel*(INDEX(Refinery_capacity,2,MATCH(C$16,Assumptions!$L$93:$R$93,0)))*Operational_days*1000*Refinery_availability*INDEX(Production_High,MATCH($B41,Assumptions!$L$102:$L$131,0),MATCH(C$16,Assumptions!$L$102:$R$102,0))+ IF( INDEX(Production_High,MATCH($B41,Assumptions!$L$102:$L$131,0),MATCH(C$16,Assumptions!$L$102:$R$102,0))>0, IF(Product_select="Diesel", INDEX(fDiesel!$J$30:$J$45, MATCH($B41, fDiesel!$B$30:$B$45,0)) * INDEX(Assumptions!$U$110:$U$112, MATCH("Diesel", Assumptions!$T$110:$T$112,0)), IF(Product_select="Gasoline", INDEX(fGasoline!$L$30:$L$45, MATCH($B41, fGasoline!$B$30:$B$45,0)) * INDEX(Assumptions!$U$110:$U$112, MATCH("Gasoline", Assumptions!$T$110:$T$112,0)), IF(Product_select="Total", INDEX(fDiesel!$J$30:$J$45, MATCH($B41, fDiesel!$B$30:$B$45,0)) * INDEX(Assumptions!$U$110:$U$112, MATCH("Diesel", Assumptions!$T$110:$T$112,0)) + INDEX(fGasoline!$L$30:$L$45, MATCH($B41, fGasoline!$B$30:$B$45,0)) * INDEX(Assumptions!$U$110:$U$112, MATCH("Gasoline", Assumptions!$T$110:$T$112,0)) ) ) ), 0 ) -> 0 | D41: =INDEX(Refinery,MATCH(Product_select,Assumptions!$L$93:$L$98,0),MATCH(D$16,Assumptions!$L$93:$R$93,0))*Crude_oil_litresPerBarrel*(INDEX(Refinery_capacity,2,MATCH(D$16,Assumptions!$L$93:$R$93,0)))*Operational_days*1000*Refinery_availability*INDEX(Production_High,MATCH($B41,Assumptions!$L$102:$L$131,0),MATCH(D$16,Assumptions!$L$102:$R$102,0))+ IF( INDEX(Production_High,MATCH($B41,Assumptions!$L$102:$L$131,0),MATCH(D$16,Assumptions!$L$102:$R$102,0))>0, IF(Product_select="Diesel", INDEX(fDiesel!$J$30:$J$45, MATCH($B41, fDiesel!$B$30:$B$45,0)) * INDEX(Assumptions!$U$110:$U$112, MATCH("Diesel", Assumptions!$T$110:$T$112,0)), IF(Product_select="Gasoline", INDEX(fGasoline!$L$30:$L$45, MATCH($B41, fGasoline!$B$30:$B$45,0)) * INDEX(Assumptions!$U$110:$U$112, MATCH("Gasoline", Assumptions!$T$110:$T$112,0)), IF(Product_select="Total", INDEX(fDiesel!$J$30:$J$45, MATCH($B41, fDiesel!$B$30:$B$45,0)) * INDEX(Assumptions!$U$110:$U$112, MATCH("Diesel", Assumptions!$T$110:$T$112,0)) + INDEX(fGasoline!$L$30:$L$45, MATCH($B41, fGasoline!$B$30:$B$45,0)) * INDEX(Assumptions!$U$110:$U$112, MATCH("Gasoline", Assumptions!$T$110:$T$112,0)) ) ) ), 0 ) -> 0 | E41: =INDEX(Refinery,MATCH(Product_select,Assumptions!$L$93:$L$98,0),MATCH(E$16,Assumptions!$L$93:$R$93,0))*Crude_oil_litresPerBarrel*(INDEX(Refinery_capacity,2,MATCH(E$16,Assumptions!$L$93:$R$93,0)))*Operational_days*1000*Refinery_availability*INDEX(Production_High,MATCH($B41,Assumptions!$L$102:$L$131,0),MATCH(E$16,Assumptions!$L$102:$R$102,0))+ IF( INDEX(Production_High,MATCH($B41,Assumptions!$L$102:$L$131,0),MATCH(E$16,Assumptions!$L$102:$R$102,0))>0, IF(Product_select="Diesel", INDEX(fDiesel!$J$30:$J$45, MATCH($B41, fDiesel!$B$30:$B$45,0)) * INDEX(Assumptions!$U$110:$U$112, MATCH("Diesel", Assumptions!$T$110:$T$112,0)), IF(Product_select="Gasoline", INDEX(fGasoline!$L$30:$L$45, MATCH($B41, fGasoline!$B$30:$B$45,0)) * INDEX(Assumptions!$U$110:$U$112, MATCH("Gasoline", Assumptions!$T$110:$T$112,0)), IF(Product_select="Total", INDEX(fDiesel!$J$30:$J$45, MATCH($B41, fDiesel!$B$30:$B$45,0)) * INDEX(Assumptions!$U$110:$U$112, MATCH("Diesel", Assumptions!$T$110:$T$112,0)) + INDEX(fGasoline!$L$30:$L$45, MATCH($B41, fGasoline!$B$30:$B$45,0)) * INDEX(Assumptions!$U$110:$U$112, MATCH("Gasoline", Assumptions!$T$110:$T$112,0)) ) ) ), 0 ) -> #N/A | F41: =INDEX(Refinery,MATCH(Product_select,Assumptions!$L$93:$L$98,0),MATCH(F$16,Assumptions!$L$93:$R$93,0))*Crude_oil_litresPerBarrel*(INDEX(Refinery_capacity,2,MATCH(F$16,Assumptions!$L$93:$R$93,0)))*Operational_days*1000*Refinery_availability*INDEX(Production_High,MATCH($B41,Assumptions!$L$102:$L$131,0),MATCH(F$16,Assumptions!$L$102:$R$102,0))+ IF( INDEX(Production_High,MATCH($B41,Assumptions!$L$102:$L$131,0),MATCH(F$16,Assumptions!$L$102:$R$102,0))>0, IF(Product_select="Diesel", INDEX(fDiesel!$J$30:$J$45, MATCH($B41, fDiesel!$B$30:$B$45,0)) * INDEX(Assumptions!$U$110:$U$112, MATCH("Diesel", Assumptions!$T$110:$T$112,0)), IF(Product_select="Gasoline", INDEX(fGasoline!$L$30:$L$45, MATCH($B41, fGasoline!$B$30:$B$45,0)) * INDEX(Assumptions!$U$110:$U$112, MATCH("Gasoline", Assumptions!$T$110:$T$112,0)), IF(Product_select="Total", INDEX(fDiesel!$J$30:$J$45, MATCH($B41, fDiesel!$B$30:$B$45,0)) * INDEX(Assumptions!$U$110:$U$112, MATCH("Diesel", Assumptions!$T$110:$T$112,0)) + INDEX(fGasoline!$L$30:$L$45, MATCH($B41, fGasoline!$B$30:$B$45,0)) * INDEX(Assumptions!$U$110:$U$112, MATCH("Gasoline", Assumptions!$T$110:$T$112,0)) ) ) ), 0 ) -> #N/A | G41: =INDEX(Refinery,MATCH(Product_select,Assumptions!$L$93:$L$98,0),MATCH(G$16,Assumptions!$L$93:$R$93,0))*Crude_oil_litresPerBarrel*(INDEX(Refinery_capacity,2,MATCH(G$16,Assumptions!$L$93:$R$93,0)))*Operational_days*1000*Refinery_availability*INDEX(Production_High,MATCH($B41,Assumptions!$L$102:$L$131,0),MATCH(G$16,Assumptions!$L$102:$R$102,0))+ IF( INDEX(Production_High,MATCH($B41,Assumptions!$L$102:$L$131,0),MATCH(G$16,Assumptions!$L$102:$R$102,0))>0, IF(Product_select="Diesel", INDEX(fDiesel!$J$30:$J$45, MATCH($B41, fDiesel!$B$30:$B$45,0)) * INDEX(Assumptions!$U$110:$U$112, MATCH("Diesel", Assumptions!$T$110:$T$112,0)), IF(Product_select="Gasoline", INDEX(fGasoline!$L$30:$L$45, MATCH($B41, fGasoline!$B$30:$B$45,0)) * INDEX(Assumptions!$U$110:$U$112, MATCH("Gasoline", Assumptions!$T$110:$T$112,0)), IF(Product_select="Total", INDEX(fDiesel!$J$30:$J$45, MATCH($B41, fDiesel!$B$30:$B$45,0)) * INDEX(Assumptions!$U$110:$U$112, MATCH("Diesel", Assumptions!$T$110:$T$112,0)) + INDEX(fGasoline!$L$30:$L$45, MATCH($B41, fGasoline!$B$30:$B$45,0)) * INDEX(Assumptions!$U$110:$U$112, MATCH("Gasoline", Assumptions!$T$110:$T$112,0)) ) ) ), 0 ) -> #N/A | H41: =INDEX(Refinery,MATCH(Product_select,Assumptions!$L$93:$L$98,0),MATCH(H$16,Assumptions!$L$93:$R$93,0))*Crude_oil_litresPerBarrel*(INDEX(Refinery_capacity,2,MATCH(H$16,Assumptions!$L$93:$R$93,0)))*Operational_days*1000*Refinery_availability*INDEX(Production_High,MATCH($B41,Assumptions!$L$102:$L$131,0),MATCH(H$16,Assumptions!$L$102:$R$102,0))+ IF( INDEX(Production_High,MATCH($B41,Assumptions!$L$102:$L$131,0),MATCH(H$16,Assumptions!$L$102:$R$102,0))>0, IF(Product_select="Diesel", INDEX(fDiesel!$J$30:$J$45, MATCH($B41, fDiesel!$B$30:$B$45,0)) * INDEX(Assumptions!$U$110:$U$112, MATCH("Diesel", Assumptions!$T$110:$T$112,0)), IF(Product_select="Gasoline", INDEX(fGasoline!$L$30:$L$45, MATCH($B41, fGasoline!$B$30:$B$45,0)) * INDEX(Assumptions!$U$110:$U$112, MATCH("Gasoline", Assumptions!$T$110:$T$112,0)), IF(Product_select="Total", INDEX(fDiesel!$J$30:$J$45, MATCH($B41, fDiesel!$B$30:$B$45,0)) * INDEX(Assumptions!$U$110:$U$112, MATCH("Diesel", Assumptions!$T$110:$T$112,0)) + INDEX(fGasoline!$L$30:$L$45, MATCH($B41, fGasoline!$B$30:$B$45,0)) * INDEX(Assumptions!$U$110:$U$112, MATCH("Gasoline", Assumptions!$T$110:$T$112,0)) ) ) ), 0 ) -> 0 | I41: =SUM(C41:H41) -> #N/A | J41: =I41/Crude_oil_litresPerBarrel/Operational_days/1000 -> #N/A | K41: =SUM(C41:H41) -> #N/A | L41: =K41/Crude_oil_litresPerBarrel/Operational_days/1000 -> #N/A | N41: =E41+F41 -> #N/A
B42: 2047 | C42: =INDEX(Refinery,MATCH(Product_select,Assumptions!$L$93:$L$98,0),MATCH(C$16,Assumptions!$L$93:$R$93,0))*Crude_oil_litresPerBarrel*(INDEX(Refinery_capacity,2,MATCH(C$16,Assumptions!$L$93:$R$93,0)))*Operational_days*1000*Refinery_availability*INDEX(Production_High,MATCH($B42,Assumptions!$L$102:$L$131,0),MATCH(C$16,Assumptions!$L$102:$R$102,0))+ IF( INDEX(Production_High,MATCH($B42,Assumptions!$L$102:$L$131,0),MATCH(C$16,Assumptions!$L$102:$R$102,0))>0, IF(Product_select="Diesel", INDEX(fDiesel!$J$30:$J$45, MATCH($B42, fDiesel!$B$30:$B$45,0)) * INDEX(Assumptions!$U$110:$U$112, MATCH("Diesel", Assumptions!$T$110:$T$112,0)), IF(Product_select="Gasoline", INDEX(fGasoline!$L$30:$L$45, MATCH($B42, fGasoline!$B$30:$B$45,0)) * INDEX(Assumptions!$U$110:$U$112, MATCH("Gasoline", Assumptions!$T$110:$T$112,0)), IF(Product_select="Total", INDEX(fDiesel!$J$30:$J$45, MATCH($B42, fDiesel!$B$30:$B$45,0)) * INDEX(Assumptions!$U$110:$U$112, MATCH("Diesel", Assumptions!$T$110:$T$112,0)) + INDEX(fGasoline!$L$30:$L$45, MATCH($B42, fGasoline!$B$30:$B$45,0)) * INDEX(Assumptions!$U$110:$U$112, MATCH("Gasoline", Assumptions!$T$110:$T$112,0)) ) ) ), 0 ) -> 0 | D42: =INDEX(Refinery,MATCH(Product_select,Assumptions!$L$93:$L$98,0),MATCH(D$16,Assumptions!$L$93:$R$93,0))*Crude_oil_litresPerBarrel*(INDEX(Refinery_capacity,2,MATCH(D$16,Assumptions!$L$93:$R$93,0)))*Operational_days*1000*Refinery_availability*INDEX(Production_High,MATCH($B42,Assumptions!$L$102:$L$131,0),MATCH(D$16,Assumptions!$L$102:$R$102,0))+ IF( INDEX(Production_High,MATCH($B42,Assumptions!$L$102:$L$131,0),MATCH(D$16,Assumptions!$L$102:$R$102,0))>0, IF(Product_select="Diesel", INDEX(fDiesel!$J$30:$J$45, MATCH($B42, fDiesel!$B$30:$B$45,0)) * INDEX(Assumptions!$U$110:$U$112, MATCH("Diesel", Assumptions!$T$110:$T$112,0)), IF(Product_select="Gasoline", INDEX(fGasoline!$L$30:$L$45, MATCH($B42, fGasoline!$B$30:$B$45,0)) * INDEX(Assumptions!$U$110:$U$112, MATCH("Gasoline", Assumptions!$T$110:$T$112,0)), IF(Product_select="Total", INDEX(fDiesel!$J$30:$J$45, MATCH($B42, fDiesel!$B$30:$B$45,0)) * INDEX(Assumptions!$U$110:$U$112, MATCH("Diesel", Assumptions!$T$110:$T$112,0)) + INDEX(fGasoline!$L$30:$L$45, MATCH($B42, fGasoline!$B$30:$B$45,0)) * INDEX(Assumptions!$U$110:$U$112, MATCH("Gasoline", Assumptions!$T$110:$T$112,0)) ) ) ), 0 ) -> 0 | E42: =INDEX(Refinery,MATCH(Product_select,Assumptions!$L$93:$L$98,0),MATCH(E$16,Assumptions!$L$93:$R$93,0))*Crude_oil_litresPerBarrel*(INDEX(Refinery_capacity,2,MATCH(E$16,Assumptions!$L$93:$R$93,0)))*Operational_days*1000*Refinery_availability*INDEX(Production_High,MATCH($B42,Assumptions!$L$102:$L$131,0),MATCH(E$16,Assumptions!$L$102:$R$102,0))+ IF( INDEX(Production_High,MATCH($B42,Assumptions!$L$102:$L$131,0),MATCH(E$16,Assumptions!$L$102:$R$102,0))>0, IF(Product_select="Diesel", INDEX(fDiesel!$J$30:$J$45, MATCH($B42, fDiesel!$B$30:$B$45,0)) * INDEX(Assumptions!$U$110:$U$112, MATCH("Diesel", Assumptions!$T$110:$T$112,0)), IF(Product_select="Gasoline", INDEX(fGasoline!$L$30:$L$45, MATCH($B42, fGasoline!$B$30:$B$45,0)) * INDEX(Assumptions!$U$110:$U$112, MATCH("Gasoline", Assumptions!$T$110:$T$112,0)), IF(Product_select="Total", INDEX(fDiesel!$J$30:$J$45, MATCH($B42, fDiesel!$B$30:$B$45,0)) * INDEX(Assumptions!$U$110:$U$112, MATCH("Diesel", Assumptions!$T$110:$T$112,0)) + INDEX(fGasoline!$L$30:$L$45, MATCH($B42, fGasoline!$B$30:$B$45,0)) * INDEX(Assumptions!$U$110:$U$112, MATCH("Gasoline", Assumptions!$T$110:$T$112,0)) ) ) ), 0 ) -> #N/A | F42: =INDEX(Refinery,MATCH(Product_select,Assumptions!$L$93:$L$98,0),MATCH(F$16,Assumptions!$L$93:$R$93,0))*Crude_oil_litresPerBarrel*(INDEX(Refinery_capacity,2,MATCH(F$16,Assumptions!$L$93:$R$93,0)))*Operational_days*1000*Refinery_availability*INDEX(Production_High,MATCH($B42,Assumptions!$L$102:$L$131,0),MATCH(F$16,Assumptions!$L$102:$R$102,0))+ IF( INDEX(Production_High,MATCH($B42,Assumptions!$L$102:$L$131,0),MATCH(F$16,Assumptions!$L$102:$R$102,0))>0, IF(Product_select="Diesel", INDEX(fDiesel!$J$30:$J$45, MATCH($B42, fDiesel!$B$30:$B$45,0)) * INDEX(Assumptions!$U$110:$U$112, MATCH("Diesel", Assumptions!$T$110:$T$112,0)), IF(Product_select="Gasoline", INDEX(fGasoline!$L$30:$L$45, MATCH($B42, fGasoline!$B$30:$B$45,0)) * INDEX(Assumptions!$U$110:$U$112, MATCH("Gasoline", Assumptions!$T$110:$T$112,0)), IF(Product_select="Total", INDEX(fDiesel!$J$30:$J$45, MATCH($B42, fDiesel!$B$30:$B$45,0)) * INDEX(Assumptions!$U$110:$U$112, MATCH("Diesel", Assumptions!$T$110:$T$112,0)) + INDEX(fGasoline!$L$30:$L$45, MATCH($B42, fGasoline!$B$30:$B$45,0)) * INDEX(Assumptions!$U$110:$U$112, MATCH("Gasoline", Assumptions!$T$110:$T$112,0)) ) ) ), 0 ) -> #N/A | G42: =INDEX(Refinery,MATCH(Product_select,Assumptions!$L$93:$L$98,0),MATCH(G$16,Assumptions!$L$93:$R$93,0))*Crude_oil_litresPerBarrel*(INDEX(Refinery_capacity,2,MATCH(G$16,Assumptions!$L$93:$R$93,0)))*Operational_days*1000*Refinery_availability*INDEX(Production_High,MATCH($B42,Assumptions!$L$102:$L$131,0),MATCH(G$16,Assumptions!$L$102:$R$102,0))+ IF( INDEX(Production_High,MATCH($B42,Assumptions!$L$102:$L$131,0),MATCH(G$16,Assumptions!$L$102:$R$102,0))>0, IF(Product_select="Diesel", INDEX(fDiesel!$J$30:$J$45, MATCH($B42, fDiesel!$B$30:$B$45,0)) * INDEX(Assumptions!$U$110:$U$112, MATCH("Diesel", Assumptions!$T$110:$T$112,0)), IF(Product_select="Gasoline", INDEX(fGasoline!$L$30:$L$45, MATCH($B42, fGasoline!$B$30:$B$45,0)) * INDEX(Assumptions!$U$110:$U$112, MATCH("Gasoline", Assumptions!$T$110:$T$112,0)), IF(Product_select="Total", INDEX(fDiesel!$J$30:$J$45, MATCH($B42, fDiesel!$B$30:$B$45,0)) * INDEX(Assumptions!$U$110:$U$112, MATCH("Diesel", Assumptions!$T$110:$T$112,0)) + INDEX(fGasoline!$L$30:$L$45, MATCH($B42, fGasoline!$B$30:$B$45,0)) * INDEX(Assumptions!$U$110:$U$112, MATCH("Gasoline", Assumptions!$T$110:$T$112,0)) ) ) ), 0 ) -> #N/A | H42: =INDEX(Refinery,MATCH(Product_select,Assumptions!$L$93:$L$98,0),MATCH(H$16,Assumptions!$L$93:$R$93,0))*Crude_oil_litresPerBarrel*(INDEX(Refinery_capacity,2,MATCH(H$16,Assumptions!$L$93:$R$93,0)))*Operational_days*1000*Refinery_availability*INDEX(Production_High,MATCH($B42,Assumptions!$L$102:$L$131,0),MATCH(H$16,Assumptions!$L$102:$R$102,0))+ IF( INDEX(Production_High,MATCH($B42,Assumptions!$L$102:$L$131,0),MATCH(H$16,Assumptions!$L$102:$R$102,0))>0, IF(Product_select="Diesel", INDEX(fDiesel!$J$30:$J$45, MATCH($B42, fDiesel!$B$30:$B$45,0)) * INDEX(Assumptions!$U$110:$U$112, MATCH("Diesel", Assumptions!$T$110:$T$112,0)), IF(Product_select="Gasoline", INDEX(fGasoline!$L$30:$L$45, MATCH($B42, fGasoline!$B$30:$B$45,0)) * INDEX(Assumptions!$U$110:$U$112, MATCH("Gasoline", Assumptions!$T$110:$T$112,0)), IF(Product_select="Total", INDEX(fDiesel!$J$30:$J$45, MATCH($B42, fDiesel!$B$30:$B$45,0)) * INDEX(Assumptions!$U$110:$U$112, MATCH("Diesel", Assumptions!$T$110:$T$112,0)) + INDEX(fGasoline!$L$30:$L$45, MATCH($B42, fGasoline!$B$30:$B$45,0)) * INDEX(Assumptions!$U$110:$U$112, MATCH("Gasoline", Assumptions!$T$110:$T$112,0)) ) ) ), 0 ) -> 0 | I42: =SUM(C42:H42) -> #N/A | J42: =I42/Crude_oil_litresPerBarrel/Operational_days/1000 -> #N/A | K42: =SUM(C42:H42) -> #N/A | L42: =K42/Crude_oil_litresPerBarrel/Operational_days/1000 -> #N/A | N42: =E42+F42 -> #N/A
